Workbook

Sheet README
A1: MWG VALUATION MODEL V2 - 5Y HISTORICAL + DRIVER-BASED FORECAST + SOTP
A3: Mục tiêu | B3: Model định giá MWG chi tiết hơn: 5 năm lịch sử, forecast theo driver ngành bán lẻ, sheet riêng cho TGDD/ĐMX/BHX/công ty con, DCF + SOTP + case IPO ĐMX.
A5: Ghi chú quan trọng | B5: Một số số lịch sử hiện là ô nhập/cần cập nhật từ BCTC MWG 2021-2025 và tài liệu IR. Cấu trúc model đã làm theo hướng full-stack để chỉ cần cấy số vào là chạy.
A8: • | B8: Historical_5Y: 2021-2025 lịch sử hợp nhất
A9: • | B9: Segment_Historical: lịch sử theo TGDD/ĐMX/BHX/khác
A10: • | B10: Industry_Drivers: tăng trưởng ngành bán lẻ/điện máy/grocery
A11: • | B11: TGDD_Forecast / DMX_Forecast / BHX_Forecast: forecast riêng từng mảng
A12: • | B12: Subsidiaries: công ty con/mảng khác chiếm doanh thu
A13: • | B13: Consolidated_Forecast: hợp nhất
A14: • | B14: DCF / SOTP / IPO_DMX / Sensitivity / Sources

Sheet Assumptions
A1: Input | B1: Base | C1: Bull | D1: Bear | E1: Unit | F1: Logic
A2: WACC | B2: 0.105 | C2: 0.095 | D2: 0.115 | E2: % | F2: Cost of capital cho MWG
A3: Terminal growth | B3: 0.035 | C3: 0.04 | D3: 0.025 | E3: % | F3: Long-run nominal growth
A4: Tax rate | B4: 0.2 | C4: 0.2 | D4: 0.2 | E4: % | F4: Thuế suất doanh nghiệp
A5: Net debt 2025A | B5: 7000 | C5: 5000 | D5: 9000 | E5: VNDbn | F5: Cập nhật theo BCTC 2025
A6: Shares out | B6: 1463 | C6: 1463 | D6: 1463 | E6: mn | F6: Cập nhật theo báo cáo mới nhất
A7: ĐMX IPO valuation | B7: 45000 | C7: 60000 | D7: 32000 | E7: VNDbn | F7: Giả định post-money ĐMX
A8: ĐMX IPO stake sold | B8: 0.2 | C8: 0.25 | D8: 0.15 | E8: % | F8: Tỷ lệ IPO/spin-off
A9: BHX target steady EBIT margin | B9: 0.04 | C9: 0.055 | D9: 0.02 | E9: % | F9: Khi đạt scale
A10: TGDD steady EBIT margin | B10: 0.05 | C10: 0.055 | D10: 0.045 | E10: % | F10: Mảng mature
A11: ĐMX steady EBIT margin | B11: 0.06 | C11: 0.07 | D11: 0.05 | E11: % | F11: Điện máy tốt hơn TGDD nếu cầu hồi phục

Sheet Historical_5Y
A1: VNDbn | B1: 2021A | C1: 2022A | D1: 2023A | E1: 2024A | F1: 2025A
A2: Revenue
A3: Gross profit
A4: EBIT
A5: NPAT
A6: Operating CF
A7: Capex
A8: Total assets
A9: Cash
A10: Debt
A11: Net debt
A12: Equity
A15: Hướng dẫn | B15: Điền số lịch sử 2021-2025 từ BCTC hợp nhất kiểm toán/quý 4.

Sheet Segment_Historical
A1: Metric | B1: 2021A | C1: 2022A | D1: 2023A | E1: 2024A | F1: 2025A
A2: TGDD revenue
A3: TGDD store count
A4: DMX revenue
A5: DMX store count
A6: DMX market share
A7: BHX revenue
A8: BHX store count
A9: BHX revenue/store/year
A10: BHX EBIT margin
A11: Other revenue
A13: Note | B13: Nếu thiếu số công khai, có thể nội suy từ annual report, presentation, bài IR, hoặc ước lượng bảo thủ để sensitivity chạy.

Sheet Industry_Drivers
A1: Driver | B1: 2026E | C1: 2027E | D1: 2028E | E1: 2029E | F1: 2030E | G1: Ghi chú
A2: VN retail sales growth | B2: 0.1 | C2: 0.09 | D2: 0.08 | E2: 0.07 | F2: 0.07 | G2: Tăng trưởng tiêu dùng danh nghĩa
A3: Consumer electronics demand growth | B3: 0.08 | C3: 0.08 | D3: 0.07 | E3: 0.06 | F3: 0.05 | G3: Chu kỳ thay mới điện thoại/điện máy
A4: Modern grocery growth | B4: 0.14 | C4: 0.13 | D4: 0.12 | E4: 0.11 | F4: 0.1 | G4: Hiện đại hóa bán lẻ thực phẩm
A5: DMX market share change | B5: 0.005 | C5: 0.004 | D5: 0.003 | E5: 0.002 | F5: 0.001 | G5: Điểm % gain/share
A6: BHX new stores | B6: 250 | C6: 220 | D6: 200 | E6: 180 | F6: 150 | G6: Mở thêm cửa hàng/năm
A7: BHX same-store sales growth | B7: 0.08 | C7: 0.07 | D7: 0.06 | E7: 0.05 | F7: 0.04 | G7: Tăng trưởng cửa hàng cũ
A8: TGDD same-store sales growth | B8: 0.04 | C8: 0.04 | D8: 0.03 | E8: 0.03 | F8: 0.02 | G8: Mảng mature
A9: ĐMX same-store sales growth | B9: 0.06 | C9: 0.05 | D9: 0.04 | E9: 0.04 | F9: 0.03 | G9: Phục hồi điện máy

Sheet TGDD_Forecast
A1: Line | B1: 2025A | C1: 2026E | D1: 2027E | E1: 2028E | F1: 2029E | G1: 2030E
A2: Store count | B2: =Segment_Historical!B2 | C2: =B2 | D2: =C2 | E2: =D2 | F2: =E2 | G2: =F2
A3: Revenue/store | C3: =B3*(1+Industry_Drivers!C8) | D3: =C3*(1+Industry_Drivers!D8) | E3: =D3*(1+Industry_Drivers!E8) | F3: =E3*(1+Industry_Drivers!F8) | G3: =F3*(1+Industry_Drivers!G8)
A4: Revenue | C4: =C2*C3 | D4: =D2*D3 | E4: =E2*E3 | F4: =F2*F3 | G4: =G2*G3
A5: Growth | C5: =IFERROR(C4/B4-1,"") | D5: =IFERROR(D4/C4-1,"") | E5: =IFERROR(E4/D4-1,"") | F5: =IFERROR(F4/E4-1,"") | G5: =IFERROR(G4/F4-1,"")
A6: EBIT margin | C6: =Assumptions!B10 | D6: =Assumptions!B10 | E6: =Assumptions!B10 | F6: =Assumptions!B10 | G6: =Assumptions!B10
A7: EBIT | C7: =C4*C6 | D7: =D4*D6 | E7: =E4*E6 | F7: =F4*F6 | G7: =G4*G6

Sheet DMX_Forecast
A1: Line | B1: 2025A | C1: 2026E | D1: 2027E | E1: 2028E | F1: 2029E | G1: 2030E
A2: Store count | C2: =B2 | D2: =C2 | E2: =D2 | F2: =E2 | G2: =F2
A3: Market share | C3: =B3+Industry_Drivers!C5 | D3: =C3+Industry_Drivers!D5 | E3: =D3+Industry_Drivers!E5 | F3: =E3+Industry_Drivers!F5 | G3: =F3+Industry_Drivers!G5
A4: Revenue/store | C4: =B4*(1+Industry_Drivers!C9) | D4: =C4*(1+Industry_Drivers!D9) | E4: =D4*(1+Industry_Drivers!E9) | F4: =E4*(1+Industry_Drivers!F9) | G4: =F4*(1+Industry_Drivers!G9)
A5: Revenue | C5: =C2*C4*(1+(C3-B3)) | D5: =D2*D4*(1+(D3-C3)) | E5: =E2*E4*(1+(E3-D3)) | F5: =F2*F4*(1+(F3-E3)) | G5: =G2*G4*(1+(G3-F3))
A6: Growth | C6: =IFERROR(C5/B5-1,"") | D6: =IFERROR(D5/C5-1,"") | E6: =IFERROR(E5/D5-1,"") | F6: =IFERROR(F5/E5-1,"") | G6: =IFERROR(G5/F5-1,"")
A7: EBIT margin | C7: =Assumptions!B11 | D7: =Assumptions!B11 | E7: =Assumptions!B11 | F7: =Assumptions!B11 | G7: =Assumptions!B11
A8: EBIT | C8: =C5*C7 | D8: =D5*D7 | E8: =E5*E7 | F8: =F5*F7 | G8: =G5*G7

Sheet BHX_Forecast
A1: Line | B1: 2025A | C1: 2026E | D1: 2027E | E1: 2028E | F1: 2029E | G1: 2030E
A2: Store count | C2: =B2+C3 | D2: =C2+D3 | E2: =D2+E3 | F2: =E2+F3 | G2: =F2+G3
A3: New stores | C3: =Industry_Drivers!C6 | D3: =Industry_Drivers!D6 | E3: =Industry_Drivers!E6 | F3: =Industry_Drivers!F6 | G3: =Industry_Drivers!G6
A4: Revenue/store | C4: =B4*(1+Industry_Drivers!C7) | D4: =C4*(1+Industry_Drivers!D7) | E4: =D4*(1+Industry_Drivers!E7) | F4: =E4*(1+Industry_Drivers!F7) | G4: =F4*(1+Industry_Drivers!G7)
A5: Same-store growth | C5: =Industry_Drivers!C7 | D5: =Industry_Drivers!D7 | E5: =Industry_Drivers!E7 | F5: =Industry_Drivers!F7 | G5: =Industry_Drivers!G7
A6: Revenue | C6: =C2*C4 | D6: =D2*D4 | E6: =E2*E4 | F6: =F2*F4 | G6: =G2*G4
A7: Growth | C7: =IFERROR(C6/B6-1,"") | D7: =IFERROR(D6/C6-1,"") | E7: =IFERROR(E6/D6-1,"") | F7: =IFERROR(F6/E6-1,"") | G7: =IFERROR(G6/F6-1,"")
A8: EBIT margin | C8: =MIN(Assumptions!B9,B8+0.008) | D8: =MIN(Assumptions!B9,C8+0.008) | E8: =MIN(Assumptions!B9,D8+0.008) | F8: =MIN(Assumptions!B9,E8+0.008) | G8: =MIN(Assumptions!B9,F8+0.008)
A9: EBIT | C9: =C6*C8 | D9: =D6*D8 | E9: =E6*E8 | F9: =F6*F8 | G9: =G6*G8

Sheet Subsidiaries
A1: Business / subsidiary | B1: 2025A Revenue | C1: 2026E Growth | D1: 2027E Growth | E1: 2028E Growth | F1: 2029E Growth | G1: 2030E Growth | H1: 2026E Revenue | I1: 2030E Revenue | J1: Notes
A2: An Khang | C2: 0.1 | D2: 0.08 | E2: 0.06 | F2: 0.05 | G2: 0.05 | H2: =B2*(1+C2) | I2: =B2*(1+C2)*(1+D2)*(1+E2)*(1+F2)*(1+G2) | J2: Nhà thuốc, currently nhỏ và volatile
A3: AVAKids / other specialty retail | C3: 0.12 | D3: 0.1 | E3: 0.08 | F3: 0.07 | G3: 0.06 | H3: =B3*(1+C3) | I3: =B3*(1+C3)*(1+D3)*(1+E3)*(1+F3)*(1+G3) | J3: Nếu còn đóng góp doanh thu đáng kể
A4: Online / services / others | C4: 0.08 | D4: 0.07 | E4: 0.06 | F4: 0.05 | G4: 0.05 | H4: =B4*(1+C4) | I4: =B4*(1+C4)*(1+D4)*(1+E4)*(1+F4)*(1+G4) | J4: Gộp mảng nhỏ

Sheet Consolidated_Forecast
A1: Line | B1: 2025A | C1: 2026E | D1: 2027E | E1: 2028E | F1: 2029E | G1: 2030E
A2: TGDD revenue | B2: =TGDD_Forecast!B4 | C2: =TGDD_Forecast!C4 | D2: =TGDD_Forecast!D4 | E2: =TGDD_Forecast!E4 | F2: =TGDD_Forecast!F4 | G2: =TGDD_Forecast!G4
A3: DMX revenue | B3: =DMX_Forecast!B5 | C3: =DMX_Forecast!C5 | D3: =DMX_Forecast!D5 | E3: =DMX_Forecast!E5 | F3: =DMX_Forecast!F5 | G3: =DMX_Forecast!G5
A4: BHX revenue | B4: =BHX_Forecast!B6 | C4: =BHX_Forecast!C6 | D4: =BHX_Forecast!D6 | E4: =BHX_Forecast!E6 | F4: =BHX_Forecast!F6 | G4: =BHX_Forecast!G6
A5: Other revenue | B5: =SUM(Subsidiaries!B2:B4) | C5: =IF(C$1="2026E",SUM(Subsidiaries!H2:H4),B5*1.06) | D5: =IF(D$1="2026E",SUM(Subsidiaries!H2:H4),C5*1.06) | E5: =IF(E$1="2026E",SUM(Subsidiaries!H2:H4),D5*1.06) | F5: =IF(F$1="2026E",SUM(Subsidiaries!H2:H4),E5*1.06) | G5: =IF(G$1="2026E",SUM(Subsidiaries!H2:H4),F5*1.06)
A6: Consolidated revenue | B6: =SUM(B2:B5) | C6: =SUM(C2:C5) | D6: =SUM(D2:D5) | E6: =SUM(E2:E5) | F6: =SUM(F2:F5) | G6: =SUM(G2:G5)
A7: Growth | C7: =IFERROR(C6/B6-1,"") | D7: =IFERROR(D6/C6-1,"") | E7: =IFERROR(E6/D6-1,"") | F7: =IFERROR(F6/E6-1,"") | G7: =IFERROR(G6/F6-1,"")
A8: Consolidated EBIT | B8: =(B2*TGDD_Forecast!B6+B3*DMX_Forecast!B7+B4*BHX_Forecast!B8)/B6 | C8: =(C2*TGDD_Forecast!C6+C3*DMX_Forecast!C7+C4*BHX_Forecast!C8)/C6 | D8: =(D2*TGDD_Forecast!D6+D3*DMX_Forecast!D7+D4*BHX_Forecast!D8)/D6 | E8: =(E2*TGDD_Forecast!E6+E3*DMX_Forecast!E7+E4*BHX_Forecast!E8)/E6 | F8: =(F2*TGDD_Forecast!F6+F3*DMX_Forecast!F7+F4*BHX_Forecast!F8)/F6 | G8: =(G2*TGDD_Forecast!G6+G3*DMX_Forecast!G7+G4*BHX_Forecast!G8)/G6
A9: EBIT margin | B9: =(B2*0+B3*0+B4*0) | C9: =(C2*TGDD_Forecast!C7+C3*DMX_Forecast!C8+C4*BHX_Forecast!C9) | D9: =(D2*TGDD_Forecast!D7+D3*DMX_Forecast!D8+D4*BHX_Forecast!D9) | E9: =(E2*TGDD_Forecast!E7+E3*DMX_Forecast!E8+E4*BHX_Forecast!E9) | F9: =(F2*TGDD_Forecast!F7+F3*DMX_Forecast!F8+F4*BHX_Forecast!F9) | G9: =(G2*TGDD_Forecast!G7+G3*DMX_Forecast!G8+G4*BHX_Forecast!G9)
A10: D&A | B10: =B6*0.015 | C10: =C6*0.015 | D10: =D6*0.015 | E10: =E6*0.015 | F10: =F6*0.015 | G10: =G6*0.015
A11: Capex | B11: =-B6*0.018 | C11: =-C6*0.018 | D11: =-D6*0.018 | E11: =-E6*0.018 | F11: =-F6*0.018 | G11: =-G6*0.018
A12: Change NWC | B12: 0 | C12: =-(C6-B6)*0.08 | D12: =-(D6-C6)*0.08 | E12: =-(E6-D6)*0.08 | F12: =-(F6-E6)*0.08 | G12: =-(G6-F6)*0.08
A13: FCFF | B13: =B9+B10+B11+B12 | C13: =C9+C10+C11+C12 | D13: =D9+D10+D11+D12 | E13: =E9+E10+E11+E12 | F13: =F9+F10+F11+F12 | G13: =G9+G10+G11+G12

Sheet DCF
A1: Item | B1: Value
A2: PV FCFF 2026-2030 | B2: =SUM(Consolidated_Forecast!C13:G13/(1+Assumptions!B2)^{1,2,3,4,5})
A3: Terminal value | B3: =Consolidated_Forecast!G13*(1+Assumptions!B3)/(Assumptions!B2-Assumptions!B3)
A4: PV Terminal | B4: =B3/(1+Assumptions!B2)^5
A5: Enterprise value | B5: =B2+B4
A6: Net debt | B6: =Assumptions!B5
A7: Equity value | B7: =B5-B6
A8: Shares | B8: =Assumptions!B6
A9: Value/share VND | B9: =B7*1000/B8

Sheet SOTP
A1: Segment | B1: 2030 Revenue | C1: Multiple | D1: EV | E1: Notes
A2: TGDD | B2: =TGDD_Forecast!G4 | C2: 0.35 | D2: =B2*C2 | E2: Mature mobile retail
A3: ĐMX | B3: =DMX_Forecast!G5 | C3: 0.45 | D3: =B3*C3 | E3: Can rerate if IPO
A4: BHX | B4: =BHX_Forecast!G6 | C4: 0.55 | D4: =B4*C4 | E4: Optionality from grocery scale
A5: Other | B5: =Consolidated_Forecast!G5 | C5: 0.2 | D5: =B5*C5 | E5: Small businesses
A7: Gross EV | D7: =SUM(D2:D5)
A8: Net debt | D8: =Assumptions!B5
A9: Equity value | D9: =D7-D8
A10: Value/share VND | D10: =D9*1000/Assumptions!B6

Sheet IPO_DMX
A1: Item | B1: Value | C1: Interpretation
A2: ĐMX IPO valuation | B2: =Assumptions!B7 | C2: Post-money valuation giả định của ĐMX
A3: Stake sold | B3: =Assumptions!B8 | C3: Tỷ lệ IPO/spin-off
A4: Cash proceeds | B4: =B2*B3 | C4: Tiền về nếu bán cổ phần
A5: Retained stake | B5: =1-B3 | C5: Tỷ lệ MWG còn nắm
A6: Retained value | B6: =B2*B5 | C6: Giá trị phần còn nắm
A7: Implied uplift vs SOTP base | B7: =B2-SOTP!D3 | C7: Nếu market value IPO > base multiple
A8: IPO logic | B8: IPO ĐMX giúp mở khóa định giá segment, tăng minh bạch, có thể giảm nợ/tài trợ BHX. | C8: Tác động mạnh nhất lên SOTP và capital structure hơn là chỉ P/E ngắn hạn.

Sheet Sensitivity
A1: Value/share sensitivity
A2: WACC vs g | B2: 0.02 | C2: 0.03 | D2: 0.035 | E2: 0.04 | F2: 0.045
A3: 0.09 | B3: =(((SUM(Consolidated_Forecast!C13:G13/(1+0.09)^{1,2,3,4,5}))+(Consolidated_Forecast!G13*(1+0.02)/(0.09-0.02)/(1+0.09)^5)-Assumptions!B5)*1000/Assumptions!B6) | C3: =(((SUM(Consolidated_Forecast!C13:G13/(1+0.09)^{1,2,3,4,5}))+(Consolidated_Forecast!G13*(1+0.03)/(0.09-0.03)/(1+0.09)^5)-Assumptions!B5)*1000/Assumptions!B6) | D3: =(((SUM(Consolidated_Forecast!C13:G13/(1+0.09)^{1,2,3,4,5}))+(Consolidated_Forecast!G13*(1+0.035)/(0.09-0.035)/(1+0.09)^5)-Assumptions!B5)*1000/Assumptions!B6) | E3: =(((SUM(Consolidated_Forecast!C13:G13/(1+0.09)^{1,2,3,4,5}))+(Consolidated_Forecast!G13*(1+0.04)/(0.09-0.04)/(1+0.09)^5)-Assumptions!B5)*1000/Assumptions!B6) | F3: =(((SUM(Consolidated_Forecast!C13:G13/(1+0.09)^{1,2,3,4,5}))+(Consolidated_Forecast!G13*(1+0.045)/(0.09-0.045)/(1+0.09)^5)-Assumptions!B5)*1000/Assumptions!B6)
A4: 0.1 | B4: =(((SUM(Consolidated_Forecast!C13:G13/(1+0.1)^{1,2,3,4,5}))+(Consolidated_Forecast!G13*(1+0.02)/(0.1-0.02)/(1+0.1)^5)-Assumptions!B5)*1000/Assumptions!B6) | C4: =(((SUM(Consolidated_Forecast!C13:G13/(1+0.1)^{1,2,3,4,5}))+(Consolidated_Forecast!G13*(1+0.03)/(0.1-0.03)/(1+0.1)^5)-Assumptions!B5)*1000/Assumptions!B6) | D4: =(((SUM(Consolidated_Forecast!C13:G13/(1+0.1)^{1,2,3,4,5}))+(Consolidated_Forecast!G13*(1+0.035)/(0.1-0.035)/(1+0.1)^5)-Assumptions!B5)*1000/Assumptions!B6) | E4: =(((SUM(Consolidated_Forecast!C13:G13/(1+0.1)^{1,2,3,4,5}))+(Consolidated_Forecast!G13*(1+0.04)/(0.1-0.04)/(1+0.1)^5)-Assumptions!B5)*1000/Assumptions!B6) | F4: =(((SUM(Consolidated_Forecast!C13:G13/(1+0.1)^{1,2,3,4,5}))+(Consolidated_Forecast!G13*(1+0.045)/(0.1-0.045)/(1+0.1)^5)-Assumptions!B5)*1000/Assumptions!B6)
A5: 0.105 | B5: =(((SUM(Consolidated_Forecast!C13:G13/(1+0.105)^{1,2,3,4,5}))+(Consolidated_Forecast!G13*(1+0.02)/(0.105-0.02)/(1+0.105)^5)-Assumptions!B5)*1000/Assumptions!B6) | C5: =(((SUM(Consolidated_Forecast!C13:G13/(1+0.105)^{1,2,3,4,5}))+(Consolidated_Forecast!G13*(1+0.03)/(0.105-0.03)/(1+0.105)^5)-Assumptions!B5)*1000/Assumptions!B6) | D5: =(((SUM(Consolidated_Forecast!C13:G13/(1+0.105)^{1,2,3,4,5}))+(Consolidated_Forecast!G13*(1+0.035)/(0.105-0.035)/(1+0.105)^5)-Assumptions!B5)*1000/Assumptions!B6) | E5: =(((SUM(Consolidated_Forecast!C13:G13/(1+0.105)^{1,2,3,4,5}))+(Consolidated_Forecast!G13*(1+0.04)/(0.105-0.04)/(1+0.105)^5)-Assumptions!B5)*1000/Assumptions!B6) | F5: =(((SUM(Consolidated_Forecast!C13:G13/(1+0.105)^{1,2,3,4,5}))+(Consolidated_Forecast!G13*(1+0.045)/(0.105-0.045)/(1+0.105)^5)-Assumptions!B5)*1000/Assumptions!B6)
A6: 0.11 | B6: =(((SUM(Consolidated_Forecast!C13:G13/(1+0.11)^{1,2,3,4,5}))+(Consolidated_Forecast!G13*(1+0.02)/(0.11-0.02)/(1+0.11)^5)-Assumptions!B5)*1000/Assumptions!B6) | C6: =(((SUM(Consolidated_Forecast!C13:G13/(1+0.11)^{1,2,3,4,5}))+(Consolidated_Forecast!G13*(1+0.03)/(0.11-0.03)/(1+0.11)^5)-Assumptions!B5)*1000/Assumptions!B6) | D6: =(((SUM(Consolidated_Forecast!C13:G13/(1+0.11)^{1,2,3,4,5}))+(Consolidated_Forecast!G13*(1+0.035)/(0.11-0.035)/(1+0.11)^5)-Assumptions!B5)*1000/Assumptions!B6) | E6: =(((SUM(Consolidated_Forecast!C13:G13/(1+0.11)^{1,2,3,4,5}))+(Consolidated_Forecast!G13*(1+0.04)/(0.11-0.04)/(1+0.11)^5)-Assumptions!B5)*1000/Assumptions!B6) | F6: =(((SUM(Consolidated_Forecast!C13:G13/(1+0.11)^{1,2,3,4,5}))+(Consolidated_Forecast!G13*(1+0.045)/(0.11-0.045)/(1+0.11)^5)-Assumptions!B5)*1000/Assumptions!B6)
A7: 0.12 | B7: =(((SUM(Consolidated_Forecast!C13:G13/(1+0.12)^{1,2,3,4,5}))+(Consolidated_Forecast!G13*(1+0.02)/(0.12-0.02)/(1+0.12)^5)-Assumptions!B5)*1000/Assumptions!B6) | C7: =(((SUM(Consolidated_Forecast!C13:G13/(1+0.12)^{1,2,3,4,5}))+(Consolidated_Forecast!G13*(1+0.03)/(0.12-0.03)/(1+0.12)^5)-Assumptions!B5)*1000/Assumptions!B6) | D7: =(((SUM(Consolidated_Forecast!C13:G13/(1+0.12)^{1,2,3,4,5}))+(Consolidated_Forecast!G13*(1+0.035)/(0.12-0.035)/(1+0.12)^5)-Assumptions!B5)*1000/Assumptions!B6) | E7: =(((SUM(Consolidated_Forecast!C13:G13/(1+0.12)^{1,2,3,4,5}))+(Consolidated_Forecast!G13*(1+0.04)/(0.12-0.04)/(1+0.12)^5)-Assumptions!B5)*1000/Assumptions!B6) | F7: =(((SUM(Consolidated_Forecast!C13:G13/(1+0.12)^{1,2,3,4,5}))+(Consolidated_Forecast!G13*(1+0.045)/(0.12-0.045)/(1+0.12)^5)-Assumptions!B5)*1000/Assumptions!B6)

Sheet Sources
A1: Nguồn | B1: Link / file | C1: Trạng thái
A2: CafeF BCTC MWG list | B2: tmp_mwg_bctc_list.json | C2: Đã lấy được list tới 2026
A3: MWG 2025 audited consolidated PDF | B3: MWG_BCTC_Hop_Nhat_2025_Kiem_Toan.pdf | C3: Đã tải về
A4: CafeF BCTC page html | B4: tmp_mwg_cafef_financials.html | C4: Đã lưu local
A5: Model notes | B5: MWG_model_notes.md | C5: Đã tạo
A6: Cần cập nhật thủ công thêm | B6: Store count, DMX market share, BHX market share/revenue/store từ IR/presentation | C6: Pending
