Workbook

Sheet Dashboard
A1: WARNING | B1: Các số segment hiện tại là structured estimate để model chạy logic. Chưa được tie-out 100% với annual report / segment note chính thức của MWG.
A2: STATUS | B2: Consolidated structure usable; segment exact 2025 still pending official tie-out.
A3: MWG VALUATION MODEL V3 - DRIVER-BASED BY SEGMENT
A5: Mục tiêu | B5: Forecast MWG theo từng ngành/mảng: TGDD (điện thoại), ĐMX (điện máy), BHX (grocery), mảng khác. Giả định liên kết với vĩ mô + vi mô doanh nghiệp.
A7: Kết quả định giá
A8: DCF value/share | B8: =DCF!B12
A9: SOTP value/share | B9: =SOTP!F12
A10: IPO ĐMX adjusted value/share | B10: =IPO_DMX!B10
A11: Blended target price | B11: =B6*0.4+B7*0.4+B8*0.2
A12: Upside/Downside vs current price | B12: =IFERROR(B9/Assumptions!B2-1,0)
A14: Trạng thái | B14: Bản V3 đã tách forecast theo driver ngành + vi mô từng mảng. Cần cập nhật số lịch sử 2021-2025 và current price để ra output chính thức.
A16: Data warning | B16: Target price hiện chỉ có ý nghĩa kịch bản/phương pháp. Không dùng như fair value cuối cho đến khi tie-out xong số lịch sử và segment 2025.

Sheet Assumptions
A1: Input | B1: Base | C1: Bull | D1: Bear | E1: Unit | F1: Ghi chú
A2: Current MWG price | B2: 70000 | C2: 68000 | D2: 68000 | E2: VND | F2: Cập nhật giá thị trường hiện tại
A3: Shares outstanding | B3: 1463 | C3: 1463 | D3: 1463 | E3: mn | F3: Cập nhật theo báo cáo mới nhất
A4: Net debt 2025A | B4: 7000 | C4: 5000 | D4: 9000 | E4: VNDbn | F4: Debt - cash, cập nhật theo BCTC
A5: Tax rate | B5: 0.2 | C5: 0.2 | D5: 0.2 | E5: % | F5: Thuế suất doanh nghiệp
A6: WACC | B6: 0.105 | C6: 0.095 | D6: 0.115 | E6: % | F6: Chi phí vốn hợp nhất
A7: Terminal growth | B7: 0.035 | C7: 0.04 | D7: 0.025 | E7: % | F7: Tăng trưởng dài hạn
A8: TGDD steady EBIT margin | B8: 0.05 | C8: 0.053 | D8: 0.043 | E8: % | F8: Mảng mature, biên ổn định
A9: DMX steady EBIT margin | B9: 0.06 | C9: 0.07 | D9: 0.05 | E9: % | F9: Điện máy lớn hơn, operating leverage tốt hơn
A10: BHX target EBIT margin | B10: 0.04 | C10: 0.055 | D10: 0.02 | E10: % | F10: Khi BHX đạt scale bền vững
A11: Other segment EBIT margin | B11: 0.015 | C11: 0.03 | D11: 0 | E11: % | F11: An Khang/AVAKids/others
A12: D&A / Revenue | B12: 0.015 | C12: 0.014 | D12: 0.016 | E12: % | F12: Khấu hao tương đối ổn định
A13: Capex / Revenue | B13: 0.018 | C13: 0.016 | D13: 0.022 | E13: % | F13: Capex duy trì + mở rộng
... A22: Risk discount to holdco | B22: 0.1 | C22: 0.05 | D22: 0.15 | E22: % | F22: Holding discount / execution risk

Sheet Macro_Drivers
A1: Macro factor | B1: 2026E | C1: 2027E | D1: 2028E | E1: 2029E | F1: 2030E | G1: Why it matters
A2: VN nominal retail sales growth | B2: 0.1 | C2: 0.09 | D2: 0.08 | E2: 0.07 | F2: 0.07 | G2: Anchor cho tổng cầu retail
A3: Disposable income growth | B3: 0.08 | C3: 0.08 | D3: 0.07 | E3: 0.06 | F3: 0.06 | G3: Ảnh hưởng cầu điện thoại/điện máy
A4: Consumer confidence index proxy | B4: 0.04 | C4: 0.04 | D4: 0.03 | E4: 0.03 | F4: 0.02 | G4: Ảnh hưởng goods ticket lớn
A5: Consumer finance / installment growth | B5: 0.09 | C5: 0.08 | D5: 0.07 | E5: 0.06 | F5: 0.06 | G5: Hỗ trợ TGDD/ĐMX trả góp
A6: Food retail modern trade growth | B6: 0.14 | C6: 0.13 | D6: 0.12 | E6: 0.11 | F6: 0.1 | G6: Anchor cho BHX
A7: Food CPI / pricing pass-through | B7: 0.04 | C7: 0.04 | D7: 0.035 | E7: 0.03 | F7: 0.03 | G7: Tác động doanh thu danh nghĩa BHX
A8: USD/VND pressure | B8: 0.02 | C8: 0.02 | D8: 0.02 | E8: 0.02 | F8: 0.02 | G8: Ảnh hưởng hàng nhập khẩu electronics

Sheet Historical_5Y
A1: WARNING | B1: Các số segment hiện tại là structured estimate để model chạy logic. Chưa được tie-out 100% với annual report / segment note chính thức của MWG.
A2: STATUS | B2: Consolidated structure usable; segment exact 2025 still pending official tie-out.
A3: VNDbn | B3: 2021A | C3: 2022A | D3: 2023A | E3: 2024A | F3: 2025A | G3: Source/Note
A4: Revenue | B4: 122958 | C4: 133405 | D4: 118280 | E4: 134341 | F4: 150000 | G4: Estimate placeholder; tie to CafeF/MWG audited 2025
A5: Gross profit | B5: 26757 | C5: 28800 | D5: 23600 | E5: 28800 | F5: 33000 | G5: Estimate placeholder
A6: EBIT | B6: 6600 | C6: 6200 | D6: 1600 | E6: 4700 | F6: 6200 | G6: Estimate placeholder
A7: NPAT | B7: 4900 | C7: 4100 | D7: 168 | E7: 3600 | F7: 4700 | G7: Estimate placeholder
A8: Operating CF | B8: 8500 | C8: 9000 | D8: 6500 | E8: 8000 | F8: 9800 | G8: Estimate placeholder
A9: Capex | B9: 2200 | C9: 2500 | D9: 1800 | E9: 2200 | F9: 2600 | G9: Estimate placeholder
A10: Cash | B10: 14500 | C10: 13000 | D10: 12000 | E10: 15000 | F10: 17000 | G10: Estimate placeholder
A11: Debt | B11: 21500 | C11: 19500 | D11: 20000 | E11: 21000 | F11: 24000 | G11: Estimate placeholder
A12: Net debt | B12: 7000 | C12: 6500 | D12: 8000 | E12: 6000 | F12: 7000 | G12: Estimate placeholder
A13: Total assets | B13: 59000 | C13: 62000 | D13: 60000 | E13: 65000 | F13: 72000 | G13: Estimate placeholder
A14: Equity | B14: 22000 | C14: 25000 | D14: 24500 | E14: 27500 | F14: 32000 | G14: Estimate placeholder
A16: Ghi chú | B16: Điền số lịch sử 2021-2025 theo BCTC kiểm toán/hợp nhất MWG. Model forecast dùng 2025A làm base year.

Sheet Segment_Historical
A1: WARNING | B1: Các số segment hiện tại là structured estimate để model chạy logic. Chưa được tie-out 100% với annual report / segment note chính thức của MWG.
A2: STATUS | B2: Consolidated structure usable; segment exact 2025 still pending official tie-out.
A3: Metric | B3: 2021A | C3: 2022A | D3: 2023A | E3: 2024A | F3: 2025A | G3: Source/Note
A4: TGDD revenue | B4: 26000 | C4: 26500 | D4: 24000 | E4: 25000 | F4: 25000 | G4: Estimate; replace with official MWG segment disclosure
A5: TGDD store count | B5: 900 | C5: 880 | D5: 850 | E5: 820 | F5: 800 | G5: Estimate store optimization
A6: TGDD revenue/store | B6: =B2/B3 | C6: =C2/C3 | D6: =D2/D3 | E6: =E2/E3 | F6: =F2/F3 | G6: Formula
A7: DMX revenue | B7: 54000 | C7: 60000 | D7: 52000 | E7: 60000 | F7: 65000 | G7: Estimate; ĐMX leading revenue contributor
A8: DMX store count | B8: 1900 | C8: 2000 | D8: 2050 | E8: 2100 | F8: 2100 | G8: Estimate
A9: DMX revenue/store | B9: =B5/B6 | C9: =C5/C6 | D9: =D5/D6 | E9: =E5/E6 | F9: =F5/F6 | G9: Formula
A10: DMX market share | B10: 0.5 | C10: 0.51 | D10: 0.5 | E10: 0.52 | F10: 0.53 | G10: Estimate market share
A11: BHX revenue | B11: 28000 | C11: 30000 | D11: 31500 | E11: 40000 | F11: 45000 | G11: Estimate; BHX growth but not overstate
A12: BHX store count | B12: 2100 | C12: 1800 | D12: 1700 | E12: 1750 | F12: 1900 | G12: Estimate
A13: BHX revenue/store | B13: =B9/B10 | C13: =C9/C10 | D13: =D9/D10 | E13: =E9/E10 | F13: =F9/F10 | G13: Formula
A14: BHX EBIT margin | B14: -0.06 | C14: -0.04 | D14: -0.01 | E14: 0.01 | F14: 0.02 | G14: Estimate EBIT margin path
A15: BHX market share | B15: 0.01 | C15: 0.012 | D15: 0.014 | E15: 0.018 | F15: 0.021 | G15: Estimate BHX market share
A16: Other revenue | B16: 14958 | C16: 16905 | D16: 10780 | E16: 9341 | F16: 15000 | G16: Residual = consolidated revenue - core segments

Sheet Micro_Drivers
A1: Micro driver | B1: 2026E | C1: 2027E | D1: 2028E | E1: 2029E | F1: 2030E | G1: Liên hệ với segment
A2: TGDD same-store sales growth | B2: 0.04 | C2: 0.04 | D2: 0.03 | E2: 0.03 | F2: 0.02 | G2: TGDD
A3: TGDD store optimization | B3: 0 | C3: 0 | D3: 0 | E3: 0 | F3: 0 | G3: TGDD
A4: DMX same-store sales growth | B4: 0.06 | C4: 0.05 | D4: 0.04 | E4: 0.04 | F4: 0.03 | G4: ĐMX
A5: DMX market share gain (ppt) | B5: 0.005 | C5: 0.004 | D5: 0.003 | E5: 0.002 | F5: 0.001 | G5: ĐMX
A6: BHX new stores | B6: 250 | C6: 220 | D6: 200 | E6: 180 | F6: 150 | G6: BHX
A7: BHX same-store sales growth | B7: 0.08 | C7: 0.07 | D7: 0.06 | E7: 0.05 | F7: 0.04 | G7: BHX
A8: BHX shrinkage improvement (ppt) | B8: 0.003 | C8: 0.002 | D8: 0.002 | E8: 0.001 | F8: 0.001 | G8: BHX
A9: BHX logistics efficiency uplift (ppt margin) | B9: 0.002 | C9: 0.002 | D9: 0.001 | E9: 0.001 | F9: 0.001 | G9: BHX
A10: Other segment growth | B10: 0.1 | C10: 0.08 | D10: 0.06 | E10: 0.05 | F10: 0.05 | G10: Others

Sheet TGDD_Forecast
A1: WARNING | B1: Các số segment hiện tại là structured estimate để model chạy logic. Chưa được tie-out 100% với annual report / segment note chính thức của MWG.
A2: STATUS | B2: Consolidated structure usable; segment exact 2025 still pending official tie-out.
A3: Line | B3: 2025A | C3: 2026E | D3: 2027E | E3: 2028E | F3: 2029E | G3: 2030E | H3: Logic
A4: Store count | B4: =Segment_Historical!F3 | C4: =B2*(1+Micro_Drivers!C3) | D4: =C2*(1+Micro_Drivers!D3) | E4: =D2*(1+Micro_Drivers!E3) | F4: =E2*(1+Micro_Drivers!F3) | G4: =F2*(1+Micro_Drivers!G3) | H4: TGDD phụ thuộc chu kỳ thay máy, thu nhập khả dụng, consumer finance và mức saturation của smartphone market.
A5: Revenue/store | B5: =Segment_Historical!F4 | C5: =B3*(1+Macro_Drivers!C3+Micro_Drivers!C2) | D5: =C3*(1+Macro_Drivers!D3+Micro_Drivers!D2) | E5: =D3*(1+Macro_Drivers!E3+Micro_Drivers!E2) | F5: =E3*(1+Macro_Drivers!F3+Micro_Drivers!F2) | G5: =F3*(1+Macro_Drivers!G3+Micro_Drivers!G2) | H5: Store count chủ yếu tối ưu, không mở rộng lớn như trước.
A6: Revenue | B6: =Segment_Historical!F2 | C6: =C2*C3 | D6: =D2*D3 | E6: =E2*E3 | F6: =F2*F3 | G6: =G2*G3
A7: Growth | C7: =IFERROR(C4/B4-1,0) | D7: =IFERROR(D4/C4-1,0) | E7: =IFERROR(E4/D4-1,0) | F7: =IFERROR(F4/E4-1,0) | G7: =IFERROR(G4/F4-1,0)
A8: EBIT margin | B8: =Assumptions!B8 | C8: =Assumptions!B8 | D8: =Assumptions!B8 | E8: =Assumptions!B8 | F8: =Assumptions!B8 | G8: =Assumptions!B8
A9: EBIT | B9: =B4*B6 | C9: =C4*C6 | D9: =D4*D6 | E9: =E4*E6 | F9: =F4*F6 | G9: =G4*G6

Sheet DMX_Forecast
A1: WARNING | B1: Các số segment hiện tại là structured estimate để model chạy logic. Chưa được tie-out 100% với annual report / segment note chính thức của MWG.
A2: STATUS | B2: Consolidated structure usable; segment exact 2025 still pending official tie-out.
A3: Line | B3: 2025A | C3: 2026E | D3: 2027E | E3: 2028E | F3: 2029E | G3: 2030E | H3: Logic
A4: Store count | B4: =Segment_Historical!F6 | C4: =B2 | D4: =C2 | E4: =D2 | F4: =E2 | G4: =F2 | H4: ĐMX link mạnh với hàng điện tử gia dụng, housing/household appliance cycle, thị phần và sức mua.
A5: Market share | B5: =Segment_Historical!F8 | C5: =B3+Micro_Drivers!C5 | D5: =C3+Micro_Drivers!D5 | E5: =D3+Micro_Drivers!E5 | F5: =E3+Micro_Drivers!F5 | G5: =F3+Micro_Drivers!G5
A6: Revenue/store | B6: =Segment_Historical!F7 | C6: =B4*(1+Macro_Drivers!C2+Macro_Drivers!C4+Micro_Drivers!C4) | D6: =C4*(1+Macro_Drivers!D2+Macro_Drivers!D4+Micro_Drivers!D4) | E6: =D4*(1+Macro_Drivers!E2+Macro_Drivers!E4+Micro_Drivers!E4) | F6: =E4*(1+Macro_Drivers!F2+Macro_Drivers!F4+Micro_Drivers!F4) | G6: =F4*(1+Macro_Drivers!G2+Macro_Drivers!G4+Micro_Drivers!G4)
A7: Revenue | B7: =Segment_Historical!F5 | C7: =C2*C4*(1+(C3-B3)) | D7: =D2*D4*(1+(D3-C3)) | E7: =E2*E4*(1+(E3-D3)) | F7: =F2*F4*(1+(F3-E3)) | G7: =G2*G4*(1+(G3-F3))
A8: Growth | C8: =IFERROR(C5/B5-1,0) | D8: =IFERROR(D5/C5-1,0) | E8: =IFERROR(E5/D5-1,0) | F8: =IFERROR(F5/E5-1,0) | G8: =IFERROR(G5/F5-1,0)
A9: EBIT margin | B9: =Assumptions!B9 | C9: =Assumptions!B9 | D9: =Assumptions!B9 | E9: =Assumptions!B9 | F9: =Assumptions!B9 | G9: =Assumptions!B9
A10: EBIT | B10: =B5*B7 | C10: =C5*C7 | D10: =D5*D7 | E10: =E5*E7 | F10: =F5*F7 | G10: =G5*G7

Sheet BHX_Forecast
A1: WARNING | B1: Các số segment hiện tại là structured estimate để model chạy logic. Chưa được tie-out 100% với annual report / segment note chính thức của MWG.
A2: STATUS | B2: Consolidated structure usable; segment exact 2025 still pending official tie-out.
A3: Line | B3: 2025A | C3: 2026E | D3: 2027E | E3: 2028E | F3: 2029E | G3: 2030E | H3: Logic
A4: Store count | B4: =Segment_Historical!F10 | C4: =B2+C3 | D4: =C2+D3 | E4: =D2+E3 | F4: =E2+F3 | G4: =F2+G3 | H4: BHX forecast theo số cửa hàng mở mới, doanh thu/cửa hàng, SSSG, food CPI, modern trade penetration và cải thiện logistics/shrinkage.
A5: New stores | B5: 0 | C5: =Micro_Drivers!C6 | D5: =Micro_Drivers!D6 | E5: =Micro_Drivers!E6 | F5: =Micro_Drivers!F6 | G5: =Micro_Drivers!G6
A6: Revenue/store | B6: =Segment_Historical!F11 | C6: =B4*(1+Macro_Drivers!C5+Macro_Drivers!C6+Micro_Drivers!C7) | D6: =C4*(1+Macro_Drivers!D5+Macro_Drivers!D6+Micro_Drivers!D7) | E6: =D4*(1+Macro_Drivers!E5+Macro_Drivers!E6+Micro_Drivers!E7) | F6: =E4*(1+Macro_Drivers!F5+Macro_Drivers!F6+Micro_Drivers!F7) | G6: =F4*(1+Macro_Drivers!G5+Macro_Drivers!G6+Micro_Drivers!G7)
A7: Same-store sales growth | B7: 0 | C7: =Micro_Drivers!C7 | D7: =Micro_Drivers!D7 | E7: =Micro_Drivers!E7 | F7: =Micro_Drivers!F7 | G7: =Micro_Drivers!G7
A8: Revenue | B8: =Segment_Historical!F9 | C8: =C2*C4 | D8: =D2*D4 | E8: =E2*E4 | F8: =F2*F4 | G8: =G2*G4
A9: Growth | C9: =IFERROR(C6/B6-1,0) | D9: =IFERROR(D6/C6-1,0) | E9: =IFERROR(E6/D6-1,0) | F9: =IFERROR(F6/E6-1,0) | G9: =IFERROR(G6/F6-1,0)
A10: EBIT margin | B10: =Segment_Historical!F12 | C10: =MIN(Assumptions!B10,B8+0.007+Micro_Drivers!C8+Micro_Drivers!C9) | D10: =MIN(Assumptions!B10,C8+0.007+Micro_Drivers!D8+Micro_Drivers!D9) | E10: =MIN(Assumptions!B10,D8+0.007+Micro_Drivers!E8+Micro_Drivers!E9) | F10: =MIN(Assumptions!B10,E8+0.007+Micro_Drivers!F8+Micro_Drivers!F9) | G10: =MIN(Assumptions!B10,F8+0.007+Micro_Drivers!G8+Micro_Drivers!G9)
A11: EBIT | B11: =B6*B8 | C11: =C6*C8 | D11: =D6*D8 | E11: =E6*E8 | F11: =F6*F8 | G11: =G6*G8
A12: Market share | B12: =Segment_Historical!F13 | C12: =B10+0.002 | D12: =C10+0.002 | E12: =D10+0.002 | F12: =E10+0.002 | G12: =F10+0.002

Sheet Other_Subsidiaries
A1: Business | B1: 2025A Revenue | C1: 2026E | D1: 2027E | E1: 2028E | F1: 2029E | G1: 2030E | H1: 2025A EBIT margin | I1: Steady EBIT margin | J1: Ghi chú
A2: An Khang | B2: 2000 | C2: =B2*(1+Micro_Drivers!C10) | D2: =C2*(1+Micro_Drivers!D10) | E2: =D2*(1+Micro_Drivers!E10) | F2: =E2*(1+Micro_Drivers!F10) | G2: =F2*(1+Micro_Drivers!G10) | H2: -0.03 | I2: 0.01 | J2: Nhà thuốc, scale/rationalization risk
A3: AVAKids / specialty retail | B3: 3000 | C3: =B3*(1+Micro_Drivers!C10) | D3: =C3*(1+Micro_Drivers!D10) | E3: =D3*(1+Micro_Drivers!E10) | F3: =E3*(1+Micro_Drivers!F10) | G3: =F3*(1+Micro_Drivers!G10) | H3: -0.01 | I3: 0.02 | J3: Small-format specialty retail
A4: Other / online / services | B4: 10000 | C4: =B4*(1+Micro_Drivers!C10) | D4: =C4*(1+Micro_Drivers!D10) | E4: =D4*(1+Micro_Drivers!E10) | F4: =E4*(1+Micro_Drivers!F10) | G4: =F4*(1+Micro_Drivers!G10) | H4: 0.03 | I4: 0.04 | J4: Gộp mảng nhỏ

Sheet Consolidated_Forecast
A1: Line | B1: 2025A | C1: 2026E | D1: 2027E | E1: 2028E | F1: 2029E | G1: 2030E | H1: Logic
A2: TGDD revenue | B2: =TGDD_Forecast!B4 | C2: =TGDD_Forecast!C4 | D2: =TGDD_Forecast!D4 | E2: =TGDD_Forecast!E4 | F2: =TGDD_Forecast!F4 | G2: =TGDD_Forecast!G4 | H2: Hợp nhất từ từng segment, không dùng 1 growth rate chung cho toàn MWG.
A3: DMX revenue | B3: =DMX_Forecast!B5 | C3: =DMX_Forecast!C5 | D3: =DMX_Forecast!D5 | E3: =DMX_Forecast!E5 | F3: =DMX_Forecast!F5 | G3: =DMX_Forecast!G5
A4: BHX revenue | B4: =BHX_Forecast!B6 | C4: =BHX_Forecast!C6 | D4: =BHX_Forecast!D6 | E4: =BHX_Forecast!E6 | F4: =BHX_Forecast!F6 | G4: =BHX_Forecast!G6
A5: Other revenue | B5: =SUM(Other_Subsidiaries!B2:B4) | C5: =SUM(Other_Subsidiaries!C2:C4) | D5: =SUM(Other_Subsidiaries!D2:D4) | E5: =SUM(Other_Subsidiaries!E2:E4) | F5: =SUM(Other_Subsidiaries!F2:F4) | G5: =SUM(Other_Subsidiaries!G2:G4)
A6: Consolidated revenue | B6: =SUM(B2:B5) | C6: =SUM(C2:C5) | D6: =SUM(D2:D5) | E6: =SUM(E2:E5) | F6: =SUM(F2:F5) | G6: =SUM(G2:G5)
A7: Growth | C7: =IFERROR(C6/B6-1,0) | D7: =IFERROR(D6/C6-1,0) | E7: =IFERROR(E6/D6-1,0) | F7: =IFERROR(F6/E6-1,0) | G7: =IFERROR(G6/F6-1,0)
A8: TGDD EBIT | B8: =TGDD_Forecast!B7 | C8: =TGDD_Forecast!C7 | D8: =TGDD_Forecast!D7 | E8: =TGDD_Forecast!E7 | F8: =TGDD_Forecast!F7 | G8: =TGDD_Forecast!G7
A9: DMX EBIT | B9: =DMX_Forecast!B8 | C9: =DMX_Forecast!C8 | D9: =DMX_Forecast!D8 | E9: =DMX_Forecast!E8 | F9: =DMX_Forecast!F8 | G9: =DMX_Forecast!G8
A10: BHX EBIT | B10: =BHX_Forecast!B9 | C10: =BHX_Forecast!C9 | D10: =BHX_Forecast!D9 | E10: =BHX_Forecast!E9 | F10: =BHX_Forecast!F9 | G10: =BHX_Forecast!G9
A11: Other EBIT | B11: =SUMPRODUCT(Other_Subsidiaries!B2:B4,Other_Subsidiaries!$I$2:$I$4) | C11: =SUMPRODUCT(Other_Subsidiaries!C2:C4,Other_Subsidiaries!$I$2:$I$4) | D11: =SUMPRODUCT(Other_Subsidiaries!D2:D4,Other_Subsidiaries!$I$2:$I$4) | E11: =SUMPRODUCT(Other_Subsidiaries!E2:E4,Other_Subsidiaries!$I$2:$I$4) | F11: =SUMPRODUCT(Other_Subsidiaries!F2:F4,Other_Subsidiaries!$I$2:$I$4) | G11: =SUMPRODUCT(Other_Subsidiaries!G2:G4,Other_Subsidiaries!$I$2:$I$4)
A12: Consolidated EBIT | B12: =SUM(B8:B11) | C12: =SUM(C8:C11) | D12: =SUM(D8:D11) | E12: =SUM(E8:E11) | F12: =SUM(F8:F11) | G12: =SUM(G8:G11)
A13: EBIT margin | B13: =IFERROR(B12/B6,0) | C13: =IFERROR(C12/C6,0) | D13: =IFERROR(D12/D6,0) | E13: =IFERROR(E12/E6,0) | F13: =IFERROR(F12/F6,0) | G13: =IFERROR(G12/G6,0)
A14: D&A | B14: =B6*Assumptions!B12 | C14: =C6*Assumptions!B12 | D14: =D6*Assumptions!B12 | E14: =E6*Assumptions!B12 | F14: =F6*Assumptions!B12 | G14: =G6*Assumptions!B12
A15: Capex | B15: =-B6*Assumptions!B13 | C15: =-C6*Assumptions!B13 | D15: =-D6*Assumptions!B13 | E15: =-E6*Assumptions!B13 | F15: =-F6*Assumptions!B13 | G15: =-G6*Assumptions!B13
A16: Change NWC | B16: 0 | C16: =-(C6-B6)*Assumptions!B14 | D16: =-(D6-C6)*Assumptions!B14 | E16: =-(E6-D6)*Assumptions!B14 | F16: =-(F6-E6)*Assumptions!B14 | G16: =-(G6-F6)*Assumptions!B14
A17: FCFF | B17: =B12*(1-Assumptions!B5)+B14+B15+B16 | C17: =C12*(1-Assumptions!B5)+C14+C15+C16 | D17: =D12*(1-Assumptions!B5)+D14+D15+D16 | E17: =E12*(1-Assumptions!B5)+E14+E15+E16 | F17: =F12*(1-Assumptions!B5)+F14+F15+F16 | G17: =G12*(1-Assumptions!B5)+G14+G15+G16

Sheet DCF
A1: Item | B1: Value | C1: Ghi chú
A2: PV FCFF 2026-2030 | B2: =SUM(B4:B8)
A3: Terminal value | B3: =Consolidated_Forecast!G17*(1+Assumptions!B6)/(Assumptions!B5-Assumptions!B6) | C3: TV từ FCFF 2030
A4: PV FCFF by year | B4: =Consolidated_Forecast!C17/(1+Assumptions!B5)^1 | C4: helper row below
A5: 2026 PV | B5: =Consolidated_Forecast!D17/(1+Assumptions!B5)^2
A6: 2027 PV | B6: =Consolidated_Forecast!E17/(1+Assumptions!B5)^3
A7: 2028 PV | B7: =Consolidated_Forecast!F17/(1+Assumptions!B5)^4
A8: 2029 PV | B8: =Consolidated_Forecast!G17/(1+Assumptions!B5)^5
A9: 2030 PV | B9: =B3/(1+Assumptions!B5)^5
A10: PV Terminal | B10: =B2+B9
A11: Enterprise value | B11: =B10-Assumptions!B4
A12: Equity value | B12: =B11*1000/Assumptions!B3
A13: Value/share | B13: =B11*1000/Assumptions!B3 | C13: VND/share

Sheet SOTP
A1: Segment | B1: 2030 Revenue | C1: Multiple | D1: EV | E1: Ownership / adj. | F1: Equity value | G1: Notes
A2: TGDD | B2: =TGDD_Forecast!G4 | C2: =Assumptions!B15 | D2: =B2*C2 | E2: 1 | F2: =D2*E2 | G2: Mature mobile retail
A3: ĐMX | B3: =DMX_Forecast!G5 | C3: =Assumptions!B16 | D3: =B3*C3 | E3: 1 | F3: =D3*E3 | G3: Điện máy, optional IPO rerating
A4: BHX | B4: =BHX_Forecast!G6 | C4: =Assumptions!B17+Assumptions!B21 | D4: =B4*C4 | E4: 1 | F4: =D4*E4 | G4: Modern grocery optionality
A5: Other | B5: =SUM(Other_Subsidiaries!G2:G4) | C5: =Assumptions!B18 | D5: =B5*C5 | E5: 1 | F5: =D5*E5 | G5: Mảng khác
A8: Gross EV | F8: =SUM(F2:F5)
A9: Net debt | F9: =Assumptions!B4
A10: Holdco discount | F10: =F8*Assumptions!B22
A11: Equity value | F11: =F8-F9-F10
A12: Value/share | F12: =F11*1000/Assumptions!B3

Sheet IPO_DMX
A1: Item | B1: Value | C1: Interpretation
A2: DMX IPO post-money | B2: =Assumptions!B19 | C2: Giá trị thị trường giả định của ĐMX khi IPO
A3: Stake sold | B3: =Assumptions!B20 | C3: Tỷ lệ bán ra
A4: Cash proceeds | B4: =B2*B3 | C4: Tiền thu về
A5: Retained stake | B5: =1-B3 | C5: Tỷ lệ còn nắm
A6: Retained value | B6: =B2*B5 | C6: Giá trị phần còn nắm
A7: DMX base SOTP EV | B7: =SOTP!D3 | C7: Giá trị ĐMX trước uplift IPO
A8: IPO uplift | B8: =MAX(0,B2-B7) | C8: Phần chênh lệch định giá nếu IPO > base
A9: Adj. equity value | B9: =SOTP!F11+B8 | C9: Cộng uplift vào equity SOTP
A10: Value/share | B10: =B9*1000/Assumptions!B3 | C10: VND/share
A11: Kết luận | B11: IPO ĐMX nên được xem như công cụ mở khóa SOTP, giảm net debt/tài trợ BHX, và làm rõ market benchmark cho mảng điện máy. | C11: Không nên chỉ nhìn như one-off gain.

Sheet Methodology
A1: Mảng | B1: Biến forecast chính | C1: Macro link | D1: Micro link | E1: Định giá
A2: TGDD | B2: store count, revenue/store, SSSG, margin | C2: thu nhập khả dụng, tín dụng tiêu dùng, confidence | D2: chu kỳ thay máy, optimization cửa hàng | E2: DCF + EV/Sales mature retail
A3: ĐMX | B3: market share, revenue/store, margin | C3: retail durables, housing/consumer cycle | D3: share gain, assortment, financing | E3: SOTP + IPO rerating logic
A4: BHX | B4: new stores, revenue/store, SSSG, margin ramp | C4: food retail growth, food CPI, urbanization | D4: shrinkage, logistics, procurement, scale | E4: EV/Sales + path to EBIT margin
A5: Others | B5: doanh thu nhỏ, margin thấp | C5: tùy thị trường ngách | D5: execution discipline | E5: conservative EV/Sales

Sheet Sources
A1: Nguồn | B1: Link / file | C1: Ứng dụng
A2: CafeF MWG BCTC page | B2: tmp_mwg_cafef_financials.html | C2: Nguồn BCTC và link PDF
A3: CafeF BCTC API list | B3: tmp_mwg_bctc_list.json | C3: Xác nhận đủ 2025 kiểm toán / 2026 Q1
A4: MWG 2025 audited consolidated PDF | B4: MWG_BCTC_Hop_Nhat_2025_Kiem_Toan.pdf | C4: Base year 2025A
A5: Macro assumptions | B5: sheet Macro_Drivers | C5: Gắn doanh thu forecast theo ngành
A6: Micro assumptions | B6: sheet Micro_Drivers | C6: Gắn riêng từng mảng

Sheet Manual_Input_Notes
A1: Mục | B1: Cách em input hiện tại | C1: Mức độ tin cậy
A2: TGDD/ĐMX/BHX revenue history | B2: Ước lượng dựa trên quy mô tương đối của các mảng và tổng doanh thu MWG, dùng để model chạy chi tiết ngay. | C2: Medium-low until official segment disclosures are keyed in
A3: BHX margin history | B3: Đặt đường cong từ lỗ sang gần hòa vốn/lãi nhẹ để phản ánh turnaround. | C3: Medium
A4: DMX market share | B4: Assumption leader position ~50%+ in modern CE retail. | C4: Medium-low
A5: Other revenue | B5: Residual = consolidated less core segments. | C5: Medium
A6: Mục tiêu | B6: Cho anh có model chi tiết chạy được ngay; vòng sau nên thay bằng số từ annual report/presentation/BCTC note nếu trích được sạch. | C6: High

Sheet Segment_PnL
A1: Line | B1: 2025A | C1: 2026E | D1: 2027E | E1: 2028E | F1: 2029E | G1: 2030E | H1: Logic
A2: TGDD Revenue | B2: =TGDD_Forecast!B4 | C2: =TGDD_Forecast!C4 | D2: =TGDD_Forecast!D4 | E2: =TGDD_Forecast!E4 | F2: =TGDD_Forecast!F4 | G2: =TGDD_Forecast!G4 | H2: Tách gross margin / opex / shrinkage để thấy profit bridge từng mảng.
A3: TGDD Gross margin | B3: 0.205 | C3: 0.205 | D3: 0.205 | E3: 0.205 | F3: 0.205 | G3: 0.205
A4: TGDD Gross profit | B4: =B2*B3 | C4: =C2*C3 | D4: =D2*D3 | E4: =E2*E3 | F4: =F2*F3 | G4: =G2*G3
A5: TGDD Opex/Sales | B5: =B3-TGDD_Forecast!B6 | C5: =C3-TGDD_Forecast!C6 | D5: =D3-TGDD_Forecast!D6 | E5: =E3-TGDD_Forecast!E6 | F5: =F3-TGDD_Forecast!F6 | G5: =G3-TGDD_Forecast!G6
A6: TGDD EBIT | B6: =TGDD_Forecast!B7 | C6: =TGDD_Forecast!C7 | D6: =TGDD_Forecast!D7 | E6: =TGDD_Forecast!E7 | F6: =TGDD_Forecast!F7 | G6: =TGDD_Forecast!G7
A7: TGDD EBIT margin | B7: =B6/B2 | C7: =C6/C2 | D7: =D6/D2 | E7: =E6/E2 | F7: =F6/F2 | G7: =G6/G2
A8: DMX Revenue | B8: =DMX_Forecast!B5 | C8: =DMX_Forecast!C5 | D8: =DMX_Forecast!D5 | E8: =DMX_Forecast!E5 | F8: =DMX_Forecast!F5 | G8: =DMX_Forecast!G5
A9: DMX Gross margin | B9: 0.215 | C9: 0.215 | D9: 0.215 | E9: 0.215 | F9: 0.215 | G9: 0.215
A10: DMX Gross profit | B10: =B8*B9 | C10: =C8*C9 | D10: =D8*D9 | E10: =E8*E9 | F10: =F8*F9 | G10: =G8*G9
A11: DMX Opex/Sales | B11: =B9-DMX_Forecast!B7 | C11: =C9-DMX_Forecast!C7 | D11: =D9-DMX_Forecast!D7 | E11: =E9-DMX_Forecast!E7 | F11: =F9-DMX_Forecast!F7 | G11: =G9-DMX_Forecast!G7
A12: DMX EBIT | B12: =DMX_Forecast!B8 | C12: =DMX_Forecast!C8 | D12: =DMX_Forecast!D8 | E12: =DMX_Forecast!E8 | F12: =DMX_Forecast!F8 | G12: =DMX_Forecast!G8
A13: DMX EBIT margin | B13: =B12/B8 | C13: =C12/C8 | D13: =D12/D8 | E13: =E12/E8 | F13: =F12/F8 | G13: =G12/G8
A14: BHX Revenue | B14: =BHX_Forecast!B6 | C14: =BHX_Forecast!C6 | D14: =BHX_Forecast!D6 | E14: =BHX_Forecast!E6 | F14: =BHX_Forecast!F6 | G14: =BHX_Forecast!G6
A15: BHX Gross margin | B15: 0.245 | C15: 0.245 | D15: 0.245 | E15: 0.245 | F15: 0.245 | G15: 0.245
A16: BHX Gross profit | B16: =B14*B15 | C16: =C14*C15 | D16: =D14*D15 | E16: =E14*E15 | F16: =F14*F15 | G16: =G14*G15
A17: BHX Shrinkage/Sales | B17: 0.025 | C17: 0.022 | D17: 0.02 | E17: 0.018 | F17: 0.017 | G17: 0.016
A18: BHX Logistics+Store Opex/Sales | B18: =B15-BHX_Forecast!B8-B17 | C18: =C15-BHX_Forecast!C8-C17 | D18: =D15-BHX_Forecast!D8-D17 | E18: =E15-BHX_Forecast!E8-E17 | F18: =F15-BHX_Forecast!F8-F17 | G18: =G15-BHX_Forecast!G8-G17
A19: BHX EBIT | B19: =BHX_Forecast!B9 | C19: =BHX_Forecast!C9 | D19: =BHX_Forecast!D9 | E19: =BHX_Forecast!E9 | F19: =BHX_Forecast!F9 | G19: =BHX_Forecast!G9
A20: BHX EBIT margin | B20: =B19/B14 | C20: =C19/C14 | D20: =D19/D14 | E20: =E19/E14 | F20: =F19/F14 | G20: =G19/G14
A21: Other Revenue | B21: =SUM(Other_Subsidiaries!B2:B4) | C21: =SUM(Other_Subsidiaries!C2:C4) | D21: =SUM(Other_Subsidiaries!D2:D4) | E21: =SUM(Other_Subsidiaries!E2:E4) | F21: =SUM(Other_Subsidiaries!F2:F4) | G21: =SUM(Other_Subsidiaries!G2:G4)
A22: Other EBIT margin | B22: 0.015 | C22: 0.015 | D22: 0.015 | E22: 0.015 | F22: 0.015 | G22: 0.015
A23: Other EBIT | B23: =B21*B22 | C23: =C21*C22 | D23: =D21*D22 | E23: =E21*E22 | F23: =F21*F22 | G23: =G21*G22
A24: Total segment EBIT | B24: =SUM(B6,B12,B19,B23) | C24: =SUM(C6,C12,C19,C23) | D24: =SUM(D6,D12,D19,D23) | E24: =SUM(E6,E12,E19,E23) | F24: =SUM(F6,F12,F19,F23) | G24: =SUM(G6,G12,G19,G23)

Sheet Peer_Multiples
A1: Peer/segment | B1: Business type | C1: EV/Sales | D1: EV/EBITDA | E1: P/E | F1: Use for MWG | G1: Note
A2: FRT | B2: ICT retail/pharmacy | C2: 0.45 | D2: 12 | E2: 22 | F2: TGDD reference | G2: VN listed peer, pharmacy mix differs
A3: DGW | B3: ICT distribution | C3: 0.3 | D3: 8 | E3: 14 | F3: TGDD/ICT sanity check | G3: Distributor lower margin
A4: WinCommerce/Masan consumer retail | B4: Grocery modern trade | C4: 0.7 | D4: 18 | E4: 30 | F4: BHX reference | G4: Grocery scale optionality
A5: Regional electronics retailer | B5: Consumer electronics | C5: 0.5 | D5: 10 | E5: 18 | F5: ĐMX reference | G5: Cycle-sensitive
A6: MWG implied blended | B6: Multi-format retail | C6: 0.45 | D6: 10 | E6: 18 | F6: Cross-check | G6: Depends BHX turnaround and IPO ĐMX

Sheet BHX_Unit_Economics
A1: Metric | B1: 2025A | C1: 2026E | D1: 2027E | E1: 2028E | F1: 2029E | G1: 2030E | H1: Interpretation
A2: Store count | B2: =BHX_Forecast!B2 | C2: =BHX_Forecast!C2 | D2: =BHX_Forecast!D2 | E2: =BHX_Forecast!E2 | F2: =BHX_Forecast!F2 | G2: =BHX_Forecast!G2 | H2: BHX phải xem theo unit economics: revenue/store, shrinkage, logistics/store opex, EBIT/store.
A3: Revenue/store/year | B3: =BHX_Forecast!B4 | C3: =BHX_Forecast!C4 | D3: =BHX_Forecast!D4 | E3: =BHX_Forecast!E4 | F3: =BHX_Forecast!F4 | G3: =BHX_Forecast!G4
A4: Revenue/store/month | B4: =B3/12 | C4: =C3/12 | D4: =D3/12 | E4: =E3/12 | F4: =F3/12 | G4: =G3/12
A5: Gross margin | B5: =Segment_PnL!B15 | C5: =Segment_PnL!C15 | D5: =Segment_PnL!D15 | E5: =Segment_PnL!E15 | F5: =Segment_PnL!F15 | G5: =Segment_PnL!G15
A6: Shrinkage | B6: =Segment_PnL!B17 | C6: =Segment_PnL!C17 | D6: =Segment_PnL!D17 | E6: =Segment_PnL!E17 | F6: =Segment_PnL!F17 | G6: =Segment_PnL!G17
A7: Logistics+store opex | B7: =Segment_PnL!B18 | C7: =Segment_PnL!C18 | D7: =Segment_PnL!D18 | E7: =Segment_PnL!E18 | F7: =Segment_PnL!F18 | G7: =Segment_PnL!G18
A8: EBIT/store/year | B8: =BHX_Forecast!B9/B2 | C8: =BHX_Forecast!C9/C2 | D8: =BHX_Forecast!D9/D2 | E8: =BHX_Forecast!E9/E2 | F8: =BHX_Forecast!F9/F2 | G8: =BHX_Forecast!G9/G2
A9: EBIT margin | B9: =BHX_Forecast!B8 | C9: =BHX_Forecast!C8 | D9: =BHX_Forecast!D8 | E9: =BHX_Forecast!E8 | F9: =BHX_Forecast!F8 | G9: =BHX_Forecast!G8
A10: Market share | B10: =BHX_Forecast!B10 | C10: =BHX_Forecast!C10 | D10: =BHX_Forecast!D10 | E10: =BHX_Forecast!E10 | F10: =BHX_Forecast!F10 | G10: =BHX_Forecast!G10

Sheet DMX_IPO_DeepDive
A1: Case | B1: IPO valuation | C1: Stake sold | D1: Proceeds | E1: Retained value | F1: Uplift vs base SOTP | G1: Value/share impact | H1: Comment
A2: Bear | B2: 32000 | C2: 0.15 | D2: =B2*C2 | E2: =B2*(1-C2) | F2: =MAX(0,B2-SOTP!D3) | G2: =F2*1000/Assumptions!B3 | H2: IPO creates observable valuation anchor; proceeds reduce balance-sheet pressure or fund BHX.
A3: Base | B3: 45000 | C3: 0.2 | D3: =B3*C3 | E3: =B3*(1-C3) | F3: =MAX(0,B3-SOTP!D3) | G3: =F3*1000/Assumptions!B3 | H3: IPO creates observable valuation anchor; proceeds reduce balance-sheet pressure or fund BHX.
A4: Bull | B4: 60000 | C4: 0.25 | D4: =B4*C4 | E4: =B4*(1-C4) | F4: =MAX(0,B4-SOTP!D3) | G4: =F4*1000/Assumptions!B3 | H4: IPO creates observable valuation anchor; proceeds reduce balance-sheet pressure or fund BHX.

Sheet Scenario_Output
A1: Output | B1: Bear | C1: Base | D1: Bull | E1: Formula/logic
A2: DCF value/share | B2: =DCF!B12*0.85 | C2: =DCF!B12 | D2: =DCF!B12*1.15 | E2: Sensitivity wrapper
A3: SOTP value/share | B3: =SOTP!F12*0.85 | C3: =SOTP!F12 | D3: =SOTP!F12*1.20 | E3: Multiple scenario
A4: IPO adjusted value/share | B4: =DMX_IPO_DeepDive!G2+SOTP!F12 | C4: =DMX_IPO_DeepDive!G3+SOTP!F12 | D4: =DMX_IPO_DeepDive!G4+SOTP!F12 | E4: DMX IPO uplift
A5: Blended target price | B5: =AVERAGE(B2:B4) | C5: =AVERAGE(C2:C4) | D5: =AVERAGE(D2:D4) | E5: Equal-weight scenario
A6: Upside/downside | B6: =B5/Assumptions!B2-1 | C6: =C5/Assumptions!B2-1 | D6: =D5/Assumptions!B2-1 | E6: vs current price

Sheet Data_Quality
A1: Area | B1: Current status | C1: Confidence | D1: Next action
A2: Consolidated 2021-2025 | B2: Input manually to make model run; needs audit tie-out | C2: Medium | D2: Tie to BCTC statements
A3: TGDD revenue/store | B3: Manual structured input | C3: Medium-low | D3: Pull from MWG annual report / monthly KPI
A4: DMX revenue/share | B4: Manual structured input | C4: Medium-low | D4: Pull market share/company presentation
A5: BHX revenue/store/margin | B5: Manual structured input with turnaround logic | C5: Medium | D5: Pull BHX disclosure, store count, monthly revenue/store
A6: IPO ĐMX | B6: Scenario-based | C6: Medium | D6: Update when IPO prospectus/valuation appears
A7: 2025 correction | B7: Adjusted 2025 segment split to sum to consolidated estimate and marked as estimate, not official. | C7: Medium-low | D7: Need official MWG segment disclosure tie-out
A8: Formula errors | B8: Removed array formulas and blank-driven formulas causing #VALUE. | C8: High | D8: Open in Excel and recalc
A9: Official 2025 consolidated PDF | B9: Downloaded from CafeF list and stored locally | C9: High | D9: Need line-item extraction / manual key-in from audited PDF
A10: Official 2025 segment revenue/profit | B10: Not yet extracted cleanly from official disclosures | C10: Low | D10: Need annual report / investor presentation / segment note
A11: Current model usage | B11: Best used for framework, scenario analysis, and sensitivity | C11: High | D11: Do not present as final audited valuation yet

Sheet Required_Exact_Data
A1: Need exact item | B1: Why needed | C1: Suggested source | D1: Priority
A2: 2021-2025 TGDD revenue | B2: Needed to tie history and revenue/store | C2: Annual report / investor presentation | D2: High
A3: 2021-2025 ĐMX revenue | B3: Core earnings driver | C3: Annual report / investor presentation | D3: High
A4: 2021-2025 BHX revenue | B4: Core grocery forecast base | C4: Annual report / investor presentation | D4: High
A5: 2021-2025 BHX EBIT margin / loss | B5: Critical for turnaround path | C5: Annual report / management commentary | D5: High
A6: 2021-2025 store count TGDD/ĐMX/BHX | B6: Needed for revenue/store logic | C6: Monthly KPI / annual report | D6: High
A7: ĐMX market share by year | B7: Needed for share-driven forecast | C7: Company commentary / industry report | D7: Medium
A8: BHX market share by year | B8: Needed for grocery penetration case | C8: Industry report / management commentary | D8: Medium
A9: Current net debt and shares | B9: Needed for final value/share | C9: Latest financial statements | D9: High
