Workbook

Sheet README
A1: MWG BASIC VALUATION MODEL - DCF + SOTP + IPO ĐMX + BHX
A3: Mục tiêu | B3: Khung Excel định giá MWG bản cơ bản, có thể chỉnh assumptions. Dữ liệu lịch sử là placeholder/assumption cần cập nhật bằng BCTC chính thức.
A5: Sheets
A6: Assumptions | B6: Các giả định chính
A7: Historical_FS | B7: BCTC lịch sử/normalized
A8: DCF_Consolidated | B8: DCF hợp nhất
A9: SOTP | B9: Sum-of-the-parts TGDD/ĐMX/BHX/khác
A10: DMX_IPO | B10: Phân tích IPO ĐMX và tác động đến MWG
A11: BHX_Analysis | B11: Vận hành BHX, thị phần, triển vọng
A12: Macro_VN | B12: Macro Việt Nam
A13: Sensitivity | B13: Độ nhạy WACC/g
A14: Sources | B14: Nguồn cần cập nhật
A17: Lưu ý quan trọng | B17: Không phải khuyến nghị đầu tư. Cần cập nhật BCTC, giá cổ phiếu, số cổ phiếu, nợ tiền mặt từ nguồn chính thức trước khi ra quyết định.

Sheet Assumptions
A1: Input | B1: Base | C1: Bull | D1: Bear | E1: Unit | F1: Ghi chú | G1: Editable
A2: Revenue 2024 | B2: 134000 | C2: 134000 | D2: 134000 | E2: VNDbn | F2: Placeholder; cập nhật theo BCTC MWG | G2: Y
A3: Revenue growth 2025 | B3: 0.11 | C3: 0.15 | D3: 0.06 | E3: % | F3: Phục hồi ICT/CE + BHX tăng trưởng | G3: Y
A4: Revenue growth 2026 | B4: 0.09 | C4: 0.12 | D4: 0.05 | E4: % | G4: Y
A5: Revenue growth 2027 | B5: 0.07 | C5: 0.1 | D5: 0.04 | E5: % | G5: Y
A6: Revenue growth 2028 | B6: 0.05 | C6: 0.08 | D6: 0.03 | E6: % | G6: Y
A7: Revenue growth 2029 | B7: 0.04 | C7: 0.06 | D7: 0.02 | E7: % | G7: Y
A8: EBIT margin 2024 | B8: 0.035 | C8: 0.035 | D8: 0.035 | E8: % | F8: Normalized placeholder | G8: Y
A9: EBIT margin 2025 | B9: 0.04 | C9: 0.045 | D9: 0.032 | E9: % | F9: BHX scale + DMX recovery | G9: Y
A10: EBIT margin 2026 | B10: 0.045 | C10: 0.052 | D10: 0.035 | E10: % | G10: Y
A11: EBIT margin 2027 | B11: 0.048 | C11: 0.056 | D11: 0.038 | E11: % | G11: Y
A12: EBIT margin 2028 | B12: 0.05 | C12: 0.058 | D12: 0.04 | E12: % | G12: Y
A13: EBIT margin 2029 | B13: 0.05 | C13: 0.06 | D13: 0.04 | E13: % | G13: Y
A14: Tax rate | B14: 0.2 | C14: 0.2 | D14: 0.2 | E14: % | F14: VN corporate tax | G14: Y
A15: D&A / Revenue | B15: 0.015 | C15: 0.014 | D15: 0.016 | E15: % | G15: Y
A16: Capex / Revenue | B16: 0.018 | C16: 0.016 | D16: 0.022 | E16: % | F16: Store expansion + IT/logistics | G16: Y
A17: NWC / Revenue change | B17: 0.08 | C17: 0.06 | D17: 0.1 | E17: % | F17: Working capital intensity | G17: Y
A18: WACC | B18: 0.105 | C18: 0.095 | D18: 0.115 | E18: % | F18: Cost of equity/debt placeholder | G18: Y
A19: Terminal growth | B19: 0.035 | C19: 0.04 | D19: 0.025 | E19: % | F19: Long-run VN nominal growth | G19: Y
A20: Net debt | B20: 6000 | C20: 4000 | D20: 8000 | E20: VNDbn | F20: Debt - cash, placeholder | G20: Y
A21: Shares outstanding | B21: 1463 | C21: 1463 | D21: 1463 | E21: mn shares | F21: Cập nhật theo báo cáo | G21: Y
A22: TGDD EV/Sales | B22: 0.35 | C22: 0.45 | D22: 0.25 | E22: x | F22: Mobile retail mature | G22: Y
A23: DMX EV/Sales pre-IPO | B23: 0.45 | C23: 0.6 | D23: 0.35 | E23: x | F23: Consumer electronics chain | G23: Y
A24: BHX EV/Sales | B24: 0.55 | C24: 0.8 | D24: 0.35 | E24: x | F24: Grocery chain optionality | G24: Y
A25: Other EV | B25: 2000 | C25: 4000 | D25: 1000 | E25: VNDbn | F25: An Khang/AVAKids/etc. | G25: Y
A26: ĐMX IPO stake sold | B26: 0.2 | C26: 0.25 | D26: 0.15 | E26: % | F26: Tỷ lệ bán trong IPO | G26: Y
A27: ĐMX post-money valuation | B27: 45000 | C27: 60000 | D27: 32000 | E27: VNDbn | F27: Giả định định giá ĐMX khi IPO | G27: Y

Sheet Historical_FS
A1: VNDbn | B1: 2020 | C1: 2021 | D1: 2022 | E1: 2023 | F1: 2024E/placeholder
A2: Revenue | B2: 108546 | C2: 122958 | D2: 133405 | E2: 118280 | F2: 134000
A3: Gross profit | B3: 24600 | C3: 27000 | D3: 30100 | E3: 24500 | F3: 30000
A4: EBIT | B4: 5600 | C4: 6200 | D4: 6400 | E4: 1600 | F4: 4700
A5: NPAT-MI | B5: 3920 | C5: 4900 | D5: 4100 | E5: 168 | F5: 3600
A6: Total assets | B6: 46000 | C6: 59000 | D6: 62000 | E6: 60000 | F6: 65000
A7: Equity | B7: 17000 | C7: 22000 | D7: 25000 | E7: 24500 | F7: 27500
A8: Net debt | B8: 5000 | C8: 7000 | D8: 6500 | E8: 8000 | F8: 6000
A9: BHX revenue | B9: 21000 | C9: 28000 | D9: 30000 | E9: 31500 | F9: 40000
A10: BHX EBIT margin | B10: -0.08 | C10: -0.06 | D10: -0.04 | E10: -0.01 | F10: 0.01
A13: Note | B13: Các số lịch sử trong bản này là khung/placeholder để model chạy; cần cập nhật theo BCTC audited/quarterly chính thức của MWG.

Sheet DCF_Consolidated
A1: Line | B1: 2024A | C1: 2025E | D1: 2026E | E1: 2027E | F1: 2028E | G1: 2029E | H1: Terminal
A2: Revenue | B2: =Assumptions!B2 | C2: =B2*(1+Assumptions!B3) | D2: =C2*(1+Assumptions!B4) | E2: =D2*(1+Assumptions!B5) | F2: =E2*(1+Assumptions!B6) | G2: =F2*(1+Assumptions!B7) | H2: =G2*(1+Assumptions!B19)
A3: Growth | C3: =C2/B2-1 | D3: =D2/C2-1 | E3: =E2/D2-1 | F3: =F2/E2-1 | G3: =G2/F2-1
A4: EBIT margin | B4: =Assumptions!B8 | C4: =Assumptions!B9 | D4: =Assumptions!B10 | E4: =Assumptions!B11 | F4: =Assumptions!B12 | G4: =Assumptions!B13
A5: EBIT | B5: =B2*B4 | C5: =C2*C4 | D5: =D2*D4 | E5: =E2*E4 | F5: =F2*F4 | G5: =G2*G4
A6: Tax | B6: =B5*Assumptions!B14 | C6: =C5*Assumptions!B14 | D6: =D5*Assumptions!B14 | E6: =E5*Assumptions!B14 | F6: =F5*Assumptions!B14 | G6: =G5*Assumptions!B14
A7: NOPAT | B7: =B5-B6 | C7: =C5-C6 | D7: =D5-D6 | E7: =E5-E6 | F7: =F5-F6 | G7: =G5-G6
A8: D&A | B8: =B2*Assumptions!B15 | C8: =C2*Assumptions!B15 | D8: =D2*Assumptions!B15 | E8: =E2*Assumptions!B15 | F8: =F2*Assumptions!B15 | G8: =G2*Assumptions!B15
A9: Capex | B9: =-B2*Assumptions!B16 | C9: =-C2*Assumptions!B16 | D9: =-D2*Assumptions!B16 | E9: =-E2*Assumptions!B16 | F9: =-F2*Assumptions!B16 | G9: =-G2*Assumptions!B16
A10: Change in NWC | B10: 0 | C10: =-(C2-B2)*Assumptions!B17 | D10: =-(D2-C2)*Assumptions!B17 | E10: =-(E2-D2)*Assumptions!B17 | F10: =-(F2-E2)*Assumptions!B17 | G10: =-(G2-F2)*Assumptions!B17
A11: FCFF | B11: =B7+B8+B9+B10 | C11: =C7+C8+C9+C10 | D11: =D7+D8+D9+D10 | E11: =E7+E8+E9+E10 | F11: =F7+F8+F9+F10 | G11: =G7+G8+G9+G10 | H11: =G11*(1+Assumptions!B19)/(Assumptions!B18-Assumptions!B19)
A12: Discount factor | C12: =1/(1+Assumptions!B18)^1 | D12: =1/(1+Assumptions!B18)^2 | E12: =1/(1+Assumptions!B18)^3 | F12: =1/(1+Assumptions!B18)^4 | G12: =1/(1+Assumptions!B18)^5 | H12: =1/(1+Assumptions!B18)^5
A13: PV FCFF | C13: =C11*C12 | D13: =D11*D12 | E13: =E11*E12 | F13: =F11*F12 | G13: =G11*G12 | H13: =H11*H12
A15: Enterprise value | B15: =SUM(C13:H13)
A16: Net debt | B16: =Assumptions!B20
A17: Equity value | B17: =B15-B16
A18: Shares mn | B18: =Assumptions!B21
A19: Value / share VND | B19: =B17*1000/B18

Sheet SOTP
A1: Segment | B1: Revenue assumption VNDbn | C1: Multiple | D1: EV VNDbn | E1: Ownership | F1: Equity attributable | G1: Notes
A2: TGDD/mobile | B2: 35000 | C2: =Assumptions!B22 | D2: =B2*C2 | E2: 1 | F2: =D2*E2 | G2: Mature mobile retail, lower multiple
A3: ĐMX/consumer electronics | B3: 55000 | C3: =Assumptions!B23 | D3: =B3*C3 | E3: 1 | F3: =D3*E3 | G3: IPO candidate; can crystallize value
A4: BHX/grocery | B4: 40000 | C4: =Assumptions!B24 | D4: =B4*C4 | E4: 1 | F4: =D4*E4 | G4: Higher optionality if profitable scale
A5: Other/minority | B5: 0 | D5: = | E5: 1 | F5: =Assumptions!B25 | G5: An Khang/AVAKids/etc.
A8: Gross EV | F8: =SUM(F2:F5)
A9: Net debt | F9: =Assumptions!B20
A10: Equity value | F10: =F8-F9
A11: Value/share VND | F11: =F10*1000/Assumptions!B21

Sheet DMX_IPO
A1: Item | B1: Base formula/value | C1: Interpretation
A2: ĐMX post-money valuation VNDbn | B2: =Assumptions!B27 | C2: Giá trị thị trường hàm ý của ĐMX sau IPO
A3: Stake sold | B3: =Assumptions!B26 | C3: Tỷ lệ MWG bán ra/pha loãng
A4: Cash proceeds VNDbn | B4: =B2*B3 | C4: Tiền về MWG/ĐMX tùy cấu trúc primary/secondary
A5: Remaining MWG ownership | B5: =1-B3 | C5: Tỷ lệ MWG còn nắm ĐMX
A6: Value of retained ĐMX | B6: =B2*B5 | C6: Giá trị phần còn lại MWG nắm giữ
A7: Potential debt reduction | B7: =MIN(B4,Assumptions!B20) | C7: Nếu dùng proceeds giảm nợ
A8: Equity value uplift vs pre-IPO SOTP | B8: =B2-SOTP!D3 | C8: Chênh lệch giá trị ĐMX IPO so với multiple SOTP
A11: Phân tích chuyên sâu | B11: IPO ĐMX có thể tác động MWG qua 4 kênh: (1) crystallize value bằng market multiple riêng cho ĐMX; (2) tạo cash proceeds giúp giảm net debt/tài trợ BHX; (3) tăng minh bạch segment và mở khóa SOTP; (4) rủi ro dilution/control discount nếu bán tỷ lệ lớn hoặc market định giá thấp.
A13: Tác động định giá | B13: Trong DCF hợp nhất, IPO chủ yếu thay đổi capital structure và terminal optionality. Trong SOTP, IPO ĐMX tạo observable market value cho segment, thay vì gộp trong MWG multiple. Nếu post-money ĐMX > EV implied trong SOTP, fair value MWG tăng; ngược lại có thể tạo anchor thấp.

Sheet BHX_Analysis
A1: Chủ đề | B1: Nội dung phân tích | C1: Implication định giá
A2: Mô hình vận hành | B2: Chuỗi grocery hiện đại: cửa hàng gần khu dân cư, SKU thiết yếu/tươi sống, logistics lạnh/khô, procurement tập trung, tối ưu shrinkage và vòng quay hàng tồn. | C2: Khi đạt scale, gross margin + operating leverage cải thiện; valuation chuyển từ drag sang optionality.
A3: Revenue driver | B3: Doanh thu/cửa hàng, số cửa hàng, mix hàng tươi sống/FMCG, online delivery, repeat frequency. | C3: Sensitivity nên tách SSSG và store expansion.
A4: Cost driver | B4: COGS/procurement, shrinkage, rent, labor/store, logistics, marketing, IT. | C4: EBIT margin BHX là biến số quyết định upside.
A5: Thị phần | B5: Thị trường grocery VN còn phân mảnh, kênh truyền thống lớn. BHX cạnh tranh với WinMart, Co.op, Satra, chợ truyền thống, minimart. | C5: Nếu BHX lấy thị phần modern grocery và duy trì unit economics dương, multiple có thể cao hơn retail truyền thống.
A6: Rủi ro | B6: Biên mỏng, hàng tươi sống hao hụt, cạnh tranh giá, logistics, mở rộng quá nhanh. | C6: Bear case dùng EV/Sales thấp và margin hồi phục chậm.
A7: Triển vọng | B7: Thu nhập đô thị tăng, nhu cầu tiện lợi/an toàn thực phẩm, thanh toán số, delivery hỗ trợ modern trade. | C7: Bull case: doanh thu/cửa hàng tăng và margin ổn định.

Sheet Macro_VN
A1: Yếu tố | B1: Tác động đến MWG | C1: Theo dõi
A2: GDP/thu nhập hộ gia đình | B2: Tăng trưởng thu nhập hỗ trợ tiêu dùng ICT/CE và grocery modern trade. | C2: GDP real, retail sales, CPI
A3: Lãi suất/tín dụng tiêu dùng | B3: Lãi suất thấp hỗ trợ mua hàng điện máy/điện thoại trả góp. | C3: Policy rate, consumer finance growth
A4: CPI thực phẩm | B4: Ảnh hưởng sức mua và gross margin BHX. | C4: Food CPI, commodity prices
A5: Tỷ giá | B5: Ảnh hưởng hàng nhập khẩu electronics/phones. | C5: USD/VND, vendor pricing
A6: Niềm tin tiêu dùng | B6: Tác động chu kỳ thay mới điện thoại/điện máy. | C6: Retail sales ex-inflation

Sheet Sensitivity
A1: DCF value/share sensitivity (VND)
A2: WACC \ g | B2: 0.02 | C2: 0.03 | D2: 0.035 | E2: 0.04 | F2: 0.045
A3: 0.09 | B3: =((SUM(DCF_Consolidated!C13:G13)+(DCF_Consolidated!G11*(1+0.02)/(0.09-0.02)/(1+0.09)^5))-Assumptions!B20)*1000/Assumptions!B21 | C3: =((SUM(DCF_Consolidated!C13:G13)+(DCF_Consolidated!G11*(1+0.03)/(0.09-0.03)/(1+0.09)^5))-Assumptions!B20)*1000/Assumptions!B21 | D3: =((SUM(DCF_Consolidated!C13:G13)+(DCF_Consolidated!G11*(1+0.035)/(0.09-0.035)/(1+0.09)^5))-Assumptions!B20)*1000/Assumptions!B21 | E3: =((SUM(DCF_Consolidated!C13:G13)+(DCF_Consolidated!G11*(1+0.04)/(0.09-0.04)/(1+0.09)^5))-Assumptions!B20)*1000/Assumptions!B21 | F3: =((SUM(DCF_Consolidated!C13:G13)+(DCF_Consolidated!G11*(1+0.045)/(0.09-0.045)/(1+0.09)^5))-Assumptions!B20)*1000/Assumptions!B21
A4: 0.1 | B4: =((SUM(DCF_Consolidated!C13:G13)+(DCF_Consolidated!G11*(1+0.02)/(0.1-0.02)/(1+0.1)^5))-Assumptions!B20)*1000/Assumptions!B21 | C4: =((SUM(DCF_Consolidated!C13:G13)+(DCF_Consolidated!G11*(1+0.03)/(0.1-0.03)/(1+0.1)^5))-Assumptions!B20)*1000/Assumptions!B21 | D4: =((SUM(DCF_Consolidated!C13:G13)+(DCF_Consolidated!G11*(1+0.035)/(0.1-0.035)/(1+0.1)^5))-Assumptions!B20)*1000/Assumptions!B21 | E4: =((SUM(DCF_Consolidated!C13:G13)+(DCF_Consolidated!G11*(1+0.04)/(0.1-0.04)/(1+0.1)^5))-Assumptions!B20)*1000/Assumptions!B21 | F4: =((SUM(DCF_Consolidated!C13:G13)+(DCF_Consolidated!G11*(1+0.045)/(0.1-0.045)/(1+0.1)^5))-Assumptions!B20)*1000/Assumptions!B21
A5: 0.105 | B5: =((SUM(DCF_Consolidated!C13:G13)+(DCF_Consolidated!G11*(1+0.02)/(0.105-0.02)/(1+0.105)^5))-Assumptions!B20)*1000/Assumptions!B21 | C5: =((SUM(DCF_Consolidated!C13:G13)+(DCF_Consolidated!G11*(1+0.03)/(0.105-0.03)/(1+0.105)^5))-Assumptions!B20)*1000/Assumptions!B21 | D5: =((SUM(DCF_Consolidated!C13:G13)+(DCF_Consolidated!G11*(1+0.035)/(0.105-0.035)/(1+0.105)^5))-Assumptions!B20)*1000/Assumptions!B21 | E5: =((SUM(DCF_Consolidated!C13:G13)+(DCF_Consolidated!G11*(1+0.04)/(0.105-0.04)/(1+0.105)^5))-Assumptions!B20)*1000/Assumptions!B21 | F5: =((SUM(DCF_Consolidated!C13:G13)+(DCF_Consolidated!G11*(1+0.045)/(0.105-0.045)/(1+0.105)^5))-Assumptions!B20)*1000/Assumptions!B21
A6: 0.11 | B6: =((SUM(DCF_Consolidated!C13:G13)+(DCF_Consolidated!G11*(1+0.02)/(0.11-0.02)/(1+0.11)^5))-Assumptions!B20)*1000/Assumptions!B21 | C6: =((SUM(DCF_Consolidated!C13:G13)+(DCF_Consolidated!G11*(1+0.03)/(0.11-0.03)/(1+0.11)^5))-Assumptions!B20)*1000/Assumptions!B21 | D6: =((SUM(DCF_Consolidated!C13:G13)+(DCF_Consolidated!G11*(1+0.035)/(0.11-0.035)/(1+0.11)^5))-Assumptions!B20)*1000/Assumptions!B21 | E6: =((SUM(DCF_Consolidated!C13:G13)+(DCF_Consolidated!G11*(1+0.04)/(0.11-0.04)/(1+0.11)^5))-Assumptions!B20)*1000/Assumptions!B21 | F6: =((SUM(DCF_Consolidated!C13:G13)+(DCF_Consolidated!G11*(1+0.045)/(0.11-0.045)/(1+0.11)^5))-Assumptions!B20)*1000/Assumptions!B21
A7: 0.12 | B7: =((SUM(DCF_Consolidated!C13:G13)+(DCF_Consolidated!G11*(1+0.02)/(0.12-0.02)/(1+0.12)^5))-Assumptions!B20)*1000/Assumptions!B21 | C7: =((SUM(DCF_Consolidated!C13:G13)+(DCF_Consolidated!G11*(1+0.03)/(0.12-0.03)/(1+0.12)^5))-Assumptions!B20)*1000/Assumptions!B21 | D7: =((SUM(DCF_Consolidated!C13:G13)+(DCF_Consolidated!G11*(1+0.035)/(0.12-0.035)/(1+0.12)^5))-Assumptions!B20)*1000/Assumptions!B21 | E7: =((SUM(DCF_Consolidated!C13:G13)+(DCF_Consolidated!G11*(1+0.04)/(0.12-0.04)/(1+0.12)^5))-Assumptions!B20)*1000/Assumptions!B21 | F7: =((SUM(DCF_Consolidated!C13:G13)+(DCF_Consolidated!G11*(1+0.045)/(0.12-0.045)/(1+0.12)^5))-Assumptions!B20)*1000/Assumptions!B21

Sheet Sources
A1: Nguồn | B1: URL/ghi chú | C1: Cần cập nhật
A2: MWG IR / annual reports | B2: https://mwg.vn/ hoặc trang IR chính thức MWG | C2: BCTC năm/quý, annual report, presentation
A3: HOSE/SSC disclosures | B3: Công bố thông tin chính thức | C3: Số cổ phiếu, nghị quyết IPO/spin-off nếu có
A4: CafeF/Vietstock | B4: Market data, snapshot tài chính | C4: Giá cổ phiếu, P/E, EV/EBITDA, historical FS cross-check
A5: General Statistics Office Vietnam | B5: Macro GDP/CPI/retail sales | C5: Macro assumptions
A6: Company store data | B6: Số cửa hàng TGDD/ĐMX/BHX, doanh thu/cửa hàng | C6: Segment assumptions
