Workbook

Sheet COVER
B2: LH REAL ESTATE ADVISORY · INVESTMENT · RESEARCH
B5: KHU PHỨC HỢP CĂN HỘ CAO TẦNG
B6: BÁO CÁO NGHIÊN CỨU KHẢ THI · FEASIBILITY STUDY
B7: Phạm Văn Đồng
B9: Prepared for | C9: Chủ đầu tư
B10: Prepared by | C10: LH Real Estate Advisory
B11: Ngày phát hành | C11: 23/7/2026
B12: STRICTLY PRIVATE & CONFIDENTIAL
B14: TÓM TẮT HIỆU QUẢ ĐẦU TƯ
B15: Kết luận đầu tư | C15: CHƯA ĐẠT NGƯỠNG
B16: NPV chủ đầu tư @12%/năm | C16: -1.1934467e+11 | D16: tr.đ
B17: IRR chủ đầu tư (levered) | C17: 0.0029682969
B18: IRR dự án — TMĐT (unlevered) | C18: 0.0023958359
B19: Thời gian hoàn vốn | C19: 4 năm
B20: Lợi nhuận sau thuế hợp nhất | C20: 6.8678296e+10 | D20: tr.đ
B21: Tổng mức đầu tư (gồm lãi vay) | C21: 1.231766e+12 | D21: tr.đ
B23: NỘI DUNG WORKBOOK
B24: DASHBOARD | C24: Bảng điều khiển: hiệu quả, cơ cấu vốn, dòng tiền, kiểm tra toàn vẹn
B25: INPUT | C25: Thông số đầu vào — sửa trực tiếp (web đọc theo địa chỉ ô)
B26: TIENDO | C26: Tiến độ giải ngân chi phí theo năm
B27: QD425 | C27: Khái toán suất vốn đầu tư — QĐ 425/QĐ-BXD
B28: FS | C28: Dòng tiền hợp nhất & hiệu quả (giá trị, không vòng lặp)
B29: CAUTRUCVON | C29: Cơ cấu vốn & nguồn tiền tài trợ theo năm (liên kết FS)
B30: PHANBOCP | C30: Cơ cấu phân bổ chi phí Bán hàng / Cho thuê (theo cơ sở phân bổ)
B31: KHAITOAN | C31: Đối chiếu khái toán & hạ tầng kỹ thuật
B32: HDSD | C32: Hướng dẫn sử dụng workbook
B34: Tài liệu do LH Real Estate Advisory lập trên cơ sở giả định của chủ đầu tư; phục vụ phân tích nội bộ, không phải khuyến nghị đầu tư. Số liệu lấy trực tiếp từ engine định lượng — DASHBOARD & FS luôn khớp web.

Sheet DASHBOARD
B1: DASHBOARD HIỆU QUẢ DỰ ÁN — Khu phức hợp căn hộ cao tầng
B3: KẾT LUẬN | C3: CHƯA ĐẠT NGƯỠNG
B5: CHỈ TIÊU HIỆU QUẢ (hợp nhất bán + cho thuê)
B6: NPV chủ đầu tư @12%/năm | C6: -1.1934467e+11 | D6: tr.đ
B7: IRR chủ đầu tư | C7: 0.0029682969
B8: IRR dự án (TMĐT) | C8: 0.0023958359
B9: Thời gian hoàn vốn | C9: 4 năm
B10: Lợi nhuận sau thuế hợp nhất | C10: 6.8678296e+10 | D10: tr.đ
B11: Thuế TNDN hợp nhất (bù lỗ 5 năm) | C11: 1.7169574e+10 | D11: tr.đ
B13: CƠ CẤU TỔNG MỨC ĐẦU TƯ
B14: Đất & pháp lý | C14: 7.4907e+11 | D14: 0.60812685 | E14: ██████████████████████████████
B15: Xây dựng (gồm VAT) | C15: 4.4376567e+11 | D15: 0.36026783 | E15: ██████████████████
B16: Lãi vay vốn hoá | C16: 38930360154 | D16: 0.03160532 | E16: ██
B17: TỔNG MỨC ĐẦU TƯ (gồm lãi vay) | C17: 1.231766e+12 | D17: 1
B19: CƠ CẤU NGUỒN VỐN
B20: Vốn vay ngân hàng | C20: 512984969875 | D20: 0.43005502 | E20: ██████████████████████████
B21: Vốn chủ sở hữu | C21: 5.9628173e+11 | D21: 0.4998859 | E21: ██████████████████████████████
B22: Vốn huy động khách hàng | C22: 8.3568969e+10 | D22: 0.070059079 | E22: ████
B24: CƠ CẤU NGUỒN VỐN THEO RỔ CHI PHÍ
B25: Rổ chi phí | C25: Tổng (triệu) | D25: Vốn chủ | E25: Vay NH / Huy động KH
B26: Chi phí đầu tư — TMĐT (chưa lãi vay) | C26: 1.1928357e+12 | D26: 3.1032089e+11 | E26: Vay 513 · KH 370
B27: Lãi vay vốn hoá (vốn chủ tài trợ) | C27: 38930360154 | D27: 38930360154 | E27: Vay 0 · KH 0
B28: Chi phí hoạt động + VAT | C28: 3.1930011e+11 | D28: 0 | E28: Vay 0 · KH 319
B29: Thuế TNDN | C29: 1.7169574e+10 | D29: 0 | E29: Vay 0 · KH 17
B30: TỔNG NGUỒN | C30: 1.5682357e+12 | D30: 3.4925125e+11 | E30: Vay 513 · KH 706
B31: Tỷ trọng (VC / Vay / KH) | C31: 0.22270329 | D31: 0.32710961 | E31: 45.0% · WACC 12.0% (vốn có CP)
B32: Lãi vay vốn hoá (đã gồm trong rổ đầu tư) | C32: 38930360154
B34: DÒNG TIỀN CHỦ ĐẦU TƯ THEO NĂM
B35: Năm | C35: Ngân lưu CĐT (triệu) | E35: Biểu đồ (|giá trị|)
B36: 2026 | C36: -200000000000 | E36: (−) █████████████████████
B37: 2027 | C37: -215000000000 | E37: (−) ██████████████████████
B38: 2028 | C38: -76428219366 | E38: (−) ████████
B39: 2029 | C39: 2.448199e+11 | E39: █████████████████████████
B40: 2030 | C40: 2.5064552e+11 | E40: ██████████████████████████
B41: 2031 | C41: 0
B42: 2032 | C42: 0
B43: 2033 | C43: 0
B44: 2034 | C44: 0
B45: 2035 | C45: 0
B46: 2036 | C46: 0
B47: 2037 | C47: 0
B49: KIỂM TRA TOÀN VẸN DỮ LIỆU
B50: Hạng mục kiểm tra | C50: Trạng thái | E50: Chi tiết
B51: Tiến độ bán Căn hộ — Σ=100% | C51: ĐẠT | E51: 100%
B52: Tiến độ bán Shop — Σ=100% | C52: ĐẠT | E52: 100%
B53: Lịch giải ngân chi phí — Σ=100%/hạng mục | C53: ĐẠT | E53: 9/9 hạng mục đạt
B54: Năm bán có ma trận thu tiền | C54: ĐẠT | E54: đủ 3 năm bán
B55: Ma trận thu tiền mỗi vintage — Σ=100% | C55: ĐẠT | E55: vintage đang dùng đạt 100%
B56: Đối soát thực thu / doanh thu | C56: ĐẠT | E56: 100.0%
B57: ✅ Tất cả 6 kiểm tra ĐẠT — dữ liệu nhất quán
B60: Số liệu lấy trực tiếp từ engine web: hợp nhất Bán + Cho thuê, TNDN bù lỗ 5 năm, chiết khấu đủ vòng đời. Sheet FS là chi tiết phát triển 13 năm (giá trị có thể khác do Dashboard đã hợp nhất + mở rộng).

Sheet INPUT
A1: FS INPUT — CHỈ SỬA GIÁ TRỊ CỘT C..F, KHÔNG CHÈN/XÓA HÀNG (web đọc theo địa chỉ ô)
B3: THAM SỐ CHUNG
B4: Tỷ suất chiết khấu CĐT (r) | C4: 12 | D4: %/năm
B5: Lãi suất vay ngân hàng | C5: 12 | D5: %/năm
B6: Thuế VAT | C6: 10 | D6: %
B7: Thuế TNDN | C7: 20 | D7: %
B8: Thuế TNDN tạm nộp/dòng thu | C8: 1 | D8: %
B9: Tốc độ tăng giá bán | C9: 5 | D9: %/năm
B10: Tổng diện tích đất dự án | C10: 3545 | D10: m2
B11: Diện tích đất xây dựng | C11: 1500 | D11: m2
B12: Chi phí chuyển nhượng (mua đất) | C12: 400 | D12: tỷ đồng
B13: Chi phí đền bù GPMB | C13: 0 | D13: tỷ đồng
B14: Tiền sử dụng đất | C14: 289.07 | D14: tỷ đồng
B15: Quỹ nhà ở xã hội | C15: 0 | D15: tỷ đồng
... B38: Chi phí vốn huy động KH | C38: 0 | D38: %/năm
B39: THÔNG SỐ TỪNG THÁP
B40: Tên tháp | C40: Tháp 1
B41: Số tầng nổi | C41: 25 | D41: 0 | E41: 0 | F41: 0 | G41: tầng
B42: Số tầng hầm | C42: 0 | D42: 0 | E42: 0 | F42: 0 | G42: tầng
B43: GFA nổi | C43: 27696.25 | D43: 0 | E43: 0 | F43: 0 | G43: m2
B44: GFA hầm | C44: 0 | D44: 0 | E44: 0 | F44: 0 | G44: m2
B45: Sàn khối đế (shop) | C45: 2011 | D45: 0 | E45: 0 | F45: 0 | G45: m2
B46: Tỷ lệ thương phẩm căn hộ | C46: 55 | D46: 0 | E46: 0 | F46: 0 | G46: %
B47: NSA shop (thương phẩm) | C47: 1581 | D47: 0 | E47: 0 | F47: 0 | G47: m2
B48: Suất XD áp dụng (gồm VAT) | C48: 13.5 | D48: 0 | E48: 0 | F48: 0 | G48: tr.đ/m2
B49: Bảng QĐ425 (1=chung cư, 2=đa năng) | C49: 1 | D49: 0 | E49: 0 | F49: 0
B50: Mục đích (1=bán, 2=cho thuê) | C50: 1 | D50: 0 | E50: 0 | F50: 0
B51: THAM SỐ MỞ RỘNG V3
B52: Chiều cao trung bình 1 tầng | C52: 3.5 | D52: m
B54: Phương pháp vay: 1=giải ngân thực tế, 2=hạn mức cơ cấu vay | C54: 2
B55: Hệ số vùng Kkv (QĐ 409/QĐ-BXD) | C55: 1 | D55: lần
B56: Hệ số thời điểm Ktg | C56: 1 | D56: lần
B57: THÔNG TIN DỰ ÁN
B58: Tên dự án | C58: Khu phức hợp căn hộ cao tầng
B59: Vị trí | C59: Phạm Văn Đồng
B60: Chủ đầu tư
B61: Đơn vị lập báo cáo
B62: Loại hình dự án | C62: Chung cư nhà ở thương mại
B63: Ghi chú pháp lý
B64: Vốn chủ: 1=tự động theo waterfall, 2=cố định theo ô C25 | C64: 1
B65: Tỷ lệ vay tiền sử dụng đất | C65: 70 | D65: %
B66: Tỷ lệ vay hạ tầng | C66: 70 | D66: %
B67: Tỷ lệ vay CPXD chính | C67: 70 | D67: %
B68: Tỷ lệ vay tư vấn/QLDA/khác | C68: 70 | D68: %
B69: Tỷ lệ vay dự phòng | C69: 70 | D69: %
B71: Loại sản phẩm BÁN (tên báo cáo) | C71: Bán hàng
B72: Loại sản phẩm CHO THUÊ / khai thác | C72: Cho thuê
B73: THÔNG SỐ CHO THUÊ / KHAI THÁC — giá thuê NET (chưa VAT)
B74: Bật mảng cho thuê (1=có · 0=không) | C74: 0
B75: Năm bắt đầu vận hành | C75: 2030 | D75: năm
B76: Số năm khai thác | C76: 45 | D76: năm
B77: Suất chiết khấu cho thuê | C77: 12 | D77: %/năm
B78: Thuế TNDN cho thuê | C78: 20 | D78: %
B79: Trượt giá thuê mỗi chu kỳ | C79: 10 | D79: %
B80: Chu kỳ điều chỉnh giá thuê | C80: 2 | D80: năm
B81: Diện tích cho thuê (NSA) | C81: 0 | D81: m²
B82: Giá thuê NSA (NET — chưa VAT) | C82: 0 | D82: ngàn/m²/tháng
B83: Số căn cho thuê | C83: 0 | D83: căn
B84: Giá thuê mỗi căn (NET — chưa VAT) | C84: 0 | D84: tr.đ/căn/tháng
B85: Số phòng khách sạn | C85: 0 | D85: phòng
B86: Giá phòng ADR (NET — chưa VAT) | C86: 0 | D86: tr.đ/đêm
... B91: Số năm khấu hao tài sản | C91: 25 | D91: năm
B92: Thoái vốn cuối kỳ (1=có · 0=giữ) | C92: 0
B93: Tuổi đời kinh tế tài sản | C93: 50 | D93: năm
B94: Cap rate thoái vốn | C94: 11 | D94: %
B95: Chi phí giao dịch thoái vốn | C95: 2 | D95: %
B96: Cơ sở phân bổ chung (1=CPXD · 2=GFA · 3=tay) | C96: 1
B97: Tỷ trọng nhập tay (khi chọn 3) | C97: 0 | D97: %
B98: OCC NSA — năm 1 | C98: 40 | D98: %
B99: OCC NSA — năm 2 | C99: 60 | D99: %
B100: OCC NSA — năm 3 | C100: 80 | D100: %
B101: OCC NSA — năm 4 | C101: 90 | D101: %
B102: OCC NSA — năm 5 | C102: 95 | D102: %
B103: OCC NSA — ổn định | C103: 95 | D103: %
B104: OCC căn — năm 1 | C104: 50 | D104: %
B105: OCC căn — năm 2 | C105: 70 | D105: %
B106: OCC căn — năm 3 | C106: 85 | D106: %
B107: OCC căn — năm 4 | C107: 92 | D107: %
B108: OCC căn — năm 5 | C108: 95 | D108: %
... B115: OCC KS — ổn định | C115: 70 | D115: %
B116: NSA căn hộ nhập trực tiếp (ưu tiên nếu >0) | C116: 15116 | D116: 0 | E116: 0 | F116: 0 | G116: m2
B117: Chi phí pháp lý nhập cứng (ưu tiên nếu >0) | C117: 60 | D117: tỷ đồng
B118: CPBH row 11 / doanh thu | C118: 8 | D118: %
B119: CPBH row 12 / doanh thu | C119: 1.5 | D119: %
B120: CPBH row 13 / doanh thu | C120: 6 | D120: %
B121: CPBH row 14 / doanh thu | C121: 1.1 | D121: %
B122: CPBH row 15 / thực thu | C122: 0.2 | D122: %
B123: CPBH row 16 / doanh thu | C123: 0 | D123: %
B124: CPBH row 17 / doanh thu | C124: 0.2 | D124: %
B125: Tỷ lệ dự phòng vào dòng CF FS | C125: 24.4 | D125: %

Sheet TIENDO
A1: TIẾN ĐỘ (%) — KHÔNG CHÈN/XÓA HÀNG CỘT
B2: Năm | C2: 2026 | D2: 2027 | E2: 2028 | F2: 2029 | G2: 2030 | H2: 2031 | I2: 2032 | J2: 2033 | K2: 2034 | L2: 2035 | M2: 2036 | N2: 2037 | O2: 2038
A3: TIẾN ĐỘ CHI PHÍ | B3: Chi phí chuyển nhượng | C3: 50 | D3: 50 | E3: 0 | F3: 0 | G3: 0 | H3: 0 | I3: 0 | J3: 0 | K3: 0 | L3: 0 | M3: 0 | N3: 0 | O3: 0
B4: Đền bù GPMB | C4: 0 | D4: 0 | E4: 100 | F4: 0 | G4: 0 | H4: 0 | I4: 0 | J4: 0 | K4: 0 | L4: 0 | M4: 0 | N4: 0 | O4: 0
B5: Tiền sử dụng đất | C5: 0 | D5: 0 | E5: 100 | F5: 0 | G5: 0 | H5: 0 | I5: 0 | J5: 0 | K5: 0 | L5: 0 | M5: 0 | N5: 0 | O5: 0
B6: Chi phí pháp lý | C6: 0 | D6: 25 | E6: 25 | F6: 25 | G6: 25 | H6: 0 | I6: 0 | J6: 0 | K6: 0 | L6: 0 | M6: 0 | N6: 0 | O6: 0
B7: Hạ tầng | C7: 0 | D7: 0 | E7: 0 | F7: 50 | G7: 50 | H7: 0 | I7: 0 | J7: 0 | K7: 0 | L7: 0 | M7: 0 | N7: 0 | O7: 0
B8: Xây dựng tháp BÁN HÀNG | C8: 0 | D8: 0 | E8: 40 | F8: 50 | G8: 10 | H8: 0 | I8: 0 | J8: 0 | K8: 0 | L8: 0 | M8: 0 | N8: 0 | O8: 0
B9: Xây dựng tháp CHO THUÊ | C9: 0 | D9: 0 | E9: 100 | F9: 0 | G9: 0 | H9: 0 | I9: 0 | J9: 0 | K9: 0 | L9: 0 | M9: 0 | N9: 0 | O9: 0
B10: Tư vấn, QLDA, khác | C10: 0 | D10: 0 | E10: 40 | F10: 50 | G10: 10 | H10: 0 | I10: 0 | J10: 0 | K10: 0 | L10: 0 | M10: 0 | N10: 0 | O10: 0
B11: Dự phòng | C11: 0 | D11: 0 | E11: 40 | F11: 50 | G11: 10 | H11: 0 | I11: 0 | J11: 0 | K11: 0 | L11: 0 | M11: 0 | N11: 0 | O11: 0
A15: TIẾN ĐỘ BÁN HÀNG
B16: Căn hộ chung cư | C16: 0 | D16: 0 | E16: 40 | F16: 40 | G16: 20 | H16: 0 | I16: 0 | J16: 0 | K16: 0 | L16: 0 | M16: 0 | N16: 0 | O16: 0
B17: Shop thương mại | C17: 0 | D17: 0 | E17: 40 | F17: 40 | G17: 20 | H17: 0 | I17: 0 | J17: 0 | K17: 0 | L17: 0 | M17: 0 | N17: 0 | O17: 0
A19: MA TRẬN THU TIỀN CĂN HỘ: hàng = năm bán (vintage), cột = năm thu
B20: Căn hộ bán năm 2026 | C20: 0 | D20: 0 | E20: 0 | F20: 0 | G20: 0 | H20: 0 | I20: 0 | J20: 0 | K20: 0 | L20: 0 | M20: 0 | N20: 0 | O20: 0
B21: Căn hộ bán năm 2027 | C21: 0 | D21: 0 | E21: 0 | F21: 0 | G21: 0 | H21: 0 | I21: 0 | J21: 0 | K21: 0 | L21: 0 | M21: 0 | N21: 0 | O21: 0
B22: Căn hộ bán năm 2028 | C22: 0 | D22: 0 | E22: 30 | F22: 65 | G22: 5 | H22: 0 | I22: 0 | J22: 0 | K22: 0 | L22: 0 | M22: 0 | N22: 0 | O22: 0
B23: Căn hộ bán năm 2029 | C23: 0 | D23: 0 | E23: 0 | F23: 95 | G23: 5 | H23: 0 | I23: 0 | J23: 0 | K23: 0 | L23: 0 | M23: 0 | N23: 0 | O23: 0
B24: Căn hộ bán năm 2030 | C24: 0 | D24: 0 | E24: 0 | F24: 0 | G24: 100 | H24: 0 | I24: 0 | J24: 0 | K24: 0 | L24: 0 | M24: 0 | N24: 0 | O24: 0
B25: Căn hộ bán năm 2031 | C25: 0 | D25: 0 | E25: 0 | F25: 0 | G25: 0 | H25: 0 | I25: 0 | J25: 0 | K25: 0 | L25: 0 | M25: 0 | N25: 0 | O25: 0
B26: Căn hộ bán năm 2032 | C26: 0 | D26: 0 | E26: 0 | F26: 0 | G26: 0 | H26: 0 | I26: 0 | J26: 0 | K26: 0 | L26: 0 | M26: 0 | N26: 0 | O26: 0
B27: Căn hộ bán năm 2033 | C27: 0 | D27: 0 | E27: 0 | F27: 0 | G27: 0 | H27: 0 | I27: 0 | J27: 0 | K27: 0 | L27: 0 | M27: 0 | N27: 0 | O27: 0
B28: Căn hộ bán năm 2034 | C28: 0 | D28: 0 | E28: 0 | F28: 0 | G28: 0 | H28: 0 | I28: 0 | J28: 0 | K28: 0 | L28: 0 | M28: 0 | N28: 0 | O28: 0
B29: Căn hộ bán năm 2035 | C29: 0 | D29: 0 | E29: 0 | F29: 0 | G29: 0 | H29: 0 | I29: 0 | J29: 0 | K29: 0 | L29: 0 | M29: 0 | N29: 0 | O29: 0
B30: Căn hộ bán năm 2036 | C30: 0 | D30: 0 | E30: 0 | F30: 0 | G30: 0 | H30: 0 | I30: 0 | J30: 0 | K30: 0 | L30: 0 | M30: 0 | N30: 0 | O30: 0
B31: Căn hộ bán năm 2037 | C31: 0 | D31: 0 | E31: 0 | F31: 0 | G31: 0 | H31: 0 | I31: 0 | J31: 0 | K31: 0 | L31: 0 | M31: 0 | N31: 0 | O31: 0
B32: Căn hộ bán năm 2038 | C32: 0 | D32: 0 | E32: 0 | F32: 0 | G32: 0 | H32: 0 | I32: 0 | J32: 0 | K32: 0 | L32: 0 | M32: 0 | N32: 0 | O32: 0
A35: MA TRẬN THU TIỀN SHOPHOUSE / THƯƠNG MẠI: hàng = năm bán, cột = năm thu
B36: Shop bán năm 2026 | C36: 0 | D36: 0 | E36: 0 | F36: 0 | G36: 0 | H36: 0 | I36: 0 | J36: 0 | K36: 0 | L36: 0 | M36: 0 | N36: 0 | O36: 0
B37: Shop bán năm 2027 | C37: 0 | D37: 0 | E37: 0 | F37: 0 | G37: 0 | H37: 0 | I37: 0 | J37: 0 | K37: 0 | L37: 0 | M37: 0 | N37: 0 | O37: 0
B38: Shop bán năm 2028 | C38: 0 | D38: 0 | E38: 30 | F38: 65 | G38: 5 | H38: 0 | I38: 0 | J38: 0 | K38: 0 | L38: 0 | M38: 0 | N38: 0 | O38: 0
B39: Shop bán năm 2029 | C39: 0 | D39: 0 | E39: 0 | F39: 95 | G39: 5 | H39: 0 | I39: 0 | J39: 0 | K39: 0 | L39: 0 | M39: 0 | N39: 0 | O39: 0
B40: Shop bán năm 2030 | C40: 0 | D40: 0 | E40: 0 | F40: 0 | G40: 100 | H40: 0 | I40: 0 | J40: 0 | K40: 0 | L40: 0 | M40: 0 | N40: 0 | O40: 0
B41: Shop bán năm 2031 | C41: 0 | D41: 0 | E41: 0 | F41: 0 | G41: 0 | H41: 0 | I41: 0 | J41: 0 | K41: 0 | L41: 0 | M41: 0 | N41: 0 | O41: 0
B42: Shop bán năm 2032 | C42: 0 | D42: 0 | E42: 0 | F42: 0 | G42: 0 | H42: 0 | I42: 0 | J42: 0 | K42: 0 | L42: 0 | M42: 0 | N42: 0 | O42: 0
B43: Shop bán năm 2033 | C43: 0 | D43: 0 | E43: 0 | F43: 0 | G43: 0 | H43: 0 | I43: 0 | J43: 0 | K43: 0 | L43: 0 | M43: 0 | N43: 0 | O43: 0
B44: Shop bán năm 2034 | C44: 0 | D44: 0 | E44: 0 | F44: 0 | G44: 0 | H44: 0 | I44: 0 | J44: 0 | K44: 0 | L44: 0 | M44: 0 | N44: 0 | O44: 0
B45: Shop bán năm 2035 | C45: 0 | D45: 0 | E45: 0 | F45: 0 | G45: 0 | H45: 0 | I45: 0 | J45: 0 | K45: 0 | L45: 0 | M45: 0 | N45: 0 | O45: 0
B46: Shop bán năm 2036 | C46: 0 | D46: 0 | E46: 0 | F46: 0 | G46: 0 | H46: 0 | I46: 0 | J46: 0 | K46: 0 | L46: 0 | M46: 0 | N46: 0 | O46: 0
B47: Shop bán năm 2037 | C47: 0 | D47: 0 | E47: 0 | F47: 0 | G47: 0 | H47: 0 | I47: 0 | J47: 0 | K47: 0 | L47: 0 | M47: 0 | N47: 0 | O47: 0
B48: Shop bán năm 2038 | C48: 0 | D48: 0 | E48: 0 | F48: 0 | G48: 0 | H48: 0 | I48: 0 | J48: 0 | K48: 0 | L48: 0 | M48: 0 | N48: 0 | O48: 0

Sheet QD425
A1: SUẤT VỐN ĐẦU TƯ — QĐ 425/QĐ-BXD 30/3/2026 (1.000 đ/m2 sàn, gồm VAT). Cột A: ngưỡng số tầng (tra MATCH); B..G: SVĐT theo 0–5 hầm; H..M: CP xây dựng; N..S: CP thiết bị.
A2: Bảng 1 — Nhà chung cư (mã 11110)
A3: 1 | B3: 9202 | C3: 10529 | D3: 11175 | E3: 11793 | F3: 13024 | G3: 14247 | H3: 7784 | I3: 8931 | J3: 9448 | K3: 10002 | L3: 11046 | M3: 12082 | N3: 432 | O3: 470 | P3: 530 | Q3: 593 | R3: 654 | S3: 716
A4: 6 | B4: 10316 | C4: 11033 | D4: 11772 | E4: 12637 | F4: 13561 | G4: 14527 | H4: 8082 | I4: 8643 | J4: 9223 | K4: 9900 | L4: 10623 | M4: 11380 | N4: 724 | O4: 774 | P4: 826 | Q4: 886 | R4: 951 | S4: 1019
A5: 8 | B5: 10629 | C5: 11122 | D5: 11671 | E5: 12344 | F5: 13091 | G5: 13896 | H5: 8458 | I5: 8850 | J5: 9286 | K5: 9822 | L5: 10417 | M5: 11057 | N5: 758 | O5: 793 | P5: 832 | Q5: 881 | R5: 934 | S5: 991
A6: 11 | B6: 11132 | C6: 11450 | D6: 11829 | E6: 12320 | F6: 12883 | G6: 13512 | H6: 9041 | I6: 9301 | J6: 9608 | K6: 10006 | L6: 10465 | M6: 10975 | N6: 758 | O6: 780 | P6: 806 | Q6: 839 | R6: 877 | S6: 920
A7: 16 | B7: 12410 | C7: 12590 | D7: 12830 | E7: 13168 | F7: 13576 | G7: 14048 | H7: 9521 | I7: 9660 | J7: 9843 | K7: 10102 | L7: 10416 | M7: 10778 | N7: 1034 | O7: 1049 | P7: 1069 | Q7: 1096 | R7: 1131 | S7: 1170
A8: 21 | B8: 13818 | C8: 13923 | D8: 14083 | E8: 14335 | F8: 14655 | G8: 15037 | H8: 10611 | I8: 10691 | J8: 10814 | K8: 11008 | L8: 11255 | M8: 11548 | N8: 1367 | O8: 1377 | P8: 1393 | Q8: 1418 | R8: 1450 | S8: 1488
A9: 25 | B9: 14508 | C9: 14570 | D9: 14679 | E9: 14868 | F9: 15116 | G9: 15420 | H9: 11144 | I9: 11191 | J9: 11274 | K9: 11420 | L9: 11610 | M9: 11843 | N9: 1436 | O9: 1442 | P9: 1453 | Q9: 1472 | R9: 1496 | S9: 1526
A10: 31 | B10: 15849 | C10: 15890 | D10: 15978 | E10: 16138 | F10: 16356 | G10: 16625 | H10: 12000 | I10: 12031 | J10: 12096 | K10: 12217 | L10: 12382 | M10: 12587 | N10: 1700 | O10: 1705 | P10: 1714 | Q10: 1731 | R10: 1754 | S10: 1783
A11: 36 | B11: 17024 | C11: 17050 | D11: 17117 | E11: 17255 | F11: 17445 | G11: 17688 | H11: 12791 | I11: 12810 | J11: 12861 | K11: 12965 | L11: 13108 | M11: 13289 | N11: 1907 | O11: 1910 | P11: 1917 | Q11: 1933 | R11: 1954 | S11: 1982
A12: 41 | B12: 18197 | C12: 18216 | D12: 18276 | E12: 18401 | F12: 18577 | G12: 18803 | H12: 13581 | I12: 13596 | J12: 13641 | K12: 13733 | L12: 13866 | M12: 14035 | N12: 2113 | O12: 2116 | P12: 2122 | Q12: 2137 | R12: 2158 | S12: 2184
A13: 46 | B13: 19370 | C13: 19381 | D13: 19430 | E13: 19541 | F13: 19702 | G13: 19912 | H13: 14373 | I13: 14381 | J13: 14418 | K13: 14499 | L13: 14620 | M13: 14774 | N13: 2320 | O13: 2321 | P13: 2328 | Q13: 2341 | R13: 2360 | S13: 2386
A16: Bảng 26 — Công trình đa năng (hỗn hợp) (mã 11260)
A17: 1 | B17: 9246 | C17: 10263 | D17: 11468 | E17: 12159 | F17: 13389 | G17: 14612 | H17: 7888 | I17: 8732 | J17: 9754 | K17: 10524 | L17: 11586 | M17: 12645 | N17: 517 | O17: 598 | P17: 671 | Q17: 747 | R17: 822 | S17: 897
A18: 6 | B18: 10851 | C18: 11531 | D18: 12243 | E18: 13090 | F18: 14001 | G18: 14961 | H18: 8673 | I18: 9215 | J18: 9783 | K18: 10460 | L18: 11189 | M18: 11957 | N18: 942 | O18: 1001 | P18: 1063 | Q18: 1136 | R18: 1215 | S18: 1298
A19: 8 | B19: 11182 | C19: 11647 | D19: 12172 | E19: 12830 | F19: 13565 | G19: 13565 | H19: 9067 | I19: 9444 | J19: 9870 | K19: 10404 | L19: 11000 | M19: 11000 | N19: 976 | O19: 1017 | P19: 1063 | Q19: 1121 | R19: 1184 | S19: 1184
A20: 11 | B20: 11696 | C20: 11993 | D20: 12353 | E20: 12828 | F20: 13381 | G20: 14001 | H20: 9700 | I20: 9946 | J20: 10245 | K20: 10638 | L20: 11097 | M20: 11610 | N20: 1332 | O20: 1367 | P20: 1407 | Q20: 1461 | R20: 1525 | S20: 1595
A21: 16 | B21: 13031 | C21: 13191 | D21: 13413 | E21: 13736 | F21: 14134 | G21: 14597 | H21: 10215 | I21: 10341 | J21: 10513 | K21: 10768 | L21: 11080 | M21: 11443 | N21: 1585 | O21: 1604 | P21: 1632 | Q21: 1671 | R21: 1720 | S21: 1776
A22: 21 | B22: 14516 | C22: 14601 | D22: 14744 | E22: 14982 | F22: 15291 | G22: 15663 | H22: 11375 | I22: 11441 | J22: 11554 | K22: 11740 | L22: 11982 | M22: 12273 | N22: 1769 | O22: 1780 | P22: 1797 | Q22: 1826 | R22: 1864 | S22: 1909
A23: 25 | B23: 15240 | C23: 15285 | D23: 15380 | E23: 15556 | F23: 15794 | G23: 16087 | H23: 11954 | I23: 11990 | J23: 12064 | K23: 12202 | L23: 12388 | M23: 12619 | N23: 1860 | O23: 1866 | P23: 1878 | Q23: 1900 | R23: 1929 | S23: 1964
A24: 31 | B24: 16656 | C24: 16682 | D24: 16754 | E24: 16902 | F24: 17109 | G24: 17369 | H24: 12863 | I24: 12884 | J24: 12939 | K24: 13054 | L24: 13213 | M24: 13414 | N24: 2206 | O24: 2209 | P24: 2218 | Q24: 2238 | R24: 2266 | S24: 2300
A25: 36 | B25: 17881 | C25: 17892 | D25: 17946 | E25: 18071 | F25: 18251 | G25: 18484 | H25: 13721 | I25: 13728 | J25: 13770 | K25: 13866 | L25: 14004 | M25: 14183 | N25: 2470 | O25: 2471 | P25: 2479 | Q25: 2496 | R25: 2521 | S25: 2553
A26: 41 | B26: 19116 | C26: 19122 | D26: 19170 | E26: 19284 | F26: 19453 | G26: 19672 | H26: 14564 | I26: 14568 | J26: 14605 | K26: 14692 | L26: 14820 | M26: 14987 | N26: 2734 | O26: 2734 | P26: 2741 | Q26: 2758 | R26: 2781 | S26: 2813
A27: 46 | B27: 20340 | C27: 20342 | D27: 20385 | E27: 20492 | F27: 20650 | G27: 20858 | H27: 15420 | I27: 15423 | J27: 15454 | K27: 15535 | L27: 15656 | M27: 15812 | N27: 3010 | O27: 3010 | P27: 3016 | Q27: 3032 | R27: 3055 | S27: 3086

Sheet FS
B1: FS — MÔ HÌNH DÒNG TIỀN HỢP NHẤT · Bán hàng + Cho thuê (công thức trực tiếp · triệu đồng)
B2: Khoản mục | C2: Tổng / Giá trị | D2: 46023 | E2: 46388 | F2: 46753 | G2: 47119 | H2: 47484 | I2: 47849 | J2: 48214 | K2: 48580 | L2: 48945 | M2: 49310 | N2: 49675 | O2: 50041 | P2: 50406 | Q2: 50771 | R2: 51136 | S2: 51502 | T2: 51867 | U2: 52232 | V2: 52597 | W2: 52963 | X2: 53328 | Y2: 53693 | Z2: 54058 | AA2: 54424 | AB2: 54789 | AC2: 55154 | AD2: 55519 | AE2: 55885 | AF2: 56250 | AG2: 56615 | AH2: 56980 | AI2: 57346 | AJ2: 57711 | AK2: 58076 | AL2: 58441 | AM2: 58807 | AN2: 59172 | AO2: 59537 | AP2: 59902 | AQ2: 60268 | AR2: 60633 | AS2: 60998 | AT2: 61363 | AU2: 61729 | AV2: 62094 | AW2: 62459 | AX2: 62824 | AY2: 63190 | AZ2: 63555 | BA2: 63920 | BB2: 64285 | BC2: 64651 | BD2: 65016 | BE2: 65381 | BF2: 65746 | BG2: 66112 | BH2: 66477 | BI2: 66842 | BJ2: 67207 | BK2: 67573
B3: KẾT QUẢ ĐẦU TƯ
B4: NPV chủ đầu tư @ r%/năm | C4: =XNPV(INPUT!$C$4/100,WEB_CF!$M$2:$M$14,WEB_CF!$O$2:$O$14)*1000 -> -119394.12
B5: IRR chủ đầu tư (levered) | C5: =XIRR(WEB_CF!$M$2:$M$14,WEB_CF!$O$2:$O$14) -> 0.0029697567
B6: IRR dự án — TMĐT (unlevered) | C6: =XIRR(WEB_CF!$L$2:$L$14,WEB_CF!$O$2:$O$14) -> 0.0023980528
B7: NPV bán riêng | C7: =WEB_RESULT!$B$13*1000 -> -118893.35
B8: Lợi nhuận sau thuế hợp nhất | C8: =$C$154-$C$155 -> 1.2888964e+10
B9: Tổng mức đầu tư (gồm lãi vay) | C9: =$C$115+$C$144 -> 1.231766e+12
B10: A · DÒNG TIỀN HỢP NHẤT THEO NĂM (triệu đồng)
B11: Thực thu Bán hàng (gồm VAT) (+) | C11: =SUM(D11:BK11) -> 1481705816250 | D11: =SUM(D37:D49)+IF(AND(D34>0,SUM(TIENDO!$C$20:$O$20)<0.0001),D34,0)+IF(AND(D35>0,SUM(TIENDO!$C$36:$O$36)<0.0001),D35,0) -> 0 | E11: =SUM(E37:E49)+IF(AND(E34>0,SUM(TIENDO!$C$21:$O$21)<0.0001),E34,0)+IF(AND(E35>0,SUM(TIENDO!$C$37:$O$37)<0.0001),E35,0) -> 0 | F11: =SUM(F37:F49)+IF(AND(F34>0,SUM(TIENDO!$C$22:$O$22)<0.0001),F34,0)+IF(AND(F35>0,SUM(TIENDO!$C$38:$O$38)<0.0001),F35,0) -> 170883900000 | G11: =SUM(G37:G49)+IF(AND(G34>0,SUM(TIENDO!$C$23:$O$23)<0.0001),G34,0)+IF(AND(G35>0,SUM(TIENDO!$C$39:$O$39)<0.0001),G35,0) -> 938437417500 | H11: =SUM(H37:H49)+IF(AND(H34>0,SUM(TIENDO!$C$24:$O$24)<0.0001),H34,0)+IF(AND(H35>0,SUM(TIENDO!$C$40:$O$40)<0.0001),H35,0) -> 372384498750 | I11: =SUM(I37:I49)+IF(AND(I34>0,SUM(TIENDO!$C$25:$O$25)<0.0001),I34,0)+IF(AND(I35>0,SUM(TIENDO!$C$41:$O$41)<0.0001),I35,0) -> 0 | J11: =SUM(J37:J49)+IF(AND(J34>0,SUM(TIENDO!$C$26:$O$26)<0.0001),J34,0)+IF(AND(J35>0,SUM(TIENDO!$C$42:$O$42)<0.0001),J35,0) -> 0 | K11: =SUM(K37:K49)+IF(AND(K34>0,SUM(TIENDO!$C$27:$O$27)<0.0001),K34,0)+IF(AND(K35>0,SUM(TIENDO!$C$43:$O$43)<0.0001),K35,0) -> 0 | L11: =SUM(L37:L49)+IF(AND(L34>0,SUM(TIENDO!$C$28:$O$28)<0.0001),L34,0)+IF(AND(L35>0,SUM(TIENDO!$C$44:$O$44)<0.0001),L35,0) -> 0 | M11: =SUM(M37:M49)+IF(AND(M34>0,SUM(TIENDO!$C$29:$O$29)<0.0001),M34,0)+IF(AND(M35>0,SUM(TIENDO!$C$45:$O$45)<0.0001),M35,0) -> 0 | N11: =SUM(N37:N49)+IF(AND(N34>0,SUM(TIENDO!$C$30:$O$30)<0.0001),N34,0)+IF(AND(N35>0,SUM(TIENDO!$C$46:$O$46)<0.0001),N35,0) -> 0 | O11: =SUM(O37:O49)+IF(AND(O34>0,SUM(TIENDO!$C$31:$O$31)<0.0001),O34,0)+IF(AND(O35>0,SUM(TIENDO!$C$47:$O$47)<0.0001),O35,0) -> 0 | P11: =SUM(P37:P49)+IF(AND(P34>0,SUM(TIENDO!$C$32:$O$32)<0.0001),P34,0)+IF(AND(P35>0,SUM(TIENDO!$C$48:$O$48)<0.0001),P35,0) -> 0 | Q11: 0 | R11: 0 | S11: 0 | T11: 0 | U11: 0 | V11: 0 | W11: 0 | X11: 0 | Y11: 0 | Z11: 0 | AA11: 0 | AB11: 0 | AC11: 0 | AD11: 0 | AE11: 0 | AF11: 0 | AG11: 0 | AH11: 0 | AI11: 0 | AJ11: 0 | AK11: 0 | AL11: 0 | AM11: 0 | AN11: 0 | AO11: 0 | AP11: 0 | AQ11: 0 | AR11: 0 | AS11: 0 | AT11: 0 | AU11: 0 | AV11: 0 | AW11: 0 | AX11: 0 | AY11: 0 | AZ11: 0 | BA11: 0 | BB11: 0 | BC11: 0 | BD11: 0 | BE11: 0 | BF11: 0 | BG11: 0 | BH11: 0 | BI11: 0 | BJ11: 0 | BK11: 0
B12: Doanh thu Cho thuê (+) | C12: =SUM(D12:BK12) -> 0 | D12: =D56+D57+D58 -> 0 | E12: =E56+E57+E58 -> 0 | F12: =F56+F57+F58 -> 0 | G12: =G56+G57+G58 -> 0 | H12: =H56+H57+H58 -> 0 | I12: =I56+I57+I58 -> 0 | J12: =J56+J57+J58 -> 0 | K12: =K56+K57+K58 -> 0 | ... BK12: =BK56+BK57+BK58 -> 0
B13: (−) Chi đầu tư Bán hàng (tổng) | C13: =SUM(D13:BK13) -> 1192835671250 | D13: =D14+D15+D16+D17 -> 200000000000 | E13: =E14+E15+E16+E17 -> 215000000000 | F13: =F14+F15+F16+F17 -> 478456668500 | G13: =G14+G15+G16+G17 -> 236882835625 | H13: =H14+H15+H16+H17 -> 62496167125 | I13: =I14+I15+I16+I17 -> 0 | J13: =J14+J15+J16+J17 -> 0 | K13: =K14+K15+K16+K17 -> 0 | ... P13: =P14+P15+P16+P17 -> 0 | Q13: 0 | R13: 0 | S13: 0 | T13: 0 | U13: 0 | V13: 0 | W13: 0 | X13: 0 | Y13: 0 | Z13: 0 | AA13: 0 | AB13: 0 | AC13: 0 | AD13: 0 | AE13: 0 | AF13: 0 | AG13: 0 | AH13: 0 | AI13: 0 | AJ13: 0 | AK13: 0 | AL13: 0 | AM13: 0 | AN13: 0 | AO13: 0 | AP13: 0 | AQ13: 0 | AR13: 0 | AS13: 0 | AT13: 0 | AU13: 0 | AV13: 0 | AW13: 0 | AX13: 0 | AY13: 0 | AZ13: 0 | BA13: 0 | BB13: 0 | BC13: 0 | BD13: 0 | BE13: 0 | BF13: 0 | BG13: 0 | BH13: 0 | BI13: 0 | BJ13: 0 | BK13: 0
B14: ↳ Đất (chuyển nhượng + đền bù) | C14: =SUM(D14:BK14) -> 400000000000 | D14: =$C$124*(1-$C$106)*TIENDO!C3/100+$C$125*(1-$C$106)*TIENDO!C4/100 -> 200000000000 | E14: =$C$124*(1-$C$106)*TIENDO!D3/100+$C$125*(1-$C$106)*TIENDO!D4/100 -> 200000000000 | F14: =$C$124*(1-$C$106)*TIENDO!E3/100+$C$125*(1-$C$106)*TIENDO!E4/100 -> 0 | G14: =$C$124*(1-$C$106)*TIENDO!F3/100+$C$125*(1-$C$106)*TIENDO!F4/100 -> 0 | H14: =$C$124*(1-$C$106)*TIENDO!G3/100+$C$125*(1-$C$106)*TIENDO!G4/100 -> 0 | I14: =$C$124*(1-$C$106)*TIENDO!H3/100+$C$125*(1-$C$106)*TIENDO!H4/100 -> 0 | J14: =$C$124*(1-$C$106)*TIENDO!I3/100+$C$125*(1-$C$106)*TIENDO!I4/100 -> 0 | K14: =$C$124*(1-$C$106)*TIENDO!J3/100+$C$125*(1-$C$106)*TIENDO!J4/100 -> 0 | ... P14: =$C$124*(1-$C$106)*TIENDO!O3/100+$C$125*(1-$C$106)*TIENDO!O4/100 -> 0 | Q14: 0 | R14: 0 | S14: 0 | T14: 0 | U14: 0 | V14: 0 | W14: 0 | X14: 0 | Y14: 0 | Z14: 0 | AA14: 0 | AB14: 0 | AC14: 0 | AD14: 0 | AE14: 0 | AF14: 0 | AG14: 0 | AH14: 0 | AI14: 0 | AJ14: 0 | AK14: 0 | AL14: 0 | AM14: 0 | AN14: 0 | AO14: 0 | AP14: 0 | AQ14: 0 | AR14: 0 | AS14: 0 | AT14: 0 | AU14: 0 | AV14: 0 | AW14: 0 | AX14: 0 | AY14: 0 | AZ14: 0 | BA14: 0 | BB14: 0 | BC14: 0 | BD14: 0 | BE14: 0 | BF14: 0 | BG14: 0 | BH14: 0 | BI14: 0 | BJ14: 0 | BK14: 0
B15: ↳ Tiền sử dụng đất | C15: =SUM(D15:BK15) -> 289070000000 | D15: =$C$126*(1-$C$106)*TIENDO!C5/100 -> 0 | E15: =$C$126*(1-$C$106)*TIENDO!D5/100 -> 0 | F15: =$C$126*(1-$C$106)*TIENDO!E5/100 -> 289070000000 | G15: =$C$126*(1-$C$106)*TIENDO!F5/100 -> 0 | H15: =$C$126*(1-$C$106)*TIENDO!G5/100 -> 0 | I15: =$C$126*(1-$C$106)*TIENDO!H5/100 -> 0 | J15: =$C$126*(1-$C$106)*TIENDO!I5/100 -> 0 | K15: =$C$126*(1-$C$106)*TIENDO!J5/100 -> 0 | ... P15: =$C$126*(1-$C$106)*TIENDO!O5/100 -> 0 | Q15: 0 | R15: 0 | S15: 0 | T15: 0 | U15: 0 | V15: 0 | W15: 0 | X15: 0 | Y15: 0 | Z15: 0 | AA15: 0 | AB15: 0 | AC15: 0 | AD15: 0 | AE15: 0 | AF15: 0 | AG15: 0 | AH15: 0 | AI15: 0 | AJ15: 0 | AK15: 0 | AL15: 0 | AM15: 0 | AN15: 0 | AO15: 0 | AP15: 0 | AQ15: 0 | AR15: 0 | AS15: 0 | AT15: 0 | AU15: 0 | AV15: 0 | AW15: 0 | AX15: 0 | AY15: 0 | AZ15: 0 | BA15: 0 | BB15: 0 | BC15: 0 | BD15: 0 | BE15: 0 | BF15: 0 | BG15: 0 | BH15: 0 | BI15: 0 | BJ15: 0 | BK15: 0
B16: ↳ Chi phí pháp lý | C16: =SUM(D16:BK16) -> 60000000000 | D16: =$C$127*(1-$C$106)*TIENDO!C6/100 -> 0 | E16: =$C$127*(1-$C$106)*TIENDO!D6/100 -> 15000000000 | F16: =$C$127*(1-$C$106)*TIENDO!E6/100 -> 15000000000 | G16: =$C$127*(1-$C$106)*TIENDO!F6/100 -> 15000000000 | H16: =$C$127*(1-$C$106)*TIENDO!G6/100 -> 15000000000 | I16: =$C$127*(1-$C$106)*TIENDO!H6/100 -> 0 | J16: =$C$127*(1-$C$106)*TIENDO!I6/100 -> 0 | K16: =$C$127*(1-$C$106)*TIENDO!J6/100 -> 0 | ... P16: =$C$127*(1-$C$106)*TIENDO!O6/100 -> 0 | Q16: 0 | R16: 0 | S16: 0 | T16: 0 | U16: 0 | V16: 0 | W16: 0 | X16: 0 | Y16: 0 | Z16: 0 | AA16: 0 | AB16: 0 | AC16: 0 | AD16: 0 | AE16: 0 | AF16: 0 | AG16: 0 | AH16: 0 | AI16: 0 | AJ16: 0 | AK16: 0 | AL16: 0 | AM16: 0 | AN16: 0 | AO16: 0 | AP16: 0 | AQ16: 0 | AR16: 0 | AS16: 0 | AT16: 0 | AU16: 0 | AV16: 0 | AW16: 0 | AX16: 0 | AY16: 0 | AZ16: 0 | BA16: 0 | BB16: 0 | BC16: 0 | BD16: 0 | BE16: 0 | BF16: 0 | BG16: 0 | BH16: 0 | BI16: 0 | BJ16: 0 | BK16: 0
B17: ↳ CPXD all-in (hạ tầng+XD+tư vấn+dự phòng) | C17: =SUM(D17:BK17) -> 443765671250 | D17: =$C$128*(1-$C$106)*TIENDO!C7/100+$C$129*1*TIENDO!C8/100+$C$131*(1-$C$105)*TIENDO!C10/100+$C$132*(1-$C$105)*TIENDO!C11/100 -> 0 | E17: =$C$128*(1-$C$106)*TIENDO!D7/100+$C$129*1*TIENDO!D8/100+$C$131*(1-$C$105)*TIENDO!D10/100+$C$132*(1-$C$105)*TIENDO!D11/100 -> 0 | F17: =$C$128*(1-$C$106)*TIENDO!E7/100+$C$129*1*TIENDO!E8/100+$C$131*(1-$C$105)*TIENDO!E10/100+$C$132*(1-$C$105)*TIENDO!E11/100 -> 174386668500 | G17: =$C$128*(1-$C$106)*TIENDO!F7/100+$C$129*1*TIENDO!F8/100+$C$131*(1-$C$105)*TIENDO!F10/100+$C$132*(1-$C$105)*TIENDO!F11/100 -> 221882835625 | H17: =$C$128*(1-$C$106)*TIENDO!G7/100+$C$129*1*TIENDO!G8/100+$C$131*(1-$C$105)*TIENDO!G10/100+$C$132*(1-$C$105)*TIENDO!G11/100 -> 47496167125 | I17: =$C$128*(1-$C$106)*TIENDO!H7/100+$C$129*1*TIENDO!H8/100+$C$131*(1-$C$105)*TIENDO!H10/100+$C$132*(1-$C$105)*TIENDO!H11/100 -> 0 | J17: =$C$128*(1-$C$106)*TIENDO!I7/100+$C$129*1*TIENDO!I8/100+$C$131*(1-$C$105)*TIENDO!I10/100+$C$132*(1-$C$105)*TIENDO!I11/100 -> 0 | K17: =$C$128*(1-$C$106)*TIENDO!J7/100+$C$129*1*TIENDO!J8/100+$C$131*(1-$C$105)*TIENDO!J10/100+$C$132*(1-$C$105)*TIENDO!J11/100 -> 0 | ... P17: =$C$128*(1-$C$106)*TIENDO!O7/100+$C$129*1*TIENDO!O8/100+$C$131*(1-$C$105)*TIENDO!O10/100+$C$132*(1-$C$105)*TIENDO!O11/100 -> 0 | Q17: 0 | R17: 0 | S17: 0 | T17: 0 | U17: 0 | V17: 0 | W17: 0 | X17: 0 | Y17: 0 | Z17: 0 | AA17: 0 | AB17: 0 | AC17: 0 | AD17: 0 | AE17: 0 | AF17: 0 | AG17: 0 | AH17: 0 | AI17: 0 | AJ17: 0 | AK17: 0 | AL17: 0 | AM17: 0 | AN17: 0 | AO17: 0 | AP17: 0 | AQ17: 0 | AR17: 0 | AS17: 0 | AT17: 0 | AU17: 0 | AV17: 0 | AW17: 0 | AX17: 0 | AY17: 0 | AZ17: 0 | BA17: 0 | BB17: 0 | BC17: 0 | BD17: 0 | BE17: 0 | BF17: 0 | BG17: 0 | BH17: 0 | BI17: 0 | BJ17: 0 | BK17: 0
B18: (−) Chi phí hoạt động Bán hàng | C18: =SUM(D18:BK18) -> 2.5188999e+11 | D18: =D36*(INPUT!$C$118+INPUT!$C$119+INPUT!$C$120+INPUT!$C$121+INPUT!$C$123+INPUT!$C$124)/100+D11*INPUT!$C$122/100 -> 0 | E18: =E36*(INPUT!$C$118+INPUT!$C$119+INPUT!$C$120+INPUT!$C$121+INPUT!$C$123+INPUT!$C$124)/100+E11*INPUT!$C$122/100 -> 0 | F18: =F36*(INPUT!$C$118+INPUT!$C$119+INPUT!$C$120+INPUT!$C$121+INPUT!$C$123+INPUT!$C$124)/100+F11*INPUT!$C$122/100 -> 96036751800 | G18: =G36*(INPUT!$C$118+INPUT!$C$119+INPUT!$C$120+INPUT!$C$121+INPUT!$C$123+INPUT!$C$124)/100+G11*INPUT!$C$122/100 -> 102356608035 | H18: =H36*(INPUT!$C$118+INPUT!$C$119+INPUT!$C$120+INPUT!$C$121+INPUT!$C$123+INPUT!$C$124)/100+H11*INPUT!$C$122/100 -> 5.3496629e+10 | I18: =I36*(INPUT!$C$118+INPUT!$C$119+INPUT!$C$120+INPUT!$C$121+INPUT!$C$123+INPUT!$C$124)/100+I11*INPUT!$C$122/100 -> 0 | J18: =J36*(INPUT!$C$118+INPUT!$C$119+INPUT!$C$120+INPUT!$C$121+INPUT!$C$123+INPUT!$C$124)/100+J11*INPUT!$C$122/100 -> 0 | K18: =K36*(INPUT!$C$118+INPUT!$C$119+INPUT!$C$120+INPUT!$C$121+INPUT!$C$123+INPUT!$C$124)/100+K11*INPUT!$C$122/100 -> 0 | ... BK18: =BK36*(INPUT!$C$118+INPUT!$C$119+INPUT!$C$120+INPUT!$C$121+INPUT!$C$123+INPUT!$C$124)/100+BK11*INPUT!$C$122/100 -> 0
B19: (−) Thuế VAT phải nộp | C19: =SUM(D19:BK19) -> 4.5180014e+10 | D19: =MAX((IF($C$136>0,$C$137*D11/$C$136,0))-((D17+D18)*INPUT!$C$6/(100+INPUT!$C$6))-0,0) -> 0 | E19: =MAX((IF($C$136>0,$C$137*D11/$C$136,0)+IF($C$136>0,$C$137*E11/$C$136,0))-((D17+D18)*INPUT!$C$6/(100+INPUT!$C$6)+(E17+E18)*INPUT!$C$6/(100+INPUT!$C$6))-SUM(D19:D19),0) -> 0 | F19: =MAX((IF($C$136>0,$C$137*D11/$C$136,0)+IF($C$136>0,$C$137*E11/$C$136,0)+IF($C$136>0,$C$137*F11/$C$136,0))-((D17+D18)*INPUT!$C$6/(100+INPUT!$C$6)+(E17+E18)*INPUT!$C$6/(100+INPUT!$C$6)+(F17+F18)*INPUT!$C$6/(100+INPUT!$C$6))-SUM(D19:E19),0) -> 0 | G19: =MAX((IF($C$136>0,$C$137*D11/$C$136,0)+IF($C$136>0,$C$137*E11/$C$136,0)+IF($C$136>0,$C$137*F11/$C$136,0)+IF($C$136>0,$C$137*G11/$C$136,0))-((D17+D18)*INPUT!$C$6/(100+INPUT!$C$6)+(E17+E18)*INPUT!$C$6/(100+INPUT!$C$6)+(F17+F18)*INPUT!$C$6/(100+INPUT!$C$6)+(G17+G18)*INPUT!$C$6/(100+INPUT!$C$6))-SUM(D19:F19),0) -> 2.7112541e+10 | H19: =MAX((IF($C$136>0,$C$137*D11/$C$136,0)+IF($C$136>0,$C$137*E11/$C$136,0)+IF($C$136>0,$C$137*F11/$C$136,0)+IF($C$136>0,$C$137*G11/$C$136,0)+IF($C$136>0,$C$137*H11/$C$136,0))-((D17+D18)*INPUT!$C$6/(100+INPUT!$C$6)+(E17+E18)*INPUT!$C$6/(100+INPUT!$C$6)+(F17+F18)*INPUT!$C$6/(100+INPUT!$C$6)+(G17+G18)*INPUT!$C$6/(100+INPUT!$C$6)+(H17+H18)*INPUT!$C$6/(100+INPUT!$C$6))-SUM(D19:G19),0) -> 1.8067473e+10 | I19: =MAX((IF($C$136>0,$C$137*D11/$C$136,0)+IF($C$136>0,$C$137*E11/$C$136,0)+IF($C$136>0,$C$137*F11/$C$136,0)+IF($C$136>0,$C$137*G11/$C$136,0)+IF($C$136>0,$C$137*H11/$C$136,0)+IF($C$136>0,$C$137*I11/$C$136,0))-((D17+D18)*INPUT!$C$6/(100+INPUT!$C$6)+(E17+E18)*INPUT!$C$6/(100+INPUT!$C$6)+(F17+F18)*INPUT!$C$6/(100+INPUT!$C$6)+(G17+G18)*INPUT!$C$6/(100+INPUT!$C$6)+(H17+H18)*INPUT!$C$6/(100+INPUT!$C$6)+(I17+I18)*INPUT!$C$6/(100+INPUT!$C$6))-SUM(D19:H19),0) -> 0 | J19: =MAX((IF($C$136>0,$C$137*D11/$C$136,0)+IF($C$136>0,$C$137*E11/$C$136,0)+IF($C$136>0,$C$137*F11/$C$136,0)+IF($C$136>0,$C$137*G11/$C$136,0)+IF($C$136>0,$C$137*H11/$C$136,0)+IF($C$136>0,$C$137*I11/$C$136,0)+IF($C$136>0,$C$137*J11/$C$136,0))-((D17+D18)*INPUT!$C$6/(100+INPUT!$C$6)+(E17+E18)*INPUT!$C$6/(100+INPUT!$C$6)+(F17+F18)*INPUT!$C$6/(100+INPUT!$C$6)+(G17+G18)*INPUT!$C$6/(100+INPUT!$C$6)+(H17+H18)*INPUT!$C$6/(100+INPUT!$C$6)+(I17+I18)*INPUT!$C$6/(100+INPUT!$C$6)+(J17+J18)*INPUT!$C$6/(100+INPUT!$C$6))-SUM(D19:I19),0) -> 0 | K19: =MAX((IF($C$136>0,$C$137*D11/$C$136,0)+IF($C$136>0,$C$137*E11/$C$136,0)+IF($C$136>0,$C$137*F11/$C$136,0)+IF($C$136>0,$C$137*G11/$C$136,0)+IF($C$136>0,$C$137*H11/$C$136,0)+IF($C$136>0,$C$137*I11/$C$136,0)+IF($C$136>0,$C$137*J11/$C$136,0)+IF($C$136>0,$C$137*K11/$C$136,0))-((D17+D18)*INPUT!$C$6/(100+INPUT!$C$6)+(E17+E18)*INPUT!$C$6/(100+INPUT!$C$6)+(F17+F18)*INPUT!$C$6/(100+INPUT!$C$6)+(G17+G18)*INPUT!$C$6/(100+INPUT!$C$6)+(H17+H18)*INPUT!$C$6/(100+INPUT!$C$6)+(I17+I18)*INPUT!$C$6/(100+INPUT!$C$6)+(J17+J18)*INPUT!$C$6/(100+INPUT!$C$6)+(K17+K18)*INPUT!$C$6/(100+INPUT!$C$6))-SUM(D19:J19),0) -> 0 | L19: =MAX((IF($C$136>0,$C$137*D11/$C$136,0)+IF($C$136>0,$C$137*E11/$C$136,0)+IF($C$136>0,$C$137*F11/$C$136,0)+IF($C$136>0,$C$137*G11/$C$136,0)+IF($C$136>0,$C$137*H11/$C$136,0)+IF($C$136>0,$C$137*I11/$C$136,0)+IF($C$136>0,$C$137*J11/$C$136,0)+IF($C$136>0,$C$137*K11/$C$136,0)+IF($C$136>0,$C$137*L11/$C$136,0))-((D17+D18)*INPUT!$C$6/(100+INPUT!$C$6)+(E17+E18)*INPUT!$C$6/(100+INPUT!$C$6)+(F17+F18)*INPUT!$C$6/(100+INPUT!$C$6)+(G17+G18)*INPUT!$C$6/(100+INPUT!$C$6)+(H17+H18)*INPUT!$C$6/(100+INPUT!$C$6)+(I17+I18)*INPUT!$C$6/(100+INPUT!$C$6)+(J17+J18)*INPUT!$C$6/(100+INPUT!$C$6)+(K17+K18)*INPUT!$C$6/(100+INPUT!$C$6)+(L17+L18)*INPUT!$C$6/(100+INPUT!$C$6))-SUM(D19:K19),0) -> 0 | M19: =MAX((IF($C$136>0,$C$137*D11/$C$136,0)+IF($C$136>0,$C$137*E11/$C$136,0)+IF($C$136>0,$C$137*F11/$C$136,0)+IF($C$136>0,$C$137*G11/$C$136,0)+IF($C$136>0,$C$137*H11/$C$136,0)+IF($C$136>0,$C$137*I11/$C$136,0)+IF($C$136>0,$C$137*J11/$C$136,0)+IF($C$136>0,$C$137*K11/$C$136,0)+IF($C$136>0,$C$137*L11/$C$136,0)+IF($C$136>0,$C$137*M11/$C$136,0))-((D17+D18)*INPUT!$C$6/(100+INPUT!$C$6)+(E17+E18)*INPUT!$C$6/(100+INPUT!$C$6)+(F17+F18)*INPUT!$C$6/(100+INPUT!$C$6)+(G17+G18)*INPUT!$C$6/(100+INPUT!$C$6)+(H17+H18)*INPUT!$C$6/(100+INPUT!$C$6)+(I17+I18)*INPUT!$C$6/(100+INPUT!$C$6)+(J17+J18)*INPUT!$C$6/(100+INPUT!$C$6)+(K17+K18)*INPUT!$C$6/(100+INPUT!$C$6)+(L17+L18)*INPUT!$C$6/(100+INPUT!$C$6)+(M17+M18)*INPUT!$C$6/(100+INPUT!$C$6))-SUM(D19:L19),0) -> 0 | N19: =MAX((IF($C$136>0,$C$137*D11/$C$136,0)+IF($C$136>0,$C$137*E11/$C$136,0)+IF($C$136>0,$C$137*F11/$C$136,0)+IF($C$136>0,$C$137*G11/$C$136,0)+IF($C$136>0,$C$137*H11/$C$136,0)+IF($C$136>0,$C$137*I11/$C$136,0)+IF($C$136>0,$C$137*J11/$C$136,0)+IF($C$136>0,$C$137*K11/$C$136,0)+IF($C$136>0,$C$137*L11/$C$136,0)+IF($C$136>0,$C$137*M11/$C$136,0)+IF($C$136>0,$C$137*N11/$C$136,0))-((D17+D18)*INPUT!$C$6/(100+INPUT!$C$6)+(E17+E18)*INPUT!$C$6/(100+INPUT!$C$6)+(F17+F18)*INPUT!$C$6/(100+INPUT!$C$6)+(G17+G18)*INPUT!$C$6/(100+INPUT!$C$6)+(H17+H18)*INPUT!$C$6/(100+INPUT!$C$6)+(I17+I18)*INPUT!$C$6/(100+INPUT!$C$6)+(J17+J18)*INPUT!$C$6/(100+INPUT!$C$6)+(K17+K18)*INPUT!$C$6/(100+INPUT!$C$6)+(L17+L18)*INPUT!$C$6/(100+INPUT!$C$6)+(M17+M18)*INPUT!$C$6/(100+INPUT!$C$6)+(N17+N18)*INPUT!$C$6/(100+INPUT!$C$6))-SUM(D19:M19),0) -> 0 | O19: =MAX((IF($C$136>0,$C$137*D11/$C$136,0)+IF($C$136>0,$C$137*E11/$C$136,0)+IF($C$136>0,$C$137*F11/$C$136,0)+IF($C$136>0,$C$137*G11/$C$136,0)+IF($C$136>0,$C$137*H11/$C$136,0)+IF($C$136>0,$C$137*I11/$C$136,0)+IF($C$136>0,$C$137*J11/$C$136,0)+IF($C$136>0,$C$137*K11/$C$136,0)+IF($C$136>0,$C$137*L11/$C$136,0)+IF($C$136>0,$C$137*M11/$C$136,0)+IF($C$136>0,$C$137*N11/$C$136,0)+IF($C$136>0,$C$137*O11/$C$136,0))-((D17+D18)*INPUT!$C$6/(100+INPUT!$C$6)+(E17+E18)*INPUT!$C$6/(100+INPUT!$C$6)+(F17+F18)*INPUT!$C$6/(100+INPUT!$C$6)+(G17+G18)*INPUT!$C$6/(100+INPUT!$C$6)+(H17+H18)*INPUT!$C$6/(100+INPUT!$C$6)+(I17+I18)*INPUT!$C$6/(100+INPUT!$C$6)+(J17+J18)*INPUT!$C$6/(100+INPUT!$C$6)+(K17+K18)*INPUT!$C$6/(100+INPUT!$C$6)+(L17+L18)*INPUT!$C$6/(100+INPUT!$C$6)+(M17+M18)*INPUT!$C$6/(100+INPUT!$C$6)+(N17+N18)*INPUT!$C$6/(100+INPUT!$C$6)+(O17+O18)*INPUT!$C$6/(100+INPUT!$C$6))-SUM(D19:N19),0) -> 0 | P19: =MAX((IF($C$136>0,$C$137*D11/$C$136,0)+IF($C$136>0,$C$137*E11/$C$136,0)+IF($C$136>0,$C$137*F11/$C$136,0)+IF($C$136>0,$C$137*G11/$C$136,0)+IF($C$136>0,$C$137*H11/$C$136,0)+IF($C$136>0,$C$137*I11/$C$136,0)+IF($C$136>0,$C$137*J11/$C$136,0)+IF($C$136>0,$C$137*K11/$C$136,0)+IF($C$136>0,$C$137*L11/$C$136,0)+IF($C$136>0,$C$137*M11/$C$136,0)+IF($C$136>0,$C$137*N11/$C$136,0)+IF($C$136>0,$C$137*O11/$C$136,0)+IF($C$136>0,$C$137*P11/$C$136,0))-((D17+D18)*INPUT!$C$6/(100+INPUT!$C$6)+(E17+E18)*INPUT!$C$6/(100+INPUT!$C$6)+(F17+F18)*INPUT!$C$6/(100+INPUT!$C$6)+(G17+G18)*INPUT!$C$6/(100+INPUT!$C$6)+(H17+H18)*INPUT!$C$6/(100+INPUT!$C$6)+(I17+I18)*INPUT!$C$6/(100+INPUT!$C$6)+(J17+J18)*INPUT!$C$6/(100+INPUT!$C$6)+(K17+K18)*INPUT!$C$6/(100+INPUT!$C$6)+(L17+L18)*INPUT!$C$6/(100+INPUT!$C$6)+(M17+M18)*INPUT!$C$6/(100+INPUT!$C$6)+(N17+N18)*INPUT!$C$6/(100+INPUT!$C$6)+(O17+O18)*INPUT!$C$6/(100+INPUT!$C$6)+(P17+P18)*INPUT!$C$6/(100+INPUT!$C$6))-SUM(D19:O19),0) -> 0 | Q19: =MAX((IF($C$136>0,$C$137*D11/$C$136,0)+IF($C$136>0,$C$137*E11/$C$136,0)+IF($C$136>0,$C$137*F11/$C$136,0)+IF($C$136>0,$C$137*G11/$C$136,0)+IF($C$136>0,$C$137*H11/$C$136,0)+IF($C$136>0,$C$137*I11/$C$136,0)+IF($C$136>0,$C$137*J11/$C$136,0)+IF($C$136>0,$C$137*K11/$C$136,0)+IF($C$136>0,$C$137*L11/$C$136,0)+IF($C$136>0,$C$137*M11/$C$136,0)+IF($C$136>0,$C$137*N11/$C$136,0)+IF($C$136>0,$C$137*O11/$C$136,0)+IF($C$136>0,$C$137*P11/$C$136,0)+IF($C$136>0,$C$137*Q11/$C$136,0))-((D17+D18)*INPUT!$C$6/(100+INPUT!$C$6)+(E17+E18)*INPUT!$C$6/(100+INPUT!$C$6)+(F17+F18)*INPUT!$C$6/(100+INPUT!$C$6)+(G17+G18)*INPUT!$C$6/(100+INPUT!$C$6)+(H17+H18)*INPUT!$C$6/(100+INPUT!$C$6)+(I17+I18)*INPUT!$C$6/(100+INPUT!$C$6)+(J17+J18)*INPUT!$C$6/(100+INPUT!$C$6)+(K17+K18)*INPUT!$C$6/(100+INPUT!$C$6)+(L17+L18)*INPUT!$C$6/(100+INPUT!$C$6)+(M17+M18)*INPUT!$C$6/(100+INPUT!$C$6)+(N17+N18)*INPUT!$C$6/(100+INPUT!$C$6)+(O17+O18)*INPUT!$C$6/(100+INPUT!$C$6)+(P17+P18)*INPUT!$C$6/(100+INPUT!$C$6)+(Q17+Q18)*INPUT!$C$6/(100+INPUT!$C$6))-SUM(D19:P19),0) -> 0 | R19: =MAX((IF($C$136>0,$C$137*D11/$C$136,0)+IF($C$136>0,$C$137*E11/$C$136,0)+IF($C$136>0,$C$137*F11/$C$136,0)+IF($C$136>0,$C$137*G11/$C$136,0)+IF($C$136>0,$C$137*H11/$C$136,0)+IF($C$136>0,$C$137*I11/$C$136,0)+IF($C$136>0,$C$137*J11/$C$136,0)+IF($C$136>0,$C$137*K11/$C$136,0)+IF($C$136>0,$C$137*L11/$C$136,0)+IF($C$136>0,$C$137*M11/$C$136,0)+IF($C$136>0,$C$137*N11/$C$136,0)+IF($C$136>0,$C$137*O11/$C$136,0)+IF($C$136>0,$C$137*P11/$C$136,0)+IF($C$136>0,$C$137*Q11/$C$136,0)+IF($C$136>0,$C$137*R11/$C$136,0))-((D17+D18)*INPUT!$C$6/(100+INPUT!$C$6)+(E17+E18)*INPUT!$C$6/(100+INPUT!$C$6)+(F17+F18)*INPUT!$C$6/(100+INPUT!$C$6)+(G17+G18)*INPUT!$C$6/(100+INPUT!$C$6)+(H17+H18)*INPUT!$C$6/(100+INPUT!$C$6)+(I17+I18)*INPUT!$C$6/(100+INPUT!$C$6)+(J17+J18)*INPUT!$C$6/(100+INPUT!$C$6)+(K17+K18)*INPUT!$C$6/(100+INPUT!$C$6)+(L17+L18)*INPUT!$C$6/(100+INPUT!$C$6)+(M17+M18)*INPUT!$C$6/(100+INPUT!$C$6)+(N17+N18)*INPUT!$C$6/(100+INPUT!$C$6)+(O17+O18)*INPUT!$C$6/(100+INPUT!$C$6)+(P17+P18)*INPUT!$C$6/(100+INPUT!$C$6)+(Q17+Q18)*INPUT!$C$6/(100+INPUT!$C$6)+(R17+R18)*INPUT!$C$6/(100+INPUT!$C$6))-SUM(D19:Q19),0) -> 0 | S19: =MAX((IF($C$136>0,$C$137*D11/$C$136,0)+IF($C$136>0,$C$137*E11/$C$136,0)+IF($C$136>0,$C$137*F11/$C$136,0)+IF($C$136>0,$C$137*G11/$C$136,0)+IF($C$136>0,$C$137*H11/$C$136,0)+IF($C$136>0,$C$137*I11/$C$136,0)+IF($C$136>0,$C$137*J11/$C$136,0)+IF($C$136>0,$C$137*K11/$C$136,0)+IF($C$136>0,$C$137*L11/$C$136,0)+IF($C$136>0,$C$137*M11/$C$136,0)+IF($C$136>0,$C$137*N11/$C$136,0)+IF($C$136>0,$C$137*O11/$C$136,0)+IF($C$136>0,$C$137*P11/$C$136,0)+IF($C$136>0,$C$137*Q11/$C$136,0)+IF($C$136>0,$C$137*R11/$C$136,0)+IF($C$136>0,$C$137*S11/$C$136,0))-((D17+D18)*INPUT!$C$6/(100+INPUT!$C$6)+(E17+E18)*INPUT!$C$6/(100+INPUT!$C$6)+(F17+F18)*INPUT!$C$6/(100+INPUT!$C$6)+(G17+G18)*INPUT!$C$6/(100+INPUT!$C$6)+(H17+H18)*INPUT!$C$6/(100+INPUT!$C$6)+(I17+I18)*INPUT!$C$6/(100+INPUT!$C$6)+(J17+J18)*INPUT!$C$6/(100+INPUT!$C$6)+(K17+K18)*INPUT!$C$6/(100+INPUT!$C$6)+(L17+L18)*INPUT!$C$6/(100+INPUT!$C$6)+(M17+M18)*INPUT!$C$6/(100+INPUT!$C$6)+(N17+N18)*INPUT!$C$6/(100+INPUT!$C$6)+(O17+O18)*INPUT!$C$6/(100+INPUT!$C$6)+(P17+P18)*INPUT!$C$6/(100+INPUT!$C$6)+(Q17+Q18)*INPUT!$C$6/(100+INPUT!$C$6)+(R17+R18)*INPUT!$C$6/(100+INPUT!$C$6)+(S17+S18)*INPUT!$C$6/(100+INPUT!$C$6))-SUM(D19:R19),0) -> 0 | T19: =MAX((IF($C$136>0,$C$137*D11/$C$136,0)+IF($C$136>0,$C$137*E11/$C$136,0)+IF($C$136>0,$C$137*F11/$C$136,0)+IF($C$136>0,$C$137*G11/$C$136,0)+IF($C$136>0,$C$137*H11/$C$136,0)+IF($C$136>0,$C$137*I11/$C$136,0)+IF($C$136>0,$C$137*J11/$C$136,0)+IF($C$136>0,$C$137*K11/$C$136,0)+IF($C$136>0,$C$137*L11/$C$136,0)+IF($C$136>0,$C$137*M11/$C$136,0)+IF($C$136>0,$C$137*N11/$C$136,0)+IF($C$136>0,$C$137*O11/$C$136,0)+IF($C$136>0,$C$137*P11/$C$136,0)+IF($C$136>0,$C$137*Q11/$C$136,0)+IF($C$136>0,$C$137*R11/$C$136,0)+IF($C$136>0,$C$137*S11/$C$136,0)+IF($C$136>0,$C$137*T11/$C$136,0))-((D17+D18)*INPUT!$C$6/(100+INPUT!$C$6)+(E17+E18)*INPUT!$C$6/(100+INPUT!$C$6)+(F17+F18)*INPUT!$C$6/(100+INPUT!$C$6)+(G17+G18)*INPUT!$C$6/(100+INPUT!$C$6)+(H17+H18)*INPUT!$C$6/(100+INPUT!$C$6)+(I17+I18)*INPUT!$C$6/(100+INPUT!$C$6)+(J17+J18)*INPUT!$C$6/(100+INPUT!$C$6)+(K17+K18)*INPUT!$C$6/(100+INPUT!$C$6)+(L17+L18)*INPUT!$C$6/(100+INPUT!$C$6)+(M17+M18)*INPUT!$C$6/(100+INPUT!$C$6)+(N17+N18)*INPUT!$C$6/(100+INPUT!$C$6)+(O17+O18)*INPUT!$C$6/(100+INPUT!$C$6)+(P17+P18)*INPUT!$C$6/(100+INPUT!$C$6)+(Q17+Q18)*INPUT!$C$6/(100+INPUT!$C$6)+(R17+R18)*INPUT!$C$6/(100+INPUT!$C$6)+(S17+S18)*INPUT!$C$6/(100+INPUT!$C$6)+(T17+T18)*INPUT!$C$6/(100+INPUT!$C$6))-SUM(D19:S19),0) -> 0 | U19: =MAX((IF($C$136>0,$C$137*D11/$C$136,0)+IF($C$136>0,$C$137*E11/$C$136,0)+IF($C$136>0,$C$137*F11/$C$136,0)+IF($C$136>0,$C$137*G11/$C$136,0)+IF($C$136>0,$C$137*H11/$C$136,0)+IF($C$136>0,$C$137*I11/$C$136,0)+IF($C$136>0,$C$137*J11/$C$136,0)+IF($C$136>0,$C$137*K11/$C$136,0)+IF($C$136>0,$C$137*L11/$C$136,0)+IF($C$136>0,$C$137*M11/$C$136,0)+IF($C$136>0,$C$137*N11/$C$136,0)+IF($C$136>0,$C$137*O11/$C$136,0)+IF($C$136>0,$C$137*P11/$C$136,0)+IF($C$136>0,$C$137*Q11/$C$136,0)+IF($C$136>0,$C$137*R11/$C$136,0)+IF($C$136>0,$C$137*S11/$C$136,0)+IF($C$136>0,$C$137*T11/$C$136,0)+IF($C$136>0,$C$137*U11/$C$136,0))-((D17+D18)*INPUT!$C$6/(100+INPUT!$C$6)+(E17+E18)*INPUT!$C$6/(100+INPUT!$C$6)+(F17+F18)*INPUT!$C$6/(100+INPUT!$C$6)+(G17+G18)*INPUT!$C$6/(100+INPUT!$C$6)+(H17+H18)*INPUT!$C$6/(100+INPUT!$C$6)+(I17+I18)*INPUT!$C$6/(100+INPUT!$C$6)+(J17+J18)*INPUT!$C$6/(100+INPUT!$C$6)+(K17+K18)*INPUT!$C$6/(100+INPUT!$C$6)+(L17+L18)*INPUT!$C$6/(100+INPUT!$C$6)+(M17+M18)*INPUT!$C$6/(100+INPUT!$C$6)+(N17+N18)*INPUT!$C$6/(100+INPUT!$C$6)+(O17+O18)*INPUT!$C$6/(100+INPUT!$C$6)+(P17+P18)*INPUT!$C$6/(100+INPUT!$C$6)+(Q17+Q18)*INPUT!$C$6/(100+INPUT!$C$6)+(R17+R18)*INPUT!$C$6/(100+INPUT!$C$6)+(S17+S18)*INPUT!$C$6/(100+INPUT!$C$6)+(T17+T18)*INPUT!$C$6/(100+INPUT!$C$6)+(U17+U18)*INPUT!$C$6/(100+INPUT!$C$6))-SUM(D19:T19),0) -> 0 | V19: =MAX((IF($C$136>0,$C$137*D11/$C$136,0)+IF($C$136>0,$C$137*E11/$C$136,0)+IF($C$136>0,$C$137*F11/$C$136,0)+IF($C$136>0,$C$137*G11/$C$136,0)+IF($C$136>0,$C$137*H11/$C$136,0)+IF($C$136>0,$C$137*I11/$C$136,0)+IF($C$136>0,$C$137*J11/$C$136,0)+IF($C$136>0,$C$137*K11/$C$136,0)+IF($C$136>0,$C$137*L11/$C$136,0)+IF($C$136>0,$C$137*M11/$C$136,0)+IF($C$136>0,$C$137*N11/$C$136,0)+IF($C$136>0,$C$137*O11/$C$136,0)+IF($C$136>0,$C$137*P11/$C$136,0)+IF($C$136>0,$C$137*Q11/$C$136,0)+IF($C$136>0,$C$137*R11/$C$136,0)+IF($C$136>0,$C$137*S11/$C$136,0)+IF($C$136>0,$C$137*T11/$C$136,0)+IF($C$136>0,$C$137*U11/$C$136,0)+IF($C$136>0,$C$137*V11/$C$136,0))-((D17+D18)*INPUT!$C$6/(100+INPUT!$C$6)+(E17+E18)*INPUT!$C$6/(100+INPUT!$C$6)+(F17+F18)*INPUT!$C$6/(100+INPUT!$C$6)+(G17+G18)*INPUT!$C$6/(100+INPUT!$C$6)+(H17+H18)*INPUT!$C$6/(100+INPUT!$C$6)+(I17+I18)*INPUT!$C$6/(100+INPUT!$C$6)+(J17+J18)*INPUT!$C$6/(100+INPUT!$C$6)+(K17+K18)*INPUT!$C$6/(100+INPUT!$C$6)+(L17+L18)*INPUT!$C$6/(100+INPUT!$C$6)+(M17+M18)*INPUT!$C$6/(100+INPUT!$C$6)+(N17+N18)*INPUT!$C$6/(100+INPUT!$C$6)+(O17+O18)*INPUT!$C$6/(100+INPUT!$C$6)+(P17+P18)*INPUT!$C$6/(100+INPUT!$C$6)+(Q17+Q18)*INPUT!$C$6/(100+INPUT!$C$6)+(R17+R18)*INPUT!$C$6/(100+INPUT!$C$6)+(S17+S18)*INPUT!$C$6/(100+INPUT!$C$6)+(T17+T18)*INPUT!$C$6/(100+INPUT!$C$6)+(U17+U18)*INPUT!$C$6/(100+INPUT!$C$6)+(V17+V18)*INPUT!$C$6/(100+INPUT!$C$6))-SUM(D19:U19),0) -> 0 | W19: =MAX((IF($C$136>0,$C$137*D11/$C$136,0)+IF($C$136>0,$C$137*E11/$C$136,0)+IF($C$136>0,$C$137*F11/$C$136,0)+IF($C$136>0,$C$137*G11/$C$136,0)+IF($C$136>0,$C$137*H11/$C$136,0)+IF($C$136>0,$C$137*I11/$C$136,0)+IF($C$136>0,$C$137*J11/$C$136,0)+IF($C$136>0,$C$137*K11/$C$136,0)+IF($C$136>0,$C$137*L11/$C$136,0)+IF($C$136>0,$C$137*M11/$C$136,0)+IF($C$136>0,$C$137*N11/$C$136,0)+IF($C$136>0,$C$137*O11/$C$136,0)+IF($C$136>0,$C$137*P11/$C$136,0)+IF($C$136>0,$C$137*Q11/$C$136,0)+IF($C$136>0,$C$137*R11/$C$136,0)+IF($C$136>0,$C$137*S11/$C$136,0)+IF($C$136>0,$C$137*T11/$C$136,0)+IF($C$136>0,$C$137*U11/$C$136,0)+IF($C$136>0,$C$137*V11/$C$136,0)+IF($C$136>0,$C$137*W11/$C$136,0))-((D17+D18)*INPUT!$C$6/(100+INPUT!$C$6)+(E17+E18)*INPUT!$C$6/(100+INPUT!$C$6)+(F17+F18)*INPUT!$C$6/(100+INPUT!$C$6)+(G17+G18)*INPUT!$C$6/(100+INPUT!$C$6)+(H17+H18)*INPUT!$C$6/(100+INPUT!$C$6)+(I17+I18)*INPUT!$C$6/(100+INPUT!$C$6)+(J17+J18)*INPUT!$C$6/(100+INPUT!$C$6)+(K17+K18)*INPUT!$C$6/(100+INPUT!$C$6)+(L17+L18)*INPUT!$C$6/(100+INPUT!$C$6)+(M17+M18)*INPUT!$C$6/(100+INPUT!$C$6)+(N17+N18)*INPUT!$C$6/(100+INPUT!$C$6)+(O17+O18)*INPUT!$C$6/(100+INPUT!$C$6)+(P17+P18)*INPUT!$C$6/(100+INPUT!$C$6)+(Q17+Q18)*INPUT!$C$6/(100+INPUT!$C$6)+(R17+R18)*INPUT!$C$6/(100+INPUT!$C$6)+(S17+S18)*INPUT!$C$6/(100+INPUT!$C$6)+(T17+T18)*INPUT!$C$6/(100+INPUT!$C$6)+(U17+U18)*INPUT!$C$6/(100+INPUT!$C$6)+(V17+V18)*INPUT!$C$6/(100+INPUT!$C$6)+(W17+W18)*INPUT!$C$6/(100+INPUT!$C$6))-SUM(D19:V19),0) -> 0 | X19: =MAX((IF($C$136>0,$C$137*D11/$C$136,0)+IF($C$136>0,$C$137*E11/$C$136,0)+IF($C$136>0,$C$137*F11/$C$136,0)+IF($C$136>0,$C$137*G11/$C$136,0)+IF($C$136>0,$C$137*H11/$C$136,0)+IF($C$136>0,$C$137*I11/$C$136,0)+IF($C$136>0,$C$137*J11/$C$136,0)+IF($C$136>0,$C$137*K11/$C$136,0)+IF($C$136>0,$C$137*L11/$C$136,0)+IF($C$136>0,$C$137*M11/$C$136,0)+IF($C$136>0,$C$137*N11/$C$136,0)+IF($C$136>0,$C$137*O11/$C$136,0)+IF($C$136>0,$C$137*P11/$C$136,0)+IF($C$136>0,$C$137*Q11/$C$136,0)+IF($C$136>0,$C$137*R11/$C$136,0)+IF($C$136>0,$C$137*S11/$C$136,0)+IF($C$136>0,$C$137*T11/$C$136,0)+IF($C$136>0,$C$137*U11/$C$136,0)+IF($C$136>0,$C$137*V11/$C$136,0)+IF($C$136>0,$C$137*W11/$C$136,0)+IF($C$136>0,$C$137*X11/$C$136,0))-((D17+D18)*INPUT!$C$6/(100+INPUT!$C$6)+(E17+E18)*INPUT!$C$6/(100+INPUT!$C$6)+(F17+F18)*INPUT!$C$6/(100+INPUT!$C$6)+(G17+G18)*INPUT!$C$6/(100+INPUT!$C$6)+(H17+H18)*INPUT!$C$6/(100+INPUT!$C$6)+(I17+I18)*INPUT!$C$6/(100+INPUT!$C$6)+(J17+J18)*INPUT!$C$6/(100+INPUT!$C$6)+(K17+K18)*INPUT!$C$6/(100+INPUT!$C$6)+(L17+L18)*INPUT!$C$6/(100+INPUT!$C$6)+(M17+M18)*INPUT!$C$6/(100+INPUT!$C$6)+(N17+N18)*INPUT!$C$6/(100+INPUT!$C$6)+(O17+O18)*INPUT!$C$6/(100+INPUT!$C$6)+(P17+P18)*INPUT!$C$6/(100+INPUT!$C$6)+(Q17+Q18)*INPUT!$C$6/(100+INPUT!$C$6)+(R17+R18)*INPUT!$C$6/(100+INPUT!$C$6)+(S17+S18)*INPUT!$C$6/(100+INPUT!$C$6)+(T17+T18)*INPUT!$C$6/(100+INPUT!$C$6)+(U17+U18)*INPUT!$C$6/(100+INPUT!$C$6)+(V17+V18)*INPUT!$C$6/(100+INPUT!$C$6)+(W17+W18)*INPUT!$C$6/(100+INPUT!$C$6)+(X17+X18)*INPUT!$C$6/(100+INPUT!$C$6))-SUM(D19:W19),0) -> 0 | Y19: =MAX((IF($C$136>0,$C$137*D11/$C$136,0)+IF($C$136>0,$C$137*E11/$C$136,0)+IF($C$136>0,$C$137*F11/$C$136,0)+IF($C$136>0,$C$137*G11/$C$136,0)+IF($C$136>0,$C$137*H11/$C$136,0)+IF($C$136>0,$C$137*I11/$C$136,0)+IF($C$136>0,$C$137*J11/$C$136,0)+IF($C$136>0,$C$137*K11/$C$136,0)+IF($C$136>0,$C$137*L11/$C$136,0)+IF($C$136>0,$C$137*M11/$C$136,0)+IF($C$136>0,$C$137*N11/$C$136,0)+IF($C$136>0,$C$137*O11/$C$136,0)+IF($C$136>0,$C$137*P11/$C$136,0)+IF($C$136>0,$C$137*Q11/$C$136,0)+IF($C$136>0,$C$137*R11/$C$136,0)+IF($C$136>0,$C$137*S11/$C$136,0)+IF($C$136>0,$C$137*T11/$C$136,0)+IF($C$136>0,$C$137*U11/$C$136,0)+IF($C$136>0,$C$137*V11/$C$136,0)+IF($C$136>0,$C$137*W11/$C$136,0)+IF($C$136>0,$C$137*X11/$C$136,0)+IF($C$136>0,$C$137*Y11/$C$136,0))-((D17+D18)*INPUT!$C$6/(100+INPUT!$C$6)+(E17+E18)*INPUT!$C$6/(100+INPUT!$C$6)+(F17+F18)*INPUT!$C$6/(100+INPUT!$C$6)+(G17+G18)*INPUT!$C$6/(100+INPUT!$C$6)+(H17+H18)*INPUT!$C$6/(100+INPUT!$C$6)+(I17+I18)*INPUT!$C$6/(100+INPUT!$C$6)+(J17+J18)*INPUT!$C$6/(100+INPUT!$C$6)+(K17+K18)*INPUT!$C$6/(100+INPUT!$C$6)+(L17+L18)*INPUT!$C$6/(100+INPUT!$C$6)+(M17+M18)*INPUT!$C$6/(100+INPUT!$C$6)+(N17+N18)*INPUT!$C$6/(100+INPUT!$C$6)+(O17+O18)*INPUT!$C$6/(100+INPUT!$C$6)+(P17+P18)*INPUT!$C$6/(100+INPUT!$C$6)+(Q17+Q18)*INPUT!$C$6/(100+INPUT!$C$6)+(R17+R18)*INPUT!$C$6/(100+INPUT!$C$6)+(S17+S18)*INPUT!$C$6/(100+INPUT!$C$6)+(T17+T18)*INPUT!$C$6/(100+INPUT!$C$6)+(U17+U18)*INPUT!$C$6/(100+INPUT!$C$6)+(V17+V18)*INPUT!$C$6/(100+INPUT!$C$6)+(W17+W18)*INPUT!$C$6/(100+INPUT!$C$6)+(X17+X18)*INPUT!$C$6/(100+INPUT!$C$6)+(Y17+Y18)*INPUT!$C$6/(100+INPUT!$C$6))-SUM(D19:X19),0) -> 0 | Z19: =MAX((IF($C$136>0,$C$137*D11/$C$136,0)+IF($C$136>0,$C$137*E11/$C$136,0)+IF($C$136>0,$C$137*F11/$C$136,0)+IF($C$136>0,$C$137*G11/$C$136,0)+IF($C$136>0,$C$137*H11/$C$136,0)+IF($C$136>0,$C$137*I11/$C$136,0)+IF($C$136>0,$C$137*J11/$C$136,0)+IF($C$136>0,$C$137*K11/$C$136,0)+IF($C$136>0,$C$137*L11/$C$136,0)+IF($C$136>0,$C$137*M11/$C$136,0)+IF($C$136>0,$C$137*N11/$C$136,0)+IF($C$136>0,$C$137*O11/$C$136,0)+IF($C$136>0,$C$137*P11/$C$136,0)+IF($C$136>0,$C$137*Q11/$C$136,0)+IF($C$136>0,$C$137*R11/$C$136,0)+IF($C$136>0,$C$137*S11/$C$136,0)+IF($C$136>0,$C$137*T11/$C$136,0)+IF($C$136>0,$C$137*U11/$C$136,0)+IF($C$136>0,$C$137*V11/$C$136,0)+IF($C$136>0,$C$137*W11/$C$136,0)+IF($C$136>0,$C$137*X11/$C$136,0)+IF($C$136>0,$C$137*Y11/$C$136,0)+IF($C$136>0,$C$137*Z11/$C$136,0))-((D17+D18)*INPUT!$C$6/(100+INPUT!$C$6)+(E17+E18)*INPUT!$C$6/(100+INPUT!$C$6)+(F17+F18)*INPUT!$C$6/(100+INPUT!$C$6)+(G17+G18)*INPUT!$C$6/(100+INPUT!$C$6)+(H17+H18)*INPUT!$C$6/(100+INPUT!$C$6)+(I17+I18)*INPUT!$C$6/(100+INPUT!$C$6)+(J17+J18)*INPUT!$C$6/(100+INPUT!$C$6)+(K17+K18)*INPUT!$C$6/(100+INPUT!$C$6)+(L17+L18)*INPUT!$C$6/(100+INPUT!$C$6)+(M17+M18)*INPUT!$C$6/(100+INPUT!$C$6)+(N17+N18)*INPUT!$C$6/(100+INPUT!$C$6)+(O17+O18)*INPUT!$C$6/(100+INPUT!$C$6)+(P17+P18)*INPUT!$C$6/(100+INPUT!$C$6)+(Q17+Q18)*INPUT!$C$6/(100+INPUT!$C$6)+(R17+R18)*INPUT!$C$6/(100+INPUT!$C$6)+(S17+S18)*INPUT!$C$6/(100+INPUT!$C$6)+(T17+T18)*INPUT!$C$6/(100+INPUT!$C$6)+(U17+U18)*INPUT!$C$6/(100+INPUT!$C$6)+(V17+V18)*INPUT!$C$6/(100+INPUT!$C$6)+(W17+W18)*INPUT!$C$6/(100+INPUT!$C$6)+(X17+X18)*INPUT!$C$6/(100+INPUT!$C$6)+(Y17+Y18)*INPUT!$C$6/(100+INPUT!$C$6)+(Z17+Z18)*INPUT!$C$6/(100+INPUT!$C$6))-SUM(D19:Y19),0) -> 0 | AA19: =MAX((IF($C$136>0,$C$137*D11/$C$136,0)+IF($C$136>0,$C$137*E11/$C$136,0)+IF($C$136>0,$C$137*F11/$C$136,0)+IF($C$136>0,$C$137*G11/$C$136,0)+IF($C$136>0,$C$137*H11/$C$136,0)+IF($C$136>0,$C$137*I11/$C$136,0)+IF($C$136>0,$C$137*J11/$C$136,0)+IF($C$136>0,$C$137*K11/$C$136,0)+IF($C$136>0,$C$137*L11/$C$136,0)+IF($C$136>0,$C$137*M11/$C$136,0)+IF($C$136>0,$C$137*N11/$C$136,0)+IF($C$136>0,$C$137*O11/$C$136,0)+IF($C$136>0,$C$137*P11/$C$136,0)+IF($C$136>0,$C$137*Q11/$C$136,0)+IF($C$136>0,$C$137*R11/$C$136,0)+IF($C$136>0,$C$137*S11/$C$136,0)+IF($C$136>0,$C$137*T11/$C$136,0)+IF($C$136>0,$C$137*U11/$C$136,0)+IF($C$136>0,$C$137*V11/$C$136,0)+IF($C$136>0,$C$137*W11/$C$136,0)+IF($C$136>0,$C$137*X11/$C$136,0)+IF($C$136>0,$C$137*Y11/$C$136,0)+IF($C$136>0,$C$137*Z11/$C$136,0)+IF($C$136>0,$C$137*AA11/$C$136,0))-((D17+D18)*INPUT!$C$6/(100+INPUT!$C$6)+(E17+E18)*INPUT!$C$6/(100+INPUT!$C$6)+(F17+F18)*INPUT!$C$6/(100+INPUT!$C$6)+(G17+G18)*INPUT!$C$6/(100+INPUT!$C$6)+(H17+H18)*INPUT!$C$6/(100+INPUT!$C$6)+(I17+I18)*INPUT!$C$6/(100+INPUT!$C$6)+(J17+J18)*INPUT!$C$6/(100+INPUT!$C$6)+(K17+K18)*INPUT!$C$6/(100+INPUT!$C$6)+(L17+L18)*INPUT!$C$6/(100+INPUT!$C$6)+(M17+M18)*INPUT!$C$6/(100+INPUT!$C$6)+(N17+N18)*INPUT!$C$6/(100+INPUT!$C$6)+(O17+O18)*INPUT!$C$6/(100+INPUT!$C$6)+(P17+P18)*INPUT!$C$6/(100+INPUT!$C$6)+(Q17+Q18)*INPUT!$C$6/(100+INPUT!$C$6)+(R17+R18)*INPUT!$C$6/(100+INPUT!$C$6)+(S17+S18)*INPUT!$C$6/(100+INPUT!$C$6)+(T17+T18)*INPUT!$C$6/(100+INPUT!$C$6)+(U17+U18)*INPUT!$C$6/(100+INPUT!$C$6)+(V17+V18)*INPUT!$C$6/(100+INPUT!$C$6)+(W17+W18)*INPUT!$C$6/(100+INPUT!$C$6)+(X17+X18)*INPUT!$C$6/(100+INPUT!$C$6)+(Y17+Y18)*INPUT!$C$6/(100+INPUT!$C$6)+(Z17+Z18)*INPUT!$C$6/(100+INPUT!$C$6)+(AA17+AA18)*INPUT!$C$6/(100+INPUT!$C$6))-SUM(D19:Z19),0) -> 0 | AB19: =MAX((IF($C$136>0,$C$137*D11/$C$136,0)+IF($C$136>0,$C$137*E11/$C$136,0)+IF($C$136>0,$C$137*F11/$C$136,0)+IF($C$136>0,$C$137*G11/$C$136,0)+IF($C$136>0,$C$137*H11/$C$136,0)+IF($C$136>0,$C$137*I11/$C$136,0)+IF($C$136>0,$C$137*J11/$C$136,0)+IF($C$136>0,$C$137*K11/$C$136,0)+IF($C$136>0,$C$137*L11/$C$136,0)+IF($C$136>0,$C$137*M11/$C$136,0)+IF($C$136>0,$C$137*N11/$C$136,0)+IF($C$136>0,$C$137*O11/$C$136,0)+IF($C$136>0,$C$137*P11/$C$136,0)+IF($C$136>0,$C$137*Q11/$C$136,0)+IF($C$136>0,$C$137*R11/$C$136,0)+IF($C$136>0,$C$137*S11/$C$136,0)+IF($C$136>0,$C$137*T11/$C$136,0)+IF($C$136>0,$C$137*U11/$C$136,0)+IF($C$136>0,$C$137*V11/$C$136,0)+IF($C$136>0,$C$137*W11/$C$136,0)+IF($C$136>0,$C$137*X11/$C$136,0)+IF($C$136>0,$C$137*Y11/$C$136,0)+IF($C$136>0,$C$137*Z11/$C$136,0)+IF($C$136>0,$C$137*AA11/$C$136,0)+IF($C$136>0,$C$137*AB11/$C$136,0))-((D17+D18)*INPUT!$C$6/(100+INPUT!$C$6)+(E17+E18)*INPUT!$C$6/(100+INPUT!$C$6)+(F17+F18)*INPUT!$C$6/(100+INPUT!$C$6)+(G17+G18)*INPUT!$C$6/(100+INPUT!$C$6)+(H17+H18)*INPUT!$C$6/(100+INPUT!$C$6)+(I17+I18)*INPUT!$C$6/(100+INPUT!$C$6)+(J17+J18)*INPUT!$C$6/(100+INPUT!$C$6)+(K17+K18)*INPUT!$C$6/(100+INPUT!$C$6)+(L17+L18)*INPUT!$C$6/(100+INPUT!$C$6)+(M17+M18)*INPUT!$C$6/(100+INPUT!$C$6)+(N17+N18)*INPUT!$C$6/(100+INPUT!$C$6)+(O17+O18)*INPUT!$C$6/(100+INPUT!$C$6)+(P17+P18)*INPUT!$C$6/(100+INPUT!$C$6)+(Q17+Q18)*INPUT!$C$6/(100+INPUT!$C$6)+(R17+R18)*INPUT!$C$6/(100+INPUT!$C$6)+(S17+S18)*INPUT!$C$6/(100+INPUT!$C$6)+(T17+T18)*INPUT!$C$6/(100+INPUT!$C$6)+(U17+U18)*INPUT!$C$6/(100+INPUT!$C$6)+(V17+V18)*INPUT!$C$6/(100+INPUT!$C$6)+(W17+W18)*INPUT!$C$6/(100+INPUT!$C$6)+(X17+X18)*INPUT!$C$6/(100+INPUT!$C$6)+(Y17+Y18)*INPUT!$C$6/(100+INPUT!$C$6)+(Z17+Z18)*INPUT!$C$6/(100+INPUT!$C$6)+(AA17+AA18)*INPUT!$C$6/(100+INPUT!$C$6)+(AB17+AB18)*INPUT!$C$6/(100+INPUT!$C$6))-SUM(D19:AA19),0) -> 0 | AC19: =MAX((IF($C$136>0,$C$137*D11/$C$136,0)+IF($C$136>0,$C$137*E11/$C$136,0)+IF($C$136>0,$C$137*F11/$C$136,0)+IF($C$136>0,$C$137*G11/$C$136,0)+IF($C$136>0,$C$137*H11/$C$136,0)+IF($C$136>0,$C$137*I11/$C$136,0)+IF($C$136>0,$C$137*J11/$C$136,0)+IF($C$136>0,$C$137*K11/$C$136,0)+IF($C$136>0,$C$137*L11/$C$136,0)+IF($C$136>0,$C$137*M11/$C$136,0)+IF($C$136>0,$C$137*N11/$C$136,0)+IF($C$136>0,$C$137*O11/$C$136,0)+IF($C$136>0,$C$137*P11/$C$136,0)+IF($C$136>0,$C$137*Q11/$C$136,0)+IF($C$136>0,$C$137*R11/$C$136,0)+IF($C$136>0,$C$137*S11/$C$136,0)+IF($C$136>0,$C$137*T11/$C$136,0)+IF($C$136>0,$C$137*U11/$C$136,0)+IF($C$136>0,$C$137*V11/$C$136,0)+IF($C$136>0,$C$137*W11/$C$136,0)+IF($C$136>0,$C$137*X11/$C$136,0)+IF($C$136>0,$C$137*Y11/$C$136,0)+IF($C$136>0,$C$137*Z11/$C$136,0)+IF($C$136>0,$C$137*AA11/$C$136,0)+IF($C$136>0,$C$137*AB11/$C$136,0)+IF($C$136>0,$C$137*AC11/$C$136,0))-((D17+D18)*INPUT!$C$6/(100+INPUT!$C$6)+(E17+E18)*INPUT!$C$6/(100+INPUT!$C$6)+(F17+F18)*INPUT!$C$6/(100+INPUT!$C$6)+(G17+G18)*INPUT!$C$6/(100+INPUT!$C$6)+(H17+H18)*INPUT!$C$6/(100+INPUT!$C$6)+(I17+I18)*INPUT!$C$6/(100+INPUT!$C$6)+(J17+J18)*INPUT!$C$6/(100+INPUT!$C$6)+(K17+K18)*INPUT!$C$6/(100+INPUT!$C$6)+(L17+L18)*INPUT!$C$6/(100+INPUT!$C$6)+(M17+M18)*INPUT!$C$6/(100+INPUT!$C$6)+(N17+N18)*INPUT!$C$6/(100+INPUT!$C$6)+(O17+O18)*INPUT!$C$6/(100+INPUT!$C$6)+(P17+P18)*INPUT!$C$6/(100+INPUT!$C$6)+(Q17+Q18)*INPUT!$C$6/(100+INPUT!$C$6)+(R17+R18)*INPUT!$C$6/(100+INPUT!$C$6)+(S17+S18)*INPUT!$C$6/(100+INPUT!$C$6)+(T17+T18)*INPUT!$C$6/(100+INPUT!$C$6)+(U17+U18)*INPUT!$C$6/(100+INPUT!$C$6)+(V17+V18)*INPUT!$C$6/(100+INPUT!$C$6)+(W17+W18)*INPUT!$C$6/(100+INPUT!$C$6)+(X17+X18)*INPUT!$C$6/(100+INPUT!$C$6)+(Y17+Y18)*INPUT!$C$6/(100+INPUT!$C$6)+(Z17+Z18)*INPUT!$C$6/(100+INPUT!$C$6)+(AA17+AA18)*INPUT!$C$6/(100+INPUT!$C$6)+(AB17+AB18)*INPUT!$C$6/(100+INPUT!$C$6)+(AC17+AC18)*INPUT!$C$6/(100+INPUT!$C$6))-SUM(D19:AB19),0) -> 0 | AD19: =MAX((IF($C$136>0,$C$137*D11/$C$136,0)+IF($C$136>0,$C$137*E11/$C$136,0)+IF($C$136>0,$C$137*F11/$C$136,0)+IF($C$136>0,$C$137*G11/$C$136,0)+IF($C$136>0,$C$137*H11/$C$136,0)+IF($C$136>0,$C$137*I11/$C$136,0)+IF($C$136>0,$C$137*J11/$C$136,0)+IF($C$136>0,$C$137*K11/$C$136,0)+IF($C$136>0,$C$137*L11/$C$136,0)+IF($C$136>0,$C$137*M11/$C$136,0)+IF($C$136>0,$C$137*N11/$C$136,0)+IF($C$136>0,$C$137*O11/$C$136,0)+IF($C$136>0,$C$137*P11/$C$136,0)+IF($C$136>0,$C$137*Q11/$C$136,0)+IF($C$136>0,$C$137*R11/$C$136,0)+IF($C$136>0,$C$137*S11/$C$136,0)+IF($C$136>0,$C$137*T11/$C$136,0)+IF($C$136>0,$C$137*U11/$C$136,0)+IF($C$136>0,$C$137*V11/$C$136,0)+IF($C$136>0,$C$137*W11/$C$136,0)+IF($C$136>0,$C$137*X11/$C$136,0)+IF($C$136>0,$C$137*Y11/$C$136,0)+IF($C$136>0,$C$137*Z11/$C$136,0)+IF($C$136>0,$C$137*AA11/$C$136,0)+IF($C$136>0,$C$137*AB11/$C$136,0)+IF($C$136>0,$C$137*AC11/$C$136,0)+IF($C$136>0,$C$137*AD11/$C$136,0))-((D17+D18)*INPUT!$C$6/(100+INPUT!$C$6)+(E17+E18)*INPUT!$C$6/(100+INPUT!$C$6)+(F17+F18)*INPUT!$C$6/(100+INPUT!$C$6)+(G17+G18)*INPUT!$C$6/(100+INPUT!$C$6)+(H17+H18)*INPUT!$C$6/(100+INPUT!$C$6)+(I17+I18)*INPUT!$C$6/(100+INPUT!$C$6)+(J17+J18)*INPUT!$C$6/(100+INPUT!$C$6)+(K17+K18)*INPUT!$C$6/(100+INPUT!$C$6)+(L17+L18)*INPUT!$C$6/(100+INPUT!$C$6)+(M17+M18)*INPUT!$C$6/(100+INPUT!$C$6)+(N17+N18)*INPUT!$C$6/(100+INPUT!$C$6)+(O17+O18)*INPUT!$C$6/(100+INPUT!$C$6)+(P17+P18)*INPUT!$C$6/(100+INPUT!$C$6)+(Q17+Q18)*INPUT!$C$6/(100+INPUT!$C$6)+(R17+R18)*INPUT!$C$6/(100+INPUT!$C$6)+(S17+S18)*INPUT!$C$6/(100+INPUT!$C$6)+(T17+T18)*INPUT!$C$6/(100+INPUT!$C$6)+(U17+U18)*INPUT!$C$6/(100+INPUT!$C$6)+(V17+V18)*INPUT!$C$6/(100+INPUT!$C$6)+(W17+W18)*INPUT!$C$6/(100+INPUT!$C$6)+(X17+X18)*INPUT!$C$6/(100+INPUT!$C$6)+(Y17+Y18)*INPUT!$C$6/(100+INPUT!$C$6)+(Z17+Z18)*INPUT!$C$6/(100+INPUT!$C$6)+(AA17+AA18)*INPUT!$C$6/(100+INPUT!$C$6)+(AB17+AB18)*INPUT!$C$6/(100+INPUT!$C$6)+(AC17+AC18)*INPUT!$C$6/(100+INPUT!$C$6)+(AD17+AD18)*INPUT!$C$6/(100+INPUT!$C$6))-SUM(D19:AC19),0) -> 0 | AE19: =MAX((IF($C$136>0,$C$137*D11/$C$136,0)+IF($C$136>0,$C$137*E11/$C$136,0)+IF($C$136>0,$C$137*F11/$C$136,0)+IF($C$136>0,$C$137*G11/$C$136,0)+IF($C$136>0,$C$137*H11/$C$136,0)+IF($C$136>0,$C$137*I11/$C$136,0)+IF($C$136>0,$C$137*J11/$C$136,0)+IF($C$136>0,$C$137*K11/$C$136,0)+IF($C$136>0,$C$137*L11/$C$136,0)+IF($C$136>0,$C$137*M11/$C$136,0)+IF($C$136>0,$C$137*N11/$C$136,0)+IF($C$136>0,$C$137*O11/$C$136,0)+IF($C$136>0,$C$137*P11/$C$136,0)+IF($C$136>0,$C$137*Q11/$C$136,0)+IF($C$136>0,$C$137*R11/$C$136,0)+IF($C$136>0,$C$137*S11/$C$136,0)+IF($C$136>0,$C$137*T11/$C$136,0)+IF($C$136>0,$C$137*U11/$C$136,0)+IF($C$136>0,$C$137*V11/$C$136,0)+IF($C$136>0,$C$137*W11/$C$136,0)+IF($C$136>0,$C$137*X11/$C$136,0)+IF($C$136>0,$C$137*Y11/$C$136,0)+IF($C$136>0,$C$137*Z11/$C$136,0)+IF($C$136>0,$C$137*AA11/$C$136,0)+IF($C$136>0,$C$137*AB11/$C$136,0)+IF($C$136>0,$C$137*AC11/$C$136,0)+IF($C$136>0,$C$137*AD11/$C$136,0)+IF($C$136>0,$C$137*AE11/$C$136,0))-((D17+D18)*INPUT!$C$6/(100+INPUT!$C$6)+(E17+E18)*INPUT!$C$6/(100+INPUT!$C$6)+(F17+F18)*INPUT!$C$6/(100+INPUT!$C$6)+(G17+G18)*INPUT!$C$6/(100+INPUT!$C$6)+(H17+H18)*INPUT!$C$6/(100+INPUT!$C$6)+(I17+I18)*INPUT!$C$6/(100+INPUT!$C$6)+(J17+J18)*INPUT!$C$6/(100+INPUT!$C$6)+(K17+K18)*INPUT!$C$6/(100+INPUT!$C$6)+(L17+L18)*INPUT!$C$6/(100+INPUT!$C$6)+(M17+M18)*INPUT!$C$6/(100+INPUT!$C$6)+(N17+N18)*INPUT!$C$6/(100+INPUT!$C$6)+(O17+O18)*INPUT!$C$6/(100+INPUT!$C$6)+(P17+P18)*INPUT!$C$6/(100+INPUT!$C$6)+(Q17+Q18)*INPUT!$C$6/(100+INPUT!$C$6)+(R17+R18)*INPUT!$C$6/(100+INPUT!$C$6)+(S17+S18)*INPUT!$C$6/(100+INPUT!$C$6)+(T17+T18)*INPUT!$C$6/(100+INPUT!$C$6)+(U17+U18)*INPUT!$C$6/(100+INPUT!$C$6)+(V17+V18)*INPUT!$C$6/(100+INPUT!$C$6)+(W17+W18)*INPUT!$C$6/(100+INPUT!$C$6)+(X17+X18)*INPUT!$C$6/(100+INPUT!$C$6)+(Y17+Y18)*INPUT!$C$6/(100+INPUT!$C$6)+(Z17+Z18)*INPUT!$C$6/(100+INPUT!$C$6)+(AA17+AA18)*INPUT!$C$6/(100+INPUT!$C$6)+(AB17+AB18)*INPUT!$C$6/(100+INPUT!$C$6)+(AC17+AC18)*INPUT!$C$6/(100+INPUT!$C$6)+(AD17+AD18)*INPUT!$C$6/(100+INPUT!$C$6)+(AE17+AE18)*INPUT!$C$6/(100+INPUT!$C$6))-SUM(D19:AD19),0) -> 0 | AF19: =MAX((IF($C$136>0,$C$137*D11/$C$136,0)+IF($C$136>0,$C$137*E11/$C$136,0)+IF($C$136>0,$C$137*F11/$C$136,0)+IF($C$136>0,$C$137*G11/$C$136,0)+IF($C$136>0,$C$137*H11/$C$136,0)+IF($C$136>0,$C$137*I11/$C$136,0)+IF($C$136>0,$C$137*J11/$C$136,0)+IF($C$136>0,$C$137*K11/$C$136,0)+IF($C$136>0,$C$137*L11/$C$136,0)+IF($C$136>0,$C$137*M11/$C$136,0)+IF($C$136>0,$C$137*N11/$C$136,0)+IF($C$136>0,$C$137*O11/$C$136,0)+IF($C$136>0,$C$137*P11/$C$136,0)+IF($C$136>0,$C$137*Q11/$C$136,0)+IF($C$136>0,$C$137*R11/$C$136,0)+IF($C$136>0,$C$137*S11/$C$136,0)+IF($C$136>0,$C$137*T11/$C$136,0)+IF($C$136>0,$C$137*U11/$C$136,0)+IF($C$136>0,$C$137*V11/$C$136,0)+IF($C$136>0,$C$137*W11/$C$136,0)+IF($C$136>0,$C$137*X11/$C$136,0)+IF($C$136>0,$C$137*Y11/$C$136,0)+IF($C$136>0,$C$137*Z11/$C$136,0)+IF($C$136>0,$C$137*AA11/$C$136,0)+IF($C$136>0,$C$137*AB11/$C$136,0)+IF($C$136>0,$C$137*AC11/$C$136,0)+IF($C$136>0,$C$137*AD11/$C$136,0)+IF($C$136>0,$C$137*AE11/$C$136,0)+IF($C$136>0,$C$137*AF11/$C$136,0))-((D17+D18)*INPUT!$C$6/(100+INPUT!$C$6)+(E17+E18)*INPUT!$C$6/(100+INPUT!$C$6)+(F17+F18)*INPUT!$C$6/(100+INPUT!$C$6)+(G17+G18)*INPUT!$C$6/(100+INPUT!$C$6)+(H17+H18)*INPUT!$C$6/(100+INPUT!$C$6)+(I17+I18)*INPUT!$C$6/(100+INPUT!$C$6)+(J17+J18)*INPUT!$C$6/(100+INPUT!$C$6)+(K17+K18)*INPUT!$C$6/(100+INPUT!$C$6)+(L17+L18)*INPUT!$C$6/(100+INPUT!$C$6)+(M17+M18)*INPUT!$C$6/(100+INPUT!$C$6)+(N17+N18)*INPUT!$C$6/(100+INPUT!$C$6)+(O17+O18)*INPUT!$C$6/(100+INPUT!$C$6)+(P17+P18)*INPUT!$C$6/(100+INPUT!$C$6)+(Q17+Q18)*INPUT!$C$6/(100+INPUT!$C$6)+(R17+R18)*INPUT!$C$6/(100+INPUT!$C$6)+(S17+S18)*INPUT!$C$6/(100+INPUT!$C$6)+(T17+T18)*INPUT!$C$6/(100+INPUT!$C$6)+(U17+U18)*INPUT!$C$6/(100+INPUT!$C$6)+(V17+V18)*INPUT!$C$6/(100+INPUT!$C$6)+(W17+W18)*INPUT!$C$6/(100+INPUT!$C$6)+(X17+X18)*INPUT!$C$6/(100+INPUT!$C$6)+(Y17+Y18)*INPUT!$C$6/(100+INPUT!$C$6)+(Z17+Z18)*INPUT!$C$6/(100+INPUT!$C$6)+(AA17+AA18)*INPUT!$C$6/(100+INPUT!$C$6)+(AB17+AB18)*INPUT!$C$6/(100+INPUT!$C$6)+(AC17+AC18)*INPUT!$C$6/(100+INPUT!$C$6)+(AD17+AD18)*INPUT!$C$6/(100+INPUT!$C$6)+(AE17+AE18)*INPUT!$C$6/(100+INPUT!$C$6)+(AF17+AF18)*INPUT!$C$6/(100+INPUT!$C$6))-SUM(D19:AE19),0) -> 0 | AG19: =MAX((IF($C$136>0,$C$137*D11/$C$136,0)+IF($C$136>0,$C$137*E11/$C$136,0)+IF($C$136>0,$C$137*F11/$C$136,0)+IF($C$136>0,$C$137*G11/$C$136,0)+IF($C$136>0,$C$137*H11/$C$136,0)+IF($C$136>0,$C$137*I11/$C$136,0)+IF($C$136>0,$C$137*J11/$C$136,0)+IF($C$136>0,$C$137*K11/$C$136,0)+IF($C$136>0,$C$137*L11/$C$136,0)+IF($C$136>0,$C$137*M11/$C$136,0)+IF($C$136>0,$C$137*N11/$C$136,0)+IF($C$136>0,$C$137*O11/$C$136,0)+IF($C$136>0,$C$137*P11/$C$136,0)+IF($C$136>0,$C$137*Q11/$C$136,0)+IF($C$136>0,$C$137*R11/$C$136,0)+IF($C$136>0,$C$137*S11/$C$136,0)+IF($C$136>0,$C$137*T11/$C$136,0)+IF($C$136>0,$C$137*U11/$C$136,0)+IF($C$136>0,$C$137*V11/$C$136,0)+IF($C$136>0,$C$137*W11/$C$136,0)+IF($C$136>0,$C$137*X11/$C$136,0)+IF($C$136>0,$C$137*Y11/$C$136,0)+IF($C$136>0,$C$137*Z11/$C$136,0)+IF($C$136>0,$C$137*AA11/$C$136,0)+IF($C$136>0,$C$137*AB11/$C$136,0)+IF($C$136>0,$C$137*AC11/$C$136,0)+IF($C$136>0,$C$137*AD11/$C$136,0)+IF($C$136>0,$C$137*AE11/$C$136,0)+IF($C$136>0,$C$137*AF11/$C$136,0)+IF($C$136>0,$C$137*AG11/$C$136,0))-((D17+D18)*INPUT!$C$6/(100+INPUT!$C$6)+(E17+E18)*INPUT!$C$6/(100+INPUT!$C$6)+(F17+F18)*INPUT!$C$6/(100+INPUT!$C$6)+(G17+G18)*INPUT!$C$6/(100+INPUT!$C$6)+(H17+H18)*INPUT!$C$6/(100+INPUT!$C$6)+(I17+I18)*INPUT!$C$6/(100+INPUT!$C$6)+(J17+J18)*INPUT!$C$6/(100+INPUT!$C$6)+(K17+K18)*INPUT!$C$6/(100+INPUT!$C$6)+(L17+L18)*INPUT!$C$6/(100+INPUT!$C$6)+(M17+M18)*INPUT!$C$6/(100+INPUT!$C$6)+(N17+N18)*INPUT!$C$6/(100+INPUT!$C$6)+(O17+O18)*INPUT!$C$6/(100+INPUT!$C$6)+(P17+P18)*INPUT!$C$6/(100+INPUT!$C$6)+(Q17+Q18)*INPUT!$C$6/(100+INPUT!$C$6)+(R17+R18)*INPUT!$C$6/(100+INPUT!$C$6)+(S17+S18)*INPUT!$C$6/(100+INPUT!$C$6)+(T17+T18)*INPUT!$C$6/(100+INPUT!$C$6)+(U17+U18)*INPUT!$C$6/(100+INPUT!$C$6)+(V17+V18)*INPUT!$C$6/(100+INPUT!$C$6)+(W17+W18)*INPUT!$C$6/(100+INPUT!$C$6)+(X17+X18)*INPUT!$C$6/(100+INPUT!$C$6)+(Y17+Y18)*INPUT!$C$6/(100+INPUT!$C$6)+(Z17+Z18)*INPUT!$C$6/(100+INPUT!$C$6)+(AA17+AA18)*INPUT!$C$6/(100+INPUT!$C$6)+(AB17+AB18)*INPUT!$C$6/(100+INPUT!$C$6)+(AC17+AC18)*INPUT!$C$6/(100+INPUT!$C$6)+(AD17+AD18)*INPUT!$C$6/(100+INPUT!$C$6)+(AE17+AE18)*INPUT!$C$6/(100+INPUT!$C$6)+(AF17+AF18)*INPUT!$C$6/(100+INPUT!$C$6)+(AG17+AG18)*INPUT!$C$6/(100+INPUT!$C$6))-SUM(D19:AF19),0) -> 0 | AH19: =MAX((IF($C$136>0,$C$137*D11/$C$136,0)+IF($C$136>0,$C$137*E11/$C$136,0)+IF($C$136>0,$C$137*F11/$C$136,0)+IF($C$136>0,$C$137*G11/$C$136,0)+IF($C$136>0,$C$137*H11/$C$136,0)+IF($C$136>0,$C$137*I11/$C$136,0)+IF($C$136>0,$C$137*J11/$C$136,0)+IF($C$136>0,$C$137*K11/$C$136,0)+IF($C$136>0,$C$137*L11/$C$136,0)+IF($C$136>0,$C$137*M11/$C$136,0)+IF($C$136>0,$C$137*N11/$C$136,0)+IF($C$136>0,$C$137*O11/$C$136,0)+IF($C$136>0,$C$137*P11/$C$136,0)+IF($C$136>0,$C$137*Q11/$C$136,0)+IF($C$136>0,$C$137*R11/$C$136,0)+IF($C$136>0,$C$137*S11/$C$136,0)+IF($C$136>0,$C$137*T11/$C$136,0)+IF($C$136>0,$C$137*U11/$C$136,0)+IF($C$136>0,$C$137*V11/$C$136,0)+IF($C$136>0,$C$137*W11/$C$136,0)+IF($C$136>0,$C$137*X11/$C$136,0)+IF($C$136>0,$C$137*Y11/$C$136,0)+IF($C$136>0,$C$137*Z11/$C$136,0)+IF($C$136>0,$C$137*AA11/$C$136,0)+IF($C$136>0,$C$137*AB11/$C$136,0)+IF($C$136>0,$C$137*AC11/$C$136,0)+IF($C$136>0,$C$137*AD11/$C$136,0)+IF($C$136>0,$C$137*AE11/$C$136,0)+IF($C$136>0,$C$137*AF11/$C$136,0)+IF($C$136>0,$C$137*AG11/$C$136,0)+IF($C$136>0,$C$137*AH11/$C$136,0))-((D17+D18)*INPUT!$C$6/(100+INPUT!$C$6)+(E17+E18)*INPUT!$C$6/(100+INPUT!$C$6)+(F17+F18)*INPUT!$C$6/(100+INPUT!$C$6)+(G17+G18)*INPUT!$C$6/(100+INPUT!$C$6)+(H17+H18)*INPUT!$C$6/(100+INPUT!$C$6)+(I17+I18)*INPUT!$C$6/(100+INPUT!$C$6)+(J17+J18)*INPUT!$C$6/(100+INPUT!$C$6)+(K17+K18)*INPUT!$C$6/(100+INPUT!$C$6)+(L17+L18)*INPUT!$C$6/(100+INPUT!$C$6)+(M17+M18)*INPUT!$C$6/(100+INPUT!$C$6)+(N17+N18)*INPUT!$C$6/(100+INPUT!$C$6)+(O17+O18)*INPUT!$C$6/(100+INPUT!$C$6)+(P17+P18)*INPUT!$C$6/(100+INPUT!$C$6)+(Q17+Q18)*INPUT!$C$6/(100+INPUT!$C$6)+(R17+R18)*INPUT!$C$6/(100+INPUT!$C$6)+(S17+S18)*INPUT!$C$6/(100+INPUT!$C$6)+(T17+T18)*INPUT!$C$6/(100+INPUT!$C$6)+(U17+U18)*INPUT!$C$6/(100+INPUT!$C$6)+(V17+V18)*INPUT!$C$6/(100+INPUT!$C$6)+(W17+W18)*INPUT!$C$6/(100+INPUT!$C$6)+(X17+X18)*INPUT!$C$6/(100+INPUT!$C$6)+(Y17+Y18)*INPUT!$C$6/(100+INPUT!$C$6)+(Z17+Z18)*INPUT!$C$6/(100+INPUT!$C$6)+(AA17+AA18)*INPUT!$C$6/(100+INPUT!$C$6)+(AB17+AB18)*INPUT!$C$6/(100+INPUT!$C$6)+(AC17+AC18)*INPUT!$C$6/(100+INPUT!$C$6)+(AD17+AD18)*INPUT!$C$6/(100+INPUT!$C$6)+(AE17+AE18)*INPUT!$C$6/(100+INPUT!$C$6)+(AF17+AF18)*INPUT!$C$6/(100+INPUT!$C$6)+(AG17+AG18)*INPUT!$C$6/(100+INPUT!$C$6)+(AH17+AH18)*INPUT!$C$6/(100+INPUT!$C$6))-SUM(D19:AG19),0) -> 0 | AI19: =MAX((IF($C$136>0,$C$137*D11/$C$136,0)+IF($C$136>0,$C$137*E11/$C$136,0)+IF($C$136>0,$C$137*F11/$C$136,0)+IF($C$136>0,$C$137*G11/$C$136,0)+IF($C$136>0,$C$137*H11/$C$136,0)+IF($C$136>0,$C$137*I11/$C$136,0)+IF($C$136>0,$C$137*J11/$C$136,0)+IF($C$136>0,$C$137*K11/$C$136,0)+IF($C$136>0,$C$137*L11/$C$136,0)+IF($C$136>0,$C$137*M11/$C$136,0)+IF($C$136>0,$C$137*N11/$C$136,0)+IF($C$136>0,$C$137*O11/$C$136,0)+IF($C$136>0,$C$137*P11/$C$136,0)+IF($C$136>0,$C$137*Q11/$C$136,0)+IF($C$136>0,$C$137*R11/$C$136,0)+IF($C$136>0,$C$137*S11/$C$136,0)+IF($C$136>0,$C$137*T11/$C$136,0)+IF($C$136>0,$C$137*U11/$C$136,0)+IF($C$136>0,$C$137*V11/$C$136,0)+IF($C$136>0,$C$137*W11/$C$136,0)+IF($C$136>0,$C$137*X11/$C$136,0)+IF($C$136>0,$C$137*Y11/$C$136,0)+IF($C$136>0,$C$137*Z11/$C$136,0)+IF($C$136>0,$C$137*AA11/$C$136,0)+IF($C$136>0,$C$137*AB11/$C$136,0)+IF($C$136>0,$C$137*AC11/$C$136,0)+IF($C$136>0,$C$137*AD11/$C$136,0)+IF($C$136>0,$C$137*AE11/$C$136,0)+IF($C$136>0,$C$137*AF11/$C$136,0)+IF($C$136>0,$C$137*AG11/$C$136,0)+IF($C$136>0,$C$137*AH11/$C$136,0)+IF($C$136>0,$C$137*AI11/$C$136,0))-((D17+D18)*INPUT!$C$6/(100+INPUT!$C$6)+(E17+E18)*INPUT!$C$6/(100+INPUT!$C$6)+(F17+F18)*INPUT!$C$6/(100+INPUT!$C$6)+(G17+G18)*INPUT!$C$6/(100+INPUT!$C$6)+(H17+H18)*INPUT!$C$6/(100+INPUT!$C$6)+(I17+I18)*INPUT!$C$6/(100+INPUT!$C$6)+(J17+J18)*INPUT!$C$6/(100+INPUT!$C$6)+(K17+K18)*INPUT!$C$6/(100+INPUT!$C$6)+(L17+L18)*INPUT!$C$6/(100+INPUT!$C$6)+(M17+M18)*INPUT!$C$6/(100+INPUT!$C$6)+(N17+N18)*INPUT!$C$6/(100+INPUT!$C$6)+(O17+O18)*INPUT!$C$6/(100+INPUT!$C$6)+(P17+P18)*INPUT!$C$6/(100+INPUT!$C$6)+(Q17+Q18)*INPUT!$C$6/(100+INPUT!$C$6)+(R17+R18)*INPUT!$C$6/(100+INPUT!$C$6)+(S17+S18)*INPUT!$C$6/(100+INPUT!$C$6)+(T17+T18)*INPUT!$C$6/(100+INPUT!$C$6)+(U17+U18)*INPUT!$C$6/(100+INPUT!$C$6)+(V17+V18)*INPUT!$C$6/(100+INPUT!$C$6)+(W17+W18)*INPUT!$C$6/(100+INPUT!$C$6)+(X17+X18)*INPUT!$C$6/(100+INPUT!$C$6)+(Y17+Y18)*INPUT!$C$6/(100+INPUT!$C$6)+(Z17+Z18)*INPUT!$C$6/(100+INPUT!$C$6)+(AA17+AA18)*INPUT!$C$6/(100+INPUT!$C$6)+(AB17+AB18)*INPUT!$C$6/(100+INPUT!$C$6)+(AC17+AC18)*INPUT!$C$6/(100+INPUT!$C$6)+(AD17+AD18)*INPUT!$C$6/(100+INPUT!$C$6)+(AE17+AE18)*INPUT!$C$6/(100+INPUT!$C$6)+(AF17+AF18)*INPUT!$C$6/(100+INPUT!$C$6)+(AG17+AG18)*INPUT!$C$6/(100+INPUT!$C$6)+(AH17+AH18)*INPUT!$C$6/(100+INPUT!$C$6)+(AI17+AI18)*INPUT!$C$6/(100+INPUT!$C$6))-SUM(D19:AH19),0) -> 0 | AJ19: =MAX((IF($C$136>0,$C$137*D11/$C$136,0)+IF($C$136>0,$C$137*E11/$C$136,0)+IF($C$136>0,$C$137*F11/$C$136,0)+IF($C$136>0,$C$137*G11/$C$136,0)+IF($C$136>0,$C$137*H11/$C$136,0)+IF($C$136>0,$C$137*I11/$C$136,0)+IF($C$136>0,$C$137*J11/$C$136,0)+IF($C$136>0,$C$137*K11/$C$136,0)+IF($C$136>0,$C$137*L11/$C$136,0)+IF($C$136>0,$C$137*M11/$C$136,0)+IF($C$136>0,$C$137*N11/$C$136,0)+IF($C$136>0,$C$137*O11/$C$136,0)+IF($C$136>0,$C$137*P11/$C$136,0)+IF($C$136>0,$C$137*Q11/$C$136,0)+IF($C$136>0,$C$137*R11/$C$136,0)+IF($C$136>0,$C$137*S11/$C$136,0)+IF($C$136>0,$C$137*T11/$C$136,0)+IF($C$136>0,$C$137*U11/$C$136,0)+IF($C$136>0,$C$137*V11/$C$136,0)+IF($C$136>0,$C$137*W11/$C$136,0)+IF($C$136>0,$C$137*X11/$C$136,0)+IF($C$136>0,$C$137*Y11/$C$136,0)+IF($C$136>0,$C$137*Z11/$C$136,0)+IF($C$136>0,$C$137*AA11/$C$136,0)+IF($C$136>0,$C$137*AB11/$C$136,0)+IF($C$136>0,$C$137*AC11/$C$136,0)+IF($C$136>0,$C$137*AD11/$C$136,0)+IF($C$136>0,$C$137*AE11/$C$136,0)+IF($C$136>0,$C$137*AF11/$C$136,0)+IF($C$136>0,$C$137*AG11/$C$136,0)+IF($C$136>0,$C$137*AH11/$C$136,0)+IF($C$136>0,$C$137*AI11/$C$136,0)+IF($C$136>0,$C$137*AJ11/$C$136,0))-((D17+D18)*INPUT!$C$6/(100+INPUT!$C$6)+(E17+E18)*INPUT!$C$6/(100+INPUT!$C$6)+(F17+F18)*INPUT!$C$6/(100+INPUT!$C$6)+(G17+G18)*INPUT!$C$6/(100+INPUT!$C$6)+(H17+H18)*INPUT!$C$6/(100+INPUT!$C$6)+(I17+I18)*INPUT!$C$6/(100+INPUT!$C$6)+(J17+J18)*INPUT!$C$6/(100+INPUT!$C$6)+(K17+K18)*INPUT!$C$6/(100+INPUT!$C$6)+(L17+L18)*INPUT!$C$6/(100+INPUT!$C$6)+(M17+M18)*INPUT!$C$6/(100+INPUT!$C$6)+(N17+N18)*INPUT!$C$6/(100+INPUT!$C$6)+(O17+O18)*INPUT!$C$6/(100+INPUT!$C$6)+(P17+P18)*INPUT!$C$6/(100+INPUT!$C$6)+(Q17+Q18)*INPUT!$C$6/(100+INPUT!$C$6)+(R17+R18)*INPUT!$C$6/(100+INPUT!$C$6)+(S17+S18)*INPUT!$C$6/(100+INPUT!$C$6)+(T17+T18)*INPUT!$C$6/(100+INPUT!$C$6)+(U17+U18)*INPUT!$C$6/(100+INPUT!$C$6)+(V17+V18)*INPUT!$C$6/(100+INPUT!$C$6)+(W17+W18)*INPUT!$C$6/(100+INPUT!$C$6)+(X17+X18)*INPUT!$C$6/(100+INPUT!$C$6)+(Y17+Y18)*INPUT!$C$6/(100+INPUT!$C$6)+(Z17+Z18)*INPUT!$C$6/(100+INPUT!$C$6)+(AA17+AA18)*INPUT!$C$6/(100+INPUT!$C$6)+(AB17+AB18)*INPUT!$C$6/(100+INPUT!$C$6)+(AC17+AC18)*INPUT!$C$6/(100+INPUT!$C$6)+(AD17+AD18)*INPUT!$C$6/(100+INPUT!$C$6)+(AE17+AE18)*INPUT!$C$6/(100+INPUT!$C$6)+(AF17+AF18)*INPUT!$C$6/(100+INPUT!$C$6)+(AG17+AG18)*INPUT!$C$6/(100+INPUT!$C$6)+(AH17+AH18)*INPUT!$C$6/(100+INPUT!$C$6)+(AI17+AI18)*INPUT!$C$6/(100+INPUT!$C$6)+(AJ17+AJ18)*INPUT!$C$6/(100+INPUT!$C$6))-SUM(D19:AI19),0) -> 0 | AK19: =MAX((IF($C$136>0,$C$137*D11/$C$136,0)+IF($C$136>0,$C$137*E11/$C$136,0)+IF($C$136>0,$C$137*F11/$C$136,0)+IF($C$136>0,$C$137*G11/$C$136,0)+IF($C$136>0,$C$137*H11/$C$136,0)+IF($C$136>0,$C$137*I11/$C$136,0)+IF($C$136>0,$C$137*J11/$C$136,0)+IF($C$136>0,$C$137*K11/$C$136,0)+IF($C$136>0,$C$137*L11/$C$136,0)+IF($C$136>0,$C$137*M11/$C$136,0)+IF($C$136>0,$C$137*N11/$C$136,0)+IF($C$136>0,$C$137*O11/$C$136,0)+IF($C$136>0,$C$137*P11/$C$136,0)+IF($C$136>0,$C$137*Q11/$C$136,0)+IF($C$136>0,$C$137*R11/$C$136,0)+IF($C$136>0,$C$137*S11/$C$136,0)+IF($C$136>0,$C$137*T11/$C$136,0)+IF($C$136>0,$C$137*U11/$C$136,0)+IF($C$136>0,$C$137*V11/$C$136,0)+IF($C$136>0,$C$137*W11/$C$136,0)+IF($C$136>0,$C$137*X11/$C$136,0)+IF($C$136>0,$C$137*Y11/$C$136,0)+IF($C$136>0,$C$137*Z11/$C$136,0)+IF($C$136>0,$C$137*AA11/$C$136,0)+IF($C$136>0,$C$137*AB11/$C$136,0)+IF($C$136>0,$C$137*AC11/$C$136,0)+IF($C$136>0,$C$137*AD11/$C$136,0)+IF($C$136>0,$C$137*AE11/$C$136,0)+IF($C$136>0,$C$137*AF11/$C$136,0)+IF($C$136>0,$C$137*AG11/$C$136,0)+IF($C$136>0,$C$137*AH11/$C$136,0)+IF($C$136>0,$C$137*AI11/$C$136,0)+IF($C$136>0,$C$137*AJ11/$C$136,0)+IF($C$136>0,$C$137*AK11/$C$136,0))-((D17+D18)*INPUT!$C$6/(100+INPUT!$C$6)+(E17+E18)*INPUT!$C$6/(100+INPUT!$C$6)+(F17+F18)*INPUT!$C$6/(100+INPUT!$C$6)+(G17+G18)*INPUT!$C$6/(100+INPUT!$C$6)+(H17+H18)*INPUT!$C$6/(100+INPUT!$C$6)+(I17+I18)*INPUT!$C$6/(100+INPUT!$C$6)+(J17+J18)*INPUT!$C$6/(100+INPUT!$C$6)+(K17+K18)*INPUT!$C$6/(100+INPUT!$C$6)+(L17+L18)*INPUT!$C$6/(100+INPUT!$C$6)+(M17+M18)*INPUT!$C$6/(100+INPUT!$C$6)+(N17+N18)*INPUT!$C$6/(100+INPUT!$C$6)+(O17+O18)*INPUT!$C$6/(100+INPUT!$C$6)+(P17+P18)*INPUT!$C$6/(100+INPUT!$C$6)+(Q17+Q18)*INPUT!$C$6/(100+INPUT!$C$6)+(R17+R18)*INPUT!$C$6/(100+INPUT!$C$6)+(S17+S18)*INPUT!$C$6/(100+INPUT!$C$6)+(T17+T18)*INPUT!$C$6/(100+INPUT!$C$6)+(U17+U18)*INPUT!$C$6/(100+INPUT!$C$6)+(V17+V18)*INPUT!$C$6/(100+INPUT!$C$6)+(W17+W18)*INPUT!$C$6/(100+INPUT!$C$6)+(X17+X18)*INPUT!$C$6/(100+INPUT!$C$6)+(Y17+Y18)*INPUT!$C$6/(100+INPUT!$C$6)+(Z17+Z18)*INPUT!$C$6/(100+INPUT!$C$6)+(AA17+AA18)*INPUT!$C$6/(100+INPUT!$C$6)+(AB17+AB18)*INPUT!$C$6/(100+INPUT!$C$6)+(AC17+AC18)*INPUT!$C$6/(100+INPUT!$C$6)+(AD17+AD18)*INPUT!$C$6/(100+INPUT!$C$6)+(AE17+AE18)*INPUT!$C$6/(100+INPUT!$C$6)+(AF17+AF18)*INPUT!$C$6/(100+INPUT!$C$6)+(AG17+AG18)*INPUT!$C$6/(100+INPUT!$C$6)+(AH17+AH18)*INPUT!$C$6/(100+INPUT!$C$6)+(AI17+AI18)*INPUT!$C$6/(100+INPUT!$C$6)+(AJ17+AJ18)*INPUT!$C$6/(100+INPUT!$C$6)+(AK17+AK18)*INPUT!$C$6/(100+INPUT!$C$6))-SUM(D19:AJ19),0) -> 0 | AL19: =MAX((IF($C$136>0,$C$137*D11/$C$136,0)+IF($C$136>0,$C$137*E11/$C$136,0)+IF($C$136>0,$C$137*F11/$C$136,0)+IF($C$136>0,$C$137*G11/$C$136,0)+IF($C$136>0,$C$137*H11/$C$136,0)+IF($C$136>0,$C$137*I11/$C$136,0)+IF($C$136>0,$C$137*J11/$C$136,0)+IF($C$136>0,$C$137*K11/$C$136,0)+IF($C$136>0,$C$137*L11/$C$136,0)+IF($C$136>0,$C$137*M11/$C$136,0)+IF($C$136>0,$C$137*N11/$C$136,0)+IF($C$136>0,$C$137*O11/$C$136,0)+IF($C$136>0,$C$137*P11/$C$136,0)+IF($C$136>0,$C$137*Q11/$C$136,0)+IF($C$136>0,$C$137*R11/$C$136,0)+IF($C$136>0,$C$137*S11/$C$136,0)+IF($C$136>0,$C$137*T11/$C$136,0)+IF($C$136>0,$C$137*U11/$C$136,0)+IF($C$136>0,$C$137*V11/$C$136,0)+IF($C$136>0,$C$137*W11/$C$136,0)+IF($C$136>0,$C$137*X11/$C$136,0)+IF($C$136>0,$C$137*Y11/$C$136,0)+IF($C$136>0,$C$137*Z11/$C$136,0)+IF($C$136>0,$C$137*AA11/$C$136,0)+IF($C$136>0,$C$137*AB11/$C$136,0)+IF($C$136>0,$C$137*AC11/$C$136,0)+IF($C$136>0,$C$137*AD11/$C$136,0)+IF($C$136>0,$C$137*AE11/$C$136,0)+IF($C$136>0,$C$137*AF11/$C$136,0)+IF($C$136>0,$C$137*AG11/$C$136,0)+IF($C$136>0,$C$137*AH11/$C$136,0)+IF($C$136>0,$C$137*AI11/$C$136,0)+IF($C$136>0,$C$137*AJ11/$C$136,0)+IF($C$136>0,$C$137*AK11/$C$136,0)+IF($C$136>0,$C$137*AL11/$C$136,0))-((D17+D18)*INPUT!$C$6/(100+INPUT!$C$6)+(E17+E18)*INPUT!$C$6/(100+INPUT!$C$6)+(F17+F18)*INPUT!$C$6/(100+INPUT!$C$6)+(G17+G18)*INPUT!$C$6/(100+INPUT!$C$6)+(H17+H18)*INPUT!$C$6/(100+INPUT!$C$6)+(I17+I18)*INPUT!$C$6/(100+INPUT!$C$6)+(J17+J18)*INPUT!$C$6/(100+INPUT!$C$6)+(K17+K18)*INPUT!$C$6/(100+INPUT!$C$6)+(L17+L18)*INPUT!$C$6/(100+INPUT!$C$6)+(M17+M18)*INPUT!$C$6/(100+INPUT!$C$6)+(N17+N18)*INPUT!$C$6/(100+INPUT!$C$6)+(O17+O18)*INPUT!$C$6/(100+INPUT!$C$6)+(P17+P18)*INPUT!$C$6/(100+INPUT!$C$6)+(Q17+Q18)*INPUT!$C$6/(100+INPUT!$C$6)+(R17+R18)*INPUT!$C$6/(100+INPUT!$C$6)+(S17+S18)*INPUT!$C$6/(100+INPUT!$C$6)+(T17+T18)*INPUT!$C$6/(100+INPUT!$C$6)+(U17+U18)*INPUT!$C$6/(100+INPUT!$C$6)+(V17+V18)*INPUT!$C$6/(100+INPUT!$C$6)+(W17+W18)*INPUT!$C$6/(100+INPUT!$C$6)+(X17+X18)*INPUT!$C$6/(100+INPUT!$C$6)+(Y17+Y18)*INPUT!$C$6/(100+INPUT!$C$6)+(Z17+Z18)*INPUT!$C$6/(100+INPUT!$C$6)+(AA17+AA18)*INPUT!$C$6/(100+INPUT!$C$6)+(AB17+AB18)*INPUT!$C$6/(100+INPUT!$C$6)+(AC17+AC18)*INPUT!$C$6/(100+INPUT!$C$6)+(AD17+AD18)*INPUT!$C$6/(100+INPUT!$C$6)+(AE17+AE18)*INPUT!$C$6/(100+INPUT!$C$6)+(AF17+AF18)*INPUT!$C$6/(100+INPUT!$C$6)+(AG17+AG18)*INPUT!$C$6/(100+INPUT!$C$6)+(AH17+AH18)*INPUT!$C$6/(100+INPUT!$C$6)+(AI17+AI18)*INPUT!$C$6/(100+INPUT!$C$6)+(AJ17+AJ18)*INPUT!$C$6/(100+INPUT!$C$6)+(AK17+AK18)*INPUT!$C$6/(100+INPUT!$C$6)+(AL17+AL18)*INPUT!$C$6/(100+INPUT!$C$6))-SUM(D19:AK19),0) -> 0 | AM19: =MAX((IF($C$136>0,$C$137*D11/$C$136,0)+IF($C$136>0,$C$137*E11/$C$136,0)+IF($C$136>0,$C$137*F11/$C$136,0)+IF($C$136>0,$C$137*G11/$C$136,0)+IF($C$136>0,$C$137*H11/$C$136,0)+IF($C$136>0,$C$137*I11/$C$136,0)+IF($C$136>0,$C$137*J11/$C$136,0)+IF($C$136>0,$C$137*K11/$C$136,0)+IF($C$136>0,$C$137*L11/$C$136,0)+IF($C$136>0,$C$137*M11/$C$136,0)+IF($C$136>0,$C$137*N11/$C$136,0)+IF($C$136>0,$C$137*O11/$C$136,0)+IF($C$136>0,$C$137*P11/$C$136,0)+IF($C$136>0,$C$137*Q11/$C$136,0)+IF($C$136>0,$C$137*R11/$C$136,0)+IF($C$136>0,$C$137*S11/$C$136,0)+IF($C$136>0,$C$137*T11/$C$136,0)+IF($C$136>0,$C$137*U11/$C$136,0)+IF($C$136>0,$C$137*V11/$C$136,0)+IF($C$136>0,$C$137*W11/$C$136,0)+IF($C$136>0,$C$137*X11/$C$136,0)+IF($C$136>0,$C$137*Y11/$C$136,0)+IF($C$136>0,$C$137*Z11/$C$136,0)+IF($C$136>0,$C$137*AA11/$C$136,0)+IF($C$136>0,$C$137*AB11/$C$136,0)+IF($C$136>0,$C$137*AC11/$C$136,0)+IF($C$136>0,$C$137*AD11/$C$136,0)+IF($C$136>0,$C$137*AE11/$C$136,0)+IF($C$136>0,$C$137*AF11/$C$136,0)+IF($C$136>0,$C$137*AG11/$C$136,0)+IF($C$136>0,$C$137*AH11/$C$136,0)+IF($C$136>0,$C$137*AI11/$C$136,0)+IF($C$136>0,$C$137*AJ11/$C$136,0)+IF($C$136>0,$C$137*AK11/$C$136,0)+IF($C$136>0,$C$137*AL11/$C$136,0)+IF($C$136>0,$C$137*AM11/$C$136,0))-((D17+D18)*INPUT!$C$6/(100+INPUT!$C$6)+(E17+E18)*INPUT!$C$6/(100+INPUT!$C$6)+(F17+F18)*INPUT!$C$6/(100+INPUT!$C$6)+(G17+G18)*INPUT!$C$6/(100+INPUT!$C$6)+(H17+H18)*INPUT!$C$6/(100+INPUT!$C$6)+(I17+I18)*INPUT!$C$6/(100+INPUT!$C$6)+(J17+J18)*INPUT!$C$6/(100+INPUT!$C$6)+(K17+K18)*INPUT!$C$6/(100+INPUT!$C$6)+(L17+L18)*INPUT!$C$6/(100+INPUT!$C$6)+(M17+M18)*INPUT!$C$6/(100+INPUT!$C$6)+(N17+N18)*INPUT!$C$6/(100+INPUT!$C$6)+(O17+O18)*INPUT!$C$6/(100+INPUT!$C$6)+(P17+P18)*INPUT!$C$6/(100+INPUT!$C$6)+(Q17+Q18)*INPUT!$C$6/(100+INPUT!$C$6)+(R17+R18)*INPUT!$C$6/(100+INPUT!$C$6)+(S17+S18)*INPUT!$C$6/(100+INPUT!$C$6)+(T17+T18)*INPUT!$C$6/(100+INPUT!$C$6)+(U17+U18)*INPUT!$C$6/(100+INPUT!$C$6)+(V17+V18)*INPUT!$C$6/(100+INPUT!$C$6)+(W17+W18)*INPUT!$C$6/(100+INPUT!$C$6)+(X17+X18)*INPUT!$C$6/(100+INPUT!$C$6)+(Y17+Y18)*INPUT!$C$6/(100+INPUT!$C$6)+(Z17+Z18)*INPUT!$C$6/(100+INPUT!$C$6)+(AA17+AA18)*INPUT!$C$6/(100+INPUT!$C$6)+(AB17+AB18)*INPUT!$C$6/(100+INPUT!$C$6)+(AC17+AC18)*INPUT!$C$6/(100+INPUT!$C$6)+(AD17+AD18)*INPUT!$C$6/(100+INPUT!$C$6)+(AE17+AE18)*INPUT!$C$6/(100+INPUT!$C$6)+(AF17+AF18)*INPUT!$C$6/(100+INPUT!$C$6)+(AG17+AG18)*INPUT!$C$6/(100+INPUT!$C$6)+(AH17+AH18)*INPUT!$C$6/(100+INPUT!$C$6)+(AI17+AI18)*INPUT!$C$6/(100+INPUT!$C$6)+(AJ17+AJ18)*INPUT!$C$6/(100+INPUT!$C$6)+(AK17+AK18)*INPUT!$C$6/(100+INPUT!$C$6)+(AL17+AL18)*INPUT!$C$6/(100+INPUT!$C$6)+(AM17+AM18)*INPUT!$C$6/(100+INPUT!$C$6))-SUM(D19:AL19),0) -> 0 | AN19: =MAX((IF($C$136>0,$C$137*D11/$C$136,0)+IF($C$136>0,$C$137*E11/$C$136,0)+IF($C$136>0,$C$137*F11/$C$136,0)+IF($C$136>0,$C$137*G11/$C$136,0)+IF($C$136>0,$C$137*H11/$C$136,0)+IF($C$136>0,$C$137*I11/$C$136,0)+IF($C$136>0,$C$137*J11/$C$136,0)+IF($C$136>0,$C$137*K11/$C$136,0)+IF($C$136>0,$C$137*L11/$C$136,0)+IF($C$136>0,$C$137*M11/$C$136,0)+IF($C$136>0,$C$137*N11/$C$136,0)+IF($C$136>0,$C$137*O11/$C$136,0)+IF($C$136>0,$C$137*P11/$C$136,0)+IF($C$136>0,$C$137*Q11/$C$136,0)+IF($C$136>0,$C$137*R11/$C$136,0)+IF($C$136>0,$C$137*S11/$C$136,0)+IF($C$136>0,$C$137*T11/$C$136,0)+IF($C$136>0,$C$137*U11/$C$136,0)+IF($C$136>0,$C$137*V11/$C$136,0)+IF($C$136>0,$C$137*W11/$C$136,0)+IF($C$136>0,$C$137*X11/$C$136,0)+IF($C$136>0,$C$137*Y11/$C$136,0)+IF($C$136>0,$C$137*Z11/$C$136,0)+IF($C$136>0,$C$137*AA11/$C$136,0)+IF($C$136>0,$C$137*AB11/$C$136,0)+IF($C$136>0,$C$137*AC11/$C$136,0)+IF($C$136>0,$C$137*AD11/$C$136,0)+IF($C$136>0,$C$137*AE11/$C$136,0)+IF($C$136>0,$C$137*AF11/$C$136,0)+IF($C$136>0,$C$137*AG11/$C$136,0)+IF($C$136>0,$C$137*AH11/$C$136,0)+IF($C$136>0,$C$137*AI11/$C$136,0)+IF($C$136>0,$C$137*AJ11/$C$136,0)+IF($C$136>0,$C$137*AK11/$C$136,0)+IF($C$136>0,$C$137*AL11/$C$136,0)+IF($C$136>0,$C$137*AM11/$C$136,0)+IF($C$136>0,$C$137*AN11/$C$136,0))-((D17+D18)*INPUT!$C$6/(100+INPUT!$C$6)+(E17+E18)*INPUT!$C$6/(100+INPUT!$C$6)+(F17+F18)*INPUT!$C$6/(100+INPUT!$C$6)+(G17+G18)*INPUT!$C$6/(100+INPUT!$C$6)+(H17+H18)*INPUT!$C$6/(100+INPUT!$C$6)+(I17+I18)*INPUT!$C$6/(100+INPUT!$C$6)+(J17+J18)*INPUT!$C$6/(100+INPUT!$C$6)+(K17+K18)*INPUT!$C$6/(100+INPUT!$C$6)+(L17+L18)*INPUT!$C$6/(100+INPUT!$C$6)+(M17+M18)*INPUT!$C$6/(100+INPUT!$C$6)+(N17+N18)*INPUT!$C$6/(100+INPUT!$C$6)+(O17+O18)*INPUT!$C$6/(100+INPUT!$C$6)+(P17+P18)*INPUT!$C$6/(100+INPUT!$C$6)+(Q17+Q18)*INPUT!$C$6/(100+INPUT!$C$6)+(R17+R18)*INPUT!$C$6/(100+INPUT!$C$6)+(S17+S18)*INPUT!$C$6/(100+INPUT!$C$6)+(T17+T18)*INPUT!$C$6/(100+INPUT!$C$6)+(U17+U18)*INPUT!$C$6/(100+INPUT!$C$6)+(V17+V18)*INPUT!$C$6/(100+INPUT!$C$6)+(W17+W18)*INPUT!$C$6/(100+INPUT!$C$6)+(X17+X18)*INPUT!$C$6/(100+INPUT!$C$6)+(Y17+Y18)*INPUT!$C$6/(100+INPUT!$C$6)+(Z17+Z18)*INPUT!$C$6/(100+INPUT!$C$6)+(AA17+AA18)*INPUT!$C$6/(100+INPUT!$C$6)+(AB17+AB18)*INPUT!$C$6/(100+INPUT!$C$6)+(AC17+AC18)*INPUT!$C$6/(100+INPUT!$C$6)+(AD17+AD18)*INPUT!$C$6/(100+INPUT!$C$6)+(AE17+AE18)*INPUT!$C$6/(100+INPUT!$C$6)+(AF17+AF18)*INPUT!$C$6/(100+INPUT!$C$6)+(AG17+AG18)*INPUT!$C$6/(100+INPUT!$C$6)+(AH17+AH18)*INPUT!$C$6/(100+INPUT!$C$6)+(AI17+AI18)*INPUT!$C$6/(100+INPUT!$C$6)+(AJ17+AJ18)*INPUT!$C$6/(100+INPUT!$C$6)+(AK17+AK18)*INPUT!$C$6/(100+INPUT!$C$6)+(AL17+AL18)*INPUT!$C$6/(100+INPUT!$C$6)+(AM17+AM18)*INPUT!$C$6/(100+INPUT!$C$6)+(AN17+AN18)*INPUT!$C$6/(100+INPUT!$C$6))-SUM(D19:AM19),0) -> 0 | AO19: =MAX((IF($C$136>0,$C$137*D11/$C$136,0)+IF($C$136>0,$C$137*E11/$C$136,0)+IF($C$136>0,$C$137*F11/$C$136,0)+IF($C$136>0,$C$137*G11/$C$136,0)+IF($C$136>0,$C$137*H11/$C$136,0)+IF($C$136>0,$C$137*I11/$C$136,0)+IF($C$136>0,$C$137*J11/$C$136,0)+IF($C$136>0,$C$137*K11/$C$136,0)+IF($C$136>0,$C$137*L11/$C$136,0)+IF($C$136>0,$C$137*M11/$C$136,0)+IF($C$136>0,$C$137*N11/$C$136,0)+IF($C$136>0,$C$137*O11/$C$136,0)+IF($C$136>0,$C$137*P11/$C$136,0)+IF($C$136>0,$C$137*Q11/$C$136,0)+IF($C$136>0,$C$137*R11/$C$136,0)+IF($C$136>0,$C$137*S11/$C$136,0)+IF($C$136>0,$C$137*T11/$C$136,0)+IF($C$136>0,$C$137*U11/$C$136,0)+IF($C$136>0,$C$137*V11/$C$136,0)+IF($C$136>0,$C$137*W11/$C$136,0)+IF($C$136>0,$C$137*X11/$C$136,0)+IF($C$136>0,$C$137*Y11/$C$136,0)+IF($C$136>0,$C$137*Z11/$C$136,0)+IF($C$136>0,$C$137*AA11/$C$136,0)+IF($C$136>0,$C$137*AB11/$C$136,0)+IF($C$136>0,$C$137*AC11/$C$136,0)+IF($C$136>0,$C$137*AD11/$C$136,0)+IF($C$136>0,$C$137*AE11/$C$136,0)+IF($C$136>0,$C$137*AF11/$C$136,0)+IF($C$136>0,$C$137*AG11/$C$136,0)+IF($C$136>0,$C$137*AH11/$C$136,0)+IF($C$136>0,$C$137*AI11/$C$136,0)+IF($C$136>0,$C$137*AJ11/$C$136,0)+IF($C$136>0,$C$137*AK11/$C$136,0)+IF($C$136>0,$C$137*AL11/$C$136,0)+IF($C$136>0,$C$137*AM11/$C$136,0)+IF($C$136>0,$C$137*AN11/$C$136,0)+IF($C$136>0,$C$137*AO11/$C$136,0))-((D17+D18)*INPUT!$C$6/(100+INPUT!$C$6)+(E17+E18)*INPUT!$C$6/(100+INPUT!$C$6)+(F17+F18)*INPUT!$C$6/(100+INPUT!$C$6)+(G17+G18)*INPUT!$C$6/(100+INPUT!$C$6)+(H17+H18)*INPUT!$C$6/(100+INPUT!$C$6)+(I17+I18)*INPUT!$C$6/(100+INPUT!$C$6)+(J17+J18)*INPUT!$C$6/(100+INPUT!$C$6)+(K17+K18)*INPUT!$C$6/(100+INPUT!$C$6)+(L17+L18)*INPUT!$C$6/(100+INPUT!$C$6)+(M17+M18)*INPUT!$C$6/(100+INPUT!$C$6)+(N17+N18)*INPUT!$C$6/(100+INPUT!$C$6)+(O17+O18)*INPUT!$C$6/(100+INPUT!$C$6)+(P17+P18)*INPUT!$C$6/(100+INPUT!$C$6)+(Q17+Q18)*INPUT!$C$6/(100+INPUT!$C$6)+(R17+R18)*INPUT!$C$6/(100+INPUT!$C$6)+(S17+S18)*INPUT!$C$6/(100+INPUT!$C$6)+(T17+T18)*INPUT!$C$6/(100+INPUT!$C$6)+(U17+U18)*INPUT!$C$6/(100+INPUT!$C$6)+(V17+V18)*INPUT!$C$6/(100+INPUT!$C$6)+(W17+W18)*INPUT!$C$6/(100+INPUT!$C$6)+(X17+X18)*INPUT!$C$6/(100+INPUT!$C$6)+(Y17+Y18)*INPUT!$C$6/(100+INPUT!$C$6)+(Z17+Z18)*INPUT!$C$6/(100+INPUT!$C$6)+(AA17+AA18)*INPUT!$C$6/(100+INPUT!$C$6)+(AB17+AB18)*INPUT!$C$6/(100+INPUT!$C$6)+(AC17+AC18)*INPUT!$C$6/(100+INPUT!$C$6)+(AD17+AD18)*INPUT!$C$6/(100+INPUT!$C$6)+(AE17+AE18)*INPUT!$C$6/(100+INPUT!$C$6)+(AF17+AF18)*INPUT!$C$6/(100+INPUT!$C$6)+(AG17+AG18)*INPUT!$C$6/(100+INPUT!$C$6)+(AH17+AH18)*INPUT!$C$6/(100+INPUT!$C$6)+(AI17+AI18)*INPUT!$C$6/(100+INPUT!$C$6)+(AJ17+AJ18)*INPUT!$C$6/(100+INPUT!$C$6)+(AK17+AK18)*INPUT!$C$6/(100+INPUT!$C$6)+(AL17+AL18)*INPUT!$C$6/(100+INPUT!$C$6)+(AM17+AM18)*INPUT!$C$6/(100+INPUT!$C$6)+(AN17+AN18)*INPUT!$C$6/(100+INPUT!$C$6)+(AO17+AO18)*INPUT!$C$6/(100+INPUT!$C$6))-SUM(D19:AN19),0) -> 0 | AP19: =MAX((IF($C$136>0,$C$137*D11/$C$136,0)+IF($C$136>0,$C$137*E11/$C$136,0)+IF($C$136>0,$C$137*F11/$C$136,0)+IF($C$136>0,$C$137*G11/$C$136,0)+IF($C$136>0,$C$137*H11/$C$136,0)+IF($C$136>0,$C$137*I11/$C$136,0)+IF($C$136>0,$C$137*J11/$C$136,0)+IF($C$136>0,$C$137*K11/$C$136,0)+IF($C$136>0,$C$137*L11/$C$136,0)+IF($C$136>0,$C$137*M11/$C$136,0)+IF($C$136>0,$C$137*N11/$C$136,0)+IF($C$136>0,$C$137*O11/$C$136,0)+IF($C$136>0,$C$137*P11/$C$136,0)+IF($C$136>0,$C$137*Q11/$C$136,0)+IF($C$136>0,$C$137*R11/$C$136,0)+IF($C$136>0,$C$137*S11/$C$136,0)+IF($C$136>0,$C$137*T11/$C$136,0)+IF($C$136>0,$C$137*U11/$C$136,0)+IF($C$136>0,$C$137*V11/$C$136,0)+IF($C$136>0,$C$137*W11/$C$136,0)+IF($C$136>0,$C$137*X11/$C$136,0)+IF($C$136>0,$C$137*Y11/$C$136,0)+IF($C$136>0,$C$137*Z11/$C$136,0)+IF($C$136>0,$C$137*AA11/$C$136,0)+IF($C$136>0,$C$137*AB11/$C$136,0)+IF($C$136>0,$C$137*AC11/$C$136,0)+IF($C$136>0,$C$137*AD11/$C$136,0)+IF($C$136>0,$C$137*AE11/$C$136,0)+IF($C$136>0,$C$137*AF11/$C$136,0)+IF($C$136>0,$C$137*AG11/$C$136,0)+IF($C$136>0,$C$137*AH11/$C$136,0)+IF($C$136>0,$C$137*AI11/$C$136,0)+IF($C$136>0,$C$137*AJ11/$C$136,0)+IF($C$136>0,$C$137*AK11/$C$136,0)+IF($C$136>0,$C$137*AL11/$C$136,0)+IF($C$136>0,$C$137*AM11/$C$136,0)+IF($C$136>0,$C$137*AN11/$C$136,0)+IF($C$136>0,$C$137*AO11/$C$136,0)+IF($C$136>0,$C$137*AP11/$C$136,0))-((D17+D18)*INPUT!$C$6/(100+INPUT!$C$6)+(E17+E18)*INPUT!$C$6/(100+INPUT!$C$6)+(F17+F18)*INPUT!$C$6/(100+INPUT!$C$6)+(G17+G18)*INPUT!$C$6/(100+INPUT!$C$6)+(H17+H18)*INPUT!$C$6/(100+INPUT!$C$6)+(I17+I18)*INPUT!$C$6/(100+INPUT!$C$6)+(J17+J18)*INPUT!$C$6/(100+INPUT!$C$6)+(K17+K18)*INPUT!$C$6/(100+INPUT!$C$6)+(L17+L18)*INPUT!$C$6/(100+INPUT!$C$6)+(M17+M18)*INPUT!$C$6/(100+INPUT!$C$6)+(N17+N18)*INPUT!$C$6/(100+INPUT!$C$6)+(O17+O18)*INPUT!$C$6/(100+INPUT!$C$6)+(P17+P18)*INPUT!$C$6/(100+INPUT!$C$6)+(Q17+Q18)*INPUT!$C$6/(100+INPUT!$C$6)+(R17+R18)*INPUT!$C$6/(100+INPUT!$C$6)+(S17+S18)*INPUT!$C$6/(100+INPUT!$C$6)+(T17+T18)*INPUT!$C$6/(100+INPUT!$C$6)+(U17+U18)*INPUT!$C$6/(100+INPUT!$C$6)+(V17+V18)*INPUT!$C$6/(100+INPUT!$C$6)+(W17+W18)*INPUT!$C$6/(100+INPUT!$C$6)+(X17+X18)*INPUT!$C$6/(100+INPUT!$C$6)+(Y17+Y18)*INPUT!$C$6/(100+INPUT!$C$6)+(Z17+Z18)*INPUT!$C$6/(100+INPUT!$C$6)+(AA17+AA18)*INPUT!$C$6/(100+INPUT!$C$6)+(AB17+AB18)*INPUT!$C$6/(100+INPUT!$C$6)+(AC17+AC18)*INPUT!$C$6/(100+INPUT!$C$6)+(AD17+AD18)*INPUT!$C$6/(100+INPUT!$C$6)+(AE17+AE18)*INPUT!$C$6/(100+INPUT!$C$6)+(AF17+AF18)*INPUT!$C$6/(100+INPUT!$C$6)+(AG17+AG18)*INPUT!$C$6/(100+INPUT!$C$6)+(AH17+AH18)*INPUT!$C$6/(100+INPUT!$C$6)+(AI17+AI18)*INPUT!$C$6/(100+INPUT!$C$6)+(AJ17+AJ18)*INPUT!$C$6/(100+INPUT!$C$6)+(AK17+AK18)*INPUT!$C$6/(100+INPUT!$C$6)+(AL17+AL18)*INPUT!$C$6/(100+INPUT!$C$6)+(AM17+AM18)*INPUT!$C$6/(100+INPUT!$C$6)+(AN17+AN18)*INPUT!$C$6/(100+INPUT!$C$6)+(AO17+AO18)*INPUT!$C$6/(100+INPUT!$C$6)+(AP17+AP18)*INPUT!$C$6/(100+INPUT!$C$6))-SUM(D19:AO19),0) -> 0 | AQ19: =MAX((IF($C$136>0,$C$137*D11/$C$136,0)+IF($C$136>0,$C$137*E11/$C$136,0)+IF($C$136>0,$C$137*F11/$C$136,0)+IF($C$136>0,$C$137*G11/$C$136,0)+IF($C$136>0,$C$137*H11/$C$136,0)+IF($C$136>0,$C$137*I11/$C$136,0)+IF($C$136>0,$C$137*J11/$C$136,0)+IF($C$136>0,$C$137*K11/$C$136,0)+IF($C$136>0,$C$137*L11/$C$136,0)+IF($C$136>0,$C$137*M11/$C$136,0)+IF($C$136>0,$C$137*N11/$C$136,0)+IF($C$136>0,$C$137*O11/$C$136,0)+IF($C$136>0,$C$137*P11/$C$136,0)+IF($C$136>0,$C$137*Q11/$C$136,0)+IF($C$136>0,$C$137*R11/$C$136,0)+IF($C$136>0,$C$137*S11/$C$136,0)+IF($C$136>0,$C$137*T11/$C$136,0)+IF($C$136>0,$C$137*U11/$C$136,0)+IF($C$136>0,$C$137*V11/$C$136,0)+IF($C$136>0,$C$137*W11/$C$136,0)+IF($C$136>0,$C$137*X11/$C$136,0)+IF($C$136>0,$C$137*Y11/$C$136,0)+IF($C$136>0,$C$137*Z11/$C$136,0)+IF($C$136>0,$C$137*AA11/$C$136,0)+IF($C$136>0,$C$137*AB11/$C$136,0)+IF($C$136>0,$C$137*AC11/$C$136,0)+IF($C$136>0,$C$137*AD11/$C$136,0)+IF($C$136>0,$C$137*AE11/$C$136,0)+IF($C$136>0,$C$137*AF11/$C$136,0)+IF($C$136>0,$C$137*AG11/$C$136,0)+IF($C$136>0,$C$137*AH11/$C$136,0)+IF($C$136>0,$C$137*AI11/$C$136,0)+IF($C$136>0,$C$137*AJ11/$C$136,0)+IF($C$136>0,$C$137*AK11/$C$136,0)+IF($C$136>0,$C$137*AL11/$C$136,0)+IF($C$136>0,$C$137*AM11/$C$136,0)+IF($C$136>0,$C$137*AN11/$C$136,0)+IF($C$136>0,$C$137*AO11/$C$136,0)+IF($C$136>0,$C$137*AP11/$C$136,0)+IF($C$136>0,$C$137*AQ11/$C$136,0))-((D17+D18)*INPUT!$C$6/(100+INPUT!$C$6)+(E17+E18)*INPUT!$C$6/(100+INPUT!$C$6)+(F17+F18)*INPUT!$C$6/(100+INPUT!$C$6)+(G17+G18)*INPUT!$C$6/(100+INPUT!$C$6)+(H17+H18)*INPUT!$C$6/(100+INPUT!$C$6)+(I17+I18)*INPUT!$C$6/(100+INPUT!$C$6)+(J17+J18)*INPUT!$C$6/(100+INPUT!$C$6)+(K17+K18)*INPUT!$C$6/(100+INPUT!$C$6)+(L17+L18)*INPUT!$C$6/(100+INPUT!$C$6)+(M17+M18)*INPUT!$C$6/(100+INPUT!$C$6)+(N17+N18)*INPUT!$C$6/(100+INPUT!$C$6)+(O17+O18)*INPUT!$C$6/(100+INPUT!$C$6)+(P17+P18)*INPUT!$C$6/(100+INPUT!$C$6)+(Q17+Q18)*INPUT!$C$6/(100+INPUT!$C$6)+(R17+R18)*INPUT!$C$6/(100+INPUT!$C$6)+(S17+S18)*INPUT!$C$6/(100+INPUT!$C$6)+(T17+T18)*INPUT!$C$6/(100+INPUT!$C$6)+(U17+U18)*INPUT!$C$6/(100+INPUT!$C$6)+(V17+V18)*INPUT!$C$6/(100+INPUT!$C$6)+(W17+W18)*INPUT!$C$6/(100+INPUT!$C$6)+(X17+X18)*INPUT!$C$6/(100+INPUT!$C$6)+(Y17+Y18)*INPUT!$C$6/(100+INPUT!$C$6)+(Z17+Z18)*INPUT!$C$6/(100+INPUT!$C$6)+(AA17+AA18)*INPUT!$C$6/(100+INPUT!$C$6)+(AB17+AB18)*INPUT!$C$6/(100+INPUT!$C$6)+(AC17+AC18)*INPUT!$C$6/(100+INPUT!$C$6)+(AD17+AD18)*INPUT!$C$6/(100+INPUT!$C$6)+(AE17+AE18)*INPUT!$C$6/(100+INPUT!$C$6)+(AF17+AF18)*INPUT!$C$6/(100+INPUT!$C$6)+(AG17+AG18)*INPUT!$C$6/(100+INPUT!$C$6)+(AH17+AH18)*INPUT!$C$6/(100+INPUT!$C$6)+(AI17+AI18)*INPUT!$C$6/(100+INPUT!$C$6)+(AJ17+AJ18)*INPUT!$C$6/(100+INPUT!$C$6)+(AK17+AK18)*INPUT!$C$6/(100+INPUT!$C$6)+(AL17+AL18)*INPUT!$C$6/(100+INPUT!$C$6)+(AM17+AM18)*INPUT!$C$6/(100+INPUT!$C$6)+(AN17+AN18)*INPUT!$C$6/(100+INPUT!$C$6)+(AO17+AO18)*INPUT!$C$6/(100+INPUT!$C$6)+(AP17+AP18)*INPUT!$C$6/(100+INPUT!$C$6)+(AQ17+AQ18)*INPUT!$C$6/(100+INPUT!$C$6))-SUM(D19:AP19),0) -> 0 | AR19: =MAX((IF($C$136>0,$C$137*D11/$C$136,0)+IF($C$136>0,$C$137*E11/$C$136,0)+IF($C$136>0,$C$137*F11/$C$136,0)+IF($C$136>0,$C$137*G11/$C$136,0)+IF($C$136>0,$C$137*H11/$C$136,0)+IF($C$136>0,$C$137*I11/$C$136,0)+IF($C$136>0,$C$137*J11/$C$136,0)+IF($C$136>0,$C$137*K11/$C$136,0)+IF($C$136>0,$C$137*L11/$C$136,0)+IF($C$136>0,$C$137*M11/$C$136,0)+IF($C$136>0,$C$137*N11/$C$136,0)+IF($C$136>0,$C$137*O11/$C$136,0)+IF($C$136>0,$C$137*P11/$C$136,0)+IF($C$136>0,$C$137*Q11/$C$136,0)+IF($C$136>0,$C$137*R11/$C$136,0)+IF($C$136>0,$C$137*S11/$C$136,0)+IF($C$136>0,$C$137*T11/$C$136,0)+IF($C$136>0,$C$137*U11/$C$136,0)+IF($C$136>0,$C$137*V11/$C$136,0)+IF($C$136>0,$C$137*W11/$C$136,0)+IF($C$136>0,$C$137*X11/$C$136,0)+IF($C$136>0,$C$137*Y11/$C$136,0)+IF($C$136>0,$C$137*Z11/$C$136,0)+IF($C$136>0,$C$137*AA11/$C$136,0)+IF($C$136>0,$C$137*AB11/$C$136,0)+IF($C$136>0,$C$137*AC11/$C$136,0)+IF($C$136>0,$C$137*AD11/$C$136,0)+IF($C$136>0,$C$137*AE11/$C$136,0)+IF($C$136>0,$C$137*AF11/$C$136,0)+IF($C$136>0,$C$137*AG11/$C$136,0)+IF($C$136>0,$C$137*AH11/$C$136,0)+IF($C$136>0,$C$137*AI11/$C$136,0)+IF($C$136>0,$C$137*AJ11/$C$136,0)+IF($C$136>0,$C$137*AK11/$C$136,0)+IF($C$136>0,$C$137*AL11/$C$136,0)+IF($C$136>0,$C$137*AM11/$C$136,0)+IF($C$136>0,$C$137*AN11/$C$136,0)+IF($C$136>0,$C$137*AO11/$C$136,0)+IF($C$136>0,$C$137*AP11/$C$136,0)+IF($C$136>0,$C$137*AQ11/$C$136,0)+IF($C$136>0,$C$137*AR11/$C$136,0))-((D17+D18)*INPUT!$C$6/(100+INPUT!$C$6)+(E17+E18)*INPUT!$C$6/(100+INPUT!$C$6)+(F17+F18)*INPUT!$C$6/(100+INPUT!$C$6)+(G17+G18)*INPUT!$C$6/(100+INPUT!$C$6)+(H17+H18)*INPUT!$C$6/(100+INPUT!$C$6)+(I17+I18)*INPUT!$C$6/(100+INPUT!$C$6)+(J17+J18)*INPUT!$C$6/(100+INPUT!$C$6)+(K17+K18)*INPUT!$C$6/(100+INPUT!$C$6)+(L17+L18)*INPUT!$C$6/(100+INPUT!$C$6)+(M17+M18)*INPUT!$C$6/(100+INPUT!$C$6)+(N17+N18)*INPUT!$C$6/(100+INPUT!$C$6)+(O17+O18)*INPUT!$C$6/(100+INPUT!$C$6)+(P17+P18)*INPUT!$C$6/(100+INPUT!$C$6)+(Q17+Q18)*INPUT!$C$6/(100+INPUT!$C$6)+(R17+R18)*INPUT!$C$6/(100+INPUT!$C$6)+(S17+S18)*INPUT!$C$6/(100+INPUT!$C$6)+(T17+T18)*INPUT!$C$6/(100+INPUT!$C$6)+(U17+U18)*INPUT!$C$6/(100+INPUT!$C$6)+(V17+V18)*INPUT!$C$6/(100+INPUT!$C$6)+(W17+W18)*INPUT!$C$6/(100+INPUT!$C$6)+(X17+X18)*INPUT!$C$6/(100+INPUT!$C$6)+(Y17+Y18)*INPUT!$C$6/(100+INPUT!$C$6)+(Z17+Z18)*INPUT!$C$6/(100+INPUT!$C$6)+(AA17+AA18)*INPUT!$C$6/(100+INPUT!$C$6)+(AB17+AB18)*INPUT!$C$6/(100+INPUT!$C$6)+(AC17+AC18)*INPUT!$C$6/(100+INPUT!$C$6)+(AD17+AD18)*INPUT!$C$6/(100+INPUT!$C$6)+(AE17+AE18)*INPUT!$C$6/(100+INPUT!$C$6)+(AF17+AF18)*INPUT!$C$6/(100+INPUT!$C$6)+(AG17+AG18)*INPUT!$C$6/(100+INPUT!$C$6)+(AH17+AH18)*INPUT!$C$6/(100+INPUT!$C$6)+(AI17+AI18)*INPUT!$C$6/(100+INPUT!$C$6)+(AJ17+AJ18)*INPUT!$C$6/(100+INPUT!$C$6)+(AK17+AK18)*INPUT!$C$6/(100+INPUT!$C$6)+(AL17+AL18)*INPUT!$C$6/(100+INPUT!$C$6)+(AM17+AM18)*INPUT!$C$6/(100+INPUT!$C$6)+(AN17+AN18)*INPUT!$C$6/(100+INPUT!$C$6)+(AO17+AO18)*INPUT!$C$6/(100+INPUT!$C$6)+(AP17+AP18)*INPUT!$C$6/(100+INPUT!$C$6)+(AQ17+AQ18)*INPUT!$C$6/(100+INPUT!$C$6)+(AR17+AR18)*INPUT!$C$6/(100+INPUT!$C$6))-SUM(D19:AQ19),0) -> 0 | AS19: =MAX((IF($C$136>0,$C$137*D11/$C$136,0)+IF($C$136>0,$C$137*E11/$C$136,0)+IF($C$136>0,$C$137*F11/$C$136,0)+IF($C$136>0,$C$137*G11/$C$136,0)+IF($C$136>0,$C$137*H11/$C$136,0)+IF($C$136>0,$C$137*I11/$C$136,0)+IF($C$136>0,$C$137*J11/$C$136,0)+IF($C$136>0,$C$137*K11/$C$136,0)+IF($C$136>0,$C$137*L11/$C$136,0)+IF($C$136>0,$C$137*M11/$C$136,0)+IF($C$136>0,$C$137*N11/$C$136,0)+IF($C$136>0,$C$137*O11/$C$136,0)+IF($C$136>0,$C$137*P11/$C$136,0)+IF($C$136>0,$C$137*Q11/$C$136,0)+IF($C$136>0,$C$137*R11/$C$136,0)+IF($C$136>0,$C$137*S11/$C$136,0)+IF($C$136>0,$C$137*T11/$C$136,0)+IF($C$136>0,$C$137*U11/$C$136,0)+IF($C$136>0,$C$137*V11/$C$136,0)+IF($C$136>0,$C$137*W11/$C$136,0)+IF($C$136>0,$C$137*X11/$C$136,0)+IF($C$136>0,$C$137*Y11/$C$136,0)+IF($C$136>0,$C$137*Z11/$C$136,0)+IF($C$136>0,$C$137*AA11/$C$136,0)+IF($C$136>0,$C$137*AB11/$C$136,0)+IF($C$136>0,$C$137*AC11/$C$136,0)+IF($C$136>0,$C$137*AD11/$C$136,0)+IF($C$136>0,$C$137*AE11/$C$136,0)+IF($C$136>0,$C$137*AF11/$C$136,0)+IF($C$136>0,$C$137*AG11/$C$136,0)+IF($C$136>0,$C$137*AH11/$C$136,0)+IF($C$136>0,$C$137*AI11/$C$136,0)+IF($C$136>0,$C$137*AJ11/$C$136,0)+IF($C$136>0,$C$137*AK11/$C$136,0)+IF($C$136>0,$C$137*AL11/$C$136,0)+IF($C$136>0,$C$137*AM11/$C$136,0)+IF($C$136>0,$C$137*AN11/$C$136,0)+IF($C$136>0,$C$137*AO11/$C$136,0)+IF($C$136>0,$C$137*AP11/$C$136,0)+IF($C$136>0,$C$137*AQ11/$C$136,0)+IF($C$136>0,$C$137*AR11/$C$136,0)+IF($C$136>0,$C$137*AS11/$C$136,0))-((D17+D18)*INPUT!$C$6/(100+INPUT!$C$6)+(E17+E18)*INPUT!$C$6/(100+INPUT!$C$6)+(F17+F18)*INPUT!$C$6/(100+INPUT!$C$6)+(G17+G18)*INPUT!$C$6/(100+INPUT!$C$6)+(H17+H18)*INPUT!$C$6/(100+INPUT!$C$6)+(I17+I18)*INPUT!$C$6/(100+INPUT!$C$6)+(J17+J18)*INPUT!$C$6/(100+INPUT!$C$6)+(K17+K18)*INPUT!$C$6/(100+INPUT!$C$6)+(L17+L18)*INPUT!$C$6/(100+INPUT!$C$6)+(M17+M18)*INPUT!$C$6/(100+INPUT!$C$6)+(N17+N18)*INPUT!$C$6/(100+INPUT!$C$6)+(O17+O18)*INPUT!$C$6/(100+INPUT!$C$6)+(P17+P18)*INPUT!$C$6/(100+INPUT!$C$6)+(Q17+Q18)*INPUT!$C$6/(100+INPUT!$C$6)+(R17+R18)*INPUT!$C$6/(100+INPUT!$C$6)+(S17+S18)*INPUT!$C$6/(100+INPUT!$C$6)+(T17+T18)*INPUT!$C$6/(100+INPUT!$C$6)+(U17+U18)*INPUT!$C$6/(100+INPUT!$C$6)+(V17+V18)*INPUT!$C$6/(100+INPUT!$C$6)+(W17+W18)*INPUT!$C$6/(100+INPUT!$C$6)+(X17+X18)*INPUT!$C$6/(100+INPUT!$C$6)+(Y17+Y18)*INPUT!$C$6/(100+INPUT!$C$6)+(Z17+Z18)*INPUT!$C$6/(100+INPUT!$C$6)+(AA17+AA18)*INPUT!$C$6/(100+INPUT!$C$6)+(AB17+AB18)*INPUT!$C$6/(100+INPUT!$C$6)+(AC17+AC18)*INPUT!$C$6/(100+INPUT!$C$6)+(AD17+AD18)*INPUT!$C$6/(100+INPUT!$C$6)+(AE17+AE18)*INPUT!$C$6/(100+INPUT!$C$6)+(AF17+AF18)*INPUT!$C$6/(100+INPUT!$C$6)+(AG17+AG18)*INPUT!$C$6/(100+INPUT!$C$6)+(AH17+AH18)*INPUT!$C$6/(100+INPUT!$C$6)+(AI17+AI18)*INPUT!$C$6/(100+INPUT!$C$6)+(AJ17+AJ18)*INPUT!$C$6/(100+INPUT!$C$6)+(AK17+AK18)*INPUT!$C$6/(100+INPUT!$C$6)+(AL17+AL18)*INPUT!$C$6/(100+INPUT!$C$6)+(AM17+AM18)*INPUT!$C$6/(100+INPUT!$C$6)+(AN17+AN18)*INPUT!$C$6/(100+INPUT!$C$6)+(AO17+AO18)*INPUT!$C$6/(100+INPUT!$C$6)+(AP17+AP18)*INPUT!$C$6/(100+INPUT!$C$6)+(AQ17+AQ18)*INPUT!$C$6/(100+INPUT!$C$6)+(AR17+AR18)*INPUT!$C$6/(100+INPUT!$C$6)+(AS17+AS18)*INPUT!$C$6/(100+INPUT!$C$6))-SUM(D19:AR19),0) -> 0 | AT19: =MAX((IF($C$136>0,$C$137*D11/$C$136,0)+IF($C$136>0,$C$137*E11/$C$136,0)+IF($C$136>0,$C$137*F11/$C$136,0)+IF($C$136>0,$C$137*G11/$C$136,0)+IF($C$136>0,$C$137*H11/$C$136,0)+IF($C$136>0,$C$137*I11/$C$136,0)+IF($C$136>0,$C$137*J11/$C$136,0)+IF($C$136>0,$C$137*K11/$C$136,0)+IF($C$136>0,$C$137*L11/$C$136,0)+IF($C$136>0,$C$137*M11/$C$136,0)+IF($C$136>0,$C$137*N11/$C$136,0)+IF($C$136>0,$C$137*O11/$C$136,0)+IF($C$136>0,$C$137*P11/$C$136,0)+IF($C$136>0,$C$137*Q11/$C$136,0)+IF($C$136>0,$C$137*R11/$C$136,0)+IF($C$136>0,$C$137*S11/$C$136,0)+IF($C$136>0,$C$137*T11/$C$136,0)+IF($C$136>0,$C$137*U11/$C$136,0)+IF($C$136>0,$C$137*V11/$C$136,0)+IF($C$136>0,$C$137*W11/$C$136,0)+IF($C$136>0,$C$137*X11/$C$136,0)+IF($C$136>0,$C$137*Y11/$C$136,0)+IF($C$136>0,$C$137*Z11/$C$136,0)+IF($C$136>0,$C$137*AA11/$C$136,0)+IF($C$136>0,$C$137*AB11/$C$136,0)+IF($C$136>0,$C$137*AC11/$C$136,0)+IF($C$136>0,$C$137*AD11/$C$136,0)+IF($C$136>0,$C$137*AE11/$C$136,0)+IF($C$136>0,$C$137*AF11/$C$136,0)+IF($C$136>0,$C$137*AG11/$C$136,0)+IF($C$136>0,$C$137*AH11/$C$136,0)+IF($C$136>0,$C$137*AI11/$C$136,0)+IF($C$136>0,$C$137*AJ11/$C$136,0)+IF($C$136>0,$C$137*AK11/$C$136,0)+IF($C$136>0,$C$137*AL11/$C$136,0)+IF($C$136>0,$C$137*AM11/$C$136,0)+IF($C$136>0,$C$137*AN11/$C$136,0)+IF($C$136>0,$C$137*AO11/$C$136,0)+IF($C$136>0,$C$137*AP11/$C$136,0)+IF($C$136>0,$C$137*AQ11/$C$136,0)+IF($C$136>0,$C$137*AR11/$C$136,0)+IF($C$136>0,$C$137*AS11/$C$136,0)+IF($C$136>0,$C$137*AT11/$C$136,0))-((D17+D18)*INPUT!$C$6/(100+INPUT!$C$6)+(E17+E18)*INPUT!$C$6/(100+INPUT!$C$6)+(F17+F18)*INPUT!$C$6/(100+INPUT!$C$6)+(G17+G18)*INPUT!$C$6/(100+INPUT!$C$6)+(H17+H18)*INPUT!$C$6/(100+INPUT!$C$6)+(I17+I18)*INPUT!$C$6/(100+INPUT!$C$6)+(J17+J18)*INPUT!$C$6/(100+INPUT!$C$6)+(K17+K18)*INPUT!$C$6/(100+INPUT!$C$6)+(L17+L18)*INPUT!$C$6/(100+INPUT!$C$6)+(M17+M18)*INPUT!$C$6/(100+INPUT!$C$6)+(N17+N18)*INPUT!$C$6/(100+INPUT!$C$6)+(O17+O18)*INPUT!$C$6/(100+INPUT!$C$6)+(P17+P18)*INPUT!$C$6/(100+INPUT!$C$6)+(Q17+Q18)*INPUT!$C$6/(100+INPUT!$C$6)+(R17+R18)*INPUT!$C$6/(100+INPUT!$C$6)+(S17+S18)*INPUT!$C$6/(100+INPUT!$C$6)+(T17+T18)*INPUT!$C$6/(100+INPUT!$C$6)+(U17+U18)*INPUT!$C$6/(100+INPUT!$C$6)+(V17+V18)*INPUT!$C$6/(100+INPUT!$C$6)+(W17+W18)*INPUT!$C$6/(100+INPUT!$C$6)+(X17+X18)*INPUT!$C$6/(100+INPUT!$C$6)+(Y17+Y18)*INPUT!$C$6/(100+INPUT!$C$6)+(Z17+Z18)*INPUT!$C$6/(100+INPUT!$C$6)+(AA17+AA18)*INPUT!$C$6/(100+INPUT!$C$6)+(AB17+AB18)*INPUT!$C$6/(100+INPUT!$C$6)+(AC17+AC18)*INPUT!$C$6/(100+INPUT!$C$6)+(AD17+AD18)*INPUT!$C$6/(100+INPUT!$C$6)+(AE17+AE18)*INPUT!$C$6/(100+INPUT!$C$6)+(AF17+AF18)*INPUT!$C$6/(100+INPUT!$C$6)+(AG17+AG18)*INPUT!$C$6/(100+INPUT!$C$6)+(AH17+AH18)*INPUT!$C$6/(100+INPUT!$C$6)+(AI17+AI18)*INPUT!$C$6/(100+INPUT!$C$6)+(AJ17+AJ18)*INPUT!$C$6/(100+INPUT!$C$6)+(AK17+AK18)*INPUT!$C$6/(100+INPUT!$C$6)+(AL17+AL18)*INPUT!$C$6/(100+INPUT!$C$6)+(AM17+AM18)*INPUT!$C$6/(100+INPUT!$C$6)+(AN17+AN18)*INPUT!$C$6/(100+INPUT!$C$6)+(AO17+AO18)*INPUT!$C$6/(100+INPUT!$C$6)+(AP17+AP18)*INPUT!$C$6/(100+INPUT!$C$6)+(AQ17+AQ18)*INPUT!$C$6/(100+INPUT!$C$6)+(AR17+AR18)*INPUT!$C$6/(100+INPUT!$C$6)+(AS17+AS18)*INPUT!$C$6/(100+INPUT!$C$6)+(AT17+AT18)*INPUT!$C$6/(100+INPUT!$C$6))-SUM(D19:AS19),0) -> 0 | AU19: =MAX((IF($C$136>0,$C$137*D11/$C$136,0)+IF($C$136>0,$C$137*E11/$C$136,0)+IF($C$136>0,$C$137*F11/$C$136,0)+IF($C$136>0,$C$137*G11/$C$136,0)+IF($C$136>0,$C$137*H11/$C$136,0)+IF($C$136>0,$C$137*I11/$C$136,0)+IF($C$136>0,$C$137*J11/$C$136,0)+IF($C$136>0,$C$137*K11/$C$136,0)+IF($C$136>0,$C$137*L11/$C$136,0)+IF($C$136>0,$C$137*M11/$C$136,0)+IF($C$136>0,$C$137*N11/$C$136,0)+IF($C$136>0,$C$137*O11/$C$136,0)+IF($C$136>0,$C$137*P11/$C$136,0)+IF($C$136>0,$C$137*Q11/$C$136,0)+IF($C$136>0,$C$137*R11/$C$136,0)+IF($C$136>0,$C$137*S11/$C$136,0)+IF($C$136>0,$C$137*T11/$C$136,0)+IF($C$136>0,$C$137*U11/$C$136,0)+IF($C$136>0,$C$137*V11/$C$136,0)+IF($C$136>0,$C$137*W11/$C$136,0)+IF($C$136>0,$C$137*X11/$C$136,0)+IF($C$136>0,$C$137*Y11/$C$136,0)+IF($C$136>0,$C$137*Z11/$C$136,0)+IF($C$136>0,$C$137*AA11/$C$136,0)+IF($C$136>0,$C$137*AB11/$C$136,0)+IF($C$136>0,$C$137*AC11/$C$136,0)+IF($C$136>0,$C$137*AD11/$C$136,0)+IF($C$136>0,$C$137*AE11/$C$136,0)+IF($C$136>0,$C$137*AF11/$C$136,0)+IF($C$136>0,$C$137*AG11/$C$136,0)+IF($C$136>0,$C$137*AH11/$C$136,0)+IF($C$136>0,$C$137*AI11/$C$136,0)+IF($C$136>0,$C$137*AJ11/$C$136,0)+IF($C$136>0,$C$137*AK11/$C$136,0)+IF($C$136>0,$C$137*AL11/$C$136,0)+IF($C$136>0,$C$137*AM11/$C$136,0)+IF($C$136>0,$C$137*AN11/$C$136,0)+IF($C$136>0,$C$137*AO11/$C$136,0)+IF($C$136>0,$C$137*AP11/$C$136,0)+IF($C$136>0,$C$137*AQ11/$C$136,0)+IF($C$136>0,$C$137*AR11/$C$136,0)+IF($C$136>0,$C$137*AS11/$C$136,0)+IF($C$136>0,$C$137*AT11/$C$136,0)+IF($C$136>0,$C$137*AU11/$C$136,0))-((D17+D18)*INPUT!$C$6/(100+INPUT!$C$6)+(E17+E18)*INPUT!$C$6/(100+INPUT!$C$6)+(F17+F18)*INPUT!$C$6/(100+INPUT!$C$6)+(G17+G18)*INPUT!$C$6/(100+INPUT!$C$6)+(H17+H18)*INPUT!$C$6/(100+INPUT!$C$6)+(I17+I18)*INPUT!$C$6/(100+INPUT!$C$6)+(J17+J18)*INPUT!$C$6/(100+INPUT!$C$6)+(K17+K18)*INPUT!$C$6/(100+INPUT!$C$6)+(L17+L18)*INPUT!$C$6/(100+INPUT!$C$6)+(M17+M18)*INPUT!$C$6/(100+INPUT!$C$6)+(N17+N18)*INPUT!$C$6/(100+INPUT!$C$6)+(O17+O18)*INPUT!$C$6/(100+INPUT!$C$6)+(P17+P18)*INPUT!$C$6/(100+INPUT!$C$6)+(Q17+Q18)*INPUT!$C$6/(100+INPUT!$C$6)+(R17+R18)*INPUT!$C$6/(100+INPUT!$C$6)+(S17+S18)*INPUT!$C$6/(100+INPUT!$C$6)+(T17+T18)*INPUT!$C$6/(100+INPUT!$C$6)+(U17+U18)*INPUT!$C$6/(100+INPUT!$C$6)+(V17+V18)*INPUT!$C$6/(100+INPUT!$C$6)+(W17+W18)*INPUT!$C$6/(100+INPUT!$C$6)+(X17+X18)*INPUT!$C$6/(100+INPUT!$C$6)+(Y17+Y18)*INPUT!$C$6/(100+INPUT!$C$6)+(Z17+Z18)*INPUT!$C$6/(100+INPUT!$C$6)+(AA17+AA18)*INPUT!$C$6/(100+INPUT!$C$6)+(AB17+AB18)*INPUT!$C$6/(100+INPUT!$C$6)+(AC17+AC18)*INPUT!$C$6/(100+INPUT!$C$6)+(AD17+AD18)*INPUT!$C$6/(100+INPUT!$C$6)+(AE17+AE18)*INPUT!$C$6/(100+INPUT!$C$6)+(AF17+AF18)*INPUT!$C$6/(100+INPUT!$C$6)+(AG17+AG18)*INPUT!$C$6/(100+INPUT!$C$6)+(AH17+AH18)*INPUT!$C$6/(100+INPUT!$C$6)+(AI17+AI18)*INPUT!$C$6/(100+INPUT!$C$6)+(AJ17+AJ18)*INPUT!$C$6/(100+INPUT!$C$6)+(AK17+AK18)*INPUT!$C$6/(100+INPUT!$C$6)+(AL17+AL18)*INPUT!$C$6/(100+INPUT!$C$6)+(AM17+AM18)*INPUT!$C$6/(100+INPUT!$C$6)+(AN17+AN18)*INPUT!$C$6/(100+INPUT!$C$6)+(AO17+AO18)*INPUT!$C$6/(100+INPUT!$C$6)+(AP17+AP18)*INPUT!$C$6/(100+INPUT!$C$6)+(AQ17+AQ18)*INPUT!$C$6/(100+INPUT!$C$6)+(AR17+AR18)*INPUT!$C$6/(100+INPUT!$C$6)+(AS17+AS18)*INPUT!$C$6/(100+INPUT!$C$6)+(AT17+AT18)*INPUT!$C$6/(100+INPUT!$C$6)+(AU17+AU18)*INPUT!$C$6/(100+INPUT!$C$6))-SUM(D19:AT19),0) -> 0 | AV19: =MAX((IF($C$136>0,$C$137*D11/$C$136,0)+IF($C$136>0,$C$137*E11/$C$136,0)+IF($C$136>0,$C$137*F11/$C$136,0)+IF($C$136>0,$C$137*G11/$C$136,0)+IF($C$136>0,$C$137*H11/$C$136,0)+IF($C$136>0,$C$137*I11/$C$136,0)+IF($C$136>0,$C$137*J11/$C$136,0)+IF($C$136>0,$C$137*K11/$C$136,0)+IF($C$136>0,$C$137*L11/$C$136,0)+IF($C$136>0,$C$137*M11/$C$136,0)+IF($C$136>0,$C$137*N11/$C$136,0)+IF($C$136>0,$C$137*O11/$C$136,0)+IF($C$136>0,$C$137*P11/$C$136,0)+IF($C$136>0,$C$137*Q11/$C$136,0)+IF($C$136>0,$C$137*R11/$C$136,0)+IF($C$136>0,$C$137*S11/$C$136,0)+IF($C$136>0,$C$137*T11/$C$136,0)+IF($C$136>0,$C$137*U11/$C$136,0)+IF($C$136>0,$C$137*V11/$C$136,0)+IF($C$136>0,$C$137*W11/$C$136,0)+IF($C$136>0,$C$137*X11/$C$136,0)+IF($C$136>0,$C$137*Y11/$C$136,0)+IF($C$136>0,$C$137*Z11/$C$136,0)+IF($C$136>0,$C$137*AA11/$C$136,0)+IF($C$136>0,$C$137*AB11/$C$136,0)+IF($C$136>0,$C$137*AC11/$C$136,0)+IF($C$136>0,$C$137*AD11/$C$136,0)+IF($C$136>0,$C$137*AE11/$C$136,0)+IF($C$136>0,$C$137*AF11/$C$136,0)+IF($C$136>0,$C$137*AG11/$C$136,0)+IF($C$136>0,$C$137*AH11/$C$136,0)+IF($C$136>0,$C$137*AI11/$C$136,0)+IF($C$136>0,$C$137*AJ11/$C$136,0)+IF($C$136>0,$C$137*AK11/$C$136,0)+IF($C$136>0,$C$137*AL11/$C$136,0)+IF($C$136>0,$C$137*AM11/$C$136,0)+IF($C$136>0,$C$137*AN11/$C$136,0)+IF($C$136>0,$C$137*AO11/$C$136,0)+IF($C$136>0,$C$137*AP11/$C$136,0)+IF($C$136>0,$C$137*AQ11/$C$136,0)+IF($C$136>0,$C$137*AR11/$C$136,0)+IF($C$136>0,$C$137*AS11/$C$136,0)+IF($C$136>0,$C$137*AT11/$C$136,0)+IF($C$136>0,$C$137*AU11/$C$136,0)+IF($C$136>0,$C$137*AV11/$C$136,0))-((D17+D18)*INPUT!$C$6/(100+INPUT!$C$6)+(E17+E18)*INPUT!$C$6/(100+INPUT!$C$6)+(F17+F18)*INPUT!$C$6/(100+INPUT!$C$6)+(G17+G18)*INPUT!$C$6/(100+INPUT!$C$6)+(H17+H18)*INPUT!$C$6/(100+INPUT!$C$6)+(I17+I18)*INPUT!$C$6/(100+INPUT!$C$6)+(J17+J18)*INPUT!$C$6/(100+INPUT!$C$6)+(K17+K18)*INPUT!$C$6/(100+INPUT!$C$6)+(L17+L18)*INPUT!$C$6/(100+INPUT!$C$6)+(M17+M18)*INPUT!$C$6/(100+INPUT!$C$6)+(N17+N18)*INPUT!$C$6/(100+INPUT!$C$6)+(O17+O18)*INPUT!$C$6/(100+INPUT!$C$6)+(P17+P18)*INPUT!$C$6/(100+INPUT!$C$6)+(Q17+Q18)*INPUT!$C$6/(100+INPUT!$C$6)+(R17+R18)*INPUT!$C$6/(100+INPUT!$C$6)+(S17+S18)*INPUT!$C$6/(100+INPUT!$C$6)+(T17+T18)*INPUT!$C$6/(100+INPUT!$C$6)+(U17+U18)*INPUT!$C$6/(100+INPUT!$C$6)+(V17+V18)*INPUT!$C$6/(100+INPUT!$C$6)+(W17+W18)*INPUT!$C$6/(100+INPUT!$C$6)+(X17+X18)*INPUT!$C$6/(100+INPUT!$C$6)+(Y17+Y18)*INPUT!$C$6/(100+INPUT!$C$6)+(Z17+Z18)*INPUT!$C$6/(100+INPUT!$C$6)+(AA17+AA18)*INPUT!$C$6/(100+INPUT!$C$6)+(AB17+AB18)*INPUT!$C$6/(100+INPUT!$C$6)+(AC17+AC18)*INPUT!$C$6/(100+INPUT!$C$6)+(AD17+AD18)*INPUT!$C$6/(100+INPUT!$C$6)+(AE17+AE18)*INPUT!$C$6/(100+INPUT!$C$6)+(AF17+AF18)*INPUT!$C$6/(100+INPUT!$C$6)+(AG17+AG18)*INPUT!$C$6/(100+INPUT!$C$6)+(AH17+AH18)*INPUT!$C$6/(100+INPUT!$C$6)+(AI17+AI18)*INPUT!$C$6/(100+INPUT!$C$6)+(AJ17+AJ18)*INPUT!$C$6/(100+INPUT!$C$6)+(AK17+AK18)*INPUT!$C$6/(100+INPUT!$C$6)+(AL17+AL18)*INPUT!$C$6/(100+INPUT!$C$6)+(AM17+AM18)*INPUT!$C$6/(100+INPUT!$C$6)+(AN17+AN18)*INPUT!$C$6/(100+INPUT!$C$6)+(AO17+AO18)*INPUT!$C$6/(100+INPUT!$C$6)+(AP17+AP18)*INPUT!$C$6/(100+INPUT!$C$6)+(AQ17+AQ18)*INPUT!$C$6/(100+INPUT!$C$6)+(AR17+AR18)*INPUT!$C$6/(100+INPUT!$C$6)+(AS17+AS18)*INPUT!$C$6/(100+INPUT!$C$6)+(AT17+AT18)*INPUT!$C$6/(100+INPUT!$C$6)+(AU17+AU18)*INPUT!$C$6/(100+INPUT!$C$6)+(AV17+AV18)*INPUT!$C$6/(100+INPUT!$C$6))-SUM(D19:AU19),0) -> 0 | AW19: =MAX((IF($C$136>0,$C$137*D11/$C$136,0)+IF($C$136>0,$C$137*E11/$C$136,0)+IF($C$136>0,$C$137*F11/$C$136,0)+IF($C$136>0,$C$137*G11/$C$136,0)+IF($C$136>0,$C$137*H11/$C$136,0)+IF($C$136>0,$C$137*I11/$C$136,0)+IF($C$136>0,$C$137*J11/$C$136,0)+IF($C$136>0,$C$137*K11/$C$136,0)+IF($C$136>0,$C$137*L11/$C$136,0)+IF($C$136>0,$C$137*M11/$C$136,0)+IF($C$136>0,$C$137*N11/$C$136,0)+IF($C$136>0,$C$137*O11/$C$136,0)+IF($C$136>0,$C$137*P11/$C$136,0)+IF($C$136>0,$C$137*Q11/$C$136,0)+IF($C$136>0,$C$137*R11/$C$136,0)+IF($C$136>0,$C$137*S11/$C$136,0)+IF($C$136>0,$C$137*T11/$C$136,0)+IF($C$136>0,$C$137*U11/$C$136,0)+IF($C$136>0,$C$137*V11/$C$136,0)+IF($C$136>0,$C$137*W11/$C$136,0)+IF($C$136>0,$C$137*X11/$C$136,0)+IF($C$136>0,$C$137*Y11/$C$136,0)+IF($C$136>0,$C$137*Z11/$C$136,0)+IF($C$136>0,$C$137*AA11/$C$136,0)+IF($C$136>0,$C$137*AB11/$C$136,0)+IF($C$136>0,$C$137*AC11/$C$136,0)+IF($C$136>0,$C$137*AD11/$C$136,0)+IF($C$136>0,$C$137*AE11/$C$136,0)+IF($C$136>0,$C$137*AF11/$C$136,0)+IF($C$136>0,$C$137*AG11/$C$136,0)+IF($C$136>0,$C$137*AH11/$C$136,0)+IF($C$136>0,$C$137*AI11/$C$136,0)+IF($C$136>0,$C$137*AJ11/$C$136,0)+IF($C$136>0,$C$137*AK11/$C$136,0)+IF($C$136>0,$C$137*AL11/$C$136,0)+IF($C$136>0,$C$137*AM11/$C$136,0)+IF($C$136>0,$C$137*AN11/$C$136,0)+IF($C$136>0,$C$137*AO11/$C$136,0)+IF($C$136>0,$C$137*AP11/$C$136,0)+IF($C$136>0,$C$137*AQ11/$C$136,0)+IF($C$136>0,$C$137*AR11/$C$136,0)+IF($C$136>0,$C$137*AS11/$C$136,0)+IF($C$136>0,$C$137*AT11/$C$136,0)+IF($C$136>0,$C$137*AU11/$C$136,0)+IF($C$136>0,$C$137*AV11/$C$136,0)+IF($C$136>0,$C$137*AW11/$C$136,0))-((D17+D18)*INPUT!$C$6/(100+INPUT!$C$6)+(E17+E18)*INPUT!$C$6/(100+INPUT!$C$6)+(F17+F18)*INPUT!$C$6/(100+INPUT!$C$6)+(G17+G18)*INPUT!$C$6/(100+INPUT!$C$6)+(H17+H18)*INPUT!$C$6/(100+INPUT!$C$6)+(I17+I18)*INPUT!$C$6/(100+INPUT!$C$6)+(J17+J18)*INPUT!$C$6/(100+INPUT!$C$6)+(K17+K18)*INPUT!$C$6/(100+INPUT!$C$6)+(L17+L18)*INPUT!$C$6/(100+INPUT!$C$6)+(M17+M18)*INPUT!$C$6/(100+INPUT!$C$6)+(N17+N18)*INPUT!$C$6/(100+INPUT!$C$6)+(O17+O18)*INPUT!$C$6/(100+INPUT!$C$6)+(P17+P18)*INPUT!$C$6/(100+INPUT!$C$6)+(Q17+Q18)*INPUT!$C$6/(100+INPUT!$C$6)+(R17+R18)*INPUT!$C$6/(100+INPUT!$C$6)+(S17+S18)*INPUT!$C$6/(100+INPUT!$C$6)+(T17+T18)*INPUT!$C$6/(100+INPUT!$C$6)+(U17+U18)*INPUT!$C$6/(100+INPUT!$C$6)+(V17+V18)*INPUT!$C$6/(100+INPUT!$C$6)+(W17+W18)*INPUT!$C$6/(100+INPUT!$C$6)+(X17+X18)*INPUT!$C$6/(100+INPUT!$C$6)+(Y17+Y18)*INPUT!$C$6/(100+INPUT!$C$6)+(Z17+Z18)*INPUT!$C$6/(100+INPUT!$C$6)+(AA17+AA18)*INPUT!$C$6/(100+INPUT!$C$6)+(AB17+AB18)*INPUT!$C$6/(100+INPUT!$C$6)+(AC17+AC18)*INPUT!$C$6/(100+INPUT!$C$6)+(AD17+AD18)*INPUT!$C$6/(100+INPUT!$C$6)+(AE17+AE18)*INPUT!$C$6/(100+INPUT!$C$6)+(AF17+AF18)*INPUT!$C$6/(100+INPUT!$C$6)+(AG17+AG18)*INPUT!$C$6/(100+INPUT!$C$6)+(AH17+AH18)*INPUT!$C$6/(100+INPUT!$C$6)+(AI17+AI18)*INPUT!$C$6/(100+INPUT!$C$6)+(AJ17+AJ18)*INPUT!$C$6/(100+INPUT!$C$6)+(AK17+AK18)*INPUT!$C$6/(100+INPUT!$C$6)+(AL17+AL18)*INPUT!$C$6/(100+INPUT!$C$6)+(AM17+AM18)*INPUT!$C$6/(100+INPUT!$C$6)+(AN17+AN18)*INPUT!$C$6/(100+INPUT!$C$6)+(AO17+AO18)*INPUT!$C$6/(100+INPUT!$C$6)+(AP17+AP18)*INPUT!$C$6/(100+INPUT!$C$6)+(AQ17+AQ18)*INPUT!$C$6/(100+INPUT!$C$6)+(AR17+AR18)*INPUT!$C$6/(100+INPUT!$C$6)+(AS17+AS18)*INPUT!$C$6/(100+INPUT!$C$6)+(AT17+AT18)*INPUT!$C$6/(100+INPUT!$C$6)+(AU17+AU18)*INPUT!$C$6/(100+INPUT!$C$6)+(AV17+AV18)*INPUT!$C$6/(100+INPUT!$C$6)+(AW17+AW18)*INPUT!$C$6/(100+INPUT!$C$6))-SUM(D19:AV19),0) -> 0 | AX19: =MAX((IF($C$136>0,$C$137*D11/$C$136,0)+IF($C$136>0,$C$137*E11/$C$136,0)+IF($C$136>0,$C$137*F11/$C$136,0)+IF($C$136>0,$C$137*G11/$C$136,0)+IF($C$136>0,$C$137*H11/$C$136,0)+IF($C$136>0,$C$137*I11/$C$136,0)+IF($C$136>0,$C$137*J11/$C$136,0)+IF($C$136>0,$C$137*K11/$C$136,0)+IF($C$136>0,$C$137*L11/$C$136,0)+IF($C$136>0,$C$137*M11/$C$136,0)+IF($C$136>0,$C$137*N11/$C$136,0)+IF($C$136>0,$C$137*O11/$C$136,0)+IF($C$136>0,$C$137*P11/$C$136,0)+IF($C$136>0,$C$137*Q11/$C$136,0)+IF($C$136>0,$C$137*R11/$C$136,0)+IF($C$136>0,$C$137*S11/$C$136,0)+IF($C$136>0,$C$137*T11/$C$136,0)+IF($C$136>0,$C$137*U11/$C$136,0)+IF($C$136>0,$C$137*V11/$C$136,0)+IF($C$136>0,$C$137*W11/$C$136,0)+IF($C$136>0,$C$137*X11/$C$136,0)+IF($C$136>0,$C$137*Y11/$C$136,0)+IF($C$136>0,$C$137*Z11/$C$136,0)+IF($C$136>0,$C$137*AA11/$C$136,0)+IF($C$136>0,$C$137*AB11/$C$136,0)+IF($C$136>0,$C$137*AC11/$C$136,0)+IF($C$136>0,$C$137*AD11/$C$136,0)+IF($C$136>0,$C$137*AE11/$C$136,0)+IF($C$136>0,$C$137*AF11/$C$136,0)+IF($C$136>0,$C$137*AG11/$C$136,0)+IF($C$136>0,$C$137*AH11/$C$136,0)+IF($C$136>0,$C$137*AI11/$C$136,0)+IF($C$136>0,$C$137*AJ11/$C$136,0)+IF($C$136>0,$C$137*AK11/$C$136,0)+IF($C$136>0,$C$137*AL11/$C$136,0)+IF($C$136>0,$C$137*AM11/$C$136,0)+IF($C$136>0,$C$137*AN11/$C$136,0)+IF($C$136>0,$C$137*AO11/$C$136,0)+IF($C$136>0,$C$137*AP11/$C$136,0)+IF($C$136>0,$C$137*AQ11/$C$136,0)+IF($C$136>0,$C$137*AR11/$C$136,0)+IF($C$136>0,$C$137*AS11/$C$136,0)+IF($C$136>0,$C$137*AT11/$C$136,0)+IF($C$136>0,$C$137*AU11/$C$136,0)+IF($C$136>0,$C$137*AV11/$C$136,0)+IF($C$136>0,$C$137*AW11/$C$136,0)+IF($C$136>0,$C$137*AX11/$C$136,0))-((D17+D18)*INPUT!$C$6/(100+INPUT!$C$6)+(E17+E18)*INPUT!$C$6/(100+INPUT!$C$6)+(F17+F18)*INPUT!$C$6/(100+INPUT!$C$6)+(G17+G18)*INPUT!$C$6/(100+INPUT!$C$6)+(H17+H18)*INPUT!$C$6/(100+INPUT!$C$6)+(I17+I18)*INPUT!$C$6/(100+INPUT!$C$6)+(J17+J18)*INPUT!$C$6/(100+INPUT!$C$6)+(K17+K18)*INPUT!$C$6/(100+INPUT!$C$6)+(L17+L18)*INPUT!$C$6/(100+INPUT!$C$6)+(M17+M18)*INPUT!$C$6/(100+INPUT!$C$6)+(N17+N18)*INPUT!$C$6/(100+INPUT!$C$6)+(O17+O18)*INPUT!$C$6/(100+INPUT!$C$6)+(P17+P18)*INPUT!$C$6/(100+INPUT!$C$6)+(Q17+Q18)*INPUT!$C$6/(100+INPUT!$C$6)+(R17+R18)*INPUT!$C$6/(100+INPUT!$C$6)+(S17+S18)*INPUT!$C$6/(100+INPUT!$C$6)+(T17+T18)*INPUT!$C$6/(100+INPUT!$C$6)+(U17+U18)*INPUT!$C$6/(100+INPUT!$C$6)+(V17+V18)*INPUT!$C$6/(100+INPUT!$C$6)+(W17+W18)*INPUT!$C$6/(100+INPUT!$C$6)+(X17+X18)*INPUT!$C$6/(100+INPUT!$C$6)+(Y17+Y18)*INPUT!$C$6/(100+INPUT!$C$6)+(Z17+Z18)*INPUT!$C$6/(100+INPUT!$C$6)+(AA17+AA18)*INPUT!$C$6/(100+INPUT!$C$6)+(AB17+AB18)*INPUT!$C$6/(100+INPUT!$C$6)+(AC17+AC18)*INPUT!$C$6/(100+INPUT!$C$6)+(AD17+AD18)*INPUT!$C$6/(100+INPUT!$C$6)+(AE17+AE18)*INPUT!$C$6/(100+INPUT!$C$6)+(AF17+AF18)*INPUT!$C$6/(100+INPUT!$C$6)+(AG17+AG18)*INPUT!$C$6/(100+INPUT!$C$6)+(AH17+AH18)*INPUT!$C$6/(100+INPUT!$C$6)+(AI17+AI18)*INPUT!$C$6/(100+INPUT!$C$6)+(AJ17+AJ18)*INPUT!$C$6/(100+INPUT!$C$6)+(AK17+AK18)*INPUT!$C$6/(100+INPUT!$C$6)+(AL17+AL18)*INPUT!$C$6/(100+INPUT!$C$6)+(AM17+AM18)*INPUT!$C$6/(100+INPUT!$C$6)+(AN17+AN18)*INPUT!$C$6/(100+INPUT!$C$6)+(AO17+AO18)*INPUT!$C$6/(100+INPUT!$C$6)+(AP17+AP18)*INPUT!$C$6/(100+INPUT!$C$6)+(AQ17+AQ18)*INPUT!$C$6/(100+INPUT!$C$6)+(AR17+AR18)*INPUT!$C$6/(100+INPUT!$C$6)+(AS17+AS18)*INPUT!$C$6/(100+INPUT!$C$6)+(AT17+AT18)*INPUT!$C$6/(100+INPUT!$C$6)+(AU17+AU18)*INPUT!$C$6/(100+INPUT!$C$6)+(AV17+AV18)*INPUT!$C$6/(100+INPUT!$C$6)+(AW17+AW18)*INPUT!$C$6/(100+INPUT!$C$6)+(AX17+AX18)*INPUT!$C$6/(100+INPUT!$C$6))-SUM(D19:AW19),0) -> 0 | AY19: =MAX((IF($C$136>0,$C$137*D11/$C$136,0)+IF($C$136>0,$C$137*E11/$C$136,0)+IF($C$136>0,$C$137*F11/$C$136,0)+IF($C$136>0,$C$137*G11/$C$136,0)+IF($C$136>0,$C$137*H11/$C$136,0)+IF($C$136>0,$C$137*I11/$C$136,0)+IF($C$136>0,$C$137*J11/$C$136,0)+IF($C$136>0,$C$137*K11/$C$136,0)+IF($C$136>0,$C$137*L11/$C$136,0)+IF($C$136>0,$C$137*M11/$C$136,0)+IF($C$136>0,$C$137*N11/$C$136,0)+IF($C$136>0,$C$137*O11/$C$136,0)+IF($C$136>0,$C$137*P11/$C$136,0)+IF($C$136>0,$C$137*Q11/$C$136,0)+IF($C$136>0,$C$137*R11/$C$136,0)+IF($C$136>0,$C$137*S11/$C$136,0)+IF($C$136>0,$C$137*T11/$C$136,0)+IF($C$136>0,$C$137*U11/$C$136,0)+IF($C$136>0,$C$137*V11/$C$136,0)+IF($C$136>0,$C$137*W11/$C$136,0)+IF($C$136>0,$C$137*X11/$C$136,0)+IF($C$136>0,$C$137*Y11/$C$136,0)+IF($C$136>0,$C$137*Z11/$C$136,0)+IF($C$136>0,$C$137*AA11/$C$136,0)+IF($C$136>0,$C$137*AB11/$C$136,0)+IF($C$136>0,$C$137*AC11/$C$136,0)+IF($C$136>0,$C$137*AD11/$C$136,0)+IF($C$136>0,$C$137*AE11/$C$136,0)+IF($C$136>0,$C$137*AF11/$C$136,0)+IF($C$136>0,$C$137*AG11/$C$136,0)+IF($C$136>0,$C$137*AH11/$C$136,0)+IF($C$136>0,$C$137*AI11/$C$136,0)+IF($C$136>0,$C$137*AJ11/$C$136,0)+IF($C$136>0,$C$137*AK11/$C$136,0)+IF($C$136>0,$C$137*AL11/$C$136,0)+IF($C$136>0,$C$137*AM11/$C$136,0)+IF($C$136>0,$C$137*AN11/$C$136,0)+IF($C$136>0,$C$137*AO11/$C$136,0)+IF($C$136>0,$C$137*AP11/$C$136,0)+IF($C$136>0,$C$137*AQ11/$C$136,0)+IF($C$136>0,$C$137*AR11/$C$136,0)+IF($C$136>0,$C$137*AS11/$C$136,0)+IF($C$136>0,$C$137*AT11/$C$136,0)+IF($C$136>0,$C$137*AU11/$C$136,0)+IF($C$136>0,$C$137*AV11/$C$136,0)+IF($C$136>0,$C$137*AW11/$C$136,0)+IF($C$136>0,$C$137*AX11/$C$136,0)+IF($C$136>0,$C$137*AY11/$C$136,0))-((D17+D18)*INPUT!$C$6/(100+INPUT!$C$6)+(E17+E18)*INPUT!$C$6/(100+INPUT!$C$6)+(F17+F18)*INPUT!$C$6/(100+INPUT!$C$6)+(G17+G18)*INPUT!$C$6/(100+INPUT!$C$6)+(H17+H18)*INPUT!$C$6/(100+INPUT!$C$6)+(I17+I18)*INPUT!$C$6/(100+INPUT!$C$6)+(J17+J18)*INPUT!$C$6/(100+INPUT!$C$6)+(K17+K18)*INPUT!$C$6/(100+INPUT!$C$6)+(L17+L18)*INPUT!$C$6/(100+INPUT!$C$6)+(M17+M18)*INPUT!$C$6/(100+INPUT!$C$6)+(N17+N18)*INPUT!$C$6/(100+INPUT!$C$6)+(O17+O18)*INPUT!$C$6/(100+INPUT!$C$6)+(P17+P18)*INPUT!$C$6/(100+INPUT!$C$6)+(Q17+Q18)*INPUT!$C$6/(100+INPUT!$C$6)+(R17+R18)*INPUT!$C$6/(100+INPUT!$C$6)+(S17+S18)*INPUT!$C$6/(100+INPUT!$C$6)+(T17+T18)*INPUT!$C$6/(100+INPUT!$C$6)+(U17+U18)*INPUT!$C$6/(100+INPUT!$C$6)+(V17+V18)*INPUT!$C$6/(100+INPUT!$C$6)+(W17+W18)*INPUT!$C$6/(100+INPUT!$C$6)+(X17+X18)*INPUT!$C$6/(100+INPUT!$C$6)+(Y17+Y18)*INPUT!$C$6/(100+INPUT!$C$6)+(Z17+Z18)*INPUT!$C$6/(100+INPUT!$C$6)+(AA17+AA18)*INPUT!$C$6/(100+INPUT!$C$6)+(AB17+AB18)*INPUT!$C$6/(100+INPUT!$C$6)+(AC17+AC18)*INPUT!$C$6/(100+INPUT!$C$6)+(AD17+AD18)*INPUT!$C$6/(100+INPUT!$C$6)+(AE17+AE18)*INPUT!$C$6/(100+INPUT!$C$6)+(AF17+AF18)*INPUT!$C$6/(100+INPUT!$C$6)+(AG17+AG18)*INPUT!$C$6/(100+INPUT!$C$6)+(AH17+AH18)*INPUT!$C$6/(100+INPUT!$C$6)+(AI17+AI18)*INPUT!$C$6/(100+INPUT!$C$6)+(AJ17+AJ18)*INPUT!$C$6/(100+INPUT!$C$6)+(AK17+AK18)*INPUT!$C$6/(100+INPUT!$C$6)+(AL17+AL18)*INPUT!$C$6/(100+INPUT!$C$6)+(AM17+AM18)*INPUT!$C$6/(100+INPUT!$C$6)+(AN17+AN18)*INPUT!$C$6/(100+INPUT!$C$6)+(AO17+AO18)*INPUT!$C$6/(100+INPUT!$C$6)+(AP17+AP18)*INPUT!$C$6/(100+INPUT!$C$6)+(AQ17+AQ18)*INPUT!$C$6/(100+INPUT!$C$6)+(AR17+AR18)*INPUT!$C$6/(100+INPUT!$C$6)+(AS17+AS18)*INPUT!$C$6/(100+INPUT!$C$6)+(AT17+AT18)*INPUT!$C$6/(100+INPUT!$C$6)+(AU17+AU18)*INPUT!$C$6/(100+INPUT!$C$6)+(AV17+AV18)*INPUT!$C$6/(100+INPUT!$C$6)+(AW17+AW18)*INPUT!$C$6/(100+INPUT!$C$6)+(AX17+AX18)*INPUT!$C$6/(100+INPUT!$C$6)+(AY17+AY18)*INPUT!$C$6/(100+INPUT!$C$6))-SUM(D19:AX19),0) -> 0 | AZ19: =MAX((IF($C$136>0,$C$137*D11/$C$136,0)+IF($C$136>0,$C$137*E11/$C$136,0)+IF($C$136>0,$C$137*F11/$C$136,0)+IF($C$136>0,$C$137*G11/$C$136,0)+IF($C$136>0,$C$137*H11/$C$136,0)+IF($C$136>0,$C$137*I11/$C$136,0)+IF($C$136>0,$C$137*J11/$C$136,0)+IF($C$136>0,$C$137*K11/$C$136,0)+IF($C$136>0,$C$137*L11/$C$136,0)+IF($C$136>0,$C$137*M11/$C$136,0)+IF($C$136>0,$C$137*N11/$C$136,0)+IF($C$136>0,$C$137*O11/$C$136,0)+IF($C$136>0,$C$137*P11/$C$136,0)+IF($C$136>0,$C$137*Q11/$C$136,0)+IF($C$136>0,$C$137*R11/$C$136,0)+IF($C$136>0,$C$137*S11/$C$136,0)+IF($C$136>0,$C$137*T11/$C$136,0)+IF($C$136>0,$C$137*U11/$C$136,0)+IF($C$136>0,$C$137*V11/$C$136,0)+IF($C$136>0,$C$137*W11/$C$136,0)+IF($C$136>0,$C$137*X11/$C$136,0)+IF($C$136>0,$C$137*Y11/$C$136,0)+IF($C$136>0,$C$137*Z11/$C$136,0)+IF($C$136>0,$C$137*AA11/$C$136,0)+IF($C$136>0,$C$137*AB11/$C$136,0)+IF($C$136>0,$C$137*AC11/$C$136,0)+IF($C$136>0,$C$137*AD11/$C$136,0)+IF($C$136>0,$C$137*AE11/$C$136,0)+IF($C$136>0,$C$137*AF11/$C$136,0)+IF($C$136>0,$C$137*AG11/$C$136,0)+IF($C$136>0,$C$137*AH11/$C$136,0)+IF($C$136>0,$C$137*AI11/$C$136,0)+IF($C$136>0,$C$137*AJ11/$C$136,0)+IF($C$136>0,$C$137*AK11/$C$136,0)+IF($C$136>0,$C$137*AL11/$C$136,0)+IF($C$136>0,$C$137*AM11/$C$136,0)+IF($C$136>0,$C$137*AN11/$C$136,0)+IF($C$136>0,$C$137*AO11/$C$136,0)+IF($C$136>0,$C$137*AP11/$C$136,0)+IF($C$136>0,$C$137*AQ11/$C$136,0)+IF($C$136>0,$C$137*AR11/$C$136,0)+IF($C$136>0,$C$137*AS11/$C$136,0)+IF($C$136>0,$C$137*AT11/$C$136,0)+IF($C$136>0,$C$137*AU11/$C$136,0)+IF($C$136>0,$C$137*AV11/$C$136,0)+IF($C$136>0,$C$137*AW11/$C$136,0)+IF($C$136>0,$C$137*AX11/$C$136,0)+IF($C$136>0,$C$137*AY11/$C$136,0)+IF($C$136>0,$C$137*AZ11/$C$136,0))-((D17+D18)*INPUT!$C$6/(100+INPUT!$C$6)+(E17+E18)*INPUT!$C$6/(100+INPUT!$C$6)+(F17+F18)*INPUT!$C$6/(100+INPUT!$C$6)+(G17+G18)*INPUT!$C$6/(100+INPUT!$C$6)+(H17+H18)*INPUT!$C$6/(100+INPUT!$C$6)+(I17+I18)*INPUT!$C$6/(100+INPUT!$C$6)+(J17+J18)*INPUT!$C$6/(100+INPUT!$C$6)+(K17+K18)*INPUT!$C$6/(100+INPUT!$C$6)+(L17+L18)*INPUT!$C$6/(100+INPUT!$C$6)+(M17+M18)*INPUT!$C$6/(100+INPUT!$C$6)+(N17+N18)*INPUT!$C$6/(100+INPUT!$C$6)+(O17+O18)*INPUT!$C$6/(100+INPUT!$C$6)+(P17+P18)*INPUT!$C$6/(100+INPUT!$C$6)+(Q17+Q18)*INPUT!$C$6/(100+INPUT!$C$6)+(R17+R18)*INPUT!$C$6/(100+INPUT!$C$6)+(S17+S18)*INPUT!$C$6/(100+INPUT!$C$6)+(T17+T18)*INPUT!$C$6/(100+INPUT!$C$6)+(U17+U18)*INPUT!$C$6/(100+INPUT!$C$6)+(V17+V18)*INPUT!$C$6/(100+INPUT!$C$6)+(W17+W18)*INPUT!$C$6/(100+INPUT!$C$6)+(X17+X18)*INPUT!$C$6/(100+INPUT!$C$6)+(Y17+Y18)*INPUT!$C$6/(100+INPUT!$C$6)+(Z17+Z18)*INPUT!$C$6/(100+INPUT!$C$6)+(AA17+AA18)*INPUT!$C$6/(100+INPUT!$C$6)+(AB17+AB18)*INPUT!$C$6/(100+INPUT!$C$6)+(AC17+AC18)*INPUT!$C$6/(100+INPUT!$C$6)+(AD17+AD18)*INPUT!$C$6/(100+INPUT!$C$6)+(AE17+AE18)*INPUT!$C$6/(100+INPUT!$C$6)+(AF17+AF18)*INPUT!$C$6/(100+INPUT!$C$6)+(AG17+AG18)*INPUT!$C$6/(100+INPUT!$C$6)+(AH17+AH18)*INPUT!$C$6/(100+INPUT!$C$6)+(AI17+AI18)*INPUT!$C$6/(100+INPUT!$C$6)+(AJ17+AJ18)*INPUT!$C$6/(100+INPUT!$C$6)+(AK17+AK18)*INPUT!$C$6/(100+INPUT!$C$6)+(AL17+AL18)*INPUT!$C$6/(100+INPUT!$C$6)+(AM17+AM18)*INPUT!$C$6/(100+INPUT!$C$6)+(AN17+AN18)*INPUT!$C$6/(100+INPUT!$C$6)+(AO17+AO18)*INPUT!$C$6/(100+INPUT!$C$6)+(AP17+AP18)*INPUT!$C$6/(100+INPUT!$C$6)+(AQ17+AQ18)*INPUT!$C$6/(100+INPUT!$C$6)+(AR17+AR18)*INPUT!$C$6/(100+INPUT!$C$6)+(AS17+AS18)*INPUT!$C$6/(100+INPUT!$C$6)+(AT17+AT18)*INPUT!$C$6/(100+INPUT!$C$6)+(AU17+AU18)*INPUT!$C$6/(100+INPUT!$C$6)+(AV17+AV18)*INPUT!$C$6/(100+INPUT!$C$6)+(AW17+AW18)*INPUT!$C$6/(100+INPUT!$C$6)+(AX17+AX18)*INPUT!$C$6/(100+INPUT!$C$6)+(AY17+AY18)*INPUT!$C$6/(100+INPUT!$C$6)+(AZ17+AZ18)*INPUT!$C$6/(100+INPUT!$C$6))-SUM(D19:AY19),0) -> 0 | BA19: =MAX((IF($C$136>0,$C$137*D11/$C$136,0)+IF($C$136>0,$C$137*E11/$C$136,0)+IF($C$136>0,$C$137*F11/$C$136,0)+IF($C$136>0,$C$137*G11/$C$136,0)+IF($C$136>0,$C$137*H11/$C$136,0)+IF($C$136>0,$C$137*I11/$C$136,0)+IF($C$136>0,$C$137*J11/$C$136,0)+IF($C$136>0,$C$137*K11/$C$136,0)+IF($C$136>0,$C$137*L11/$C$136,0)+IF($C$136>0,$C$137*M11/$C$136,0)+IF($C$136>0,$C$137*N11/$C$136,0)+IF($C$136>0,$C$137*O11/$C$136,0)+IF($C$136>0,$C$137*P11/$C$136,0)+IF($C$136>0,$C$137*Q11/$C$136,0)+IF($C$136>0,$C$137*R11/$C$136,0)+IF($C$136>0,$C$137*S11/$C$136,0)+IF($C$136>0,$C$137*T11/$C$136,0)+IF($C$136>0,$C$137*U11/$C$136,0)+IF($C$136>0,$C$137*V11/$C$136,0)+IF($C$136>0,$C$137*W11/$C$136,0)+IF($C$136>0,$C$137*X11/$C$136,0)+IF($C$136>0,$C$137*Y11/$C$136,0)+IF($C$136>0,$C$137*Z11/$C$136,0)+IF($C$136>0,$C$137*AA11/$C$136,0)+IF($C$136>0,$C$137*AB11/$C$136,0)+IF($C$136>0,$C$137*AC11/$C$136,0)+IF($C$136>0,$C$137*AD11/$C$136,0)+IF($C$136>0,$C$137*AE11/$C$136,0)+IF($C$136>0,$C$137*AF11/$C$136,0)+IF($C$136>0,$C$137*AG11/$C$136,0)+IF($C$136>0,$C$137*AH11/$C$136,0)+IF($C$136>0,$C$137*AI11/$C$136,0)+IF($C$136>0,$C$137*AJ11/$C$136,0)+IF($C$136>0,$C$137*AK11/$C$136,0)+IF($C$136>0,$C$137*AL11/$C$136,0)+IF($C$136>0,$C$137*AM11/$C$136,0)+IF($C$136>0,$C$137*AN11/$C$136,0)+IF($C$136>0,$C$137*AO11/$C$136,0)+IF($C$136>0,$C$137*AP11/$C$136,0)+IF($C$136>0,$C$137*AQ11/$C$136,0)+IF($C$136>0,$C$137*AR11/$C$136,0)+IF($C$136>0,$C$137*AS11/$C$136,0)+IF($C$136>0,$C$137*AT11/$C$136,0)+IF($C$136>0,$C$137*AU11/$C$136,0)+IF($C$136>0,$C$137*AV11/$C$136,0)+IF($C$136>0,$C$137*AW11/$C$136,0)+IF($C$136>0,$C$137*AX11/$C$136,0)+IF($C$136>0,$C$137*AY11/$C$136,0)+IF($C$136>0,$C$137*AZ11/$C$136,0)+IF($C$136>0,$C$137*BA11/$C$136,0))-((D17+D18)*INPUT!$C$6/(100+INPUT!$C$6)+(E17+E18)*INPUT!$C$6/(100+INPUT!$C$6)+(F17+F18)*INPUT!$C$6/(100+INPUT!$C$6)+(G17+G18)*INPUT!$C$6/(100+INPUT!$C$6)+(H17+H18)*INPUT!$C$6/(100+INPUT!$C$6)+(I17+I18)*INPUT!$C$6/(100+INPUT!$C$6)+(J17+J18)*INPUT!$C$6/(100+INPUT!$C$6)+(K17+K18)*INPUT!$C$6/(100+INPUT!$C$6)+(L17+L18)*INPUT!$C$6/(100+INPUT!$C$6)+(M17+M18)*INPUT!$C$6/(100+INPUT!$C$6)+(N17+N18)*INPUT!$C$6/(100+INPUT!$C$6)+(O17+O18)*INPUT!$C$6/(100+INPUT!$C$6)+(P17+P18)*INPUT!$C$6/(100+INPUT!$C$6)+(Q17+Q18)*INPUT!$C$6/(100+INPUT!$C$6)+(R17+R18)*INPUT!$C$6/(100+INPUT!$C$6)+(S17+S18)*INPUT!$C$6/(100+INPUT!$C$6)+(T17+T18)*INPUT!$C$6/(100+INPUT!$C$6)+(U17+U18)*INPUT!$C$6/(100+INPUT!$C$6)+(V17+V18)*INPUT!$C$6/(100+INPUT!$C$6)+(W17+W18)*INPUT!$C$6/(100+INPUT!$C$6)+(X17+X18)*INPUT!$C$6/(100+INPUT!$C$6)+(Y17+Y18)*INPUT!$C$6/(100+INPUT!$C$6)+(Z17+Z18)*INPUT!$C$6/(100+INPUT!$C$6)+(AA17+AA18)*INPUT!$C$6/(100+INPUT!$C$6)+(AB17+AB18)*INPUT!$C$6/(100+INPUT!$C$6)+(AC17+AC18)*INPUT!$C$6/(100+INPUT!$C$6)+(AD17+AD18)*INPUT!$C$6/(100+INPUT!$C$6)+(AE17+AE18)*INPUT!$C$6/(100+INPUT!$C$6)+(AF17+AF18)*INPUT!$C$6/(100+INPUT!$C$6)+(AG17+AG18)*INPUT!$C$6/(100+INPUT!$C$6)+(AH17+AH18)*INPUT!$C$6/(100+INPUT!$C$6)+(AI17+AI18)*INPUT!$C$6/(100+INPUT!$C$6)+(AJ17+AJ18)*INPUT!$C$6/(100+INPUT!$C$6)+(AK17+AK18)*INPUT!$C$6/(100+INPUT!$C$6)+(AL17+AL18)*INPUT!$C$6/(100+INPUT!$C$6)+(AM17+AM18)*INPUT!$C$6/(100+INPUT!$C$6)+(AN17+AN18)*INPUT!$C$6/(100+INPUT!$C$6)+(AO17+AO18)*INPUT!$C$6/(100+INPUT!$C$6)+(AP17+AP18)*INPUT!$C$6/(100+INPUT!$C$6)+(AQ17+AQ18)*INPUT!$C$6/(100+INPUT!$C$6)+(AR17+AR18)*INPUT!$C$6/(100+INPUT!$C$6)+(AS17+AS18)*INPUT!$C$6/(100+INPUT!$C$6)+(AT17+AT18)*INPUT!$C$6/(100+INPUT!$C$6)+(AU17+AU18)*INPUT!$C$6/(100+INPUT!$C$6)+(AV17+AV18)*INPUT!$C$6/(100+INPUT!$C$6)+(AW17+AW18)*INPUT!$C$6/(100+INPUT!$C$6)+(AX17+AX18)*INPUT!$C$6/(100+INPUT!$C$6)+(AY17+AY18)*INPUT!$C$6/(100+INPUT!$C$6)+(AZ17+AZ18)*INPUT!$C$6/(100+INPUT!$C$6)+(BA17+BA18)*INPUT!$C$6/(100+INPUT!$C$6))-SUM(D19:AZ19),0) -> 0 | BB19: =MAX((IF($C$136>0,$C$137*D11/$C$136,0)+IF($C$136>0,$C$137*E11/$C$136,0)+IF($C$136>0,$C$137*F11/$C$136,0)+IF($C$136>0,$C$137*G11/$C$136,0)+IF($C$136>0,$C$137*H11/$C$136,0)+IF($C$136>0,$C$137*I11/$C$136,0)+IF($C$136>0,$C$137*J11/$C$136,0)+IF($C$136>0,$C$137*K11/$C$136,0)+IF($C$136>0,$C$137*L11/$C$136,0)+IF($C$136>0,$C$137*M11/$C$136,0)+IF($C$136>0,$C$137*N11/$C$136,0)+IF($C$136>0,$C$137*O11/$C$136,0)+IF($C$136>0,$C$137*P11/$C$136,0)+IF($C$136>0,$C$137*Q11/$C$136,0)+IF($C$136>0,$C$137*R11/$C$136,0)+IF($C$136>0,$C$137*S11/$C$136,0)+IF($C$136>0,$C$137*T11/$C$136,0)+IF($C$136>0,$C$137*U11/$C$136,0)+IF($C$136>0,$C$137*V11/$C$136,0)+IF($C$136>0,$C$137*W11/$C$136,0)+IF($C$136>0,$C$137*X11/$C$136,0)+IF($C$136>0,$C$137*Y11/$C$136,0)+IF($C$136>0,$C$137*Z11/$C$136,0)+IF($C$136>0,$C$137*AA11/$C$136,0)+IF($C$136>0,$C$137*AB11/$C$136,0)+IF($C$136>0,$C$137*AC11/$C$136,0)+IF($C$136>0,$C$137*AD11/$C$136,0)+IF($C$136>0,$C$137*AE11/$C$136,0)+IF($C$136>0,$C$137*AF11/$C$136,0)+IF($C$136>0,$C$137*AG11/$C$136,0)+IF($C$136>0,$C$137*AH11/$C$136,0)+IF($C$136>0,$C$137*AI11/$C$136,0)+IF($C$136>0,$C$137*AJ11/$C$136,0)+IF($C$136>0,$C$137*AK11/$C$136,0)+IF($C$136>0,$C$137*AL11/$C$136,0)+IF($C$136>0,$C$137*AM11/$C$136,0)+IF($C$136>0,$C$137*AN11/$C$136,0)+IF($C$136>0,$C$137*AO11/$C$136,0)+IF($C$136>0,$C$137*AP11/$C$136,0)+IF($C$136>0,$C$137*AQ11/$C$136,0)+IF($C$136>0,$C$137*AR11/$C$136,0)+IF($C$136>0,$C$137*AS11/$C$136,0)+IF($C$136>0,$C$137*AT11/$C$136,0)+IF($C$136>0,$C$137*AU11/$C$136,0)+IF($C$136>0,$C$137*AV11/$C$136,0)+IF($C$136>0,$C$137*AW11/$C$136,0)+IF($C$136>0,$C$137*AX11/$C$136,0)+IF($C$136>0,$C$137*AY11/$C$136,0)+IF($C$136>0,$C$137*AZ11/$C$136,0)+IF($C$136>0,$C$137*BA11/$C$136,0)+IF($C$136>0,$C$137*BB11/$C$136,0))-((D17+D18)*INPUT!$C$6/(100+INPUT!$C$6)+(E17+E18)*INPUT!$C$6/(100+INPUT!$C$6)+(F17+F18)*INPUT!$C$6/(100+INPUT!$C$6)+(G17+G18)*INPUT!$C$6/(100+INPUT!$C$6)+(H17+H18)*INPUT!$C$6/(100+INPUT!$C$6)+(I17+I18)*INPUT!$C$6/(100+INPUT!$C$6)+(J17+J18)*INPUT!$C$6/(100+INPUT!$C$6)+(K17+K18)*INPUT!$C$6/(100+INPUT!$C$6)+(L17+L18)*INPUT!$C$6/(100+INPUT!$C$6)+(M17+M18)*INPUT!$C$6/(100+INPUT!$C$6)+(N17+N18)*INPUT!$C$6/(100+INPUT!$C$6)+(O17+O18)*INPUT!$C$6/(100+INPUT!$C$6)+(P17+P18)*INPUT!$C$6/(100+INPUT!$C$6)+(Q17+Q18)*INPUT!$C$6/(100+INPUT!$C$6)+(R17+R18)*INPUT!$C$6/(100+INPUT!$C$6)+(S17+S18)*INPUT!$C$6/(100+INPUT!$C$6)+(T17+T18)*INPUT!$C$6/(100+INPUT!$C$6)+(U17+U18)*INPUT!$C$6/(100+INPUT!$C$6)+(V17+V18)*INPUT!$C$6/(100+INPUT!$C$6)+(W17+W18)*INPUT!$C$6/(100+INPUT!$C$6)+(X17+X18)*INPUT!$C$6/(100+INPUT!$C$6)+(Y17+Y18)*INPUT!$C$6/(100+INPUT!$C$6)+(Z17+Z18)*INPUT!$C$6/(100+INPUT!$C$6)+(AA17+AA18)*INPUT!$C$6/(100+INPUT!$C$6)+(AB17+AB18)*INPUT!$C$6/(100+INPUT!$C$6)+(AC17+AC18)*INPUT!$C$6/(100+INPUT!$C$6)+(AD17+AD18)*INPUT!$C$6/(100+INPUT!$C$6)+(AE17+AE18)*INPUT!$C$6/(100+INPUT!$C$6)+(AF17+AF18)*INPUT!$C$6/(100+INPUT!$C$6)+(AG17+AG18)*INPUT!$C$6/(100+INPUT!$C$6)+(AH17+AH18)*INPUT!$C$6/(100+INPUT!$C$6)+(AI17+AI18)*INPUT!$C$6/(100+INPUT!$C$6)+(AJ17+AJ18)*INPUT!$C$6/(100+INPUT!$C$6)+(AK17+AK18)*INPUT!$C$6/(100+INPUT!$C$6)+(AL17+AL18)*INPUT!$C$6/(100+INPUT!$C$6)+(AM17+AM18)*INPUT!$C$6/(100+INPUT!$C$6)+(AN17+AN18)*INPUT!$C$6/(100+INPUT!$C$6)+(AO17+AO18)*INPUT!$C$6/(100+INPUT!$C$6)+(AP17+AP18)*INPUT!$C$6/(100+INPUT!$C$6)+(AQ17+AQ18)*INPUT!$C$6/(100+INPUT!$C$6)+(AR17+AR18)*INPUT!$C$6/(100+INPUT!$C$6)+(AS17+AS18)*INPUT!$C$6/(100+INPUT!$C$6)+(AT17+AT18)*INPUT!$C$6/(100+INPUT!$C$6)+(AU17+AU18)*INPUT!$C$6/(100+INPUT!$C$6)+(AV17+AV18)*INPUT!$C$6/(100+INPUT!$C$6)+(AW17+AW18)*INPUT!$C$6/(100+INPUT!$C$6)+(AX17+AX18)*INPUT!$C$6/(100+INPUT!$C$6)+(AY17+AY18)*INPUT!$C$6/(100+INPUT!$C$6)+(AZ17+AZ18)*INPUT!$C$6/(100+INPUT!$C$6)+(BA17+BA18)*INPUT!$C$6/(100+INPUT!$C$6)+(BB17+BB18)*INPUT!$C$6/(100+INPUT!$C$6))-SUM(D19:BA19),0) -> 0 | BC19: =MAX((IF($C$136>0,$C$137*D11/$C$136,0)+IF($C$136>0,$C$137*E11/$C$136,0)+IF($C$136>0,$C$137*F11/$C$136,0)+IF($C$136>0,$C$137*G11/$C$136,0)+IF($C$136>0,$C$137*H11/$C$136,0)+IF($C$136>0,$C$137*I11/$C$136,0)+IF($C$136>0,$C$137*J11/$C$136,0)+IF($C$136>0,$C$137*K11/$C$136,0)+IF($C$136>0,$C$137*L11/$C$136,0)+IF($C$136>0,$C$137*M11/$C$136,0)+IF($C$136>0,$C$137*N11/$C$136,0)+IF($C$136>0,$C$137*O11/$C$136,0)+IF($C$136>0,$C$137*P11/$C$136,0)+IF($C$136>0,$C$137*Q11/$C$136,0)+IF($C$136>0,$C$137*R11/$C$136,0)+IF($C$136>0,$C$137*S11/$C$136,0)+IF($C$136>0,$C$137*T11/$C$136,0)+IF($C$136>0,$C$137*U11/$C$136,0)+IF($C$136>0,$C$137*V11/$C$136,0)+IF($C$136>0,$C$137*W11/$C$136,0)+IF($C$136>0,$C$137*X11/$C$136,0)+IF($C$136>0,$C$137*Y11/$C$136,0)+IF($C$136>0,$C$137*Z11/$C$136,0)+IF($C$136>0,$C$137*AA11/$C$136,0)+IF($C$136>0,$C$137*AB11/$C$136,0)+IF($C$136>0,$C$137*AC11/$C$136,0)+IF($C$136>0,$C$137*AD11/$C$136,0)+IF($C$136>0,$C$137*AE11/$C$136,0)+IF($C$136>0,$C$137*AF11/$C$136,0)+IF($C$136>0,$C$137*AG11/$C$136,0)+IF($C$136>0,$C$137*AH11/$C$136,0)+IF($C$136>0,$C$137*AI11/$C$136,0)+IF($C$136>0,$C$137*AJ11/$C$136,0)+IF($C$136>0,$C$137*AK11/$C$136,0)+IF($C$136>0,$C$137*AL11/$C$136,0)+IF($C$136>0,$C$137*AM11/$C$136,0)+IF($C$136>0,$C$137*AN11/$C$136,0)+IF($C$136>0,$C$137*AO11/$C$136,0)+IF($C$136>0,$C$137*AP11/$C$136,0)+IF($C$136>0,$C$137*AQ11/$C$136,0)+IF($C$136>0,$C$137*AR11/$C$136,0)+IF($C$136>0,$C$137*AS11/$C$136,0)+IF($C$136>0,$C$137*AT11/$C$136,0)+IF($C$136>0,$C$137*AU11/$C$136,0)+IF($C$136>0,$C$137*AV11/$C$136,0)+IF($C$136>0,$C$137*AW11/$C$136,0)+IF($C$136>0,$C$137*AX11/$C$136,0)+IF($C$136>0,$C$137*AY11/$C$136,0)+IF($C$136>0,$C$137*AZ11/$C$136,0)+IF($C$136>0,$C$137*BA11/$C$136,0)+IF($C$136>0,$C$137*BB11/$C$136,0)+IF($C$136>0,$C$137*BC11/$C$136,0))-((D17+D18)*INPUT!$C$6/(100+INPUT!$C$6)+(E17+E18)*INPUT!$C$6/(100+INPUT!$C$6)+(F17+F18)*INPUT!$C$6/(100+INPUT!$C$6)+(G17+G18)*INPUT!$C$6/(100+INPUT!$C$6)+(H17+H18)*INPUT!$C$6/(100+INPUT!$C$6)+(I17+I18)*INPUT!$C$6/(100+INPUT!$C$6)+(J17+J18)*INPUT!$C$6/(100+INPUT!$C$6)+(K17+K18)*INPUT!$C$6/(100+INPUT!$C$6)+(L17+L18)*INPUT!$C$6/(100+INPUT!$C$6)+(M17+M18)*INPUT!$C$6/(100+INPUT!$C$6)+(N17+N18)*INPUT!$C$6/(100+INPUT!$C$6)+(O17+O18)*INPUT!$C$6/(100+INPUT!$C$6)+(P17+P18)*INPUT!$C$6/(100+INPUT!$C$6)+(Q17+Q18)*INPUT!$C$6/(100+INPUT!$C$6)+(R17+R18)*INPUT!$C$6/(100+INPUT!$C$6)+(S17+S18)*INPUT!$C$6/(100+INPUT!$C$6)+(T17+T18)*INPUT!$C$6/(100+INPUT!$C$6)+(U17+U18)*INPUT!$C$6/(100+INPUT!$C$6)+(V17+V18)*INPUT!$C$6/(100+INPUT!$C$6)+(W17+W18)*INPUT!$C$6/(100+INPUT!$C$6)+(X17+X18)*INPUT!$C$6/(100+INPUT!$C$6)+(Y17+Y18)*INPUT!$C$6/(100+INPUT!$C$6)+(Z17+Z18)*INPUT!$C$6/(100+INPUT!$C$6)+(AA17+AA18)*INPUT!$C$6/(100+INPUT!$C$6)+(AB17+AB18)*INPUT!$C$6/(100+INPUT!$C$6)+(AC17+AC18)*INPUT!$C$6/(100+INPUT!$C$6)+(AD17+AD18)*INPUT!$C$6/(100+INPUT!$C$6)+(AE17+AE18)*INPUT!$C$6/(100+INPUT!$C$6)+(AF17+AF18)*INPUT!$C$6/(100+INPUT!$C$6)+(AG17+AG18)*INPUT!$C$6/(100+INPUT!$C$6)+(AH17+AH18)*INPUT!$C$6/(100+INPUT!$C$6)+(AI17+AI18)*INPUT!$C$6/(100+INPUT!$C$6)+(AJ17+AJ18)*INPUT!$C$6/(100+INPUT!$C$6)+(AK17+AK18)*INPUT!$C$6/(100+INPUT!$C$6)+(AL17+AL18)*INPUT!$C$6/(100+INPUT!$C$6)+(AM17+AM18)*INPUT!$C$6/(100+INPUT!$C$6)+(AN17+AN18)*INPUT!$C$6/(100+INPUT!$C$6)+(AO17+AO18)*INPUT!$C$6/(100+INPUT!$C$6)+(AP17+AP18)*INPUT!$C$6/(100+INPUT!$C$6)+(AQ17+AQ18)*INPUT!$C$6/(100+INPUT!$C$6)+(AR17+AR18)*INPUT!$C$6/(100+INPUT!$C$6)+(AS17+AS18)*INPUT!$C$6/(100+INPUT!$C$6)+(AT17+AT18)*INPUT!$C$6/(100+INPUT!$C$6)+(AU17+AU18)*INPUT!$C$6/(100+INPUT!$C$6)+(AV17+AV18)*INPUT!$C$6/(100+INPUT!$C$6)+(AW17+AW18)*INPUT!$C$6/(100+INPUT!$C$6)+(AX17+AX18)*INPUT!$C$6/(100+INPUT!$C$6)+(AY17+AY18)*INPUT!$C$6/(100+INPUT!$C$6)+(AZ17+AZ18)*INPUT!$C$6/(100+INPUT!$C$6)+(BA17+BA18)*INPUT!$C$6/(100+INPUT!$C$6)+(BB17+BB18)*INPUT!$C$6/(100+INPUT!$C$6)+(BC17+BC18)*INPUT!$C$6/(100+INPUT!$C$6))-SUM(D19:BB19),0) -> 0 | BD19: =MAX((IF($C$136>0,$C$137*D11/$C$136,0)+IF($C$136>0,$C$137*E11/$C$136,0)+IF($C$136>0,$C$137*F11/$C$136,0)+IF($C$136>0,$C$137*G11/$C$136,0)+IF($C$136>0,$C$137*H11/$C$136,0)+IF($C$136>0,$C$137*I11/$C$136,0)+IF($C$136>0,$C$137*J11/$C$136,0)+IF($C$136>0,$C$137*K11/$C$136,0)+IF($C$136>0,$C$137*L11/$C$136,0)+IF($C$136>0,$C$137*M11/$C$136,0)+IF($C$136>0,$C$137*N11/$C$136,0)+IF($C$136>0,$C$137*O11/$C$136,0)+IF($C$136>0,$C$137*P11/$C$136,0)+IF($C$136>0,$C$137*Q11/$C$136,0)+IF($C$136>0,$C$137*R11/$C$136,0)+IF($C$136>0,$C$137*S11/$C$136,0)+IF($C$136>0,$C$137*T11/$C$136,0)+IF($C$136>0,$C$137*U11/$C$136,0)+IF($C$136>0,$C$137*V11/$C$136,0)+IF($C$136>0,$C$137*W11/$C$136,0)+IF($C$136>0,$C$137*X11/$C$136,0)+IF($C$136>0,$C$137*Y11/$C$136,0)+IF($C$136>0,$C$137*Z11/$C$136,0)+IF($C$136>0,$C$137*AA11/$C$136,0)+IF($C$136>0,$C$137*AB11/$C$136,0)+IF($C$136>0,$C$137*AC11/$C$136,0)+IF($C$136>0,$C$137*AD11/$C$136,0)+IF($C$136>0,$C$137*AE11/$C$136,0)+IF($C$136>0,$C$137*AF11/$C$136,0)+IF($C$136>0,$C$137*AG11/$C$136,0)+IF($C$136>0,$C$137*AH11/$C$136,0)+IF($C$136>0,$C$137*AI11/$C$136,0)+IF($C$136>0,$C$137*AJ11/$C$136,0)+IF($C$136>0,$C$137*AK11/$C$136,0)+IF($C$136>0,$C$137*AL11/$C$136,0)+IF($C$136>0,$C$137*AM11/$C$136,0)+IF($C$136>0,$C$137*AN11/$C$136,0)+IF($C$136>0,$C$137*AO11/$C$136,0)+IF($C$136>0,$C$137*AP11/$C$136,0)+IF($C$136>0,$C$137*AQ11/$C$136,0)+IF($C$136>0,$C$137*AR11/$C$136,0)+IF($C$136>0,$C$137*AS11/$C$136,0)+IF($C$136>0,$C$137*AT11/$C$136,0)+IF($C$136>0,$C$137*AU11/$C$136,0)+IF($C$136>0,$C$137*AV11/$C$136,0)+IF($C$136>0,$C$137*AW11/$C$136,0)+IF($C$136>0,$C$137*AX11/$C$136,0)+IF($C$136>0,$C$137*AY11/$C$136,0)+IF($C$136>0,$C$137*AZ11/$C$136,0)+IF($C$136>0,$C$137*BA11/$C$136,0)+IF($C$136>0,$C$137*BB11/$C$136,0)+IF($C$136>0,$C$137*BC11/$C$136,0)+IF($C$136>0,$C$137*BD11/$C$136,0))-((D17+D18)*INPUT!$C$6/(100+INPUT!$C$6)+(E17+E18)*INPUT!$C$6/(100+INPUT!$C$6)+(F17+F18)*INPUT!$C$6/(100+INPUT!$C$6)+(G17+G18)*INPUT!$C$6/(100+INPUT!$C$6)+(H17+H18)*INPUT!$C$6/(100+INPUT!$C$6)+(I17+I18)*INPUT!$C$6/(100+INPUT!$C$6)+(J17+J18)*INPUT!$C$6/(100+INPUT!$C$6)+(K17+K18)*INPUT!$C$6/(100+INPUT!$C$6)+(L17+L18)*INPUT!$C$6/(100+INPUT!$C$6)+(M17+M18)*INPUT!$C$6/(100+INPUT!$C$6)+(N17+N18)*INPUT!$C$6/(100+INPUT!$C$6)+(O17+O18)*INPUT!$C$6/(100+INPUT!$C$6)+(P17+P18)*INPUT!$C$6/(100+INPUT!$C$6)+(Q17+Q18)*INPUT!$C$6/(100+INPUT!$C$6)+(R17+R18)*INPUT!$C$6/(100+INPUT!$C$6)+(S17+S18)*INPUT!$C$6/(100+INPUT!$C$6)+(T17+T18)*INPUT!$C$6/(100+INPUT!$C$6)+(U17+U18)*INPUT!$C$6/(100+INPUT!$C$6)+(V17+V18)*INPUT!$C$6/(100+INPUT!$C$6)+(W17+W18)*INPUT!$C$6/(100+INPUT!$C$6)+(X17+X18)*INPUT!$C$6/(100+INPUT!$C$6)+(Y17+Y18)*INPUT!$C$6/(100+INPUT!$C$6)+(Z17+Z18)*INPUT!$C$6/(100+INPUT!$C$6)+(AA17+AA18)*INPUT!$C$6/(100+INPUT!$C$6)+(AB17+AB18)*INPUT!$C$6/(100+INPUT!$C$6)+(AC17+AC18)*INPUT!$C$6/(100+INPUT!$C$6)+(AD17+AD18)*INPUT!$C$6/(100+INPUT!$C$6)+(AE17+AE18)*INPUT!$C$6/(100+INPUT!$C$6)+(AF17+AF18)*INPUT!$C$6/(100+INPUT!$C$6)+(AG17+AG18)*INPUT!$C$6/(100+INPUT!$C$6)+(AH17+AH18)*INPUT!$C$6/(100+INPUT!$C$6)+(AI17+AI18)*INPUT!$C$6/(100+INPUT!$C$6)+(AJ17+AJ18)*INPUT!$C$6/(100+INPUT!$C$6)+(AK17+AK18)*INPUT!$C$6/(100+INPUT!$C$6)+(AL17+AL18)*INPUT!$C$6/(100+INPUT!$C$6)+(AM17+AM18)*INPUT!$C$6/(100+INPUT!$C$6)+(AN17+AN18)*INPUT!$C$6/(100+INPUT!$C$6)+(AO17+AO18)*INPUT!$C$6/(100+INPUT!$C$6)+(AP17+AP18)*INPUT!$C$6/(100+INPUT!$C$6)+(AQ17+AQ18)*INPUT!$C$6/(100+INPUT!$C$6)+(AR17+AR18)*INPUT!$C$6/(100+INPUT!$C$6)+(AS17+AS18)*INPUT!$C$6/(100+INPUT!$C$6)+(AT17+AT18)*INPUT!$C$6/(100+INPUT!$C$6)+(AU17+AU18)*INPUT!$C$6/(100+INPUT!$C$6)+(AV17+AV18)*INPUT!$C$6/(100+INPUT!$C$6)+(AW17+AW18)*INPUT!$C$6/(100+INPUT!$C$6)+(AX17+AX18)*INPUT!$C$6/(100+INPUT!$C$6)+(AY17+AY18)*INPUT!$C$6/(100+INPUT!$C$6)+(AZ17+AZ18)*INPUT!$C$6/(100+INPUT!$C$6)+(BA17+BA18)*INPUT!$C$6/(100+INPUT!$C$6)+(BB17+BB18)*INPUT!$C$6/(100+INPUT!$C$6)+(BC17+BC18)*INPUT!$C$6/(100+INPUT!$C$6)+(BD17+BD18)*INPUT!$C$6/(100+INPUT!$C$6))-SUM(D19:BC19),0) -> 0 | BE19: =MAX((IF($C$136>0,$C$137*D11/$C$136,0)+IF($C$136>0,$C$137*E11/$C$136,0)+IF($C$136>0,$C$137*F11/$C$136,0)+IF($C$136>0,$C$137*G11/$C$136,0)+IF($C$136>0,$C$137*H11/$C$136,0)+IF($C$136>0,$C$137*I11/$C$136,0)+IF($C$136>0,$C$137*J11/$C$136,0)+IF($C$136>0,$C$137*K11/$C$136,0)+IF($C$136>0,$C$137*L11/$C$136,0)+IF($C$136>0,$C$137*M11/$C$136,0)+IF($C$136>0,$C$137*N11/$C$136,0)+IF($C$136>0,$C$137*O11/$C$136,0)+IF($C$136>0,$C$137*P11/$C$136,0)+IF($C$136>0,$C$137*Q11/$C$136,0)+IF($C$136>0,$C$137*R11/$C$136,0)+IF($C$136>0,$C$137*S11/$C$136,0)+IF($C$136>0,$C$137*T11/$C$136,0)+IF($C$136>0,$C$137*U11/$C$136,0)+IF($C$136>0,$C$137*V11/$C$136,0)+IF($C$136>0,$C$137*W11/$C$136,0)+IF($C$136>0,$C$137*X11/$C$136,0)+IF($C$136>0,$C$137*Y11/$C$136,0)+IF($C$136>0,$C$137*Z11/$C$136,0)+IF($C$136>0,$C$137*AA11/$C$136,0)+IF($C$136>0,$C$137*AB11/$C$136,0)+IF($C$136>0,$C$137*AC11/$C$136,0)+IF($C$136>0,$C$137*AD11/$C$136,0)+IF($C$136>0,$C$137*AE11/$C$136,0)+IF($C$136>0,$C$137*AF11/$C$136,0)+IF($C$136>0,$C$137*AG11/$C$136,0)+IF($C$136>0,$C$137*AH11/$C$136,0)+IF($C$136>0,$C$137*AI11/$C$136,0)+IF($C$136>0,$C$137*AJ11/$C$136,0)+IF($C$136>0,$C$137*AK11/$C$136,0)+IF($C$136>0,$C$137*AL11/$C$136,0)+IF($C$136>0,$C$137*AM11/$C$136,0)+IF($C$136>0,$C$137*AN11/$C$136,0)+IF($C$136>0,$C$137*AO11/$C$136,0)+IF($C$136>0,$C$137*AP11/$C$136,0)+IF($C$136>0,$C$137*AQ11/$C$136,0)+IF($C$136>0,$C$137*AR11/$C$136,0)+IF($C$136>0,$C$137*AS11/$C$136,0)+IF($C$136>0,$C$137*AT11/$C$136,0)+IF($C$136>0,$C$137*AU11/$C$136,0)+IF($C$136>0,$C$137*AV11/$C$136,0)+IF($C$136>0,$C$137*AW11/$C$136,0)+IF($C$136>0,$C$137*AX11/$C$136,0)+IF($C$136>0,$C$137*AY11/$C$136,0)+IF($C$136>0,$C$137*AZ11/$C$136,0)+IF($C$136>0,$C$137*BA11/$C$136,0)+IF($C$136>0,$C$137*BB11/$C$136,0)+IF($C$136>0,$C$137*BC11/$C$136,0)+IF($C$136>0,$C$137*BD11/$C$136,0)+IF($C$136>0,$C$137*BE11/$C$136,0))-((D17+D18)*INPUT!$C$6/(100+INPUT!$C$6)+(E17+E18)*INPUT!$C$6/(100+INPUT!$C$6)+(F17+F18)*INPUT!$C$6/(100+INPUT!$C$6)+(G17+G18)*INPUT!$C$6/(100+INPUT!$C$6)+(H17+H18)*INPUT!$C$6/(100+INPUT!$C$6)+(I17+I18)*INPUT!$C$6/(100+INPUT!$C$6)+(J17+J18)*INPUT!$C$6/(100+INPUT!$C$6)+(K17+K18)*INPUT!$C$6/(100+INPUT!$C$6)+(L17+L18)*INPUT!$C$6/(100+INPUT!$C$6)+(M17+M18)*INPUT!$C$6/(100+INPUT!$C$6)+(N17+N18)*INPUT!$C$6/(100+INPUT!$C$6)+(O17+O18)*INPUT!$C$6/(100+INPUT!$C$6)+(P17+P18)*INPUT!$C$6/(100+INPUT!$C$6)+(Q17+Q18)*INPUT!$C$6/(100+INPUT!$C$6)+(R17+R18)*INPUT!$C$6/(100+INPUT!$C$6)+(S17+S18)*INPUT!$C$6/(100+INPUT!$C$6)+(T17+T18)*INPUT!$C$6/(100+INPUT!$C$6)+(U17+U18)*INPUT!$C$6/(100+INPUT!$C$6)+(V17+V18)*INPUT!$C$6/(100+INPUT!$C$6)+(W17+W18)*INPUT!$C$6/(100+INPUT!$C$6)+(X17+X18)*INPUT!$C$6/(100+INPUT!$C$6)+(Y17+Y18)*INPUT!$C$6/(100+INPUT!$C$6)+(Z17+Z18)*INPUT!$C$6/(100+INPUT!$C$6)+(AA17+AA18)*INPUT!$C$6/(100+INPUT!$C$6)+(AB17+AB18)*INPUT!$C$6/(100+INPUT!$C$6)+(AC17+AC18)*INPUT!$C$6/(100+INPUT!$C$6)+(AD17+AD18)*INPUT!$C$6/(100+INPUT!$C$6)+(AE17+AE18)*INPUT!$C$6/(100+INPUT!$C$6)+(AF17+AF18)*INPUT!$C$6/(100+INPUT!$C$6)+(AG17+AG18)*INPUT!$C$6/(100+INPUT!$C$6)+(AH17+AH18)*INPUT!$C$6/(100+INPUT!$C$6)+(AI17+AI18)*INPUT!$C$6/(100+INPUT!$C$6)+(AJ17+AJ18)*INPUT!$C$6/(100+INPUT!$C$6)+(AK17+AK18)*INPUT!$C$6/(100+INPUT!$C$6)+(AL17+AL18)*INPUT!$C$6/(100+INPUT!$C$6)+(AM17+AM18)*INPUT!$C$6/(100+INPUT!$C$6)+(AN17+AN18)*INPUT!$C$6/(100+INPUT!$C$6)+(AO17+AO18)*INPUT!$C$6/(100+INPUT!$C$6)+(AP17+AP18)*INPUT!$C$6/(100+INPUT!$C$6)+(AQ17+AQ18)*INPUT!$C$6/(100+INPUT!$C$6)+(AR17+AR18)*INPUT!$C$6/(100+INPUT!$C$6)+(AS17+AS18)*INPUT!$C$6/(100+INPUT!$C$6)+(AT17+AT18)*INPUT!$C$6/(100+INPUT!$C$6)+(AU17+AU18)*INPUT!$C$6/(100+INPUT!$C$6)+(AV17+AV18)*INPUT!$C$6/(100+INPUT!$C$6)+(AW17+AW18)*INPUT!$C$6/(100+INPUT!$C$6)+(AX17+AX18)*INPUT!$C$6/(100+INPUT!$C$6)+(AY17+AY18)*INPUT!$C$6/(100+INPUT!$C$6)+(AZ17+AZ18)*INPUT!$C$6/(100+INPUT!$C$6)+(BA17+BA18)*INPUT!$C$6/(100+INPUT!$C$6)+(BB17+BB18)*INPUT!$C$6/(100+INPUT!$C$6)+(BC17+BC18)*INPUT!$C$6/(100+INPUT!$C$6)+(BD17+BD18)*INPUT!$C$6/(100+INPUT!$C$6)+(BE17+BE18)*INPUT!$C$6/(100+INPUT!$C$6))-SUM(D19:BD19),0) -> 0 | BF19: =MAX((IF($C$136>0,$C$137*D11/$C$136,0)+IF($C$136>0,$C$137*E11/$C$136,0)+IF($C$136>0,$C$137*F11/$C$136,0)+IF($C$136>0,$C$137*G11/$C$136,0)+IF($C$136>0,$C$137*H11/$C$136,0)+IF($C$136>0,$C$137*I11/$C$136,0)+IF($C$136>0,$C$137*J11/$C$136,0)+IF($C$136>0,$C$137*K11/$C$136,0)+IF($C$136>0,$C$137*L11/$C$136,0)+IF($C$136>0,$C$137*M11/$C$136,0)+IF($C$136>0,$C$137*N11/$C$136,0)+IF($C$136>0,$C$137*O11/$C$136,0)+IF($C$136>0,$C$137*P11/$C$136,0)+IF($C$136>0,$C$137*Q11/$C$136,0)+IF($C$136>0,$C$137*R11/$C$136,0)+IF($C$136>0,$C$137*S11/$C$136,0)+IF($C$136>0,$C$137*T11/$C$136,0)+IF($C$136>0,$C$137*U11/$C$136,0)+IF($C$136>0,$C$137*V11/$C$136,0)+IF($C$136>0,$C$137*W11/$C$136,0)+IF($C$136>0,$C$137*X11/$C$136,0)+IF($C$136>0,$C$137*Y11/$C$136,0)+IF($C$136>0,$C$137*Z11/$C$136,0)+IF($C$136>0,$C$137*AA11/$C$136,0)+IF($C$136>0,$C$137*AB11/$C$136,0)+IF($C$136>0,$C$137*AC11/$C$136,0)+IF($C$136>0,$C$137*AD11/$C$136,0)+IF($C$136>0,$C$137*AE11/$C$136,0)+IF($C$136>0,$C$137*AF11/$C$136,0)+IF($C$136>0,$C$137*AG11/$C$136,0)+IF($C$136>0,$C$137*AH11/$C$136,0)+IF($C$136>0,$C$137*AI11/$C$136,0)+IF($C$136>0,$C$137*AJ11/$C$136,0)+IF($C$136>0,$C$137*AK11/$C$136,0)+IF($C$136>0,$C$137*AL11/$C$136,0)+IF($C$136>0,$C$137*AM11/$C$136,0)+IF($C$136>0,$C$137*AN11/$C$136,0)+IF($C$136>0,$C$137*AO11/$C$136,0)+IF($C$136>0,$C$137*AP11/$C$136,0)+IF($C$136>0,$C$137*AQ11/$C$136,0)+IF($C$136>0,$C$137*AR11/$C$136,0)+IF($C$136>0,$C$137*AS11/$C$136,0)+IF($C$136>0,$C$137*AT11/$C$136,0)+IF($C$136>0,$C$137*AU11/$C$136,0)+IF($C$136>0,$C$137*AV11/$C$136,0)+IF($C$136>0,$C$137*AW11/$C$136,0)+IF($C$136>0,$C$137*AX11/$C$136,0)+IF($C$136>0,$C$137*AY11/$C$136,0)+IF($C$136>0,$C$137*AZ11/$C$136,0)+IF($C$136>0,$C$137*BA11/$C$136,0)+IF($C$136>0,$C$137*BB11/$C$136,0)+IF($C$136>0,$C$137*BC11/$C$136,0)+IF($C$136>0,$C$137*BD11/$C$136,0)+IF($C$136>0,$C$137*BE11/$C$136,0)+IF($C$136>0,$C$137*BF11/$C$136,0))-((D17+D18)*INPUT!$C$6/(100+INPUT!$C$6)+(E17+E18)*INPUT!$C$6/(100+INPUT!$C$6)+(F17+F18)*INPUT!$C$6/(100+INPUT!$C$6)+(G17+G18)*INPUT!$C$6/(100+INPUT!$C$6)+(H17+H18)*INPUT!$C$6/(100+INPUT!$C$6)+(I17+I18)*INPUT!$C$6/(100+INPUT!$C$6)+(J17+J18)*INPUT!$C$6/(100+INPUT!$C$6)+(K17+K18)*INPUT!$C$6/(100+INPUT!$C$6)+(L17+L18)*INPUT!$C$6/(100+INPUT!$C$6)+(M17+M18)*INPUT!$C$6/(100+INPUT!$C$6)+(N17+N18)*INPUT!$C$6/(100+INPUT!$C$6)+(O17+O18)*INPUT!$C$6/(100+INPUT!$C$6)+(P17+P18)*INPUT!$C$6/(100+INPUT!$C$6)+(Q17+Q18)*INPUT!$C$6/(100+INPUT!$C$6)+(R17+R18)*INPUT!$C$6/(100+INPUT!$C$6)+(S17+S18)*INPUT!$C$6/(100+INPUT!$C$6)+(T17+T18)*INPUT!$C$6/(100+INPUT!$C$6)+(U17+U18)*INPUT!$C$6/(100+INPUT!$C$6)+(V17+V18)*INPUT!$C$6/(100+INPUT!$C$6)+(W17+W18)*INPUT!$C$6/(100+INPUT!$C$6)+(X17+X18)*INPUT!$C$6/(100+INPUT!$C$6)+(Y17+Y18)*INPUT!$C$6/(100+INPUT!$C$6)+(Z17+Z18)*INPUT!$C$6/(100+INPUT!$C$6)+(AA17+AA18)*INPUT!$C$6/(100+INPUT!$C$6)+(AB17+AB18)*INPUT!$C$6/(100+INPUT!$C$6)+(AC17+AC18)*INPUT!$C$6/(100+INPUT!$C$6)+(AD17+AD18)*INPUT!$C$6/(100+INPUT!$C$6)+(AE17+AE18)*INPUT!$C$6/(100+INPUT!$C$6)+(AF17+AF18)*INPUT!$C$6/(100+INPUT!$C$6)+(AG17+AG18)*INPUT!$C$6/(100+INPUT!$C$6)+(AH17+AH18)*INPUT!$C$6/(100+INPUT!$C$6)+(AI17+AI18)*INPUT!$C$6/(100+INPUT!$C$6)+(AJ17+AJ18)*INPUT!$C$6/(100+INPUT!$C$6)+(AK17+AK18)*INPUT!$C$6/(100+INPUT!$C$6)+(AL17+AL18)*INPUT!$C$6/(100+INPUT!$C$6)+(AM17+AM18)*INPUT!$C$6/(100+INPUT!$C$6)+(AN17+AN18)*INPUT!$C$6/(100+INPUT!$C$6)+(AO17+AO18)*INPUT!$C$6/(100+INPUT!$C$6)+(AP17+AP18)*INPUT!$C$6/(100+INPUT!$C$6)+(AQ17+AQ18)*INPUT!$C$6/(100+INPUT!$C$6)+(AR17+AR18)*INPUT!$C$6/(100+INPUT!$C$6)+(AS17+AS18)*INPUT!$C$6/(100+INPUT!$C$6)+(AT17+AT18)*INPUT!$C$6/(100+INPUT!$C$6)+(AU17+AU18)*INPUT!$C$6/(100+INPUT!$C$6)+(AV17+AV18)*INPUT!$C$6/(100+INPUT!$C$6)+(AW17+AW18)*INPUT!$C$6/(100+INPUT!$C$6)+(AX17+AX18)*INPUT!$C$6/(100+INPUT!$C$6)+(AY17+AY18)*INPUT!$C$6/(100+INPUT!$C$6)+(AZ17+AZ18)*INPUT!$C$6/(100+INPUT!$C$6)+(BA17+BA18)*INPUT!$C$6/(100+INPUT!$C$6)+(BB17+BB18)*INPUT!$C$6/(100+INPUT!$C$6)+(BC17+BC18)*INPUT!$C$6/(100+INPUT!$C$6)+(BD17+BD18)*INPUT!$C$6/(100+INPUT!$C$6)+(BE17+BE18)*INPUT!$C$6/(100+INPUT!$C$6)+(BF17+BF18)*INPUT!$C$6/(100+INPUT!$C$6))-SUM(D19:BE19),0) -> 0 | BG19: =MAX((IF($C$136>0,$C$137*D11/$C$136,0)+IF($C$136>0,$C$137*E11/$C$136,0)+IF($C$136>0,$C$137*F11/$C$136,0)+IF($C$136>0,$C$137*G11/$C$136,0)+IF($C$136>0,$C$137*H11/$C$136,0)+IF($C$136>0,$C$137*I11/$C$136,0)+IF($C$136>0,$C$137*J11/$C$136,0)+IF($C$136>0,$C$137*K11/$C$136,0)+IF($C$136>0,$C$137*L11/$C$136,0)+IF($C$136>0,$C$137*M11/$C$136,0)+IF($C$136>0,$C$137*N11/$C$136,0)+IF($C$136>0,$C$137*O11/$C$136,0)+IF($C$136>0,$C$137*P11/$C$136,0)+IF($C$136>0,$C$137*Q11/$C$136,0)+IF($C$136>0,$C$137*R11/$C$136,0)+IF($C$136>0,$C$137*S11/$C$136,0)+IF($C$136>0,$C$137*T11/$C$136,0)+IF($C$136>0,$C$137*U11/$C$136,0)+IF($C$136>0,$C$137*V11/$C$136,0)+IF($C$136>0,$C$137*W11/$C$136,0)+IF($C$136>0,$C$137*X11/$C$136,0)+IF($C$136>0,$C$137*Y11/$C$136,0)+IF($C$136>0,$C$137*Z11/$C$136,0)+IF($C$136>0,$C$137*AA11/$C$136,0)+IF($C$136>0,$C$137*AB11/$C$136,0)+IF($C$136>0,$C$137*AC11/$C$136,0)+IF($C$136>0,$C$137*AD11/$C$136,0)+IF($C$136>0,$C$137*AE11/$C$136,0)+IF($C$136>0,$C$137*AF11/$C$136,0)+IF($C$136>0,$C$137*AG11/$C$136,0)+IF($C$136>0,$C$137*AH11/$C$136,0)+IF($C$136>0,$C$137*AI11/$C$136,0)+IF($C$136>0,$C$137*AJ11/$C$136,0)+IF($C$136>0,$C$137*AK11/$C$136,0)+IF($C$136>0,$C$137*AL11/$C$136,0)+IF($C$136>0,$C$137*AM11/$C$136,0)+IF($C$136>0,$C$137*AN11/$C$136,0)+IF($C$136>0,$C$137*AO11/$C$136,0)+IF($C$136>0,$C$137*AP11/$C$136,0)+IF($C$136>0,$C$137*AQ11/$C$136,0)+IF($C$136>0,$C$137*AR11/$C$136,0)+IF($C$136>0,$C$137*AS11/$C$136,0)+IF($C$136>0,$C$137*AT11/$C$136,0)+IF($C$136>0,$C$137*AU11/$C$136,0)+IF($C$136>0,$C$137*AV11/$C$136,0)+IF($C$136>0,$C$137*AW11/$C$136,0)+IF($C$136>0,$C$137*AX11/$C$136,0)+IF($C$136>0,$C$137*AY11/$C$136,0)+IF($C$136>0,$C$137*AZ11/$C$136,0)+IF($C$136>0,$C$137*BA11/$C$136,0)+IF($C$136>0,$C$137*BB11/$C$136,0)+IF($C$136>0,$C$137*BC11/$C$136,0)+IF($C$136>0,$C$137*BD11/$C$136,0)+IF($C$136>0,$C$137*BE11/$C$136,0)+IF($C$136>0,$C$137*BF11/$C$136,0)+IF($C$136>0,$C$137*BG11/$C$136,0))-((D17+D18)*INPUT!$C$6/(100+INPUT!$C$6)+(E17+E18)*INPUT!$C$6/(100+INPUT!$C$6)+(F17+F18)*INPUT!$C$6/(100+INPUT!$C$6)+(G17+G18)*INPUT!$C$6/(100+INPUT!$C$6)+(H17+H18)*INPUT!$C$6/(100+INPUT!$C$6)+(I17+I18)*INPUT!$C$6/(100+INPUT!$C$6)+(J17+J18)*INPUT!$C$6/(100+INPUT!$C$6)+(K17+K18)*INPUT!$C$6/(100+INPUT!$C$6)+(L17+L18)*INPUT!$C$6/(100+INPUT!$C$6)+(M17+M18)*INPUT!$C$6/(100+INPUT!$C$6)+(N17+N18)*INPUT!$C$6/(100+INPUT!$C$6)+(O17+O18)*INPUT!$C$6/(100+INPUT!$C$6)+(P17+P18)*INPUT!$C$6/(100+INPUT!$C$6)+(Q17+Q18)*INPUT!$C$6/(100+INPUT!$C$6)+(R17+R18)*INPUT!$C$6/(100+INPUT!$C$6)+(S17+S18)*INPUT!$C$6/(100+INPUT!$C$6)+(T17+T18)*INPUT!$C$6/(100+INPUT!$C$6)+(U17+U18)*INPUT!$C$6/(100+INPUT!$C$6)+(V17+V18)*INPUT!$C$6/(100+INPUT!$C$6)+(W17+W18)*INPUT!$C$6/(100+INPUT!$C$6)+(X17+X18)*INPUT!$C$6/(100+INPUT!$C$6)+(Y17+Y18)*INPUT!$C$6/(100+INPUT!$C$6)+(Z17+Z18)*INPUT!$C$6/(100+INPUT!$C$6)+(AA17+AA18)*INPUT!$C$6/(100+INPUT!$C$6)+(AB17+AB18)*INPUT!$C$6/(100+INPUT!$C$6)+(AC17+AC18)*INPUT!$C$6/(100+INPUT!$C$6)+(AD17+AD18)*INPUT!$C$6/(100+INPUT!$C$6)+(AE17+AE18)*INPUT!$C$6/(100+INPUT!$C$6)+(AF17+AF18)*INPUT!$C$6/(100+INPUT!$C$6)+(AG17+AG18)*INPUT!$C$6/(100+INPUT!$C$6)+(AH17+AH18)*INPUT!$C$6/(100+INPUT!$C$6)+(AI17+AI18)*INPUT!$C$6/(100+INPUT!$C$6)+(AJ17+AJ18)*INPUT!$C$6/(100+INPUT!$C$6)+(AK17+AK18)*INPUT!$C$6/(100+INPUT!$C$6)+(AL17+AL18)*INPUT!$C$6/(100+INPUT!$C$6)+(AM17+AM18)*INPUT!$C$6/(100+INPUT!$C$6)+(AN17+AN18)*INPUT!$C$6/(100+INPUT!$C$6)+(AO17+AO18)*INPUT!$C$6/(100+INPUT!$C$6)+(AP17+AP18)*INPUT!$C$6/(100+INPUT!$C$6)+(AQ17+AQ18)*INPUT!$C$6/(100+INPUT!$C$6)+(AR17+AR18)*INPUT!$C$6/(100+INPUT!$C$6)+(AS17+AS18)*INPUT!$C$6/(100+INPUT!$C$6)+(AT17+AT18)*INPUT!$C$6/(100+INPUT!$C$6)+(AU17+AU18)*INPUT!$C$6/(100+INPUT!$C$6)+(AV17+AV18)*INPUT!$C$6/(100+INPUT!$C$6)+(AW17+AW18)*INPUT!$C$6/(100+INPUT!$C$6)+(AX17+AX18)*INPUT!$C$6/(100+INPUT!$C$6)+(AY17+AY18)*INPUT!$C$6/(100+INPUT!$C$6)+(AZ17+AZ18)*INPUT!$C$6/(100+INPUT!$C$6)+(BA17+BA18)*INPUT!$C$6/(100+INPUT!$C$6)+(BB17+BB18)*INPUT!$C$6/(100+INPUT!$C$6)+(BC17+BC18)*INPUT!$C$6/(100+INPUT!$C$6)+(BD17+BD18)*INPUT!$C$6/(100+INPUT!$C$6)+(BE17+BE18)*INPUT!$C$6/(100+INPUT!$C$6)+(BF17+BF18)*INPUT!$C$6/(100+INPUT!$C$6)+(BG17+BG18)*INPUT!$C$6/(100+INPUT!$C$6))-SUM(D19:BF19),0) -> 0 | BH19: =MAX((IF($C$136>0,$C$137*D11/$C$136,0)+IF($C$136>0,$C$137*E11/$C$136,0)+IF($C$136>0,$C$137*F11/$C$136,0)+IF($C$136>0,$C$137*G11/$C$136,0)+IF($C$136>0,$C$137*H11/$C$136,0)+IF($C$136>0,$C$137*I11/$C$136,0)+IF($C$136>0,$C$137*J11/$C$136,0)+IF($C$136>0,$C$137*K11/$C$136,0)+IF($C$136>0,$C$137*L11/$C$136,0)+IF($C$136>0,$C$137*M11/$C$136,0)+IF($C$136>0,$C$137*N11/$C$136,0)+IF($C$136>0,$C$137*O11/$C$136,0)+IF($C$136>0,$C$137*P11/$C$136,0)+IF($C$136>0,$C$137*Q11/$C$136,0)+IF($C$136>0,$C$137*R11/$C$136,0)+IF($C$136>0,$C$137*S11/$C$136,0)+IF($C$136>0,$C$137*T11/$C$136,0)+IF($C$136>0,$C$137*U11/$C$136,0)+IF($C$136>0,$C$137*V11/$C$136,0)+IF($C$136>0,$C$137*W11/$C$136,0)+IF($C$136>0,$C$137*X11/$C$136,0)+IF($C$136>0,$C$137*Y11/$C$136,0)+IF($C$136>0,$C$137*Z11/$C$136,0)+IF($C$136>0,$C$137*AA11/$C$136,0)+IF($C$136>0,$C$137*AB11/$C$136,0)+IF($C$136>0,$C$137*AC11/$C$136,0)+IF($C$136>0,$C$137*AD11/$C$136,0)+IF($C$136>0,$C$137*AE11/$C$136,0)+IF($C$136>0,$C$137*AF11/$C$136,0)+IF($C$136>0,$C$137*AG11/$C$136,0)+IF($C$136>0,$C$137*AH11/$C$136,0)+IF($C$136>0,$C$137*AI11/$C$136,0)+IF($C$136>0,$C$137*AJ11/$C$136,0)+IF($C$136>0,$C$137*AK11/$C$136,0)+IF($C$136>0,$C$137*AL11/$C$136,0)+IF($C$136>0,$C$137*AM11/$C$136,0)+IF($C$136>0,$C$137*AN11/$C$136,0)+IF($C$136>0,$C$137*AO11/$C$136,0)+IF($C$136>0,$C$137*AP11/$C$136,0)+IF($C$136>0,$C$137*AQ11/$C$136,0)+IF($C$136>0,$C$137*AR11/$C$136,0)+IF($C$136>0,$C$137*AS11/$C$136,0)+IF($C$136>0,$C$137*AT11/$C$136,0)+IF($C$136>0,$C$137*AU11/$C$136,0)+IF($C$136>0,$C$137*AV11/$C$136,0)+IF($C$136>0,$C$137*AW11/$C$136,0)+IF($C$136>0,$C$137*AX11/$C$136,0)+IF($C$136>0,$C$137*AY11/$C$136,0)+IF($C$136>0,$C$137*AZ11/$C$136,0)+IF($C$136>0,$C$137*BA11/$C$136,0)+IF($C$136>0,$C$137*BB11/$C$136,0)+IF($C$136>0,$C$137*BC11/$C$136,0)+IF($C$136>0,$C$137*BD11/$C$136,0)+IF($C$136>0,$C$137*BE11/$C$136,0)+IF($C$136>0,$C$137*BF11/$C$136,0)+IF($C$136>0,$C$137*BG11/$C$136,0)+IF($C$136>0,$C$137*BH11/$C$136,0))-((D17+D18)*INPUT!$C$6/(100+INPUT!$C$6)+(E17+E18)*INPUT!$C$6/(100+INPUT!$C$6)+(F17+F18)*INPUT!$C$6/(100+INPUT!$C$6)+(G17+G18)*INPUT!$C$6/(100+INPUT!$C$6)+(H17+H18)*INPUT!$C$6/(100+INPUT!$C$6)+(I17+I18)*INPUT!$C$6/(100+INPUT!$C$6)+(J17+J18)*INPUT!$C$6/(100+INPUT!$C$6)+(K17+K18)*INPUT!$C$6/(100+INPUT!$C$6)+(L17+L18)*INPUT!$C$6/(100+INPUT!$C$6)+(M17+M18)*INPUT!$C$6/(100+INPUT!$C$6)+(N17+N18)*INPUT!$C$6/(100+INPUT!$C$6)+(O17+O18)*INPUT!$C$6/(100+INPUT!$C$6)+(P17+P18)*INPUT!$C$6/(100+INPUT!$C$6)+(Q17+Q18)*INPUT!$C$6/(100+INPUT!$C$6)+(R17+R18)*INPUT!$C$6/(100+INPUT!$C$6)+(S17+S18)*INPUT!$C$6/(100+INPUT!$C$6)+(T17+T18)*INPUT!$C$6/(100+INPUT!$C$6)+(U17+U18)*INPUT!$C$6/(100+INPUT!$C$6)+(V17+V18)*INPUT!$C$6/(100+INPUT!$C$6)+(W17+W18)*INPUT!$C$6/(100+INPUT!$C$6)+(X17+X18)*INPUT!$C$6/(100+INPUT!$C$6)+(Y17+Y18)*INPUT!$C$6/(100+INPUT!$C$6)+(Z17+Z18)*INPUT!$C$6/(100+INPUT!$C$6)+(AA17+AA18)*INPUT!$C$6/(100+INPUT!$C$6)+(AB17+AB18)*INPUT!$C$6/(100+INPUT!$C$6)+(AC17+AC18)*INPUT!$C$6/(100+INPUT!$C$6)+(AD17+AD18)*INPUT!$C$6/(100+INPUT!$C$6)+(AE17+AE18)*INPUT!$C$6/(100+INPUT!$C$6)+(AF17+AF18)*INPUT!$C$6/(100+INPUT!$C$6)+(AG17+AG18)*INPUT!$C$6/(100+INPUT!$C$6)+(AH17+AH18)*INPUT!$C$6/(100+INPUT!$C$6)+(AI17+AI18)*INPUT!$C$6/(100+INPUT!$C$6)+(AJ17+AJ18)*INPUT!$C$6/(100+INPUT!$C$6)+(AK17+AK18)*INPUT!$C$6/(100+INPUT!$C$6)+(AL17+AL18)*INPUT!$C$6/(100+INPUT!$C$6)+(AM17+AM18)*INPUT!$C$6/(100+INPUT!$C$6)+(AN17+AN18)*INPUT!$C$6/(100+INPUT!$C$6)+(AO17+AO18)*INPUT!$C$6/(100+INPUT!$C$6)+(AP17+AP18)*INPUT!$C$6/(100+INPUT!$C$6)+(AQ17+AQ18)*INPUT!$C$6/(100+INPUT!$C$6)+(AR17+AR18)*INPUT!$C$6/(100+INPUT!$C$6)+(AS17+AS18)*INPUT!$C$6/(100+INPUT!$C$6)+(AT17+AT18)*INPUT!$C$6/(100+INPUT!$C$6)+(AU17+AU18)*INPUT!$C$6/(100+INPUT!$C$6)+(AV17+AV18)*INPUT!$C$6/(100+INPUT!$C$6)+(AW17+AW18)*INPUT!$C$6/(100+INPUT!$C$6)+(AX17+AX18)*INPUT!$C$6/(100+INPUT!$C$6)+(AY17+AY18)*INPUT!$C$6/(100+INPUT!$C$6)+(AZ17+AZ18)*INPUT!$C$6/(100+INPUT!$C$6)+(BA17+BA18)*INPUT!$C$6/(100+INPUT!$C$6)+(BB17+BB18)*INPUT!$C$6/(100+INPUT!$C$6)+(BC17+BC18)*INPUT!$C$6/(100+INPUT!$C$6)+(BD17+BD18)*INPUT!$C$6/(100+INPUT!$C$6)+(BE17+BE18)*INPUT!$C$6/(100+INPUT!$C$6)+(BF17+BF18)*INPUT!$C$6/(100+INPUT!$C$6)+(BG17+BG18)*INPUT!$C$6/(100+INPUT!$C$6)+(BH17+BH18)*INPUT!$C$6/(100+INPUT!$C$6))-SUM(D19:BG19),0) -> 0 | BI19: =MAX((IF($C$136>0,$C$137*D11/$C$136,0)+IF($C$136>0,$C$137*E11/$C$136,0)+IF($C$136>0,$C$137*F11/$C$136,0)+IF($C$136>0,$C$137*G11/$C$136,0)+IF($C$136>0,$C$137*H11/$C$136,0)+IF($C$136>0,$C$137*I11/$C$136,0)+IF($C$136>0,$C$137*J11/$C$136,0)+IF($C$136>0,$C$137*K11/$C$136,0)+IF($C$136>0,$C$137*L11/$C$136,0)+IF($C$136>0,$C$137*M11/$C$136,0)+IF($C$136>0,$C$137*N11/$C$136,0)+IF($C$136>0,$C$137*O11/$C$136,0)+IF($C$136>0,$C$137*P11/$C$136,0)+IF($C$136>0,$C$137*Q11/$C$136,0)+IF($C$136>0,$C$137*R11/$C$136,0)+IF($C$136>0,$C$137*S11/$C$136,0)+IF($C$136>0,$C$137*T11/$C$136,0)+IF($C$136>0,$C$137*U11/$C$136,0)+IF($C$136>0,$C$137*V11/$C$136,0)+IF($C$136>0,$C$137*W11/$C$136,0)+IF($C$136>0,$C$137*X11/$C$136,0)+IF($C$136>0,$C$137*Y11/$C$136,0)+IF($C$136>0,$C$137*Z11/$C$136,0)+IF($C$136>0,$C$137*AA11/$C$136,0)+IF($C$136>0,$C$137*AB11/$C$136,0)+IF($C$136>0,$C$137*AC11/$C$136,0)+IF($C$136>0,$C$137*AD11/$C$136,0)+IF($C$136>0,$C$137*AE11/$C$136,0)+IF($C$136>0,$C$137*AF11/$C$136,0)+IF($C$136>0,$C$137*AG11/$C$136,0)+IF($C$136>0,$C$137*AH11/$C$136,0)+IF($C$136>0,$C$137*AI11/$C$136,0)+IF($C$136>0,$C$137*AJ11/$C$136,0)+IF($C$136>0,$C$137*AK11/$C$136,0)+IF($C$136>0,$C$137*AL11/$C$136,0)+IF($C$136>0,$C$137*AM11/$C$136,0)+IF($C$136>0,$C$137*AN11/$C$136,0)+IF($C$136>0,$C$137*AO11/$C$136,0)+IF($C$136>0,$C$137*AP11/$C$136,0)+IF($C$136>0,$C$137*AQ11/$C$136,0)+IF($C$136>0,$C$137*AR11/$C$136,0)+IF($C$136>0,$C$137*AS11/$C$136,0)+IF($C$136>0,$C$137*AT11/$C$136,0)+IF($C$136>0,$C$137*AU11/$C$136,0)+IF($C$136>0,$C$137*AV11/$C$136,0)+IF($C$136>0,$C$137*AW11/$C$136,0)+IF($C$136>0,$C$137*AX11/$C$136,0)+IF($C$136>0,$C$137*AY11/$C$136,0)+IF($C$136>0,$C$137*AZ11/$C$136,0)+IF($C$136>0,$C$137*BA11/$C$136,0)+IF($C$136>0,$C$137*BB11/$C$136,0)+IF($C$136>0,$C$137*BC11/$C$136,0)+IF($C$136>0,$C$137*BD11/$C$136,0)+IF($C$136>0,$C$137*BE11/$C$136,0)+IF($C$136>0,$C$137*BF11/$C$136,0)+IF($C$136>0,$C$137*BG11/$C$136,0)+IF($C$136>0,$C$137*BH11/$C$136,0)+IF($C$136>0,$C$137*BI11/$C$136,0))-((D17+D18)*INPUT!$C$6/(100+INPUT!$C$6)+(E17+E18)*INPUT!$C$6/(100+INPUT!$C$6)+(F17+F18)*INPUT!$C$6/(100+INPUT!$C$6)+(G17+G18)*INPUT!$C$6/(100+INPUT!$C$6)+(H17+H18)*INPUT!$C$6/(100+INPUT!$C$6)+(I17+I18)*INPUT!$C$6/(100+INPUT!$C$6)+(J17+J18)*INPUT!$C$6/(100+INPUT!$C$6)+(K17+K18)*INPUT!$C$6/(100+INPUT!$C$6)+(L17+L18)*INPUT!$C$6/(100+INPUT!$C$6)+(M17+M18)*INPUT!$C$6/(100+INPUT!$C$6)+(N17+N18)*INPUT!$C$6/(100+INPUT!$C$6)+(O17+O18)*INPUT!$C$6/(100+INPUT!$C$6)+(P17+P18)*INPUT!$C$6/(100+INPUT!$C$6)+(Q17+Q18)*INPUT!$C$6/(100+INPUT!$C$6)+(R17+R18)*INPUT!$C$6/(100+INPUT!$C$6)+(S17+S18)*INPUT!$C$6/(100+INPUT!$C$6)+(T17+T18)*INPUT!$C$6/(100+INPUT!$C$6)+(U17+U18)*INPUT!$C$6/(100+INPUT!$C$6)+(V17+V18)*INPUT!$C$6/(100+INPUT!$C$6)+(W17+W18)*INPUT!$C$6/(100+INPUT!$C$6)+(X17+X18)*INPUT!$C$6/(100+INPUT!$C$6)+(Y17+Y18)*INPUT!$C$6/(100+INPUT!$C$6)+(Z17+Z18)*INPUT!$C$6/(100+INPUT!$C$6)+(AA17+AA18)*INPUT!$C$6/(100+INPUT!$C$6)+(AB17+AB18)*INPUT!$C$6/(100+INPUT!$C$6)+(AC17+AC18)*INPUT!$C$6/(100+INPUT!$C$6)+(AD17+AD18)*INPUT!$C$6/(100+INPUT!$C$6)+(AE17+AE18)*INPUT!$C$6/(100+INPUT!$C$6)+(AF17+AF18)*INPUT!$C$6/(100+INPUT!$C$6)+(AG17+AG18)*INPUT!$C$6/(100+INPUT!$C$6)+(AH17+AH18)*INPUT!$C$6/(100+INPUT!$C$6)+(AI17+AI18)*INPUT!$C$6/(100+INPUT!$C$6)+(AJ17+AJ18)*INPUT!$C$6/(100+INPUT!$C$6)+(AK17+AK18)*INPUT!$C$6/(100+INPUT!$C$6)+(AL17+AL18)*INPUT!$C$6/(100+INPUT!$C$6)+(AM17+AM18)*INPUT!$C$6/(100+INPUT!$C$6)+(AN17+AN18)*INPUT!$C$6/(100+INPUT!$C$6)+(AO17+AO18)*INPUT!$C$6/(100+INPUT!$C$6)+(AP17+AP18)*INPUT!$C$6/(100+INPUT!$C$6)+(AQ17+AQ18)*INPUT!$C$6/(100+INPUT!$C$6)+(AR17+AR18)*INPUT!$C$6/(100+INPUT!$C$6)+(AS17+AS18)*INPUT!$C$6/(100+INPUT!$C$6)+(AT17+AT18)*INPUT!$C$6/(100+INPUT!$C$6)+(AU17+AU18)*INPUT!$C$6/(100+INPUT!$C$6)+(AV17+AV18)*INPUT!$C$6/(100+INPUT!$C$6)+(AW17+AW18)*INPUT!$C$6/(100+INPUT!$C$6)+(AX17+AX18)*INPUT!$C$6/(100+INPUT!$C$6)+(AY17+AY18)*INPUT!$C$6/(100+INPUT!$C$6)+(AZ17+AZ18)*INPUT!$C$6/(100+INPUT!$C$6)+(BA17+BA18)*INPUT!$C$6/(100+INPUT!$C$6)+(BB17+BB18)*INPUT!$C$6/(100+INPUT!$C$6)+(BC17+BC18)*INPUT!$C$6/(100+INPUT!$C$6)+(BD17+BD18)*INPUT!$C$6/(100+INPUT!$C$6)+(BE17+BE18)*INPUT!$C$6/(100+INPUT!$C$6)+(BF17+BF18)*INPUT!$C$6/(100+INPUT!$C$6)+(BG17+BG18)*INPUT!$C$6/(100+INPUT!$C$6)+(BH17+BH18)*INPUT!$C$6/(100+INPUT!$C$6)+(BI17+BI18)*INPUT!$C$6/(100+INPUT!$C$6))-SUM(D19:BH19),0) -> 0 | BJ19: =MAX((IF($C$136>0,$C$137*D11/$C$136,0)+IF($C$136>0,$C$137*E11/$C$136,0)+IF($C$136>0,$C$137*F11/$C$136,0)+IF($C$136>0,$C$137*G11/$C$136,0)+IF($C$136>0,$C$137*H11/$C$136,0)+IF($C$136>0,$C$137*I11/$C$136,0)+IF($C$136>0,$C$137*J11/$C$136,0)+IF($C$136>0,$C$137*K11/$C$136,0)+IF($C$136>0,$C$137*L11/$C$136,0)+IF($C$136>0,$C$137*M11/$C$136,0)+IF($C$136>0,$C$137*N11/$C$136,0)+IF($C$136>0,$C$137*O11/$C$136,0)+IF($C$136>0,$C$137*P11/$C$136,0)+IF($C$136>0,$C$137*Q11/$C$136,0)+IF($C$136>0,$C$137*R11/$C$136,0)+IF($C$136>0,$C$137*S11/$C$136,0)+IF($C$136>0,$C$137*T11/$C$136,0)+IF($C$136>0,$C$137*U11/$C$136,0)+IF($C$136>0,$C$137*V11/$C$136,0)+IF($C$136>0,$C$137*W11/$C$136,0)+IF($C$136>0,$C$137*X11/$C$136,0)+IF($C$136>0,$C$137*Y11/$C$136,0)+IF($C$136>0,$C$137*Z11/$C$136,0)+IF($C$136>0,$C$137*AA11/$C$136,0)+IF($C$136>0,$C$137*AB11/$C$136,0)+IF($C$136>0,$C$137*AC11/$C$136,0)+IF($C$136>0,$C$137*AD11/$C$136,0)+IF($C$136>0,$C$137*AE11/$C$136,0)+IF($C$136>0,$C$137*AF11/$C$136,0)+IF($C$136>0,$C$137*AG11/$C$136,0)+IF($C$136>0,$C$137*AH11/$C$136,0)+IF($C$136>0,$C$137*AI11/$C$136,0)+IF($C$136>0,$C$137*AJ11/$C$136,0)+IF($C$136>0,$C$137*AK11/$C$136,0)+IF($C$136>0,$C$137*AL11/$C$136,0)+IF($C$136>0,$C$137*AM11/$C$136,0)+IF($C$136>0,$C$137*AN11/$C$136,0)+IF($C$136>0,$C$137*AO11/$C$136,0)+IF($C$136>0,$C$137*AP11/$C$136,0)+IF($C$136>0,$C$137*AQ11/$C$136,0)+IF($C$136>0,$C$137*AR11/$C$136,0)+IF($C$136>0,$C$137*AS11/$C$136,0)+IF($C$136>0,$C$137*AT11/$C$136,0)+IF($C$136>0,$C$137*AU11/$C$136,0)+IF($C$136>0,$C$137*AV11/$C$136,0)+IF($C$136>0,$C$137*AW11/$C$136,0)+IF($C$136>0,$C$137*AX11/$C$136,0)+IF($C$136>0,$C$137*AY11/$C$136,0)+IF($C$136>0,$C$137*AZ11/$C$136,0)+IF($C$136>0,$C$137*BA11/$C$136,0)+IF($C$136>0,$C$137*BB11/$C$136,0)+IF($C$136>0,$C$137*BC11/$C$136,0)+IF($C$136>0,$C$137*BD11/$C$136,0)+IF($C$136>0,$C$137*BE11/$C$136,0)+IF($C$136>0,$C$137*BF11/$C$136,0)+IF($C$136>0,$C$137*BG11/$C$136,0)+IF($C$136>0,$C$137*BH11/$C$136,0)+IF($C$136>0,$C$137*BI11/$C$136,0)+IF($C$136>0,$C$137*BJ11/$C$136,0))-((D17+D18)*INPUT!$C$6/(100+INPUT!$C$6)+(E17+E18)*INPUT!$C$6/(100+INPUT!$C$6)+(F17+F18)*INPUT!$C$6/(100+INPUT!$C$6)+(G17+G18)*INPUT!$C$6/(100+INPUT!$C$6)+(H17+H18)*INPUT!$C$6/(100+INPUT!$C$6)+(I17+I18)*INPUT!$C$6/(100+INPUT!$C$6)+(J17+J18)*INPUT!$C$6/(100+INPUT!$C$6)+(K17+K18)*INPUT!$C$6/(100+INPUT!$C$6)+(L17+L18)*INPUT!$C$6/(100+INPUT!$C$6)+(M17+M18)*INPUT!$C$6/(100+INPUT!$C$6)+(N17+N18)*INPUT!$C$6/(100+INPUT!$C$6)+(O17+O18)*INPUT!$C$6/(100+INPUT!$C$6)+(P17+P18)*INPUT!$C$6/(100+INPUT!$C$6)+(Q17+Q18)*INPUT!$C$6/(100+INPUT!$C$6)+(R17+R18)*INPUT!$C$6/(100+INPUT!$C$6)+(S17+S18)*INPUT!$C$6/(100+INPUT!$C$6)+(T17+T18)*INPUT!$C$6/(100+INPUT!$C$6)+(U17+U18)*INPUT!$C$6/(100+INPUT!$C$6)+(V17+V18)*INPUT!$C$6/(100+INPUT!$C$6)+(W17+W18)*INPUT!$C$6/(100+INPUT!$C$6)+(X17+X18)*INPUT!$C$6/(100+INPUT!$C$6)+(Y17+Y18)*INPUT!$C$6/(100+INPUT!$C$6)+(Z17+Z18)*INPUT!$C$6/(100+INPUT!$C$6)+(AA17+AA18)*INPUT!$C$6/(100+INPUT!$C$6)+(AB17+AB18)*INPUT!$C$6/(100+INPUT!$C$6)+(AC17+AC18)*INPUT!$C$6/(100+INPUT!$C$6)+(AD17+AD18)*INPUT!$C$6/(100+INPUT!$C$6)+(AE17+AE18)*INPUT!$C$6/(100+INPUT!$C$6)+(AF17+AF18)*INPUT!$C$6/(100+INPUT!$C$6)+(AG17+AG18)*INPUT!$C$6/(100+INPUT!$C$6)+(AH17+AH18)*INPUT!$C$6/(100+INPUT!$C$6)+(AI17+AI18)*INPUT!$C$6/(100+INPUT!$C$6)+(AJ17+AJ18)*INPUT!$C$6/(100+INPUT!$C$6)+(AK17+AK18)*INPUT!$C$6/(100+INPUT!$C$6)+(AL17+AL18)*INPUT!$C$6/(100+INPUT!$C$6)+(AM17+AM18)*INPUT!$C$6/(100+INPUT!$C$6)+(AN17+AN18)*INPUT!$C$6/(100+INPUT!$C$6)+(AO17+AO18)*INPUT!$C$6/(100+INPUT!$C$6)+(AP17+AP18)*INPUT!$C$6/(100+INPUT!$C$6)+(AQ17+AQ18)*INPUT!$C$6/(100+INPUT!$C$6)+(AR17+AR18)*INPUT!$C$6/(100+INPUT!$C$6)+(AS17+AS18)*INPUT!$C$6/(100+INPUT!$C$6)+(AT17+AT18)*INPUT!$C$6/(100+INPUT!$C$6)+(AU17+AU18)*INPUT!$C$6/(100+INPUT!$C$6)+(AV17+AV18)*INPUT!$C$6/(100+INPUT!$C$6)+(AW17+AW18)*INPUT!$C$6/(100+INPUT!$C$6)+(AX17+AX18)*INPUT!$C$6/(100+INPUT!$C$6)+(AY17+AY18)*INPUT!$C$6/(100+INPUT!$C$6)+(AZ17+AZ18)*INPUT!$C$6/(100+INPUT!$C$6)+(BA17+BA18)*INPUT!$C$6/(100+INPUT!$C$6)+(BB17+BB18)*INPUT!$C$6/(100+INPUT!$C$6)+(BC17+BC18)*INPUT!$C$6/(100+INPUT!$C$6)+(BD17+BD18)*INPUT!$C$6/(100+INPUT!$C$6)+(BE17+BE18)*INPUT!$C$6/(100+INPUT!$C$6)+(BF17+BF18)*INPUT!$C$6/(100+INPUT!$C$6)+(BG17+BG18)*INPUT!$C$6/(100+INPUT!$C$6)+(BH17+BH18)*INPUT!$C$6/(100+INPUT!$C$6)+(BI17+BI18)*INPUT!$C$6/(100+INPUT!$C$6)+(BJ17+BJ18)*INPUT!$C$6/(100+INPUT!$C$6))-SUM(D19:BI19),0) -> 0 | BK19: =MAX((IF($C$136>0,$C$137*D11/$C$136,0)+IF($C$136>0,$C$137*E11/$C$136,0)+IF($C$136>0,$C$137*F11/$C$136,0)+IF($C$136>0,$C$137*G11/$C$136,0)+IF($C$136>0,$C$137*H11/$C$136,0)+IF($C$136>0,$C$137*I11/$C$136,0)+IF($C$136>0,$C$137*J11/$C$136,0)+IF($C$136>0,$C$137*K11/$C$136,0)+IF($C$136>0,$C$137*L11/$C$136,0)+IF($C$136>0,$C$137*M11/$C$136,0)+IF($C$136>0,$C$137*N11/$C$136,0)+IF($C$136>0,$C$137*O11/$C$136,0)+IF($C$136>0,$C$137*P11/$C$136,0)+IF($C$136>0,$C$137*Q11/$C$136,0)+IF($C$136>0,$C$137*R11/$C$136,0)+IF($C$136>0,$C$137*S11/$C$136,0)+IF($C$136>0,$C$137*T11/$C$136,0)+IF($C$136>0,$C$137*U11/$C$136,0)+IF($C$136>0,$C$137*V11/$C$136,0)+IF($C$136>0,$C$137*W11/$C$136,0)+IF($C$136>0,$C$137*X11/$C$136,0)+IF($C$136>0,$C$137*Y11/$C$136,0)+IF($C$136>0,$C$137*Z11/$C$136,0)+IF($C$136>0,$C$137*AA11/$C$136,0)+IF($C$136>0,$C$137*AB11/$C$136,0)+IF($C$136>0,$C$137*AC11/$C$136,0)+IF($C$136>0,$C$137*AD11/$C$136,0)+IF($C$136>0,$C$137*AE11/$C$136,0)+IF($C$136>0,$C$137*AF11/$C$136,0)+IF($C$136>0,$C$137*AG11/$C$136,0)+IF($C$136>0,$C$137*AH11/$C$136,0)+IF($C$136>0,$C$137*AI11/$C$136,0)+IF($C$136>0,$C$137*AJ11/$C$136,0)+IF($C$136>0,$C$137*AK11/$C$136,0)+IF($C$136>0,$C$137*AL11/$C$136,0)+IF($C$136>0,$C$137*AM11/$C$136,0)+IF($C$136>0,$C$137*AN11/$C$136,0)+IF($C$136>0,$C$137*AO11/$C$136,0)+IF($C$136>0,$C$137*AP11/$C$136,0)+IF($C$136>0,$C$137*AQ11/$C$136,0)+IF($C$136>0,$C$137*AR11/$C$136,0)+IF($C$136>0,$C$137*AS11/$C$136,0)+IF($C$136>0,$C$137*AT11/$C$136,0)+IF($C$136>0,$C$137*AU11/$C$136,0)+IF($C$136>0,$C$137*AV11/$C$136,0)+IF($C$136>0,$C$137*AW11/$C$136,0)+IF($C$136>0,$C$137*AX11/$C$136,0)+IF($C$136>0,$C$137*AY11/$C$136,0)+IF($C$136>0,$C$137*AZ11/$C$136,0)+IF($C$136>0,$C$137*BA11/$C$136,0)+IF($C$136>0,$C$137*BB11/$C$136,0)+IF($C$136>0,$C$137*BC11/$C$136,0)+IF($C$136>0,$C$137*BD11/$C$136,0)+IF($C$136>0,$C$137*BE11/$C$136,0)+IF($C$136>0,$C$137*BF11/$C$136,0)+IF($C$136>0,$C$137*BG11/$C$136,0)+IF($C$136>0,$C$137*BH11/$C$136,0)+IF($C$136>0,$C$137*BI11/$C$136,0)+IF($C$136>0,$C$137*BJ11/$C$136,0)+IF($C$136>0,$C$137*BK11/$C$136,0))-((D17+D18)*INPUT!$C$6/(100+INPUT!$C$6)+(E17+E18)*INPUT!$C$6/(100+INPUT!$C$6)+(F17+F18)*INPUT!$C$6/(100+INPUT!$C$6)+(G17+G18)*INPUT!$C$6/(100+INPUT!$C$6)+(H17+H18)*INPUT!$C$6/(100+INPUT!$C$6)+(I17+I18)*INPUT!$C$6/(100+INPUT!$C$6)+(J17+J18)*INPUT!$C$6/(100+INPUT!$C$6)+(K17+K18)*INPUT!$C$6/(100+INPUT!$C$6)+(L17+L18)*INPUT!$C$6/(100+INPUT!$C$6)+(M17+M18)*INPUT!$C$6/(100+INPUT!$C$6)+(N17+N18)*INPUT!$C$6/(100+INPUT!$C$6)+(O17+O18)*INPUT!$C$6/(100+INPUT!$C$6)+(P17+P18)*INPUT!$C$6/(100+INPUT!$C$6)+(Q17+Q18)*INPUT!$C$6/(100+INPUT!$C$6)+(R17+R18)*INPUT!$C$6/(100+INPUT!$C$6)+(S17+S18)*INPUT!$C$6/(100+INPUT!$C$6)+(T17+T18)*INPUT!$C$6/(100+INPUT!$C$6)+(U17+U18)*INPUT!$C$6/(100+INPUT!$C$6)+(V17+V18)*INPUT!$C$6/(100+INPUT!$C$6)+(W17+W18)*INPUT!$C$6/(100+INPUT!$C$6)+(X17+X18)*INPUT!$C$6/(100+INPUT!$C$6)+(Y17+Y18)*INPUT!$C$6/(100+INPUT!$C$6)+(Z17+Z18)*INPUT!$C$6/(100+INPUT!$C$6)+(AA17+AA18)*INPUT!$C$6/(100+INPUT!$C$6)+(AB17+AB18)*INPUT!$C$6/(100+INPUT!$C$6)+(AC17+AC18)*INPUT!$C$6/(100+INPUT!$C$6)+(AD17+AD18)*INPUT!$C$6/(100+INPUT!$C$6)+(AE17+AE18)*INPUT!$C$6/(100+INPUT!$C$6)+(AF17+AF18)*INPUT!$C$6/(100+INPUT!$C$6)+(AG17+AG18)*INPUT!$C$6/(100+INPUT!$C$6)+(AH17+AH18)*INPUT!$C$6/(100+INPUT!$C$6)+(AI17+AI18)*INPUT!$C$6/(100+INPUT!$C$6)+(AJ17+AJ18)*INPUT!$C$6/(100+INPUT!$C$6)+(AK17+AK18)*INPUT!$C$6/(100+INPUT!$C$6)+(AL17+AL18)*INPUT!$C$6/(100+INPUT!$C$6)+(AM17+AM18)*INPUT!$C$6/(100+INPUT!$C$6)+(AN17+AN18)*INPUT!$C$6/(100+INPUT!$C$6)+(AO17+AO18)*INPUT!$C$6/(100+INPUT!$C$6)+(AP17+AP18)*INPUT!$C$6/(100+INPUT!$C$6)+(AQ17+AQ18)*INPUT!$C$6/(100+INPUT!$C$6)+(AR17+AR18)*INPUT!$C$6/(100+INPUT!$C$6)+(AS17+AS18)*INPUT!$C$6/(100+INPUT!$C$6)+(AT17+AT18)*INPUT!$C$6/(100+INPUT!$C$6)+(AU17+AU18)*INPUT!$C$6/(100+INPUT!$C$6)+(AV17+AV18)*INPUT!$C$6/(100+INPUT!$C$6)+(AW17+AW18)*INPUT!$C$6/(100+INPUT!$C$6)+(AX17+AX18)*INPUT!$C$6/(100+INPUT!$C$6)+(AY17+AY18)*INPUT!$C$6/(100+INPUT!$C$6)+(AZ17+AZ18)*INPUT!$C$6/(100+INPUT!$C$6)+(BA17+BA18)*INPUT!$C$6/(100+INPUT!$C$6)+(BB17+BB18)*INPUT!$C$6/(100+INPUT!$C$6)+(BC17+BC18)*INPUT!$C$6/(100+INPUT!$C$6)+(BD17+BD18)*INPUT!$C$6/(100+INPUT!$C$6)+(BE17+BE18)*INPUT!$C$6/(100+INPUT!$C$6)+(BF17+BF18)*INPUT!$C$6/(100+INPUT!$C$6)+(BG17+BG18)*INPUT!$C$6/(100+INPUT!$C$6)+(BH17+BH18)*INPUT!$C$6/(100+INPUT!$C$6)+(BI17+BI18)*INPUT!$C$6/(100+INPUT!$C$6)+(BJ17+BJ18)*INPUT!$C$6/(100+INPUT!$C$6)+(BK17+BK18)*INPUT!$C$6/(100+INPUT!$C$6))-SUM(D19:BJ19),0) -> 0
B20: (−) Capex Cho thuê (tổng) | C20: =SUM(D20:BK20) -> 0 | D20: =D21+D22+D23+D24 -> 0 | E20: =E21+E22+E23+E24 -> 0 | F20: =F21+F22+F23+F24 -> 0 | G20: =G21+G22+G23+G24 -> 0 | H20: =H21+H22+H23+H24 -> 0 | I20: =I21+I22+I23+I24 -> 0 | J20: =J21+J22+J23+J24 -> 0 | K20: =K21+K22+K23+K24 -> 0 | ... P20: =P21+P22+P23+P24 -> 0 | Q20: 0 | R20: 0 | S20: 0 | T20: 0 | U20: 0 | V20: 0 | W20: 0 | X20: 0 | Y20: 0 | Z20: 0 | AA20: 0 | AB20: 0 | AC20: 0 | AD20: 0 | AE20: 0 | AF20: 0 | AG20: 0 | AH20: 0 | AI20: 0 | AJ20: 0 | AK20: 0 | AL20: 0 | AM20: 0 | AN20: 0 | AO20: 0 | AP20: 0 | AQ20: 0 | AR20: 0 | AS20: 0 | AT20: 0 | AU20: 0 | AV20: 0 | AW20: 0 | AX20: 0 | AY20: 0 | AZ20: 0 | BA20: 0 | BB20: 0 | BC20: 0 | BD20: 0 | BE20: 0 | BF20: 0 | BG20: 0 | BH20: 0 | BI20: 0 | BJ20: 0 | BK20: 0
B21: ↳ Đất (chuyển nhượng + đền bù) | C21: =SUM(D21:BK21) -> 0 | D21: =$C$124*$C$106*TIENDO!C3/100+$C$125*$C$106*TIENDO!C4/100 -> 0 | E21: =$C$124*$C$106*TIENDO!D3/100+$C$125*$C$106*TIENDO!D4/100 -> 0 | F21: =$C$124*$C$106*TIENDO!E3/100+$C$125*$C$106*TIENDO!E4/100 -> 0 | G21: =$C$124*$C$106*TIENDO!F3/100+$C$125*$C$106*TIENDO!F4/100 -> 0 | H21: =$C$124*$C$106*TIENDO!G3/100+$C$125*$C$106*TIENDO!G4/100 -> 0 | I21: =$C$124*$C$106*TIENDO!H3/100+$C$125*$C$106*TIENDO!H4/100 -> 0 | J21: =$C$124*$C$106*TIENDO!I3/100+$C$125*$C$106*TIENDO!I4/100 -> 0 | K21: =$C$124*$C$106*TIENDO!J3/100+$C$125*$C$106*TIENDO!J4/100 -> 0 | ... P21: =$C$124*$C$106*TIENDO!O3/100+$C$125*$C$106*TIENDO!O4/100 -> 0 | Q21: 0 | R21: 0 | S21: 0 | T21: 0 | U21: 0 | V21: 0 | W21: 0 | X21: 0 | Y21: 0 | Z21: 0 | AA21: 0 | AB21: 0 | AC21: 0 | AD21: 0 | AE21: 0 | AF21: 0 | AG21: 0 | AH21: 0 | AI21: 0 | AJ21: 0 | AK21: 0 | AL21: 0 | AM21: 0 | AN21: 0 | AO21: 0 | AP21: 0 | AQ21: 0 | AR21: 0 | AS21: 0 | AT21: 0 | AU21: 0 | AV21: 0 | AW21: 0 | AX21: 0 | AY21: 0 | AZ21: 0 | BA21: 0 | BB21: 0 | BC21: 0 | BD21: 0 | BE21: 0 | BF21: 0 | BG21: 0 | BH21: 0 | BI21: 0 | BJ21: 0 | BK21: 0
B22: ↳ Tiền sử dụng đất | C22: =SUM(D22:BK22) -> 0 | D22: =$C$126*$C$106*TIENDO!C5/100 -> 0 | E22: =$C$126*$C$106*TIENDO!D5/100 -> 0 | F22: =$C$126*$C$106*TIENDO!E5/100 -> 0 | G22: =$C$126*$C$106*TIENDO!F5/100 -> 0 | H22: =$C$126*$C$106*TIENDO!G5/100 -> 0 | I22: =$C$126*$C$106*TIENDO!H5/100 -> 0 | J22: =$C$126*$C$106*TIENDO!I5/100 -> 0 | K22: =$C$126*$C$106*TIENDO!J5/100 -> 0 | ... P22: =$C$126*$C$106*TIENDO!O5/100 -> 0 | Q22: 0 | R22: 0 | S22: 0 | T22: 0 | U22: 0 | V22: 0 | W22: 0 | X22: 0 | Y22: 0 | Z22: 0 | AA22: 0 | AB22: 0 | AC22: 0 | AD22: 0 | AE22: 0 | AF22: 0 | AG22: 0 | AH22: 0 | AI22: 0 | AJ22: 0 | AK22: 0 | AL22: 0 | AM22: 0 | AN22: 0 | AO22: 0 | AP22: 0 | AQ22: 0 | AR22: 0 | AS22: 0 | AT22: 0 | AU22: 0 | AV22: 0 | AW22: 0 | AX22: 0 | AY22: 0 | AZ22: 0 | BA22: 0 | BB22: 0 | BC22: 0 | BD22: 0 | BE22: 0 | BF22: 0 | BG22: 0 | BH22: 0 | BI22: 0 | BJ22: 0 | BK22: 0
B23: ↳ Chi phí pháp lý | C23: =SUM(D23:BK23) -> 0 | D23: =$C$127*$C$106*TIENDO!C6/100 -> 0 | E23: =$C$127*$C$106*TIENDO!D6/100 -> 0 | F23: =$C$127*$C$106*TIENDO!E6/100 -> 0 | G23: =$C$127*$C$106*TIENDO!F6/100 -> 0 | H23: =$C$127*$C$106*TIENDO!G6/100 -> 0 | I23: =$C$127*$C$106*TIENDO!H6/100 -> 0 | J23: =$C$127*$C$106*TIENDO!I6/100 -> 0 | K23: =$C$127*$C$106*TIENDO!J6/100 -> 0 | ... P23: =$C$127*$C$106*TIENDO!O6/100 -> 0 | Q23: 0 | R23: 0 | S23: 0 | T23: 0 | U23: 0 | V23: 0 | W23: 0 | X23: 0 | Y23: 0 | Z23: 0 | AA23: 0 | AB23: 0 | AC23: 0 | AD23: 0 | AE23: 0 | AF23: 0 | AG23: 0 | AH23: 0 | AI23: 0 | AJ23: 0 | AK23: 0 | AL23: 0 | AM23: 0 | AN23: 0 | AO23: 0 | AP23: 0 | AQ23: 0 | AR23: 0 | AS23: 0 | AT23: 0 | AU23: 0 | AV23: 0 | AW23: 0 | AX23: 0 | AY23: 0 | AZ23: 0 | BA23: 0 | BB23: 0 | BC23: 0 | BD23: 0 | BE23: 0 | BF23: 0 | BG23: 0 | BH23: 0 | BI23: 0 | BJ23: 0 | BK23: 0
B24: ↳ CPXD all-in (hạ tầng+XD+tư vấn+dự phòng) | C24: =SUM(D24:BK24) -> 0 | D24: =($C$128*$C$106*TIENDO!C7/100+$C$130*1*TIENDO!C9/100+$C$131*$C$105*TIENDO!C10/100+$C$132*$C$105*TIENDO!C11/100)/(1+INPUT!$C$6/100) -> 0 | E24: =($C$128*$C$106*TIENDO!D7/100+$C$130*1*TIENDO!D9/100+$C$131*$C$105*TIENDO!D10/100+$C$132*$C$105*TIENDO!D11/100)/(1+INPUT!$C$6/100) -> 0 | F24: =($C$128*$C$106*TIENDO!E7/100+$C$130*1*TIENDO!E9/100+$C$131*$C$105*TIENDO!E10/100+$C$132*$C$105*TIENDO!E11/100)/(1+INPUT!$C$6/100) -> 0 | G24: =($C$128*$C$106*TIENDO!F7/100+$C$130*1*TIENDO!F9/100+$C$131*$C$105*TIENDO!F10/100+$C$132*$C$105*TIENDO!F11/100)/(1+INPUT!$C$6/100) -> 0 | H24: =($C$128*$C$106*TIENDO!G7/100+$C$130*1*TIENDO!G9/100+$C$131*$C$105*TIENDO!G10/100+$C$132*$C$105*TIENDO!G11/100)/(1+INPUT!$C$6/100) -> 0 | I24: =($C$128*$C$106*TIENDO!H7/100+$C$130*1*TIENDO!H9/100+$C$131*$C$105*TIENDO!H10/100+$C$132*$C$105*TIENDO!H11/100)/(1+INPUT!$C$6/100) -> 0 | J24: =($C$128*$C$106*TIENDO!I7/100+$C$130*1*TIENDO!I9/100+$C$131*$C$105*TIENDO!I10/100+$C$132*$C$105*TIENDO!I11/100)/(1+INPUT!$C$6/100) -> 0 | K24: =($C$128*$C$106*TIENDO!J7/100+$C$130*1*TIENDO!J9/100+$C$131*$C$105*TIENDO!J10/100+$C$132*$C$105*TIENDO!J11/100)/(1+INPUT!$C$6/100) -> 0 | ... P24: =($C$128*$C$106*TIENDO!O7/100+$C$130*1*TIENDO!O9/100+$C$131*$C$105*TIENDO!O10/100+$C$132*$C$105*TIENDO!O11/100)/(1+INPUT!$C$6/100) -> 0 | Q24: 0 | R24: 0 | S24: 0 | T24: 0 | U24: 0 | V24: 0 | W24: 0 | X24: 0 | Y24: 0 | Z24: 0 | AA24: 0 | AB24: 0 | AC24: 0 | AD24: 0 | AE24: 0 | AF24: 0 | AG24: 0 | AH24: 0 | AI24: 0 | AJ24: 0 | AK24: 0 | AL24: 0 | AM24: 0 | AN24: 0 | AO24: 0 | AP24: 0 | AQ24: 0 | AR24: 0 | AS24: 0 | AT24: 0 | AU24: 0 | AV24: 0 | AW24: 0 | AX24: 0 | AY24: 0 | AZ24: 0 | BA24: 0 | BB24: 0 | BC24: 0 | BD24: 0 | BE24: 0 | BF24: 0 | BG24: 0 | BH24: 0 | BI24: 0 | BJ24: 0 | BK24: 0
B25: (−) Vận hành Cho thuê (opex+FF&E+BH) | C25: =SUM(D25:BK25) -> 0 | D25: =D59+D60+D61 -> 0 | E25: =E59+E60+E61 -> 0 | F25: =F59+F60+F61 -> 0 | G25: =G59+G60+G61 -> 0 | H25: =H59+H60+H61 -> 0 | I25: =I59+I60+I61 -> 0 | J25: =J59+J60+J61 -> 0 | K25: =K59+K60+K61 -> 0 | ... BK25: =BK59+BK60+BK61 -> 0
B26: (−) Thuế TNDN hợp nhất (bù lỗ 5 năm) | C26: =SUM(D26:BK26) -> 3.2222411e+09 | D26: =IF(AND(D11>0,SUM(E11:BK11)=0),MAX($C$154*INPUT!$C$7/100-0,0),D11*INPUT!$C$8/100) -> 0 | E26: =IF(AND(E11>0,SUM(F11:BK11)=0),MAX($C$154*INPUT!$C$7/100-SUM(D26:D26),-SUM(D26:D26)),E11*INPUT!$C$8/100) -> 0 | F26: =IF(AND(F11>0,SUM(G11:BK11)=0),MAX($C$154*INPUT!$C$7/100-SUM(D26:E26),-SUM(D26:E26)),F11*INPUT!$C$8/100) -> 1708839000 | G26: =IF(AND(G11>0,SUM(H11:BK11)=0),MAX($C$154*INPUT!$C$7/100-SUM(D26:F26),-SUM(D26:F26)),G11*INPUT!$C$8/100) -> 9384374175 | H26: =IF(AND(H11>0,SUM(I11:BK11)=0),MAX($C$154*INPUT!$C$7/100-SUM(D26:G26),-SUM(D26:G26)),H11*INPUT!$C$8/100) -> -7.8709721e+09 | I26: =IF(AND(I11>0,SUM(J11:BK11)=0),MAX($C$154*INPUT!$C$7/100-SUM(D26:H26),-SUM(D26:H26)),I11*INPUT!$C$8/100) -> 0 | J26: =IF(AND(J11>0,SUM(K11:BK11)=0),MAX($C$154*INPUT!$C$7/100-SUM(D26:I26),-SUM(D26:I26)),J11*INPUT!$C$8/100) -> 0 | K26: =IF(AND(K11>0,SUM(L11:BK11)=0),MAX($C$154*INPUT!$C$7/100-SUM(D26:J26),-SUM(D26:J26)),K11*INPUT!$C$8/100) -> 0 | L26: =IF(AND(L11>0,SUM(M11:BK11)=0),MAX($C$154*INPUT!$C$7/100-SUM(D26:K26),-SUM(D26:K26)),L11*INPUT!$C$8/100) -> 0 | M26: =IF(AND(M11>0,SUM(N11:BK11)=0),MAX($C$154*INPUT!$C$7/100-SUM(D26:L26),-SUM(D26:L26)),M11*INPUT!$C$8/100) -> 0 | N26: =IF(AND(N11>0,SUM(O11:BK11)=0),MAX($C$154*INPUT!$C$7/100-SUM(D26:M26),-SUM(D26:M26)),N11*INPUT!$C$8/100) -> 0 | O26: =IF(AND(O11>0,SUM(P11:BK11)=0),MAX($C$154*INPUT!$C$7/100-SUM(D26:N26),-SUM(D26:N26)),O11*INPUT!$C$8/100) -> 0 | P26: =IF(AND(P11>0,SUM(Q11:BK11)=0),MAX($C$154*INPUT!$C$7/100-SUM(D26:O26),-SUM(D26:O26)),P11*INPUT!$C$8/100) -> 0 | Q26: =IF(AND(Q11>0,SUM(R11:BK11)=0),MAX($C$154*INPUT!$C$7/100-SUM(D26:P26),-SUM(D26:P26)),Q11*INPUT!$C$8/100) -> 0 | R26: =IF(AND(R11>0,SUM(S11:BK11)=0),MAX($C$154*INPUT!$C$7/100-SUM(D26:Q26),-SUM(D26:Q26)),R11*INPUT!$C$8/100) -> 0 | S26: =IF(AND(S11>0,SUM(T11:BK11)=0),MAX($C$154*INPUT!$C$7/100-SUM(D26:R26),-SUM(D26:R26)),S11*INPUT!$C$8/100) -> 0 | T26: =IF(AND(T11>0,SUM(U11:BK11)=0),MAX($C$154*INPUT!$C$7/100-SUM(D26:S26),-SUM(D26:S26)),T11*INPUT!$C$8/100) -> 0 | U26: =IF(AND(U11>0,SUM(V11:BK11)=0),MAX($C$154*INPUT!$C$7/100-SUM(D26:T26),-SUM(D26:T26)),U11*INPUT!$C$8/100) -> 0 | V26: =IF(AND(V11>0,SUM(W11:BK11)=0),MAX($C$154*INPUT!$C$7/100-SUM(D26:U26),-SUM(D26:U26)),V11*INPUT!$C$8/100) -> 0 | W26: =IF(AND(W11>0,SUM(X11:BK11)=0),MAX($C$154*INPUT!$C$7/100-SUM(D26:V26),-SUM(D26:V26)),W11*INPUT!$C$8/100) -> 0 | X26: =IF(AND(X11>0,SUM(Y11:BK11)=0),MAX($C$154*INPUT!$C$7/100-SUM(D26:W26),-SUM(D26:W26)),X11*INPUT!$C$8/100) -> 0 | Y26: =IF(AND(Y11>0,SUM(Z11:BK11)=0),MAX($C$154*INPUT!$C$7/100-SUM(D26:X26),-SUM(D26:X26)),Y11*INPUT!$C$8/100) -> 0 | Z26: =IF(AND(Z11>0,SUM(AA11:BK11)=0),MAX($C$154*INPUT!$C$7/100-SUM(D26:Y26),-SUM(D26:Y26)),Z11*INPUT!$C$8/100) -> 0 | AA26: =IF(AND(AA11>0,SUM(AB11:BK11)=0),MAX($C$154*INPUT!$C$7/100-SUM(D26:Z26),-SUM(D26:Z26)),AA11*INPUT!$C$8/100) -> 0 | AB26: =IF(AND(AB11>0,SUM(AC11:BK11)=0),MAX($C$154*INPUT!$C$7/100-SUM(D26:AA26),-SUM(D26:AA26)),AB11*INPUT!$C$8/100) -> 0 | AC26: =IF(AND(AC11>0,SUM(AD11:BK11)=0),MAX($C$154*INPUT!$C$7/100-SUM(D26:AB26),-SUM(D26:AB26)),AC11*INPUT!$C$8/100) -> 0 | AD26: =IF(AND(AD11>0,SUM(AE11:BK11)=0),MAX($C$154*INPUT!$C$7/100-SUM(D26:AC26),-SUM(D26:AC26)),AD11*INPUT!$C$8/100) -> 0 | AE26: =IF(AND(AE11>0,SUM(AF11:BK11)=0),MAX($C$154*INPUT!$C$7/100-SUM(D26:AD26),-SUM(D26:AD26)),AE11*INPUT!$C$8/100) -> 0 | AF26: =IF(AND(AF11>0,SUM(AG11:BK11)=0),MAX($C$154*INPUT!$C$7/100-SUM(D26:AE26),-SUM(D26:AE26)),AF11*INPUT!$C$8/100) -> 0 | AG26: =IF(AND(AG11>0,SUM(AH11:BK11)=0),MAX($C$154*INPUT!$C$7/100-SUM(D26:AF26),-SUM(D26:AF26)),AG11*INPUT!$C$8/100) -> 0 | AH26: =IF(AND(AH11>0,SUM(AI11:BK11)=0),MAX($C$154*INPUT!$C$7/100-SUM(D26:AG26),-SUM(D26:AG26)),AH11*INPUT!$C$8/100) -> 0 | AI26: =IF(AND(AI11>0,SUM(AJ11:BK11)=0),MAX($C$154*INPUT!$C$7/100-SUM(D26:AH26),-SUM(D26:AH26)),AI11*INPUT!$C$8/100) -> 0 | AJ26: =IF(AND(AJ11>0,SUM(AK11:BK11)=0),MAX($C$154*INPUT!$C$7/100-SUM(D26:AI26),-SUM(D26:AI26)),AJ11*INPUT!$C$8/100) -> 0 | AK26: =IF(AND(AK11>0,SUM(AL11:BK11)=0),MAX($C$154*INPUT!$C$7/100-SUM(D26:AJ26),-SUM(D26:AJ26)),AK11*INPUT!$C$8/100) -> 0 | AL26: =IF(AND(AL11>0,SUM(AM11:BK11)=0),MAX($C$154*INPUT!$C$7/100-SUM(D26:AK26),-SUM(D26:AK26)),AL11*INPUT!$C$8/100) -> 0 | AM26: =IF(AND(AM11>0,SUM(AN11:BK11)=0),MAX($C$154*INPUT!$C$7/100-SUM(D26:AL26),-SUM(D26:AL26)),AM11*INPUT!$C$8/100) -> 0 | AN26: =IF(AND(AN11>0,SUM(AO11:BK11)=0),MAX($C$154*INPUT!$C$7/100-SUM(D26:AM26),-SUM(D26:AM26)),AN11*INPUT!$C$8/100) -> 0 | AO26: =IF(AND(AO11>0,SUM(AP11:BK11)=0),MAX($C$154*INPUT!$C$7/100-SUM(D26:AN26),-SUM(D26:AN26)),AO11*INPUT!$C$8/100) -> 0 | AP26: =IF(AND(AP11>0,SUM(AQ11:BK11)=0),MAX($C$154*INPUT!$C$7/100-SUM(D26:AO26),-SUM(D26:AO26)),AP11*INPUT!$C$8/100) -> 0 | AQ26: =IF(AND(AQ11>0,SUM(AR11:BK11)=0),MAX($C$154*INPUT!$C$7/100-SUM(D26:AP26),-SUM(D26:AP26)),AQ11*INPUT!$C$8/100) -> 0 | AR26: =IF(AND(AR11>0,SUM(AS11:BK11)=0),MAX($C$154*INPUT!$C$7/100-SUM(D26:AQ26),-SUM(D26:AQ26)),AR11*INPUT!$C$8/100) -> 0 | AS26: =IF(AND(AS11>0,SUM(AT11:BK11)=0),MAX($C$154*INPUT!$C$7/100-SUM(D26:AR26),-SUM(D26:AR26)),AS11*INPUT!$C$8/100) -> 0 | AT26: =IF(AND(AT11>0,SUM(AU11:BK11)=0),MAX($C$154*INPUT!$C$7/100-SUM(D26:AS26),-SUM(D26:AS26)),AT11*INPUT!$C$8/100) -> 0 | AU26: =IF(AND(AU11>0,SUM(AV11:BK11)=0),MAX($C$154*INPUT!$C$7/100-SUM(D26:AT26),-SUM(D26:AT26)),AU11*INPUT!$C$8/100) -> 0 | AV26: =IF(AND(AV11>0,SUM(AW11:BK11)=0),MAX($C$154*INPUT!$C$7/100-SUM(D26:AU26),-SUM(D26:AU26)),AV11*INPUT!$C$8/100) -> 0 | AW26: =IF(AND(AW11>0,SUM(AX11:BK11)=0),MAX($C$154*INPUT!$C$7/100-SUM(D26:AV26),-SUM(D26:AV26)),AW11*INPUT!$C$8/100) -> 0 | AX26: =IF(AND(AX11>0,SUM(AY11:BK11)=0),MAX($C$154*INPUT!$C$7/100-SUM(D26:AW26),-SUM(D26:AW26)),AX11*INPUT!$C$8/100) -> 0 | AY26: =IF(AND(AY11>0,SUM(AZ11:BK11)=0),MAX($C$154*INPUT!$C$7/100-SUM(D26:AX26),-SUM(D26:AX26)),AY11*INPUT!$C$8/100) -> 0 | AZ26: =IF(AND(AZ11>0,SUM(BA11:BK11)=0),MAX($C$154*INPUT!$C$7/100-SUM(D26:AY26),-SUM(D26:AY26)),AZ11*INPUT!$C$8/100) -> 0 | BA26: =IF(AND(BA11>0,SUM(BB11:BK11)=0),MAX($C$154*INPUT!$C$7/100-SUM(D26:AZ26),-SUM(D26:AZ26)),BA11*INPUT!$C$8/100) -> 0 | BB26: =IF(AND(BB11>0,SUM(BC11:BK11)=0),MAX($C$154*INPUT!$C$7/100-SUM(D26:BA26),-SUM(D26:BA26)),BB11*INPUT!$C$8/100) -> 0 | BC26: =IF(AND(BC11>0,SUM(BD11:BK11)=0),MAX($C$154*INPUT!$C$7/100-SUM(D26:BB26),-SUM(D26:BB26)),BC11*INPUT!$C$8/100) -> 0 | BD26: =IF(AND(BD11>0,SUM(BE11:BK11)=0),MAX($C$154*INPUT!$C$7/100-SUM(D26:BC26),-SUM(D26:BC26)),BD11*INPUT!$C$8/100) -> 0 | BE26: =IF(AND(BE11>0,SUM(BF11:BK11)=0),MAX($C$154*INPUT!$C$7/100-SUM(D26:BD26),-SUM(D26:BD26)),BE11*INPUT!$C$8/100) -> 0 | BF26: =IF(AND(BF11>0,SUM(BG11:BK11)=0),MAX($C$154*INPUT!$C$7/100-SUM(D26:BE26),-SUM(D26:BE26)),BF11*INPUT!$C$8/100) -> 0 | BG26: =IF(AND(BG11>0,SUM(BH11:BK11)=0),MAX($C$154*INPUT!$C$7/100-SUM(D26:BF26),-SUM(D26:BF26)),BG11*INPUT!$C$8/100) -> 0 | BH26: =IF(AND(BH11>0,SUM(BI11:BK11)=0),MAX($C$154*INPUT!$C$7/100-SUM(D26:BG26),-SUM(D26:BG26)),BH11*INPUT!$C$8/100) -> 0 | BI26: =IF(AND(BI11>0,SUM(BJ11:BK11)=0),MAX($C$154*INPUT!$C$7/100-SUM(D26:BH26),-SUM(D26:BH26)),BI11*INPUT!$C$8/100) -> 0 | BJ26: =IF(AND(BJ11>0,SUM(BK11:BK11)=0),MAX($C$154*INPUT!$C$7/100-SUM(D26:BI26),-SUM(D26:BI26)),BJ11*INPUT!$C$8/100) -> 0 | BK26: =IF(AND(BK11>0,TRUE),MAX($C$154*INPUT!$C$7/100-SUM(D26:BJ26),-SUM(D26:BJ26)),BK11*INPUT!$C$8/100) -> 0
B27: Σ NGN LƯU HĐKD — TMĐT (sau thuế) | C27: =SUM(D27:BK27) -> -5.0352459e+10 | D27: =D11+D12-D13-D18-D19-D20-D25-D26-D28 -> -200000000000 | E27: =E11+E12-E13-E18-E19-E20-E25-E26-E28 -> -215000000000 | F27: =F11+F12-F13-F18-F19-F20-F25-F26-F28 -> -405318359300 | G27: =G11+G12-G13-G18-G19-G20-G25-G26-G28 -> 5.237707e+11 | H27: =H11+H12-H13-H18-H19-H20-H25-H26-H28 -> 2.461952e+11 | I27: =I11+I12-I13-I18-I19-I20-I25-I26-I28 -> 0 | J27: =J11+J12-J13-J18-J19-J20-J25-J26-J28 -> 0 | K27: =K11+K12-K13-K18-K19-K20-K25-K26-K28 -> 0 | ... BK27: =BK11+BK12-BK13-BK18-BK19-BK20-BK25-BK26-BK28 -> 0
B28: (−) Lãi vay (trên dòng tiền tổng) | C28: =SUM(D28:BK28) -> 38930360154 | D28: =INPUT!$C$5/100*D88 -> 0 | E28: =INPUT!$C$5/100*E88 -> 0 | F28: =INPUT!$C$5/100*F88 -> 0 | G28: =INPUT!$C$5/100*G88 -> 38930360154 | H28: =INPUT!$C$5/100*H88 -> 0 | I28: =INPUT!$C$5/100*I88 -> 0 | J28: =INPUT!$C$5/100*J88 -> 0 | K28: =INPUT!$C$5/100*K88 -> 0 | ... BK28: =INPUT!$C$5/100*BK88 -> 0
B29: (+) Giải ngân vốn vay | C29: =SUM(D29:BK29) -> 512984969875 | D29: =IF(INPUT!$C$54=2,MAX(D85,0),MIN(D90,MAX(D91,0))) -> 0 | E29: =IF(INPUT!$C$54=2,MAX(E85,0),MIN(E90,MAX(E91,0))) -> 0 | F29: =IF(INPUT!$C$54=2,MAX(F85,0),MIN(F90,MAX(F91,0))) -> 324419667950 | G29: =IF(INPUT!$C$54=2,MAX(G85,0),MIN(G90,MAX(G91,0))) -> 1.5531798e+11 | H29: =IF(INPUT!$C$54=2,MAX(H85,0),MIN(H90,MAX(H91,0))) -> 3.3247317e+10 | I29: =IF(INPUT!$C$54=2,MAX(I85,0),MIN(I90,MAX(I91,0))) -> 0 | J29: =IF(INPUT!$C$54=2,MAX(J85,0),MIN(J90,MAX(J91,0))) -> 0 | K29: =IF(INPUT!$C$54=2,MAX(K85,0),MIN(K90,MAX(K91,0))) -> 0 | ... BK29: =IF(INPUT!$C$54=2,MAX(BK85,0),MIN(BK90,MAX(BK91,0))) -> 0
B30: (−) Trả nợ gốc | C30: =SUM(D30:BK30) -> 512984969875 | D30: =MIN(D88+D29,D92) -> 0 | E30: =MIN(E88+E29,E92) -> 0 | F30: =MIN(F88+F29,F92) -> 0 | G30: =MIN(G88+G29,G92) -> 4.7973765e+11 | H30: =MIN(H88+H29,H92) -> 3.3247317e+10 | I30: =MIN(I88+I29,I92) -> 0 | J30: =MIN(J88+J29,J92) -> 0 | K30: =MIN(K88+K29,K92) -> 0 | ... BK30: =MIN(BK88+BK29,BK92) -> 0
B31: Dư nợ vay cuối kỳ (memo) | C31: =SUM(D31:BK31) -> 324419667950 | D31: =D88+D29-D30 -> 0 | E31: =E88+E29-E30 -> 0 | F31: =F88+F29-F30 -> 324419667950 | G31: =G88+G29-G30 -> 0 | H31: =H88+H29-H30 -> 0 | I31: =I88+I29-I30 -> 0 | J31: =J88+J29-J30 -> 0 | K31: =K88+K29-K30 -> 0 | ... BK31: =BK88+BK29-BK30 -> 0
B32: Σ NGN LƯU CHỦ ĐẦU TƯ (levered, sau thuế) | C32: =SUM(D32:BK32) -> -5.0352459e+10 | D32: =D27+D29-D30 -> -200000000000 | E32: =E27+E29-E30 -> -215000000000 | F32: =F27+F29-F30 -> -80898691350 | G32: =G27+G29-G30 -> 1.9935103e+11 | H32: =H27+H29-H30 -> 2.461952e+11 | I32: =I27+I29-I30 -> 0 | J32: =J27+J29-J30 -> 0 | K32: =K27+K29-K30 -> 0 | ... BK32: =BK27+BK29-BK30 -> 0
B33: B · CHI TIẾT DOANH THU & THU TIỀN
B34: DT căn hộ ghi nhận (theo tiến độ bán) | D34: =IF(TIENDO!C16>0,$C$98*TIENDO!C16/100*$C$120*(1+$C$119)^(2026-$C$122),0) -> 0 | E34: =IF(TIENDO!D16>0,$C$98*TIENDO!D16/100*$C$120*(1+$C$119)^(2027-$C$122),0) -> 0 | F34: =IF(TIENDO!E16>0,$C$98*TIENDO!E16/100*$C$120*(1+$C$119)^(2028-$C$122),0) -> 497266440000 | G34: =IF(TIENDO!F16>0,$C$98*TIENDO!F16/100*$C$120*(1+$C$119)^(2029-$C$122),0) -> 522129762000 | H34: =IF(TIENDO!G16>0,$C$98*TIENDO!G16/100*$C$120*(1+$C$119)^(2030-$C$122),0) -> 274118125050 | I34: =IF(TIENDO!H16>0,$C$98*TIENDO!H16/100*$C$120*(1+$C$119)^(2031-$C$122),0) -> 0 | J34: =IF(TIENDO!I16>0,$C$98*TIENDO!I16/100*$C$120*(1+$C$119)^(2032-$C$122),0) -> 0 | K34: =IF(TIENDO!J16>0,$C$98*TIENDO!J16/100*$C$120*(1+$C$119)^(2033-$C$122),0) -> 0 | L34: =IF(TIENDO!K16>0,$C$98*TIENDO!K16/100*$C$120*(1+$C$119)^(2034-$C$122),0) -> 0 | M34: =IF(TIENDO!L16>0,$C$98*TIENDO!L16/100*$C$120*(1+$C$119)^(2035-$C$122),0) -> 0 | N34: =IF(TIENDO!M16>0,$C$98*TIENDO!M16/100*$C$120*(1+$C$119)^(2036-$C$122),0) -> 0 | O34: =IF(TIENDO!N16>0,$C$98*TIENDO!N16/100*$C$120*(1+$C$119)^(2037-$C$122),0) -> 0 | P34: =IF(TIENDO!O16>0,$C$98*TIENDO!O16/100*$C$120*(1+$C$119)^(2038-$C$122),0) -> 0 | Q34: 0 | R34: 0 | S34: 0 | T34: 0 | U34: 0 | V34: 0 | W34: 0 | X34: 0 | Y34: 0 | Z34: 0 | AA34: 0 | AB34: 0 | AC34: 0 | AD34: 0 | AE34: 0 | AF34: 0 | AG34: 0 | AH34: 0 | AI34: 0 | AJ34: 0 | AK34: 0 | AL34: 0 | AM34: 0 | AN34: 0 | AO34: 0 | AP34: 0 | AQ34: 0 | AR34: 0 | AS34: 0 | AT34: 0 | AU34: 0 | AV34: 0 | AW34: 0 | AX34: 0 | AY34: 0 | AZ34: 0 | BA34: 0 | BB34: 0 | BC34: 0 | BD34: 0 | BE34: 0 | BF34: 0 | BG34: 0 | BH34: 0 | BI34: 0 | BJ34: 0 | BK34: 0
B35: DT shop ghi nhận | D35: =IF(TIENDO!C17>0,$C$99*TIENDO!C17/100*$C$121*(1+$C$119)^(2026-$C$123),0) -> 0 | E35: =IF(TIENDO!D17>0,$C$99*TIENDO!D17/100*$C$121*(1+$C$119)^(2027-$C$123),0) -> 0 | F35: =IF(TIENDO!E17>0,$C$99*TIENDO!E17/100*$C$121*(1+$C$119)^(2028-$C$123),0) -> 72346560000 | G35: =IF(TIENDO!F17>0,$C$99*TIENDO!F17/100*$C$121*(1+$C$119)^(2029-$C$123),0) -> 75963888000 | H35: =IF(TIENDO!G17>0,$C$99*TIENDO!G17/100*$C$121*(1+$C$119)^(2030-$C$123),0) -> 39881041200 | I35: =IF(TIENDO!H17>0,$C$99*TIENDO!H17/100*$C$121*(1+$C$119)^(2031-$C$123),0) -> 0 | J35: =IF(TIENDO!I17>0,$C$99*TIENDO!I17/100*$C$121*(1+$C$119)^(2032-$C$123),0) -> 0 | K35: =IF(TIENDO!J17>0,$C$99*TIENDO!J17/100*$C$121*(1+$C$119)^(2033-$C$123),0) -> 0 | L35: =IF(TIENDO!K17>0,$C$99*TIENDO!K17/100*$C$121*(1+$C$119)^(2034-$C$123),0) -> 0 | M35: =IF(TIENDO!L17>0,$C$99*TIENDO!L17/100*$C$121*(1+$C$119)^(2035-$C$123),0) -> 0 | N35: =IF(TIENDO!M17>0,$C$99*TIENDO!M17/100*$C$121*(1+$C$119)^(2036-$C$123),0) -> 0 | O35: =IF(TIENDO!N17>0,$C$99*TIENDO!N17/100*$C$121*(1+$C$119)^(2037-$C$123),0) -> 0 | P35: =IF(TIENDO!O17>0,$C$99*TIENDO!O17/100*$C$121*(1+$C$119)^(2038-$C$123),0) -> 0 | Q35: 0 | R35: 0 | S35: 0 | T35: 0 | U35: 0 | V35: 0 | W35: 0 | X35: 0 | Y35: 0 | Z35: 0 | AA35: 0 | AB35: 0 | AC35: 0 | AD35: 0 | AE35: 0 | AF35: 0 | AG35: 0 | AH35: 0 | AI35: 0 | AJ35: 0 | AK35: 0 | AL35: 0 | AM35: 0 | AN35: 0 | AO35: 0 | AP35: 0 | AQ35: 0 | AR35: 0 | AS35: 0 | AT35: 0 | AU35: 0 | AV35: 0 | AW35: 0 | AX35: 0 | AY35: 0 | AZ35: 0 | BA35: 0 | BB35: 0 | BC35: 0 | BD35: 0 | BE35: 0 | BF35: 0 | BG35: 0 | BH35: 0 | BI35: 0 | BJ35: 0 | BK35: 0
B36: Tổng DT ghi nhận theo vintage | D36: =D34+D35 -> 0 | E36: =E34+E35 -> 0 | F36: =F34+F35 -> 569613000000 | G36: =G34+G35 -> 598093650000 | H36: =H34+H35 -> 313999166250 | I36: =I34+I35 -> 0 | J36: =J34+J35 -> 0 | K36: =K34+K35 -> 0 | ... BK36: =BK34+BK35 -> 0
B37: thu từ DT bán năm 2026 | D37: =D34*TIENDO!C20/100+D35*TIENDO!C36/100 -> 0 | E37: =D34*TIENDO!D20/100+D35*TIENDO!D36/100 -> 0 | F37: =D34*TIENDO!E20/100+D35*TIENDO!E36/100 -> 0 | G37: =D34*TIENDO!F20/100+D35*TIENDO!F36/100 -> 0 | H37: =D34*TIENDO!G20/100+D35*TIENDO!G36/100 -> 0 | I37: =D34*TIENDO!H20/100+D35*TIENDO!H36/100 -> 0 | J37: =D34*TIENDO!I20/100+D35*TIENDO!I36/100 -> 0 | K37: =D34*TIENDO!J20/100+D35*TIENDO!J36/100 -> 0 | L37: =D34*TIENDO!K20/100+D35*TIENDO!K36/100 -> 0 | M37: =D34*TIENDO!L20/100+D35*TIENDO!L36/100 -> 0 | N37: =D34*TIENDO!M20/100+D35*TIENDO!M36/100 -> 0 | O37: =D34*TIENDO!N20/100+D35*TIENDO!N36/100 -> 0 | P37: =D34*TIENDO!O20/100+D35*TIENDO!O36/100 -> 0 | Q37: 0 | R37: 0 | S37: 0 | T37: 0 | U37: 0 | V37: 0 | W37: 0 | X37: 0 | Y37: 0 | Z37: 0 | AA37: 0 | AB37: 0 | AC37: 0 | AD37: 0 | AE37: 0 | AF37: 0 | AG37: 0 | AH37: 0 | AI37: 0 | AJ37: 0 | AK37: 0 | AL37: 0 | AM37: 0 | AN37: 0 | AO37: 0 | AP37: 0 | AQ37: 0 | AR37: 0 | AS37: 0 | AT37: 0 | AU37: 0 | AV37: 0 | AW37: 0 | AX37: 0 | AY37: 0 | AZ37: 0 | BA37: 0 | BB37: 0 | BC37: 0 | BD37: 0 | BE37: 0 | BF37: 0 | BG37: 0 | BH37: 0 | BI37: 0 | BJ37: 0 | BK37: 0
B38: thu từ DT bán năm 2027 | D38: =E34*TIENDO!C21/100+E35*TIENDO!C37/100 -> 0 | E38: =E34*TIENDO!D21/100+E35*TIENDO!D37/100 -> 0 | F38: =E34*TIENDO!E21/100+E35*TIENDO!E37/100 -> 0 | G38: =E34*TIENDO!F21/100+E35*TIENDO!F37/100 -> 0 | H38: =E34*TIENDO!G21/100+E35*TIENDO!G37/100 -> 0 | I38: =E34*TIENDO!H21/100+E35*TIENDO!H37/100 -> 0 | J38: =E34*TIENDO!I21/100+E35*TIENDO!I37/100 -> 0 | K38: =E34*TIENDO!J21/100+E35*TIENDO!J37/100 -> 0 | L38: =E34*TIENDO!K21/100+E35*TIENDO!K37/100 -> 0 | M38: =E34*TIENDO!L21/100+E35*TIENDO!L37/100 -> 0 | N38: =E34*TIENDO!M21/100+E35*TIENDO!M37/100 -> 0 | O38: =E34*TIENDO!N21/100+E35*TIENDO!N37/100 -> 0 | P38: =E34*TIENDO!O21/100+E35*TIENDO!O37/100 -> 0 | Q38: 0 | R38: 0 | S38: 0 | T38: 0 | U38: 0 | V38: 0 | W38: 0 | X38: 0 | Y38: 0 | Z38: 0 | AA38: 0 | AB38: 0 | AC38: 0 | AD38: 0 | AE38: 0 | AF38: 0 | AG38: 0 | AH38: 0 | AI38: 0 | AJ38: 0 | AK38: 0 | AL38: 0 | AM38: 0 | AN38: 0 | AO38: 0 | AP38: 0 | AQ38: 0 | AR38: 0 | AS38: 0 | AT38: 0 | AU38: 0 | AV38: 0 | AW38: 0 | AX38: 0 | AY38: 0 | AZ38: 0 | BA38: 0 | BB38: 0 | BC38: 0 | BD38: 0 | BE38: 0 | BF38: 0 | BG38: 0 | BH38: 0 | BI38: 0 | BJ38: 0 | BK38: 0
B39: thu từ DT bán năm 2028 | D39: =F34*TIENDO!C22/100+F35*TIENDO!C38/100 -> 0 | E39: =F34*TIENDO!D22/100+F35*TIENDO!D38/100 -> 0 | F39: =F34*TIENDO!E22/100+F35*TIENDO!E38/100 -> 170883900000 | G39: =F34*TIENDO!F22/100+F35*TIENDO!F38/100 -> 370248450000 | H39: =F34*TIENDO!G22/100+F35*TIENDO!G38/100 -> 28480650000 | I39: =F34*TIENDO!H22/100+F35*TIENDO!H38/100 -> 0 | J39: =F34*TIENDO!I22/100+F35*TIENDO!I38/100 -> 0 | K39: =F34*TIENDO!J22/100+F35*TIENDO!J38/100 -> 0 | L39: =F34*TIENDO!K22/100+F35*TIENDO!K38/100 -> 0 | M39: =F34*TIENDO!L22/100+F35*TIENDO!L38/100 -> 0 | N39: =F34*TIENDO!M22/100+F35*TIENDO!M38/100 -> 0 | O39: =F34*TIENDO!N22/100+F35*TIENDO!N38/100 -> 0 | P39: =F34*TIENDO!O22/100+F35*TIENDO!O38/100 -> 0 | Q39: 0 | R39: 0 | S39: 0 | T39: 0 | U39: 0 | V39: 0 | W39: 0 | X39: 0 | Y39: 0 | Z39: 0 | AA39: 0 | AB39: 0 | AC39: 0 | AD39: 0 | AE39: 0 | AF39: 0 | AG39: 0 | AH39: 0 | AI39: 0 | AJ39: 0 | AK39: 0 | AL39: 0 | AM39: 0 | AN39: 0 | AO39: 0 | AP39: 0 | AQ39: 0 | AR39: 0 | AS39: 0 | AT39: 0 | AU39: 0 | AV39: 0 | AW39: 0 | AX39: 0 | AY39: 0 | AZ39: 0 | BA39: 0 | BB39: 0 | BC39: 0 | BD39: 0 | BE39: 0 | BF39: 0 | BG39: 0 | BH39: 0 | BI39: 0 | BJ39: 0 | BK39: 0
B40: thu từ DT bán năm 2029 | D40: =G34*TIENDO!C23/100+G35*TIENDO!C39/100 -> 0 | E40: =G34*TIENDO!D23/100+G35*TIENDO!D39/100 -> 0 | F40: =G34*TIENDO!E23/100+G35*TIENDO!E39/100 -> 0 | G40: =G34*TIENDO!F23/100+G35*TIENDO!F39/100 -> 568188967500 | H40: =G34*TIENDO!G23/100+G35*TIENDO!G39/100 -> 29904682500 | I40: =G34*TIENDO!H23/100+G35*TIENDO!H39/100 -> 0 | J40: =G34*TIENDO!I23/100+G35*TIENDO!I39/100 -> 0 | K40: =G34*TIENDO!J23/100+G35*TIENDO!J39/100 -> 0 | L40: =G34*TIENDO!K23/100+G35*TIENDO!K39/100 -> 0 | M40: =G34*TIENDO!L23/100+G35*TIENDO!L39/100 -> 0 | N40: =G34*TIENDO!M23/100+G35*TIENDO!M39/100 -> 0 | O40: =G34*TIENDO!N23/100+G35*TIENDO!N39/100 -> 0 | P40: =G34*TIENDO!O23/100+G35*TIENDO!O39/100 -> 0 | Q40: 0 | R40: 0 | S40: 0 | T40: 0 | U40: 0 | V40: 0 | W40: 0 | X40: 0 | Y40: 0 | Z40: 0 | AA40: 0 | AB40: 0 | AC40: 0 | AD40: 0 | AE40: 0 | AF40: 0 | AG40: 0 | AH40: 0 | AI40: 0 | AJ40: 0 | AK40: 0 | AL40: 0 | AM40: 0 | AN40: 0 | AO40: 0 | AP40: 0 | AQ40: 0 | AR40: 0 | AS40: 0 | AT40: 0 | AU40: 0 | AV40: 0 | AW40: 0 | AX40: 0 | AY40: 0 | AZ40: 0 | BA40: 0 | BB40: 0 | BC40: 0 | BD40: 0 | BE40: 0 | BF40: 0 | BG40: 0 | BH40: 0 | BI40: 0 | BJ40: 0 | BK40: 0
B41: thu từ DT bán năm 2030 | D41: =H34*TIENDO!C24/100+H35*TIENDO!C40/100 -> 0 | E41: =H34*TIENDO!D24/100+H35*TIENDO!D40/100 -> 0 | F41: =H34*TIENDO!E24/100+H35*TIENDO!E40/100 -> 0 | G41: =H34*TIENDO!F24/100+H35*TIENDO!F40/100 -> 0 | H41: =H34*TIENDO!G24/100+H35*TIENDO!G40/100 -> 313999166250 | I41: =H34*TIENDO!H24/100+H35*TIENDO!H40/100 -> 0 | J41: =H34*TIENDO!I24/100+H35*TIENDO!I40/100 -> 0 | K41: =H34*TIENDO!J24/100+H35*TIENDO!J40/100 -> 0 | L41: =H34*TIENDO!K24/100+H35*TIENDO!K40/100 -> 0 | M41: =H34*TIENDO!L24/100+H35*TIENDO!L40/100 -> 0 | N41: =H34*TIENDO!M24/100+H35*TIENDO!M40/100 -> 0 | O41: =H34*TIENDO!N24/100+H35*TIENDO!N40/100 -> 0 | P41: =H34*TIENDO!O24/100+H35*TIENDO!O40/100 -> 0 | Q41: 0 | R41: 0 | S41: 0 | T41: 0 | U41: 0 | V41: 0 | W41: 0 | X41: 0 | Y41: 0 | Z41: 0 | AA41: 0 | AB41: 0 | AC41: 0 | AD41: 0 | AE41: 0 | AF41: 0 | AG41: 0 | AH41: 0 | AI41: 0 | AJ41: 0 | AK41: 0 | AL41: 0 | AM41: 0 | AN41: 0 | AO41: 0 | AP41: 0 | AQ41: 0 | AR41: 0 | AS41: 0 | AT41: 0 | AU41: 0 | AV41: 0 | AW41: 0 | AX41: 0 | AY41: 0 | AZ41: 0 | BA41: 0 | BB41: 0 | BC41: 0 | BD41: 0 | BE41: 0 | BF41: 0 | BG41: 0 | BH41: 0 | BI41: 0 | BJ41: 0 | BK41: 0
B42: thu từ DT bán năm 2031 | D42: =I34*TIENDO!C25/100+I35*TIENDO!C41/100 -> 0 | E42: =I34*TIENDO!D25/100+I35*TIENDO!D41/100 -> 0 | F42: =I34*TIENDO!E25/100+I35*TIENDO!E41/100 -> 0 | G42: =I34*TIENDO!F25/100+I35*TIENDO!F41/100 -> 0 | H42: =I34*TIENDO!G25/100+I35*TIENDO!G41/100 -> 0 | I42: =I34*TIENDO!H25/100+I35*TIENDO!H41/100 -> 0 | J42: =I34*TIENDO!I25/100+I35*TIENDO!I41/100 -> 0 | K42: =I34*TIENDO!J25/100+I35*TIENDO!J41/100 -> 0 | L42: =I34*TIENDO!K25/100+I35*TIENDO!K41/100 -> 0 | M42: =I34*TIENDO!L25/100+I35*TIENDO!L41/100 -> 0 | N42: =I34*TIENDO!M25/100+I35*TIENDO!M41/100 -> 0 | O42: =I34*TIENDO!N25/100+I35*TIENDO!N41/100 -> 0 | P42: =I34*TIENDO!O25/100+I35*TIENDO!O41/100 -> 0 | Q42: 0 | R42: 0 | S42: 0 | T42: 0 | U42: 0 | V42: 0 | W42: 0 | X42: 0 | Y42: 0 | Z42: 0 | AA42: 0 | AB42: 0 | AC42: 0 | AD42: 0 | AE42: 0 | AF42: 0 | AG42: 0 | AH42: 0 | AI42: 0 | AJ42: 0 | AK42: 0 | AL42: 0 | AM42: 0 | AN42: 0 | AO42: 0 | AP42: 0 | AQ42: 0 | AR42: 0 | AS42: 0 | AT42: 0 | AU42: 0 | AV42: 0 | AW42: 0 | AX42: 0 | AY42: 0 | AZ42: 0 | BA42: 0 | BB42: 0 | BC42: 0 | BD42: 0 | BE42: 0 | BF42: 0 | BG42: 0 | BH42: 0 | BI42: 0 | BJ42: 0 | BK42: 0
B43: thu từ DT bán năm 2032 | D43: =J34*TIENDO!C26/100+J35*TIENDO!C42/100 -> 0 | E43: =J34*TIENDO!D26/100+J35*TIENDO!D42/100 -> 0 | F43: =J34*TIENDO!E26/100+J35*TIENDO!E42/100 -> 0 | G43: =J34*TIENDO!F26/100+J35*TIENDO!F42/100 -> 0 | H43: =J34*TIENDO!G26/100+J35*TIENDO!G42/100 -> 0 | I43: =J34*TIENDO!H26/100+J35*TIENDO!H42/100 -> 0 | J43: =J34*TIENDO!I26/100+J35*TIENDO!I42/100 -> 0 | K43: =J34*TIENDO!J26/100+J35*TIENDO!J42/100 -> 0 | L43: =J34*TIENDO!K26/100+J35*TIENDO!K42/100 -> 0 | M43: =J34*TIENDO!L26/100+J35*TIENDO!L42/100 -> 0 | N43: =J34*TIENDO!M26/100+J35*TIENDO!M42/100 -> 0 | O43: =J34*TIENDO!N26/100+J35*TIENDO!N42/100 -> 0 | P43: =J34*TIENDO!O26/100+J35*TIENDO!O42/100 -> 0 | Q43: 0 | R43: 0 | S43: 0 | T43: 0 | U43: 0 | V43: 0 | W43: 0 | X43: 0 | Y43: 0 | Z43: 0 | AA43: 0 | AB43: 0 | AC43: 0 | AD43: 0 | AE43: 0 | AF43: 0 | AG43: 0 | AH43: 0 | AI43: 0 | AJ43: 0 | AK43: 0 | AL43: 0 | AM43: 0 | AN43: 0 | AO43: 0 | AP43: 0 | AQ43: 0 | AR43: 0 | AS43: 0 | AT43: 0 | AU43: 0 | AV43: 0 | AW43: 0 | AX43: 0 | AY43: 0 | AZ43: 0 | BA43: 0 | BB43: 0 | BC43: 0 | BD43: 0 | BE43: 0 | BF43: 0 | BG43: 0 | BH43: 0 | BI43: 0 | BJ43: 0 | BK43: 0
B44: thu từ DT bán năm 2033 | D44: =K34*TIENDO!C27/100+K35*TIENDO!C43/100 -> 0 | E44: =K34*TIENDO!D27/100+K35*TIENDO!D43/100 -> 0 | F44: =K34*TIENDO!E27/100+K35*TIENDO!E43/100 -> 0 | G44: =K34*TIENDO!F27/100+K35*TIENDO!F43/100 -> 0 | H44: =K34*TIENDO!G27/100+K35*TIENDO!G43/100 -> 0 | I44: =K34*TIENDO!H27/100+K35*TIENDO!H43/100 -> 0 | J44: =K34*TIENDO!I27/100+K35*TIENDO!I43/100 -> 0 | K44: =K34*TIENDO!J27/100+K35*TIENDO!J43/100 -> 0 | L44: =K34*TIENDO!K27/100+K35*TIENDO!K43/100 -> 0 | M44: =K34*TIENDO!L27/100+K35*TIENDO!L43/100 -> 0 | N44: =K34*TIENDO!M27/100+K35*TIENDO!M43/100 -> 0 | O44: =K34*TIENDO!N27/100+K35*TIENDO!N43/100 -> 0 | P44: =K34*TIENDO!O27/100+K35*TIENDO!O43/100 -> 0 | Q44: 0 | R44: 0 | S44: 0 | T44: 0 | U44: 0 | V44: 0 | W44: 0 | X44: 0 | Y44: 0 | Z44: 0 | AA44: 0 | AB44: 0 | AC44: 0 | AD44: 0 | AE44: 0 | AF44: 0 | AG44: 0 | AH44: 0 | AI44: 0 | AJ44: 0 | AK44: 0 | AL44: 0 | AM44: 0 | AN44: 0 | AO44: 0 | AP44: 0 | AQ44: 0 | AR44: 0 | AS44: 0 | AT44: 0 | AU44: 0 | AV44: 0 | AW44: 0 | AX44: 0 | AY44: 0 | AZ44: 0 | BA44: 0 | BB44: 0 | BC44: 0 | BD44: 0 | BE44: 0 | BF44: 0 | BG44: 0 | BH44: 0 | BI44: 0 | BJ44: 0 | BK44: 0
B45: thu từ DT bán năm 2034 | D45: =L34*TIENDO!C28/100+L35*TIENDO!C44/100 -> 0 | E45: =L34*TIENDO!D28/100+L35*TIENDO!D44/100 -> 0 | F45: =L34*TIENDO!E28/100+L35*TIENDO!E44/100 -> 0 | G45: =L34*TIENDO!F28/100+L35*TIENDO!F44/100 -> 0 | H45: =L34*TIENDO!G28/100+L35*TIENDO!G44/100 -> 0 | I45: =L34*TIENDO!H28/100+L35*TIENDO!H44/100 -> 0 | J45: =L34*TIENDO!I28/100+L35*TIENDO!I44/100 -> 0 | K45: =L34*TIENDO!J28/100+L35*TIENDO!J44/100 -> 0 | L45: =L34*TIENDO!K28/100+L35*TIENDO!K44/100 -> 0 | M45: =L34*TIENDO!L28/100+L35*TIENDO!L44/100 -> 0 | N45: =L34*TIENDO!M28/100+L35*TIENDO!M44/100 -> 0 | O45: =L34*TIENDO!N28/100+L35*TIENDO!N44/100 -> 0 | P45: =L34*TIENDO!O28/100+L35*TIENDO!O44/100 -> 0 | Q45: 0 | R45: 0 | S45: 0 | T45: 0 | U45: 0 | V45: 0 | W45: 0 | X45: 0 | Y45: 0 | Z45: 0 | AA45: 0 | AB45: 0 | AC45: 0 | AD45: 0 | AE45: 0 | AF45: 0 | AG45: 0 | AH45: 0 | AI45: 0 | AJ45: 0 | AK45: 0 | AL45: 0 | AM45: 0 | AN45: 0 | AO45: 0 | AP45: 0 | AQ45: 0 | AR45: 0 | AS45: 0 | AT45: 0 | AU45: 0 | AV45: 0 | AW45: 0 | AX45: 0 | AY45: 0 | AZ45: 0 | BA45: 0 | BB45: 0 | BC45: 0 | BD45: 0 | BE45: 0 | BF45: 0 | BG45: 0 | BH45: 0 | BI45: 0 | BJ45: 0 | BK45: 0
B46: thu từ DT bán năm 2035 | D46: =M34*TIENDO!C29/100+M35*TIENDO!C45/100 -> 0 | E46: =M34*TIENDO!D29/100+M35*TIENDO!D45/100 -> 0 | F46: =M34*TIENDO!E29/100+M35*TIENDO!E45/100 -> 0 | G46: =M34*TIENDO!F29/100+M35*TIENDO!F45/100 -> 0 | H46: =M34*TIENDO!G29/100+M35*TIENDO!G45/100 -> 0 | I46: =M34*TIENDO!H29/100+M35*TIENDO!H45/100 -> 0 | J46: =M34*TIENDO!I29/100+M35*TIENDO!I45/100 -> 0 | K46: =M34*TIENDO!J29/100+M35*TIENDO!J45/100 -> 0 | L46: =M34*TIENDO!K29/100+M35*TIENDO!K45/100 -> 0 | M46: =M34*TIENDO!L29/100+M35*TIENDO!L45/100 -> 0 | N46: =M34*TIENDO!M29/100+M35*TIENDO!M45/100 -> 0 | O46: =M34*TIENDO!N29/100+M35*TIENDO!N45/100 -> 0 | P46: =M34*TIENDO!O29/100+M35*TIENDO!O45/100 -> 0 | Q46: 0 | R46: 0 | S46: 0 | T46: 0 | U46: 0 | V46: 0 | W46: 0 | X46: 0 | Y46: 0 | Z46: 0 | AA46: 0 | AB46: 0 | AC46: 0 | AD46: 0 | AE46: 0 | AF46: 0 | AG46: 0 | AH46: 0 | AI46: 0 | AJ46: 0 | AK46: 0 | AL46: 0 | AM46: 0 | AN46: 0 | AO46: 0 | AP46: 0 | AQ46: 0 | AR46: 0 | AS46: 0 | AT46: 0 | AU46: 0 | AV46: 0 | AW46: 0 | AX46: 0 | AY46: 0 | AZ46: 0 | BA46: 0 | BB46: 0 | BC46: 0 | BD46: 0 | BE46: 0 | BF46: 0 | BG46: 0 | BH46: 0 | BI46: 0 | BJ46: 0 | BK46: 0
B47: thu từ DT bán năm 2036 | D47: =N34*TIENDO!C30/100+N35*TIENDO!C46/100 -> 0 | E47: =N34*TIENDO!D30/100+N35*TIENDO!D46/100 -> 0 | F47: =N34*TIENDO!E30/100+N35*TIENDO!E46/100 -> 0 | G47: =N34*TIENDO!F30/100+N35*TIENDO!F46/100 -> 0 | H47: =N34*TIENDO!G30/100+N35*TIENDO!G46/100 -> 0 | I47: =N34*TIENDO!H30/100+N35*TIENDO!H46/100 -> 0 | J47: =N34*TIENDO!I30/100+N35*TIENDO!I46/100 -> 0 | K47: =N34*TIENDO!J30/100+N35*TIENDO!J46/100 -> 0 | L47: =N34*TIENDO!K30/100+N35*TIENDO!K46/100 -> 0 | M47: =N34*TIENDO!L30/100+N35*TIENDO!L46/100 -> 0 | N47: =N34*TIENDO!M30/100+N35*TIENDO!M46/100 -> 0 | O47: =N34*TIENDO!N30/100+N35*TIENDO!N46/100 -> 0 | P47: =N34*TIENDO!O30/100+N35*TIENDO!O46/100 -> 0 | Q47: 0 | R47: 0 | S47: 0 | T47: 0 | U47: 0 | V47: 0 | W47: 0 | X47: 0 | Y47: 0 | Z47: 0 | AA47: 0 | AB47: 0 | AC47: 0 | AD47: 0 | AE47: 0 | AF47: 0 | AG47: 0 | AH47: 0 | AI47: 0 | AJ47: 0 | AK47: 0 | AL47: 0 | AM47: 0 | AN47: 0 | AO47: 0 | AP47: 0 | AQ47: 0 | AR47: 0 | AS47: 0 | AT47: 0 | AU47: 0 | AV47: 0 | AW47: 0 | AX47: 0 | AY47: 0 | AZ47: 0 | BA47: 0 | BB47: 0 | BC47: 0 | BD47: 0 | BE47: 0 | BF47: 0 | BG47: 0 | BH47: 0 | BI47: 0 | BJ47: 0 | BK47: 0
B48: thu từ DT bán năm 2037 | D48: =O34*TIENDO!C31/100+O35*TIENDO!C47/100 -> 0 | E48: =O34*TIENDO!D31/100+O35*TIENDO!D47/100 -> 0 | F48: =O34*TIENDO!E31/100+O35*TIENDO!E47/100 -> 0 | G48: =O34*TIENDO!F31/100+O35*TIENDO!F47/100 -> 0 | H48: =O34*TIENDO!G31/100+O35*TIENDO!G47/100 -> 0 | I48: =O34*TIENDO!H31/100+O35*TIENDO!H47/100 -> 0 | J48: =O34*TIENDO!I31/100+O35*TIENDO!I47/100 -> 0 | K48: =O34*TIENDO!J31/100+O35*TIENDO!J47/100 -> 0 | L48: =O34*TIENDO!K31/100+O35*TIENDO!K47/100 -> 0 | M48: =O34*TIENDO!L31/100+O35*TIENDO!L47/100 -> 0 | N48: =O34*TIENDO!M31/100+O35*TIENDO!M47/100 -> 0 | O48: =O34*TIENDO!N31/100+O35*TIENDO!N47/100 -> 0 | P48: =O34*TIENDO!O31/100+O35*TIENDO!O47/100 -> 0 | Q48: 0 | R48: 0 | S48: 0 | T48: 0 | U48: 0 | V48: 0 | W48: 0 | X48: 0 | Y48: 0 | Z48: 0 | AA48: 0 | AB48: 0 | AC48: 0 | AD48: 0 | AE48: 0 | AF48: 0 | AG48: 0 | AH48: 0 | AI48: 0 | AJ48: 0 | AK48: 0 | AL48: 0 | AM48: 0 | AN48: 0 | AO48: 0 | AP48: 0 | AQ48: 0 | AR48: 0 | AS48: 0 | AT48: 0 | AU48: 0 | AV48: 0 | AW48: 0 | AX48: 0 | AY48: 0 | AZ48: 0 | BA48: 0 | BB48: 0 | BC48: 0 | BD48: 0 | BE48: 0 | BF48: 0 | BG48: 0 | BH48: 0 | BI48: 0 | BJ48: 0 | BK48: 0
B49: thu từ DT bán năm 2038 | D49: =P34*TIENDO!C32/100+P35*TIENDO!C48/100 -> 0 | E49: =P34*TIENDO!D32/100+P35*TIENDO!D48/100 -> 0 | F49: =P34*TIENDO!E32/100+P35*TIENDO!E48/100 -> 0 | G49: =P34*TIENDO!F32/100+P35*TIENDO!F48/100 -> 0 | H49: =P34*TIENDO!G32/100+P35*TIENDO!G48/100 -> 0 | I49: =P34*TIENDO!H32/100+P35*TIENDO!H48/100 -> 0 | J49: =P34*TIENDO!I32/100+P35*TIENDO!I48/100 -> 0 | K49: =P34*TIENDO!J32/100+P35*TIENDO!J48/100 -> 0 | L49: =P34*TIENDO!K32/100+P35*TIENDO!K48/100 -> 0 | M49: =P34*TIENDO!L32/100+P35*TIENDO!L48/100 -> 0 | N49: =P34*TIENDO!M32/100+P35*TIENDO!M48/100 -> 0 | O49: =P34*TIENDO!N32/100+P35*TIENDO!N48/100 -> 0 | P49: =P34*TIENDO!O32/100+P35*TIENDO!O48/100 -> 0 | Q49: 0 | R49: 0 | S49: 0 | T49: 0 | U49: 0 | V49: 0 | W49: 0 | X49: 0 | Y49: 0 | Z49: 0 | AA49: 0 | AB49: 0 | AC49: 0 | AD49: 0 | AE49: 0 | AF49: 0 | AG49: 0 | AH49: 0 | AI49: 0 | AJ49: 0 | AK49: 0 | AL49: 0 | AM49: 0 | AN49: 0 | AO49: 0 | AP49: 0 | AQ49: 0 | AR49: 0 | AS49: 0 | AT49: 0 | AU49: 0 | AV49: 0 | AW49: 0 | AX49: 0 | AY49: 0 | AZ49: 0 | BA49: 0 | BB49: 0 | BC49: 0 | BD49: 0 | BE49: 0 | BF49: 0 | BG49: 0 | BH49: 0 | BI49: 0 | BJ49: 0 | BK49: 0
B50: C · CHI TIẾT CHO THUÊ
